Workbook

Sheet Dashboard
A1: Play Before Pixels: financial model dashboard
A2: AlphaPlay LLC (Maryland) d/b/a Play Before Pixels. Revised draft for the founder, September 28, 2026. Planning estimates only: these are not forecasts of income or promises of results. Base plan: lean-path costs, first sales Dec 2026, and the school wave, board book and retail all off. Budget on Conservative; measure progress against Expected. Change any blue cell on Assumptions and every tab updates.
A5: Measure | B5: Conservative | C5: Expected | D5: Strong | E5: Where it comes from
A6: Sales and profit by year (model year 1 = Oct 2026 - Sep 2027)
A7: Gross sales, year 1 | B7: ='36-Month Forecast'!AM120 | C7: ='36-Month Forecast'!AM254 | D7: ='36-Month Forecast'!AM388 | E7: 36-Month Forecast
A8: Gross sales, year 2 | B8: ='36-Month Forecast'!AN120 | C8: ='36-Month Forecast'!AN254 | D8: ='36-Month Forecast'!AN388
A9: Gross sales, year 3 | B9: ='36-Month Forecast'!AO120 | C9: ='36-Month Forecast'!AO254 | D9: ='36-Month Forecast'!AO388
A10: Net contribution, year 1 | B10: ='36-Month Forecast'!AM121 | C10: ='36-Month Forecast'!AM255 | D10: ='36-Month Forecast'!AM389 | E10: After platform, payment, print/POD and fulfilment costs
A11: Net contribution, year 2 | B11: ='36-Month Forecast'!AN121 | C11: ='36-Month Forecast'!AN255 | D11: ='36-Month Forecast'!AN389
A12: Net contribution, year 3 | B12: ='36-Month Forecast'!AO121 | C12: ='36-Month Forecast'!AO255 | D12: ='36-Month Forecast'!AO389
A13: Net operating result, year 1 | B13: ='36-Month Forecast'!AM126 | C13: ='36-Month Forecast'!AM260 | D13: ='36-Month Forecast'!AM394 | E13: Contribution - ads - operating costs - wave fixed costs
A14: Net operating result, year 2 | B14: ='36-Month Forecast'!AN126 | C14: ='36-Month Forecast'!AN260 | D14: ='36-Month Forecast'!AN394
A15: Net operating result, year 3 | B15: ='36-Month Forecast'!AO126 | C15: ='36-Month Forecast'!AO260 | D15: ='36-Month Forecast'!AO394
A16: One-time costs over 36 months (startup + wave launch + retail readiness) | B16: ='36-Month Forecast'!AP128+'36-Month Forecast'!AP129 | C16: ='36-Month Forecast'!AP262+'36-Month Forecast'!AP263 | D16: ='36-Month Forecast'!AP396+'36-Month Forecast'!AP397 | E16: Startup Costs; Retail Readiness Costs
A17: Inventory purchases over 36 months (board-book print runs) | B17: ='36-Month Forecast'!AP136 | C17: ='36-Month Forecast'!AP270 | D17: ='36-Month Forecast'!AP404 | E17: Sized from pre-sale orders
A18: Cumulative net result after one-time costs, month 36 | B18: ='36-Month Forecast'!AL131 | C18: ='36-Month Forecast'!AL265 | D18: ='36-Month Forecast'!AL399
A20: Cash and break-even
A21: Break-even: trailing-12-month result >= 0 from | B21: ='Break-even'!B8 | C21: ='Break-even'!C8 | D21: ='Break-even'!D8 | E21: Headline measure (Break-even tab)
A22: First month with a monthly operating result >= 0 | B22: ='Break-even'!B10 | C22: ='Break-even'!C10 | D22: ='Break-even'!D10
A23: Founder capital needed through month 36 (funding need) | B23: ='Break-even'!B13 | C23: ='Break-even'!C13 | D23: ='Break-even'!D13 | E23: Cash Flow: cumulative founder capital
A24: ...of which by Sep 2027 (month 12) | B24: ='Break-even'!B14 | C24: ='Break-even'!C14 | D24: ='Break-even'!D14
A25: Self-funding from (no founder capital after this month) | B25: ='Break-even'!B18 | C25: ='Break-even'!C18 | D25: ='Break-even'!D18
A26: Household-money cap passed in (placeholder cap) | B26: ='Break-even'!B20 | C26: ='Break-even'!C20 | D26: ='Break-even'!D20 | E26: Hard stop and re-forecast
A27: Total cash at month 36 (operating + tax reserve) | B27: ='Cash Flow'!AL32 | C27: ='Cash Flow'!AL63 | D27: ='Cash Flow'!AL94
A28: Operating balance vs 3-month reserve target, month 36 | B28: ='Cash Flow'!AL35 | C28: ='Cash Flow'!AL66 | D28: ='Cash Flow'!AL97 | E28: ops/ROUTINE.md reserve target
A30: Volume, anchors and mix
A31: Digital units per product per month at full ramp (site + Etsy + MoR) | B31: ='Assumptions'!$C$122*'Assumptions'!$C$123+'Assumptions'!$C$131*'Assumptions'!$C$132+'Assumptions'!$C$155*'Assumptions'!$C$156 | C31: ='Assumptions'!$D$122*'Assumptions'!$D$123+'Assumptions'!$D$131*'Assumptions'!$D$132+'Assumptions'!$D$155*'Assumptions'!$D$156 | D31: ='Assumptions'!$E$122*'Assumptions'!$E$123+'Assumptions'!$E$131*'Assumptions'!$E$132+'Assumptions'!$E$155*'Assumptions'!$E$156 | E31: Section 1.5 anchors: floor 2.5, Low 10, Base 30, breakout 75
A32: Orders, year 1 | B32: ='36-Month Forecast'!AM116 | C32: ='36-Month Forecast'!AM250 | D32: ='36-Month Forecast'!AM384
A33: Orders, year 3 | B33: ='36-Month Forecast'!AO116 | C33: ='36-Month Forecast'!AO250 | D33: ='36-Month Forecast'!AO384
A34: ...of which Etsy orders, year 3 | B34: ='36-Month Forecast'!AO34 | C34: ='36-Month Forecast'!AO168 | D34: ='36-Month Forecast'!AO302 | E34: Compare: strongest routine-card shop, 2,189 lifetime sales (DEMAND-CHECK)
A35: Orders in month 36 | B35: ='36-Month Forecast'!AL116 | C35: ='36-Month Forecast'!AL250 | D35: ='36-Month Forecast'!AL384
A36: Average gross sale per order, year 3 | B36: =IF('36-Month Forecast'!AO116=0,0,'36-Month Forecast'!AO120/'36-Month Forecast'!AO116) | C36: =IF('36-Month Forecast'!AO250=0,0,'36-Month Forecast'!AO254/'36-Month Forecast'!AO250) | D36: =IF('36-Month Forecast'!AO384=0,0,'36-Month Forecast'!AO388/'36-Month Forecast'!AO384)
A37: Email subscribers at month 36 | B37: ='36-Month Forecast'!AL114 | C37: ='36-Month Forecast'!AL248 | D37: ='36-Month Forecast'!AL382
A38: Share of 36-month contribution from digital (site, Etsy, MoR, course) | B38: =IF('36-Month Forecast'!AP121=0,0,('36-Month Forecast'!AP28+'36-Month Forecast'!AP38+'36-Month Forecast'!AP68+'36-Month Forecast'!AP78)/'36-Month Forecast'!AP121) | C38: =IF('36-Month Forecast'!AP255=0,0,('36-Month Forecast'!AP162+'36-Month Forecast'!AP172+'36-Month Forecast'!AP202+'36-Month Forecast'!AP212)/'36-Month Forecast'!AP255) | D38: =IF('36-Month Forecast'!AP389=0,0,('36-Month Forecast'!AP296+'36-Month Forecast'!AP306+'36-Month Forecast'!AP336+'36-Month Forecast'!AP346)/'36-Month Forecast'!AP389)
A39: Share from print-on-demand books (KDP, IngramSpark) | B39: =IF('36-Month Forecast'!AP121=0,0,('36-Month Forecast'!AP48+'36-Month Forecast'!AP58)/'36-Month Forecast'!AP121) | C39: =IF('36-Month Forecast'!AP255=0,0,('36-Month Forecast'!AP182+'36-Month Forecast'!AP192)/'36-Month Forecast'!AP255) | D39: =IF('36-Month Forecast'!AP389=0,0,('36-Month Forecast'!AP316+'36-Month Forecast'!AP326)/'36-Month Forecast'!AP389)
A40: Share from the board book (gated option; 0 in base) | B40: =IF('36-Month Forecast'!AP121=0,0,'36-Month Forecast'!AP88/'36-Month Forecast'!AP121) | C40: =IF('36-Month Forecast'!AP255=0,0,'36-Month Forecast'!AP222/'36-Month Forecast'!AP255) | D40: =IF('36-Month Forecast'!AP389=0,0,'36-Month Forecast'!AP356/'36-Month Forecast'!AP389)
A41: Share from the school/group wave (overlay only; 0 in base) | B41: =IF('36-Month Forecast'!AP121=0,0,'36-Month Forecast'!AP99/'36-Month Forecast'!AP121) | C41: =IF('36-Month Forecast'!AP255=0,0,'36-Month Forecast'!AP233/'36-Month Forecast'!AP255) | D41: =IF('36-Month Forecast'!AP389=0,0,'36-Month Forecast'!AP367/'36-Month Forecast'!AP389)
A42: Share from retail and wholesale (0 in base) | B42: =IF('36-Month Forecast'!AP121=0,0,'36-Month Forecast'!AP109/'36-Month Forecast'!AP121) | C42: =IF('36-Month Forecast'!AP255=0,0,'36-Month Forecast'!AP243/'36-Month Forecast'!AP255) | D42: =IF('36-Month Forecast'!AP389=0,0,'36-Month Forecast'!AP377/'36-Month Forecast'!AP389)
A43: Board-book pre-sale copies (only if the board book is switched on) | B43: ='36-Month Forecast'!$B$12 | C43: ='36-Month Forecast'!$B$146 | D43: ='36-Month Forecast'!$B$280 | E43: Gated option
A44: ...go line: copies needed to fund the planned run | B44: ='36-Month Forecast'!$B$13 | C44: ='36-Month Forecast'!$B$147 | D44: ='36-Month Forecast'!$B$281 | E44: Below this line: refund, keep the POD paperback
A45: ...go (1) / no-go (0) | B45: ='36-Month Forecast'!$B$14 | C45: ='36-Month Forecast'!$B$148 | D45: ='36-Month Forecast'!$B$282
A46: Board-book copies at the 3PL, month 36 | B46: ='36-Month Forecast'!AL138 | C46: ='36-Month Forecast'!AL272 | D46: ='36-Month Forecast'!AL406 | E46: Cash tied up in stock
A48: How to use
A49: 1. Edit blue cells only. Yellow cells on Assumptions are the levers that move results most (first-sale month, sales per product, include flags, IngramSpark discount, cost position).
A50: 2. Base plan = lean path: cost position 0 (low-end quotes) and every GATED one-time item at Include = 0. Set the cost position to 0.5 to see mid-point costs.
A51: 3. The school wave, the board book and retail are OFF in every scenario. Switch an include flag to 1 to see it as an overlay; school only if counsel clears it in writing.
A52: 4. Every [VERIFY] figure must be checked on the live page or a written quote before money is committed.
A53: 5. Replace the sales-per-product and units-per-title guesses with the first 90 days of real data from the Friday scorecard.
A55: Chart data: net operating result by model year
A56: Year 1 | B56: =B13 | C56: =C13 | D56: =D13
A57: Year 2 | B57: =B14 | C57: =C14 | D57: =D14
A58: Year 3 | B58: =B15 | C58: =C15 | D58: =D15

Sheet Assumptions
A1: Assumptions: every input in the model
A2: Blue = editable input. Yellow fill = key scenario lever. Black = formula. Green = link to another tab. Status: Repo = figure found in a repository file (most are themselves marked UNVERIFIED there); Assumption = planning input chosen for this model; [VERIFY] = outside fact not in the repo, check before relying on it.
A5: ID | B5: Input | C5: Value / Conservative | D5: Expected | E5: Strong | F5: Unit | G5: Source / basis | H5: Status
A7: 1. General settings
A8: start | B8: Model start month (month 1; costs start here) | C8: 46296 | F8: month | G8: Plan dated Sept 28, 2026. Setup costs (trademark, copyright, attorneys) begin in October 2026. | H8: Repo
A9: first_sale | B9: First month any listing can take money (Gate A met) | C9: 3 | F9: month # | G9: Gate A (section 5.12): business bank account open, employment counsel's go-ahead, GL insurance bound and the publish safeguards built. As of Sept 28, 2026 none is done, so the model assumes Gate A by the end of Nov 2026 and first sales in Dec 2026 (month 3). Each month of slip moves every channel back one month. | H9: Assumption
A10: pos | B10: Cost position inside every Low-High range (0 = low, 1 = high) | C10: 0 | F10: 0-1 | G10: Base plan = lean path: low-end quotes (0). Mid-point (0.5) and high end (1) are shown as sensitivities in section 3.9. Drives the Model column on Startup Costs, Monthly Operating Costs and Retail Readiness Costs. | H10: Assumption
A11: ramp | B11: Months for a new listing to reach full sales rate (review ramp) | C11: 6 | F11: months | G11: A new faceless shop starts with zero reviews against incumbents with 2,000-11,000 (marketing/DEMAND-CHECK.md, 'One honest warning'). | H11: Assumption
A12: mdtax | B12: Maryland sales tax on direct (own-site) sales | C12: 0.06 | F12: % of price | G12: commerce/storefront-setup-guide.md A3 (UNVERIFIED). Collected on top of price and remitted: pass-through, never counted as revenue. | H12: Repo [VERIFY]
A13: refund | B13: Refund and chargeback allowance, direct digital sales | C13: 0.02 | F13: % of price | G13: ops/GAPS-ROUND-2.md G2-12: first refund request under about $15 is refunded automatically. | H13: Assumption
A14: refund_course | B14: Refund allowance, 30-Day Screen Reset (money-back guarantee) | C14: 0.05 | F14: % of price | G14: DEMAND-CHECK course row: 'Add a money-back guarantee'. | H14: Assumption
A15: taxres | B15: Tax reserve (% of cumulative profit to date, after one-time costs) | C15: 0.25 | F15: % | G15: finance/TAX-AUTOPILOT.md §2: accountant picks the rate; 25-30% is common. Reserved only against cumulative profit, because a single-member LLC's losses pass through to the founder's return; the accountant sets the §195 startup-cost treatment. | H15: Repo range
A16: open | B16: Opening cash in the business account | C16: 0 | F16: $ | G16: finance/BANKING.md: the Chase checking account is closed; a new no-fee account opens empty. | H16: Repo
A17: owner | B17: Planned owner capital contribution in month 1 (the forecast adds any further top-up needed) | C17: 0 | F17: $ | G17: Cash Flow adds a founder top-up in any month the operating account would go below zero, so the funding need is always visible. | H17: Assumption
A18: card | B18: Existing balance on the Chase business card (an LLC liability), paid in month 1 | C18: 0 | F18: $ | G18: finance/BANKING.md: the Chase business card is still open. Balance not in the repo: founder to enter. | H18: Founder to enter
A19: cap | B19: Household-money cap: most founder capital the business may take (placeholder) | C19: 12000 | F19: $ | G19: ops/GAPS-ROUND-2.md G2-10 asks the founder to write down a cap and a review date; neither is set. $12,000 is a placeholder only. Hard stop: when cumulative founder capital reaches the cap, all non-deadline spending stops and the plan is re-forecast. | H19: Founder to set
... A21: resmo | B21: Cash reserve target (months of fixed costs) | C21: 3 | F21: months | G21: ops/ROUTINE.md weekly scorecard ('3-month reserve target'); BLIND-SPOTS #20 says 2-3 months. | H21: Repo
A23: 2. Platform fees and royalties (used by Unit Economics)
A24: shop_pct | B24: Shopify Payments card rate | C24: 0.029 | F24: % of price | G24: commerce/storefront-setup-guide.md §1; finance/money-and-tax-setup.md fees table (Basic plan, UNVERIFIED). | H24: Repo [VERIFY]
A25: shop_fix | B25: Shopify Payments fixed fee | C25: 0.3 | F25: $ per order | G25: Same source. | H25: Repo [VERIFY]
A26: etsy_tx | B26: Etsy transaction fee | C26: 0.065 | F26: % of price | G26: storefront-setup-guide §10 (UNVERIFIED). | H26: Repo [VERIFY]
A27: etsy_pay | B27: Etsy payment processing (US) | C27: 0.03 | F27: % of price | G27: Same source. | H27: Repo [VERIFY]
A28: etsy_payfix | B28: Etsy payment processing fixed fee | C28: 0.25 | F28: $ per order | G28: Same source. | H28: Repo [VERIFY]
A29: etsy_list | B29: Etsy listing fee (renews on each sale) | C29: 0.2 | F29: $ per sale | G29: Same source. | H29: Repo [VERIFY]
A30: etsy_oa | B30: Etsy Offsite Ads fee when an ad drives the sale | C30: 0.15 | F30: % of price | G30: Same source: 15%, or 12% and mandatory above $10,000 in 12 months. | H30: Repo [VERIFY]
A31: etsy_oashare | B31: Share of Etsy sales that come through Offsite Ads | C31: 0.1 | F31: % of Etsy sales | G31: No data yet; check the Etsy statement after 90 days. | H31: Assumption
A32: kdp_roy | B32: KDP paperback royalty rate (list price $9.99 or more) | C32: 0.6 | F32: % of list | G32: storefront-setup-guide §6: 60% at $9.99+ since June 10, 2025 (UNVERIFIED). | H32: Repo [VERIFY]
A33: kdp_base | B33: KDP print cost: fixed part | C33: 1 | F33: $ per copy | G33: products/*/listing.json price_notes: $1.00 + $0.07/page premium color. | H33: Repo [VERIFY]
A34: kdp_color | B34: KDP print cost: premium color, per page | C34: 0.07 | F34: $ per page | G34: Same source. KDP may price short color books at a flat rate; confirm in the calculator. | H34: Repo [VERIFY]
A35: kdp_bw_flat | B35: KDP print cost: black-and-white paperback, 24-108 pages (flat) | C35: 2.3 | F35: $ per copy | G35: products/guide-100-plays/listing.json: KDP's flat $2.30 for 24-108 B/W pages (82-page, 8 x 10 in book). Check whether 8 x 10 counts as large trim, which may cost more. | H35: Repo [VERIFY]
... A54: tee_pod | B54: Adult tee: POD base cost incl. print | C54: 12.5 | F54: $ per unit | G54: Not in the repo; shipping assumed charged to the buyer. Tee is weight 0 until trademark clearance (Wave 3). | H54: [VERIFY]
A56: 3. Physical products: board book (gated option) and retail stock
A57: bb_price | B57: Board book retail price (Up! Go! More!) | C57: 12.99 | F57: $ | G57: DEMAND-CHECK §4 rule 9; board-up-go-more/listing.json. | H57: Repo
A58: min_run | B58: Planned first offset run | C58: 1000 | F58: copies | G58: BLIND-SPOTS #11: quotes at 500, 1,000 and 2,500 copies (5,000 added for a retail edition). | H58: Assumption
A59: ID | B59: Offset quote table (run size -> print cost per copy) | C59: Run size | D59: Cost per copy | F59: Unit | G59: Source / basis | H59: Status
A60: quote_500 | B60: Quote at 500 copies | C60: 500 | D60: 5.5 | F60: $ per copy | G60: Above the BLIND-SPOTS range at a short run; no quote exists. | H60: Assumption [VERIFY]
A61: quote_1000 | B61: Quote at 1,000 copies | C61: 1000 | D61: 4 | F61: $ per copy | G61: BLIND-SPOTS #11: $1.80-$4 at 1,000-3,000 copies; a 1,000-copy run sits at the high end. | H61: Repo [VERIFY]
A62: quote_2500 | B62: Quote at 2,500 copies | C62: 2500 | D62: 2.2 | F62: $ per copy | G62: Interpolated toward $1.80 at 3,000 copies (BLIND-SPOTS #11). | H62: Assumption [VERIFY]
A63: quote_5000 | B63: Quote at 5,000 copies | C63: 5000 | D63: 1.6 | F63: $ per copy | G63: Below the repo range; retail-edition planning figure only. | H63: Assumption [VERIFY]
A64: bb_print | B64: Offset print cost per copy used in model (quote at the planned run size) | C64: =LOOKUP('Assumptions'!$C$58,'Assumptions'!$C$60:$C$63,'Assumptions'!$D$60:$D$63) | F64: $ per copy | G64: Largest quoted run size at or below the planned run. | H64: Formula
A65: freight | B65: Freight, duties and warehouse receiving | C65: 0.25 | F65: % of print cost | G65: BLIND-SPOTS #11 asks quotes to cover shipping, duties and warehouse fees; no figure given. | H65: Assumption [VERIFY]
A66: landed | B66: Landed cost per copy (print + freight/duties) | C66: ='Assumptions'!$C$64*(1+'Assumptions'!$C$65) | F66: $ per copy | G66: Cost rules by channel (section 3.8): own site/FBA at or below 35% of retail; Faire/wholesale 25%; chain 20%. | H66: Formula
A67: pick | B67: 3PL pick, pack and ship-handling per single order | C67: 3.5 | F67: $ per order | G67: Not in the repo; postage is a separate line (ship_sub). | H67: [VERIFY]
A68: whs_handle | B68: 3PL handling per unit on wholesale cartons | C68: 1 | F68: $ per unit | G68: Not in the repo. | H68: [VERIFY]
A69: tpl_min | B69: 3PL monthly minimum / storage | C69: 150 | F69: $ per month | G69: Not in the repo; replace with written 3PL quotes (many 3PLs set higher minimums). | H69: [VERIFY]
A70: seller_central | B70: Amazon Seller Central Professional plan | C70: 39.99 | F70: $ per month | G70: storefront-setup-guide §19 (UNVERIFIED). | H70: Repo [VERIFY]
A71: buffer | B71: Print buffer over pre-sale units | C71: 0.4 | F71: % | G71: BLIND-SPOTS #16: 'Order what sold plus 30-50%'. | H71: Repo range
A72: presale_len | B72: Pre-sale length before the print decision | C72: 3 | F72: months | G72: BLIND-SPOTS #16: three-month pre-sale. | H72: Repo
A73: presale_buf | B73: Buffer in the pre-sale funding goal | C73: 0.15 | F73: % | G73: BLIND-SPOTS #16: goal = printing + shipping + duties + fees + delivery + about 15% buffer. | H73: Repo
A74: presale_fail | B74: Cost of a pre-sale that misses the go line (card fees not returned on refunds) | C74: 100 | F74: $ | G74: Assumption. Below the go line the pre-sale is refunded in full and the talk-along paperback stays on print-on-demand (section 3.10 rule 4). | H74: Assumption
A75: reorder_lead | B75: Reorder lead time (print + freight) | C75: 3 | F75: months | G75: Not in the repo; offset printing abroad plus ocean freight commonly takes 2-4 months. | H75: Assumption [VERIFY]
A76: school_setup | B76: School/group wave one-time setup (TPT Premium, purchasing kit, host-kit build, counsel review of terms, fraud-check SOP) | C76: 739 | F76: $ | G76: TPT Premium $59.95/yr and purchasing kit $0-50 (MARKETING-PLAYBOOK); host kit $0-100; counsel review of license and PO terms about $500 (assumption). | H76: Repo + Assumption
A77: retail_lead | B77: Retail readiness spend lead time before retail launch | C77: 3 | F77: months | G77: Readiness checklist must be done before pitching (AMAZON-AND-RETAIL-ROADMAP B5). | H77: Assumption
A79: 4. Payout delay by channel (months after the sale month)
A80: lag_SITE | B80: Payout delay: Own site: printables and PDFs (Shopify) | C80: 0 | F80: months | G80: Shopify Payments pays out within days (storefront guide A6). | H80: Repo
A81: lag_ETSY | B81: Payout delay: Etsy: printables | C81: 1 | F81: months | G81: Etsy deposits on a schedule, but new sellers face a 14-day hold and a possible rolling reserve (section 5 risk 1); one month assumed. | H81: Assumption
A82: lag_KDP | B82: Payout delay: Amazon KDP: paperbacks | C82: 2 | F82: months | G82: KDP pays about 60 days after month end (A6). | H82: Repo
A83: lag_INGRAM | B83: Payout delay: IngramSpark: paperbacks to bookstores and libraries | C83: 3 | F83: months | G83: IngramSpark pays about 90 days after month end (A6, UNVERIFIED). | H83: Repo
A84: lag_MOR | B84: Payout delay: International digital via merchant of record (Gumroad) | C84: 0 | F84: months | G84: Gumroad pays weekly (A6, UNVERIFIED). | H84: Repo
A85: lag_COURSE | B85: Payout delay: 30-Day Screen Reset written course (Wave 2) | C85: 0 | F85: months | G85: Sold on Shopify; same payout timing. | H85: Repo
A86: lag_BOARD | B86: Payout delay: Board book: pre-sale, then 3PL and Amazon FBA (gated option; off in base) | C86: 0 | F86: months | G86: Shopify within days; Seller Central about every 14 days (A6). | H86: Repo
A87: lag_SCHOOL | B87: Payout delay: School and group licenses + TPT (overlay only if counsel clears in writing; off in base) | C87: 1 | F87: months | G87: TPT pays monthly; school invoices are net-30 (commerce/PAYMENTS.md). | H87: Repo
A88: lag_RETAIL | B88: Payout delay: Retail and wholesale: Faire, Walmart Marketplace (off in base) | C88: 1 | F88: months | G88: Faire/Walmart settlement timing UNVERIFIED; one month assumed. | H88: Assumption
A90: 5. Seasonality index by calendar month (the forecast divides by the 12-month average, so the index always averages 1.00)
A91: ID | B91: Calendar month | C91: Consumer index | D91: School / group index | F91: Unit | G91: Source / basis | H91: Status
A92: season_1 | B92: Jan | C92: 1.25 | D92: 1.1 | F92: index | G92: Shape follows the repo calendar: January Reset launch (Wave 2), spring Screen-Free Week, summer kits listed in March, holiday gifts Nov-Dec (BLIND-SPOTS #2, #6; DEMAND-CHECK rule 7). School index follows the school year. Levels are assumptions. | H92: Assumption
A93: season_2 | B93: Feb | C93: 0.9 | D93: 1 | F93: index | H93: Assumption
A94: season_3 | B94: Mar | C94: 1 | D94: 1 | F94: index | H94: Assumption
A95: season_4 | B95: Apr | C95: 1.05 | D95: 0.9 | F95: index | H95: Assumption
A96: season_5 | B96: May | C96: 0.95 | D96: 0.7 | F96: index | H96: Assumption
A97: season_6 | B97: Jun | C97: 1 | D97: 0.4 | F97: index | H97: Assumption
A98: season_7 | B98: Jul | C98: 0.95 | D98: 0.6 | F98: index | H98: Assumption
A99: season_8 | B99: Aug | C99: 0.85 | D99: 1.3 | F99: index | H99: Assumption
A100: season_9 | B100: Sep | C100: 0.85 | D100: 1.4 | F100: index | H100: Assumption
A101: season_10 | B101: Oct | C101: 0.95 | D101: 1.2 | F101: index | H101: Assumption
A102: season_11 | B102: Nov | C102: 1.3 | D102: 1 | F102: index | H102: Assumption
A103: season_12 | B103: Dec | C103: 1.35 | D103: 0.7 | F103: index | H103: Assumption
A105: 6. Scenario drivers: traffic -> conversion -> orders -> order value (yellow = key levers)
A106: ID | B106: Driver | C106: Conservative | D106: Expected | E106: Strong | F106: Unit | G106: Source / basis | H106: Status
A108: 6a. Digital catalog size (drives the own site, Etsy and the merchant of record)
A109: ID | B109: Driver | C109: Conservative | D109: Expected | E109: Strong | F109: Unit | G109: Source / basis | H109: Status
A110: prod_start | B110: Digital products live in the first-sale month | C110: 5 | D110: 5 | E110: 5 | F110: products | G110: The launch-first five (ops/QUEUE.md; section 1.5 counts them as 5 listings). | H110: Repo
A111: prod_add | B111: Digital products added per month | C111: 0.5 | D111: 0.75 | E111: 1 | F111: products | G111: Publish cap is 5 new Etsy listings a week (ops/ROUTINE.md), but each product needs demand evidence first; weak items fold into bundles. | H111: Assumption
A112: prod_cap | B112: Most digital products live at once | C112: 12 | D112: 15 | E112: 20 | F112: products | G112: Kill rule and bundling keep the catalog small (ops/QUEUE.md). | H112: Assumption
A114: 6b. Scenario drivers by channel (yellow = key levers)
A115: ID | B115: Driver | C115: Conservative | D115: Expected | E115: Strong | F115: Unit | G115: Source / basis | H115: Status
B116: Own site: printables and PDFs (Shopify) | driver = Product-months live (products x sales index x season)
A117: SITE_inc | B117: Include in scenario (1 = yes, 0 = no) | C117: 1 | D117: 1 | E117: 1 | F117: flag | H117: Assumption
A118: SITE_launch | B118: Launch month (model month #; never earlier than the first-sale month) | C118: 3 | D118: 3 | E118: 3 | F118: month # | G118: Launch-first five (ops/QUEUE.md). Listings are built Oct-Nov; money can be taken only from the first-sale month (Gate A). | H118: Repo timing
A119: SITE_g1 | B119: Monthly growth in sales per product, year 1 | C119: 0 | D119: 0.005 | E119: 0.01 | F119: % per month | H119: Assumption
A120: SITE_g2 | B120: Monthly growth in sales per product, year 2 | C120: 0 | D120: 0.005 | E120: 0.01 | F120: % per month | H120: Assumption
A121: SITE_g3 | B121: Monthly growth in sales per product, year 3 | C121: 0 | D121: 0 | E121: 0.005 | F121: % per month | H121: Assumption
A122: SITE_cvr | B122: Orders per live product per month at full ramp | C122: 3 | D122: 4 | E122: 8 | F122: orders | G122: Anchored to section 1.5: all digital channels together sell about 10 (Conservative = section 1 Low), 15 (Expected) or 30 (Strong = section 1 Base) units per product per month at full ramp. | H122: Assumption
A123: SITE_items | B123: Items per order | C123: 1.15 | D123: 1.25 | E123: 1.35 | F123: items | H123: Assumption
A124: site_cvr | B124: Own-site conversion rate (used only to estimate sessions for list sign-ups) | C124: 0.01 | D124: 0.015 | E124: 0.02 | F124: % of sessions | G124: MARKETING-PLAYBOOK traffic checklist: working target 1.5-3% site conversion. | H124: Repo range
B125: Etsy: printables | driver = Product-months live (products x sales index x season)
A126: ETSY_inc | B126: Include in scenario (1 = yes, 0 = no) | C126: 1 | D126: 1 | E126: 1 | F126: flag | H126: Assumption
A127: ETSY_launch | B127: Launch month (model month #; never earlier than the first-sale month) | C127: 3 | D127: 3 | E127: 3 | F127: month # | G127: Launch-first five on Etsy + site (DEMAND-CHECK §3); first-sale month applies. | H127: Repo timing
A128: ETSY_g1 | B128: Monthly growth in sales per product, year 1 | C128: 0 | D128: 0.005 | E128: 0.01 | F128: % per month | H128: Assumption
A129: ETSY_g2 | B129: Monthly growth in sales per product, year 2 | C129: 0 | D129: 0.005 | E129: 0.01 | F129: % per month | H129: Assumption
...

Sheet Unit Economics
A1: Unit economics: net to AlphaPlay LLC per unit, by product and channel
A2: Net per unit = Price x (1 - platform % - payment % - refund %) - fixed fees - print/POD/landed cost - fulfilment. Sales tax and VAT are pass-through and never counted as revenue. Blue prices are editable; other channels link to them.
A5: Channel code | B5: Product | C5: Channel / route | D5: Wave | E5: Price to customer ($) | F5: Platform / marketplace fee % | G5: Platform fixed fee ($/unit) | H5: Payment processing % | I5: Payment fixed fee ($) | J5: Refund / deduction allowance % | K5: Print, POD or landed cost ($/unit) | L5: Fulfilment ($/unit) | M5: Net per unit ($) | N5: Net margin % | O5: Inventory cost paid up front ($/unit) | P5: Mix weight in channel | Q5: Sales tax / VAT handling | R5: Source / notes
A6: SITE | B6: Visual routine cards (200+ editable; 0-5 set at launch, 5-12 set added free when G1 clears) | C6: Own site (Shopify) | D6: 1 | E6: 6.5 | F6: 0 | G6: 0 | H6: ='Assumptions'!$C$24 | I6: ='Assumptions'!$C$25 | J6: ='Assumptions'!$C$13 | K6: 0 | L6: 0 | M6: =E6*(1-F6-H6-J6)-G6-I6-K6-L6 | N6: =IF(E6=0,0,M6/E6) | O6: 0 | P6: 25 | Q6: Shopify Tax adds MD 6% at checkout; AlphaPlay remits (pass-through, not revenue) | R6: Everyday price $6.50 under BRAND.md 'Honest pricing' (no anchor or permanent sale).
A7: SITE | B7: "I'm bored" play cards (150, age-banded) | C7: Own site (Shopify) | D7: 1 | E7: 6.5 | F7: 0 | G7: 0 | H7: ='Assumptions'!$C$24 | I7: ='Assumptions'!$C$25 | J7: ='Assumptions'!$C$13 | K7: 0 | L7: 0 | M7: =E7*(1-F7-H7-J7)-G7-I7-K7-L7 | N7: =IF(E7=0,0,M7/E7) | O7: 0 | P7: 15 | Q7: Shopify Tax adds MD 6% at checkout; AlphaPlay remits (pass-through, not revenue) | R7: DEMAND-CHECK §3 #2.
A8: SITE | B8: Play-First Family Kit (2-5 pages at launch; 5-12 pages added free when G1 clears) | C8: Own site (Shopify) | D8: 1 | E8: 11 | F8: 0 | G8: 0 | H8: ='Assumptions'!$C$24 | I8: ='Assumptions'!$C$25 | J8: ='Assumptions'!$C$13 | K8: 0 | L8: 0 | M8: =E8*(1-F8-H8-J8)-G8-I8-K8-L8 | N8: =IF(E8=0,0,M8/E8) | O8: 0 | P8: 20 | Q8: Shopify Tax adds MD 6% at checkout; AlphaPlay remits (pass-through, not revenue) | R8: DEMAND-CHECK §3 #3.
A9: SITE | B9: Toddler busy book printable (120-150 pages) | C9: Own site (Shopify) | D9: 1 | E9: 11.99 | F9: 0 | G9: 0 | H9: ='Assumptions'!$C$24 | I9: ='Assumptions'!$C$25 | J9: ='Assumptions'!$C$13 | K9: 0 | L9: 0 | M9: =E9*(1-F9-H9-J9)-G9-I9-K9-L9 | N9: =IF(E9=0,0,M9/E9) | O9: 0 | P9: 18 | Q9: Shopify Tax adds MD 6% at checkout; AlphaPlay remits (pass-through, not revenue) | R9: Everyday price $11.99 under BRAND.md 'Honest pricing' (DEMAND-CHECK §3 #4 street level).
A10: SITE | B10: 100 Screen-Free Plays (PDF) | C10: Own site (Shopify) | D10: 1 | E10: 9.99 | F10: 0 | G10: 0 | H10: ='Assumptions'!$C$24 | I10: ='Assumptions'!$C$25 | J10: ='Assumptions'!$C$13 | K10: 0 | L10: 0 | M10: =E10*(1-F10-H10-J10)-G10-I10-K10-L10 | N10: =IF(E10=0,0,M10/E10) | O10: 0 | P10: 10 | Q10: Shopify Tax adds MD 6% at checkout; AlphaPlay remits (pass-through, not revenue) | R10: DEMAND-CHECK §3 #5.
A11: SITE | B11: Screen-Free Car Ride & Waiting Pack | C11: Own site (Shopify) | D11: 1 | E11: 6 | F11: 0 | G11: 0 | H11: ='Assumptions'!$C$24 | I11: ='Assumptions'!$C$25 | J11: ='Assumptions'!$C$13 | K11: 0 | L11: 0 | M11: =E11*(1-F11-H11-J11)-G11-I11-K11-L11 | N11: =IF(E11=0,0,M11/E11) | O11: 0 | P11: 5 | Q11: Shopify Tax adds MD 6% at checkout; AlphaPlay remits (pass-through, not revenue) | R11: DEMAND-CHECK §3 first alternate.
A12: SITE | B12: First-words flash cards (printable) | C12: Own site (Shopify) | D12: 1 | E12: 6.99 | F12: 0 | G12: 0 | H12: ='Assumptions'!$C$24 | I12: ='Assumptions'!$C$25 | J12: ='Assumptions'!$C$13 | K12: 0 | L12: 0 | M12: =E12*(1-F12-H12-J12)-G12-I12-K12-L12 | N12: =IF(E12=0,0,M12/E12) | O12: 0 | P12: 3 | Q12: Shopify Tax adds MD 6% at checkout; AlphaPlay remits (pass-through, not revenue) | R12: DEMAND-CHECK §2 #3.
A13: SITE | B13: ALPHAPLAY Spelling Games printable (G1; trademark-use product) | C13: Own site (Shopify) | D13: 1 | E13: 6 | F13: 0 | G13: 0 | H13: ='Assumptions'!$C$24 | I13: ='Assumptions'!$C$25 | J13: ='Assumptions'!$C$13 | K13: 0 | L13: 0 | M13: =E13*(1-F13-H13-J13)-G13-I13-K13-L13 | N13: =IF(E13=0,0,M13/E13) | O13: 0 | P13: 0 | Q13: Shopify Tax adds MD 6% at checkout; AlphaPlay remits (pass-through, not revenue) | R13: ops/QUEUE.md #1. Weight 0: its job is to protect the mark, it is G1 pending counsel, and the demand check found no sales evidence.
A14: SITE | B14: Adult tee (POD, 2-3 cleared designs max) | C14: Own site (Shopify) + POD partner | D14: 1 | E14: 27 | F14: 0 | G14: 0 | H14: ='Assumptions'!$C$24 | I14: ='Assumptions'!$C$25 | J14: ='Assumptions'!$C$13 | K14: ='Assumptions'!$C$54 | L14: 0 | M14: =E14*(1-F14-H14-J14)-G14-I14-K14-L14 | N14: =IF(E14=0,0,M14/E14) | O14: 0 | P14: 0 | Q14: Shopify Tax adds MD 6% at checkout; AlphaPlay remits (pass-through, not revenue) | R14: DEMAND-CHECK tees row: $27. Weight 0 until the designs clear trademark review (Wave 3).
A15: ETSY | B15: Visual routine cards (200+ editable; 0-5 set at launch, 5-12 set added free when G1 clears) | C15: Etsy | D15: 1 | E15: =E6 | F15: ='Assumptions'!$C$26+'Assumptions'!$C$30*'Assumptions'!$C$31 | G15: ='Assumptions'!$C$29 | H15: ='Assumptions'!$C$27 | I15: ='Assumptions'!$C$28 | J15: ='Assumptions'!$C$13 | K15: 0 | L15: 0 | M15: =E15*(1-F15-H15-J15)-G15-I15-K15-L15 | N15: =IF(E15=0,0,M15/E15) | O15: 0 | P15: 25 | Q15: Etsy is marketplace facilitator: collects and remits | R15: Price linked to the own-site row.
A16: ETSY | B16: "I'm bored" play cards (150, age-banded) | C16: Etsy | D16: 1 | E16: =E7 | F16: ='Assumptions'!$C$26+'Assumptions'!$C$30*'Assumptions'!$C$31 | G16: ='Assumptions'!$C$29 | H16: ='Assumptions'!$C$27 | I16: ='Assumptions'!$C$28 | J16: ='Assumptions'!$C$13 | K16: 0 | L16: 0 | M16: =E16*(1-F16-H16-J16)-G16-I16-K16-L16 | N16: =IF(E16=0,0,M16/E16) | O16: 0 | P16: 15 | Q16: Etsy is marketplace facilitator: collects and remits | R16: Price linked to the own-site row.
A17: ETSY | B17: Play-First Family Kit (2-5 pages at launch; 5-12 pages added free when G1 clears) | C17: Etsy | D17: 1 | E17: =E8 | F17: ='Assumptions'!$C$26+'Assumptions'!$C$30*'Assumptions'!$C$31 | G17: ='Assumptions'!$C$29 | H17: ='Assumptions'!$C$27 | I17: ='Assumptions'!$C$28 | J17: ='Assumptions'!$C$13 | K17: 0 | L17: 0 | M17: =E17*(1-F17-H17-J17)-G17-I17-K17-L17 | N17: =IF(E17=0,0,M17/E17) | O17: 0 | P17: 20 | Q17: Etsy is marketplace facilitator: collects and remits | R17: Price linked to the own-site row.
A18: ETSY | B18: Toddler busy book printable (120-150 pages) | C18: Etsy | D18: 1 | E18: =E9 | F18: ='Assumptions'!$C$26+'Assumptions'!$C$30*'Assumptions'!$C$31 | G18: ='Assumptions'!$C$29 | H18: ='Assumptions'!$C$27 | I18: ='Assumptions'!$C$28 | J18: ='Assumptions'!$C$13 | K18: 0 | L18: 0 | M18: =E18*(1-F18-H18-J18)-G18-I18-K18-L18 | N18: =IF(E18=0,0,M18/E18) | O18: 0 | P18: 18 | Q18: Etsy is marketplace facilitator: collects and remits | R18: Price linked to the own-site row.
A19: ETSY | B19: 100 Screen-Free Plays (PDF) | C19: Etsy | D19: 1 | E19: =E10 | F19: ='Assumptions'!$C$26+'Assumptions'!$C$30*'Assumptions'!$C$31 | G19: ='Assumptions'!$C$29 | H19: ='Assumptions'!$C$27 | I19: ='Assumptions'!$C$28 | J19: ='Assumptions'!$C$13 | K19: 0 | L19: 0 | M19: =E19*(1-F19-H19-J19)-G19-I19-K19-L19 | N19: =IF(E19=0,0,M19/E19) | O19: 0 | P19: 10 | Q19: Etsy is marketplace facilitator: collects and remits | R19: Price linked to the own-site row.
A20: ETSY | B20: Screen-Free Car Ride & Waiting Pack | C20: Etsy | D20: 1 | E20: =E11 | F20: ='Assumptions'!$C$26+'Assumptions'!$C$30*'Assumptions'!$C$31 | G20: ='Assumptions'!$C$29 | H20: ='Assumptions'!$C$27 | I20: ='Assumptions'!$C$28 | J20: ='Assumptions'!$C$13 | K20: 0 | L20: 0 | M20: =E20*(1-F20-H20-J20)-G20-I20-K20-L20 | N20: =IF(E20=0,0,M20/E20) | O20: 0 | P20: 5 | Q20: Etsy is marketplace facilitator: collects and remits | R20: Price linked to the own-site row.
A21: ETSY | B21: First-words flash cards (printable) | C21: Etsy | D21: 1 | E21: =E12 | F21: ='Assumptions'!$C$26+'Assumptions'!$C$30*'Assumptions'!$C$31 | G21: ='Assumptions'!$C$29 | H21: ='Assumptions'!$C$27 | I21: ='Assumptions'!$C$28 | J21: ='Assumptions'!$C$13 | K21: 0 | L21: 0 | M21: =E21*(1-F21-H21-J21)-G21-I21-K21-L21 | N21: =IF(E21=0,0,M21/E21) | O21: 0 | P21: 3 | Q21: Etsy is marketplace facilitator: collects and remits | R21: Price linked to the own-site row.
A22: ETSY | B22: ALPHAPLAY Spelling Games printable (G1; trademark-use product) | C22: Etsy | D22: 1 | E22: =E13 | F22: ='Assumptions'!$C$26+'Assumptions'!$C$30*'Assumptions'!$C$31 | G22: ='Assumptions'!$C$29 | H22: ='Assumptions'!$C$27 | I22: ='Assumptions'!$C$28 | J22: ='Assumptions'!$C$13 | K22: 0 | L22: 0 | M22: =E22*(1-F22-H22-J22)-G22-I22-K22-L22 | N22: =IF(E22=0,0,M22/E22) | O22: 0 | P22: 0 | Q22: Etsy is marketplace facilitator: collects and remits | R22: Price linked to the own-site row.
A23: MOR | B23: Visual routine cards (200+ editable; 0-5 set at launch, 5-12 set added free when G1 clears) | C23: Gumroad (merchant of record), buyers outside the US | D23: 1-2 | E23: =E6 | F23: ='Assumptions'!$C$40 | G23: ='Assumptions'!$C$41 | H23: 0 | I23: 0 | J23: ='Assumptions'!$C$13 | K23: 0 | L23: 0 | M23: =E23*(1-F23-H23-J23)-G23-I23-K23-L23 | N23: =IF(E23=0,0,M23/E23) | O23: 0 | P23: 25 | Q23: Merchant of record collects and remits US sales tax and EU/UK VAT | R23: International plan: one MoR for international digital sales.
A24: MOR | B24: "I'm bored" play cards (150, age-banded) | C24: Gumroad (merchant of record), buyers outside the US | D24: 1-2 | E24: =E7 | F24: ='Assumptions'!$C$40 | G24: ='Assumptions'!$C$41 | H24: 0 | I24: 0 | J24: ='Assumptions'!$C$13 | K24: 0 | L24: 0 | M24: =E24*(1-F24-H24-J24)-G24-I24-K24-L24 | N24: =IF(E24=0,0,M24/E24) | O24: 0 | P24: 15 | Q24: Merchant of record collects and remits US sales tax and EU/UK VAT | R24: International plan: one MoR for international digital sales.
A25: MOR | B25: Play-First Family Kit (2-5 pages at launch; 5-12 pages added free when G1 clears) | C25: Gumroad (merchant of record), buyers outside the US | D25: 1-2 | E25: =E8 | F25: ='Assumptions'!$C$40 | G25: ='Assumptions'!$C$41 | H25: 0 | I25: 0 | J25: ='Assumptions'!$C$13 | K25: 0 | L25: 0 | M25: =E25*(1-F25-H25-J25)-G25-I25-K25-L25 | N25: =IF(E25=0,0,M25/E25) | O25: 0 | P25: 20 | Q25: Merchant of record collects and remits US sales tax and EU/UK VAT | R25: International plan: one MoR for international digital sales.
A26: MOR | B26: Toddler busy book printable (120-150 pages) | C26: Gumroad (merchant of record), buyers outside the US | D26: 1-2 | E26: =E9 | F26: ='Assumptions'!$C$40 | G26: ='Assumptions'!$C$41 | H26: 0 | I26: 0 | J26: ='Assumptions'!$C$13 | K26: 0 | L26: 0 | M26: =E26*(1-F26-H26-J26)-G26-I26-K26-L26 | N26: =IF(E26=0,0,M26/E26) | O26: 0 | P26: 18 | Q26: Merchant of record collects and remits US sales tax and EU/UK VAT | R26: International plan: one MoR for international digital sales.
A27: MOR | B27: 100 Screen-Free Plays (PDF) | C27: Gumroad (merchant of record), buyers outside the US | D27: 1-2 | E27: =E10 | F27: ='Assumptions'!$C$40 | G27: ='Assumptions'!$C$41 | H27: 0 | I27: 0 | J27: ='Assumptions'!$C$13 | K27: 0 | L27: 0 | M27: =E27*(1-F27-H27-J27)-G27-I27-K27-L27 | N27: =IF(E27=0,0,M27/E27) | O27: 0 | P27: 10 | Q27: Merchant of record collects and remits US sales tax and EU/UK VAT | R27: International plan: one MoR for international digital sales.
A28: KDP | B28: 100 Screen-Free Plays (paperback, B/W interior) | C28: Amazon KDP | D28: 1 | E28: 16.99 | F28: =1-'Assumptions'!$C$32 | G28: 0 | H28: 0 | I28: 0 | J28: 0 | K28: ='Assumptions'!$C$35 | L28: 0 | M28: =E28*(1-F28-H28-J28)-G28-I28-K28-L28 | N28: =IF(E28=0,0,M28/E28) | O28: 0 | P28: 50 | Q28: Amazon is the retailer; royalty only, no sales tax for AlphaPlay | R28: guide-100-plays/listing.json: $16.99; KDP flat $2.30 B/W print; net about $7.89 [VERIFY].
A29: KDP | B29: The Day the Tablet Slept (paperback) | C29: Amazon KDP | D29: 1 | E29: 11.99 | F29: =1-'Assumptions'!$C$32 | G29: 0 | H29: 0 | I29: 0 | J29: 0 | K29: ='Assumptions'!$C$33+'Assumptions'!$C$34*'Assumptions'!$C$36 | L29: 0 | M29: =E29*(1-F29-H29-J29)-G29-I29-K29-L29 | N29: =IF(E29=0,0,M29/E29) | O29: 0 | P29: 20 | Q29: Amazon is the retailer; royalty only, no sales tax for AlphaPlay | R29: picture-tablet-slept/listing.json: $11.99; about $3.95/copy royalty.
A30: KDP | B30: Up! Go! More! (talk-along paperback) | C30: Amazon KDP | D30: 1 | E30: 11.99 | F30: =1-'Assumptions'!$C$32 | G30: 0 | H30: 0 | I30: 0 | J30: 0 | K30: ='Assumptions'!$C$33+'Assumptions'!$C$34*'Assumptions'!$C$36 | L30: 0 | M30: =E30*(1-F30-H30-J30)-G30-I30-K30-L30 | N30: =IF(E30=0,0,M30/E30) | O30: 0 | P30: 30 | Q30: Amazon is the retailer; royalty only, no sales tax for AlphaPlay | R30: board-up-go-more/listing.json: $11.99 paperback edition sells now with no inventory.
A31: INGRAM | B31: 100 Screen-Free Plays (paperback via Ingram) | C31: IngramSpark (same ISBN; KDP Expanded Distribution off) | D31: 2 | E31: =E28 | F31: ='Assumptions'!$C$37 | G31: 0 | H31: 0 | I31: 0 | J31: 0 | K31: ='Assumptions'!$C$35 | L31: 0 | M31: =E31*(1-F31-H31-J31)-G31-I31-K31-L31 | N31: =IF(E31=0,0,M31/E31) | O31: 0 | P31: 50 | Q31: Retailer collects; AlphaPlay receives publisher compensation | R31: storefront-setup-guide Part D. Print cost proxy = KDP flat B/W rate [VERIFY].
A32: INGRAM | B32: Up! Go! More! (paperback via Ingram) | C32: IngramSpark | D32: 2 | E32: =E30 | F32: ='Assumptions'!$C$37 | G32: 0 | H32: 0 | I32: 0 | J32: 0 | K32: ='Assumptions'!$C$39 | L32: 0 | M32: =E32*(1-F32-H32-J32)-G32-I32-K32-L32 | N32: =IF(E32=0,0,M32/E32) | O32: 0 | P32: 50 | Q32: Retailer collects; AlphaPlay receives publisher compensation | R32: board-up-go-more/listing.json channels.
A33: INGRAM | B33: The Day the Tablet Slept (hardcover; gated) | C33: IngramSpark | D33: gated | E33: 19.99 | F33: ='Assumptions'!$C$37 | G33: 0 | H33: 0 | I33: 0 | J33: 0 | K33: ='Assumptions'!$C$38 | L33: 0 | M33: =E33*(1-F33-H33-J33)-G33-I33-K33-L33 | N33: =IF(E33=0,0,M33/E33) | O33: 0 | P33: 0 | Q33: Retailer collects; AlphaPlay receives publisher compensation | R33: picture-tablet-slept/listing.json: turn on only after the paperback sells (demand 'Weak'). Weight 0. Laps Not Apps is not in this channel: it is now a personalized keepsake printed per order (amazon_route 'none-with-reason').
A34: COURSE | B34: 30-Day Screen Reset (written program) | C34: Own site (Shopify) + automated email | D34: 2 | E34: 27 | F34: 0 | G34: 0 | H34: ='Assumptions'!$C$24 | I34: ='Assumptions'!$C$25 | J34: ='Assumptions'!$C$14 | K34: 0 | L34: 0 | M34: =E34*(1-F34-H34-J34)-G34-I34-K34-L34 | N34: =IF(E34=0,0,M34/E34) | O34: 0 | P34: 70 | Q34: Shopify Tax adds MD 6% at checkout; AlphaPlay remits (pass-through, not revenue) | R34: DEMAND-CHECK course row: $27.
A35: COURSE | B35: 30-Day Screen Reset bundle | C35: Own site (Shopify) + automated email | D35: 2 | E35: 49 | F35: 0 | G35: 0 | H35: ='Assumptions'!$C$24 | I35: ='Assumptions'!$C$25 | J35: ='Assumptions'!$C$14 | K35: 0 | L35: 0 | M35: =E35*(1-F35-H35-J35)-G35-I35-K35-L35 | N35: =IF(E35=0,0,M35/E35) | O35: 0 | P35: 30 | Q35: Shopify Tax adds MD 6% at checkout; AlphaPlay remits (pass-through, not revenue) | R35: DEMAND-CHECK course row: $49 bundle.
A36: BOARD | B36: Up! Go! More! board book | C36: Own site; offset stock at a 3PL | D36: gated | E36: ='Assumptions'!$C$57 | F36: 0 | G36: 0 | H36: ='Assumptions'!$C$24 | I36: ='Assumptions'!$C$25 | J36: ='Assumptions'!$C$13 | K36: ='Assumptions'!$C$66 | L36: ='Assumptions'!$C$67+'Assumptions'!$C$48 | M36: =E36*(1-F36-H36-J36)-G36-I36-K36-L36 | N36: =IF(E36=0,0,M36/E36) | O36: ='Assumptions'!$C$66 | P36: 60 | Q36: Shopify Tax adds MD 6% at checkout; AlphaPlay remits (pass-through, not revenue) | R36: Offset run held and shipped by a 3PL, never the founder (BRAND.md). Pick/pack plus about $2 of postage absorbed.
A37: BOARD | B37: Up! Go! More! board book | C37: Amazon FBA (from the print month; the pre-sale is own-site only) | D37: gated | E37: ='Assumptions'!$C$57 | F37: ='Assumptions'!$C$44 | G37: ='Assumptions'!$C$46 | H37: 0 | I37: 0 | J37: 0 | K37: ='Assumptions'!$C$66 | L37: ='Assumptions'!$C$45+'Assumptions'!$C$47 | M37: =E37*(1-F37-H37-J37)-G37-I37-K37-L37 | N37: =IF(E37=0,0,M37/E37) | O37: ='Assumptions'!$C$66 | P37: 40 | Q37: Amazon collects and remits | R37: AMAZON-AND-RETAIL-ROADMAP A: board books via FBA; closing fee, storage and placement allowance included [VERIFY].
A38: SCHOOL | B38: TPT single resource (e.g., talk brain breaks) | C38: Teachers Pay Teachers | D38: 4 (held) | E38: 5 | F38: =1-'Assumptions'!$C$42 | G38: ='Assumptions'!$C$43 | H38: 0 | I38: 0 | J38: 0 | K38: 0 | L38: 0 | M38: =E38*(1-F38-H38-J38)-G38-I38-K38-L38 | N38: =IF(E38=0,0,M38/E38) | O38: 0 | P38: 40 | Q38: TPT remits as marketplace (UNVERIFIED) | R38: DEMAND-CHECK teacher table: $5 singles; held for counsel.
A39: SCHOOL | B39: Classroom Talk and Play growth bundle | C39: Teachers Pay Teachers | D39: 4 (held) | E39: 22 | F39: =1-'Assumptions'!$C$42 | G39: ='Assumptions'!$C$43 | H39: 0 | I39: 0 | J39: 0 | K39: 0 | L39: 0 | M39: =E39*(1-F39-H39-J39)-G39-I39-K39-L39 | N39: =IF(E39=0,0,M39/E39) | O39: 0 | P39: 20 | Q39: TPT remits as marketplace (UNVERIFIED) | R39: DEMAND-CHECK §2 #11: $22-26.
A40: SCHOOL | B40: Single-classroom license | C40: Direct invoice / Shopify draft order | D40: 4 (held) | E40: 29 | F40: 0 | G40: 0 | H40: ='Assumptions'!$C$24 | I40: ='Assumptions'!$C$25 | J40: 0 | K40: 0 | L40: 0 | M40: =E40*(1-F40-H40-J40)-G40-I40-K40-L40 | N40: =IF(E40=0,0,M40/E40) | O40: 0 | P40: 20 | Q40: Tax-exempt certificate kept on file; otherwise MD 6% | R40: MARKETING-PLAYBOOK School Purchasing Kit: Single Classroom $29.
A41: SCHOOL | B41: Host-it-yourself parent-night kit, single site | C41: Direct invoice / Shopify | D41: 4 (held) | E41: 129 | F41: 0 | G41: 0 | H41: ='Assumptions'!$C$24 | I41: ='Assumptions'!$C$25 | J41: 0 | K41: 0 | L41: 0 | M41: =E41*(1-F41-H41-J41)-G41-I41-K41-L41 | N41: =IF(E41=0,0,M41/E41) | O41: 0 | P41: 2 | Q41: Tax-exempt certificate kept on file; otherwise MD 6% | R41: DEMAND-CHECK: $129 single site. Near-zero weight: no kit sales counts exist and a free leader program competes.
A42: SCHOOL | B42: Host kit, multi-site | C42: Direct invoice / Shopify | D42: 4 (held) | E42: 249 | F42: 0 | G42: 0 | H42: ='Assumptions'!$C$24 | I42: ='Assumptions'!$C$25 | J42: 0 | K42: 0 | L42: 0 | M42: =E42*(1-F42-H42-J42)-G42-I42-K42-L42 | N42: =IF(E42=0,0,M42/E42) | O42: 0 | P42: 0 | Q42: Tax-exempt certificate kept on file; otherwise MD 6% | R42: DEMAND-CHECK: $249 multi-site. Weight 0 until there is evidence.
A43: RETAIL | B43: Up! Go! More! board book (wholesale) | C43: Faire wholesale to boutiques | D43: 5 (retail) | E43: ='Assumptions'!$C$57*'Assumptions'!$C$51 | F43: ='Assumptions'!$C$49 | G43: 0 | H43: ='Assumptions'!$C$50 | I43: 0 | J43: ='Assumptions'!$C$53 | K43: ='Assumptions'!$C$66 | L43: ='Assumptions'!$C$68 | M43: =E43*(1-F43-H43-J43)-G43-I43-K43-L43 | N43: =IF(E43=0,0,M43/E43) | O43: ='Assumptions'!$C$66 | P43: 60 | Q43: Wholesale: exempt with the retailer's resale certificate | R43: Wholesale pays about half of retail (AMAZON-AND-RETAIL-ROADMAP B4).
A44: RETAIL | B44: Up! Go! More! board book | C44: Walmart Marketplace (3PL-fulfilled) | D44: 5 (retail) | E44: ='Assumptions'!$C$57 | F44: ='Assumptions'!$C$52 | G44: 0 | H44: 0 | I44: 0 | J44: ='Assumptions'!$C$53 | K44: ='Assumptions'!$C$66 | L44: ='Assumptions'!$C$67+'Assumptions'!$C$48 | M44: =E44*(1-F44-H44-J44)-G44-I44-K44-L44 | N44: =IF(E44=0,0,M44/E44) | O44: ='Assumptions'!$C$66 | P44: 40 | Q44: Marketplace facilitator [VERIFY for Target Plus] | R44: Walmart Marketplace by application (ROADMAP B3).
A45: RETAIL | B45: Up! Go! More! board book | C45: Target Plus (invitation-only) [VERIFY] | D45: 5 (retail) | E45: ='Assumptions'!$C$57 | F45: ='Assumptions'!$C$52 | G45: 0 | H45: 0 | I45: 0 | J45: ='Assumptions'!$C$53 | K45: ='Assumptions'!$C$66 | L45: ='Assumptions'!$C$67+'Assumptions'!$C$48 | M45: =E45*(1-F45-H45-J45)-G45-I45-K45-L45 | N45: =IF(E45=0,0,M45/E45) | O45: ='Assumptions'!$C$66 | P45: 0 | Q45: Marketplace facilitator [VERIFY for Target Plus] | R45: Target Plus is invitation-only (ROADMAP B3) [VERIFY terms]. Weight 0: no forecast revenue until an invitation arrives.
A47: Channel blend used by the forecast (weighted by mix weight)
A48: Channel code | B48: Channel | E48: Blended price ($/item) | F48: Blended net per item ($) | G48: Net margin % | H48: Inventory cost paid up front ($/item) | I48: Payout delay (months)
A49: SITE | B49: Own site: printables and PDFs (Shopify) | E49: =SUMPRODUCT(--($A$6:$A$45=$A49),$E$6:$E$45,$P$6:$P$45)/SUMIF($A$6:$A$45,$A49,$P$6:$P$45) | F49: =SUMPRODUCT(--($A$6:$A$45=$A49),$M$6:$M$45,$P$6:$P$45)/SUMIF($A$6:$A$45,$A49,$P$6:$P$45) | G49: =IF(E49=0,0,F49/E49) | H49: =SUMPRODUCT(--($A$6:$A$45=$A49),$O$6:$O$45,$P$6:$P$45)/SUMIF($A$6:$A$45,$A49,$P$6:$P$45) | I49: ='Assumptions'!$C$80
A50: ETSY | B50: Etsy: printables | E50: =SUMPRODUCT(--($A$6:$A$45=$A50),$E$6:$E$45,$P$6:$P$45)/SUMIF($A$6:$A$45,$A50,$P$6:$P$45) | F50: =SUMPRODUCT(--($A$6:$A$45=$A50),$M$6:$M$45,$P$6:$P$45)/SUMIF($A$6:$A$45,$A50,$P$6:$P$45) | G50: =IF(E50=0,0,F50/E50) | H50: =SUMPRODUCT(--($A$6:$A$45=$A50),$O$6:$O$45,$P$6:$P$45)/SUMIF($A$6:$A$45,$A50,$P$6:$P$45) | I50: ='Assumptions'!$C$81
A51: KDP | B51: Amazon KDP: paperbacks | E51: =SUMPRODUCT(--($A$6:$A$45=$A51),$E$6:$E$45,$P$6:$P$45)/SUMIF($A$6:$A$45,$A51,$P$6:$P$45) | F51: =SUMPRODUCT(--($A$6:$A$45=$A51),$M$6:$M$45,$P$6:$P$45)/SUMIF($A$6:$A$45,$A51,$P$6:$P$45) | G51: =IF(E51=0,0,F51/E51) | H51: =SUMPRODUCT(--($A$6:$A$45=$A51),$O$6:$O$45,$P$6:$P$45)/SUMIF($A$6:$A$45,$A51,$P$6:$P$45) | I51: ='Assumptions'!$C$82
A52: INGRAM | B52: IngramSpark: paperbacks to bookstores and libraries | E52: =SUMPRODUCT(--($A$6:$A$45=$A52),$E$6:$E$45,$P$6:$P$45)/SUMIF($A$6:$A$45,$A52,$P$6:$P$45) | F52: =SUMPRODUCT(--($A$6:$A$45=$A52),$M$6:$M$45,$P$6:$P$45)/SUMIF($A$6:$A$45,$A52,$P$6:$P$45) | G52: =IF(E52=0,0,F52/E52) | H52: =SUMPRODUCT(--($A$6:$A$45=$A52),$O$6:$O$45,$P$6:$P$45)/SUMIF($A$6:$A$45,$A52,$P$6:$P$45) | I52: ='Assumptions'!$C$83
A53: MOR | B53: International digital via merchant of record (Gumroad) | E53: =SUMPRODUCT(--($A$6:$A$45=$A53),$E$6:$E$45,$P$6:$P$45)/SUMIF($A$6:$A$45,$A53,$P$6:$P$45) | F53: =SUMPRODUCT(--($A$6:$A$45=$A53),$M$6:$M$45,$P$6:$P$45)/SUMIF($A$6:$A$45,$A53,$P$6:$P$45) | G53: =IF(E53=0,0,F53/E53) | H53: =SUMPRODUCT(--($A$6:$A$45=$A53),$O$6:$O$45,$P$6:$P$45)/SUMIF($A$6:$A$45,$A53,$P$6:$P$45) | I53: ='Assumptions'!$C$84
A54: COURSE | B54: 30-Day Screen Reset written course (Wave 2) | E54: =SUMPRODUCT(--($A$6:$A$45=$A54),$E$6:$E$45,$P$6:$P$45)/SUMIF($A$6:$A$45,$A54,$P$6:$P$45) | F54: =SUMPRODUCT(--($A$6:$A$45=$A54),$M$6:$M$45,$P$6:$P$45)/SUMIF($A$6:$A$45,$A54,$P$6:$P$45) | G54: =IF(E54=0,0,F54/E54) | H54: =SUMPRODUCT(--($A$6:$A$45=$A54),$O$6:$O$45,$P$6:$P$45)/SUMIF($A$6:$A$45,$A54,$P$6:$P$45) | I54: ='Assumptions'!$C$85
A55: BOARD | B55: Board book: pre-sale, then 3PL and Amazon FBA (gated option; off in base) | E55: =SUMPRODUCT(--($A$6:$A$45=$A55),$E$6:$E$45,$P$6:$P$45)/SUMIF($A$6:$A$45,$A55,$P$6:$P$45) | F55: =SUMPRODUCT(--($A$6:$A$45=$A55),$M$6:$M$45,$P$6:$P$45)/SUMIF($A$6:$A$45,$A55,$P$6:$P$45) | G55: =IF(E55=0,0,F55/E55) | H55: =SUMPRODUCT(--($A$6:$A$45=$A55),$O$6:$O$45,$P$6:$P$45)/SUMIF($A$6:$A$45,$A55,$P$6:$P$45) | I55: ='Assumptions'!$C$86
A56: SCHOOL | B56: School and group licenses + TPT (overlay only if counsel clears in writing; off in base) | E56: =SUMPRODUCT(--($A$6:$A$45=$A56),$E$6:$E$45,$P$6:$P$45)/SUMIF($A$6:$A$45,$A56,$P$6:$P$45) | F56: =SUMPRODUCT(--($A$6:$A$45=$A56),$M$6:$M$45,$P$6:$P$45)/SUMIF($A$6:$A$45,$A56,$P$6:$P$45) | G56: =IF(E56=0,0,F56/E56) | H56: =SUMPRODUCT(--($A$6:$A$45=$A56),$O$6:$O$45,$P$6:$P$45)/SUMIF($A$6:$A$45,$A56,$P$6:$P$45) | I56: ='Assumptions'!$C$87
A57: RETAIL | B57: Retail and wholesale: Faire, Walmart Marketplace (off in base) | E57: =SUMPRODUCT(--($A$6:$A$45=$A57),$E$6:$E$45,$P$6:$P$45)/SUMIF($A$6:$A$45,$A57,$P$6:$P$45) | F57: =SUMPRODUCT(--($A$6:$A$45=$A57),$M$6:$M$45,$P$6:$P$45)/SUMIF($A$6:$A$45,$A57,$P$6:$P$45) | G57: =IF(E57=0,0,F57/E57) | H57: =SUMPRODUCT(--($A$6:$A$45=$A57),$O$6:$O$45,$P$6:$P$45)/SUMIF($A$6:$A$45,$A57,$P$6:$P$45) | I57: ='Assumptions'!$C$88
A59: Notes
A60: KDP and IngramSpark: 'price' is the list price the reader pays; AlphaPlay receives the royalty or publisher compensation shown in Net per unit.
A61: Board book and retail rows: the landed print cost is deducted in Net per unit (true margin). Cash Flow adds it back and instead pays for whole print runs up front.
A62: Fixed per-order fees are applied per item, which slightly understates net on multi-item orders (a conservative simplification).
A63: IngramSpark: base discount 40%. The hardcover is gated at weight 0 (about $0.50 a copy at 55%); Laps Not Apps is now a per-order personalized book and is not in this channel.
A64: Board book: own-site orders absorb about $2 of postage; FBA rows include the closing fee and a storage/placement allowance. Mix weights of 0 mark gated products that earn no forecast revenue.
A65: The board-book blend applies only from the print month; pre-sale orders use the own-site row (no FBA stock exists before printing).

Sheet Startup Costs
A1: Startup costs: one-time items
A2: Model ($) = Low + cost position x (High - Low), using the cost position on Assumptions. Set Include to 0 to drop an item. Recurring items (insurance, domains, subscriptions) live on Monthly Operating Costs.
A5: Item | B5: Category | C5: Low ($) | D5: High ($) | E5: Model ($) | F5: Month incurred (model month #) | G5: Include (1/0) | H5: Source | I5: Status
A6: Trade-name filing, 'Play Before Pixels' (SDAT) | B6: Legal/entity | C6: 25 | D6: 50 | E6: =C6+'Assumptions'!$C$10*(D6-C6) | F6: 1 | G6: 1 | H6: legal/protection/PROTECTION-PLAN.md: $25 ($50 expedited). | I6: Repo
A7: Principal office / resident agent change (SDAT) | B7: Legal/entity | C7: 25 | D7: 50 | E7: =C7+'Assumptions'!$C$10*(D7-C7) | F7: 1 | G7: 1 | H7: PROTECTION-PLAN: $25 ($50 expedited). | I7: Repo
A8: DMCA designated agent registration | B8: Legal/IP | C8: 6 | D8: 6 | E8: =C8+'Assumptions'!$C$10*(D8-C8) | F8: 1 | G8: 1 | H8: PROTECTION-PLAN: $6, renews every 3 years. | I8: Repo
A9: Etsy shop opening fee (may apply) | B9: Channels | C9: 0 | D9: 15 | E9: =C9+'Assumptions'!$C$10*(D9-C9) | F9: 1 | G9: 1 | H9: storefront-setup-guide §10. | I9: Repo [VERIFY]
A10: ISBNs: KDP's free ISBN (founder's decision; a Bowker 10-pack, $295, only if IngramSpark editions are added) | B10: Publishing | C10: 0 | D10: 0 | E10: =C10+'Assumptions'!$C$10*(D10-C10) | F10: 1 | G10: 1 | H10: business/DECISIONS.md 2026-09-28. | I10: Decided
A11: Trademark clearance search + attorney opinion, PLAY BEFORE PIXELS | B11: Legal/IP | C11: 500 | D11: 2500 | E11: =C11+'Assumptions'!$C$10*(D11-C11) | F11: 1 | G11: 1 | H11: legal/DECISION-MEMO.json step 2. | I11: Repo [VERIFY]
A12: USPTO application, PLAY BEFORE PIXELS, classes 16 + 41 | B12: Legal/IP | C12: 700 | D12: 700 | E12: =C12+'Assumptions'!$C$10*(D12-C12) | F12: 2 | G12: 1 | H12: PROTECTION-PLAN #7: $350/class, within 90 days. | I12: Repo
A13: ALPHAPLAY Statement of Use ($150/class) or extension (up to $625) | B13: Legal/IP | C13: 150 | D13: 625 | E13: =C13+'Assumptions'!$C$10*(D13-C13) | F13: 5 | G13: 1 | H13: PROTECTION-PLAN #6: due Mar 8, 2027; target Feb 1, 2027. | I13: Repo
A14: Trademark attorney, ALPHAPLAY filing | B14: Legal/IP | C14: 300 | D14: 1000 | E14: =C14+'Assumptions'!$C$10*(D14-C14) | F14: 4 | G14: 1 | H14: marketing/BLIND-SPOTS.md #9. | I14: Repo
A15: Copyright registrations for pending works (before Nov 11, 2026) | B15: Legal/IP | C15: 360 | D15: 680 | E15: =C15+'Assumptions'!$C$10*(D15-C15) | F15: 2 | G15: 1 | H15: PROTECTION-PLAN: about 8 filings at $45-$85. | I15: Repo
A16: Attorney: IP assignment to the LLC + operating-agreement refresh | B16: Legal/entity | C16: 500 | D16: 2000 | E16: =C16+'Assumptions'!$C$10*(D16-C16) | F16: 3 | G16: 1 | H16: PROTECTION-PLAN #5 (after employment counsel answers). | I16: Repo [VERIFY]
A17: Attorney: Terms of Sale and website legal pages | B17: Legal | C17: 500 | D17: 2500 | E17: =C17+'Assumptions'!$C$10*(D17-C17) | F17: 1 | G17: 1 | H17: PROTECTION-PLAN contracts table; DECISION-MEMO $500-$2,000. | I17: Repo [VERIFY]
... A39: GATED (seasonal calendars): tradition reviewers (4 traditions) | B39: Product | C39: 400 | D39: 1200 | E39: =C39+'Assumptions'!$C$10*(D39-C39) | F39: 14 | G39: 0 | H39: Section 5.4: quote needed; $100-$300 each assumed. | I39: Assumption
A40: Total (included items) | C40: =SUMPRODUCT(C6:C39,$G$6:$G$39) | D40: =SUMPRODUCT(D6:D39,$G$6:$G$39) | E40: =SUMPRODUCT(E6:E39,$G$6:$G$39)
A41: Gated items not in the base plan (total at model cost) | C41: =SUMPRODUCT(C6:C39,1-$G$6:$G$39) | D41: =SUMPRODUCT(D6:D39,1-$G$6:$G$39) | E41: =SUMPRODUCT(E6:E39,1-$G$6:$G$39)
A42: Timing summary
A43: Months 1-3 (Oct-Dec 2026) | E43: =SUMPRODUCT(($F$6:$F$39>=1)*($F$6:$F$39<=3)*$G$6:$G$39*$E$6:$E$39)
A44: Months 4-12 | E44: =SUMPRODUCT(($F$6:$F$39>=4)*($F$6:$F$39<=12)*$G$6:$G$39*$E$6:$E$39)
A45: Year 2 | E45: =SUMPRODUCT(($F$6:$F$39>=13)*($F$6:$F$39<=24)*$G$6:$G$39*$E$6:$E$39)
A46: Year 3 | E46: =SUMPRODUCT(($F$6:$F$39>=25)*($F$6:$F$39<=36)*$G$6:$G$39*$E$6:$E$39)
A48: GATED rows are listed with their trigger and month so nothing in the plan is unpriced; they stay at Include = 0 until the named gate is met. Not included: employment-counsel fees (a personal matter for the founder); board-book illustration, CPSIA testing, 3PL setup and the first run (Retail Readiness Costs).

Sheet Monthly Operating Costs
A1: Monthly operating costs: subscriptions, Claude plan, email platform, connectors, insurance and reserve
A2: Low/High are the amount per billing period (per month for Monthly items, per year for Annual items). Model = Low + cost position x (High - Low). Annual items hit in their start month and every 12 months after. Insurance is shown billed monthly (annual premium / 12).
N3: Year | O3: =INT((O4-1)/12)+1 | P3: =INT((P4-1)/12)+1 | Q3: =INT((Q4-1)/12)+1 | R3: =INT((R4-1)/12)+1 | S3: =INT((S4-1)/12)+1 | T3: =INT((T4-1)/12)+1 | U3: =INT((U4-1)/12)+1 | V3: =INT((V4-1)/12)+1 | ... AX3: =INT((AX4-1)/12)+1
N4: Month # | O4: 1 | P4: 2 | Q4: 3 | R4: 4 | S4: 5 | T4: 6 | U4: 7 | V4: 8 | W4: 9 | X4: 10 | Y4: 11 | Z4: 12 | AA4: 13 | AB4: 14 | AC4: 15 | AD4: 16 | AE4: 17 | AF4: 18 | AG4: 19 | AH4: 20 | AI4: 21 | AJ4: 22 | AK4: 23 | AL4: 24 | AM4: 25 | AN4: 26 | AO4: 27 | AP4: 28 | AQ4: 29 | AR4: 30 | AS4: 31 | AT4: 32 | AU4: 33 | AV4: 34 | AW4: 35 | AX4: 36
A5: Item | B5: Category | C5: Low ($) | D5: High ($) | E5: Model ($ per period) | F5: Frequency | G5: Start month | H5: End month | I5: Year 1 total | J5: Year 2 total | K5: Year 3 total | L5: Source | M5: Status | N5: Include (1/0) | O5: =DATE(YEAR('Assumptions'!$C$8),MONTH('Assumptions'!$C$8)+O4-1,1) | P5: =DATE(YEAR('Assumptions'!$C$8),MONTH('Assumptions'!$C$8)+P4-1,1) | Q5: =DATE(YEAR('Assumptions'!$C$8),MONTH('Assumptions'!$C$8)+Q4-1,1) | R5: =DATE(YEAR('Assumptions'!$C$8),MONTH('Assumptions'!$C$8)+R4-1,1) | S5: =DATE(YEAR('Assumptions'!$C$8),MONTH('Assumptions'!$C$8)+S4-1,1) | T5: =DATE(YEAR('Assumptions'!$C$8),MONTH('Assumptions'!$C$8)+T4-1,1) | U5: =DATE(YEAR('Assumptions'!$C$8),MONTH('Assumptions'!$C$8)+U4-1,1) | V5: =DATE(YEAR('Assumptions'!$C$8),MONTH('Assumptions'!$C$8)+V4-1,1) | ... AX5: =DATE(YEAR('Assumptions'!$C$8),MONTH('Assumptions'!$C$8)+AX4-1,1)
A6: Shopify Basic plan | B6: Store | C6: 39 | D6: 39 | E6: =C6+'Assumptions'!$C$10*(D6-C6) | F6: Monthly | G6: 1 | H6: 36 | I6: =SUMIF($O$3:$AX$3,1,O6:AX6) | J6: =SUMIF($O$3:$AX$3,2,O6:AX6) | K6: =SUMIF($O$3:$AX$3,3,O6:AX6) | L6: storefront-setup-guide §1: $39/mo ($29 billed yearly). | M6: Repo [VERIFY] | N6: 1 | O6: =$N6*IF(AND(O$4>=$G6,O$4<=$H6),IF($F6="Monthly",$E6,IF(MOD(O$4-$G6,12)=0,$E6,0)),0) | P6: =$N6*IF(AND(P$4>=$G6,P$4<=$H6),IF($F6="Monthly",$E6,IF(MOD(P$4-$G6,12)=0,$E6,0)),0) | Q6: =$N6*IF(AND(Q$4>=$G6,Q$4<=$H6),IF($F6="Monthly",$E6,IF(MOD(Q$4-$G6,12)=0,$E6,0)),0) | R6: =$N6*IF(AND(R$4>=$G6,R$4<=$H6),IF($F6="Monthly",$E6,IF(MOD(R$4-$G6,12)=0,$E6,0)),0) | S6: =$N6*IF(AND(S$4>=$G6,S$4<=$H6),IF($F6="Monthly",$E6,IF(MOD(S$4-$G6,12)=0,$E6,0)),0) | T6: =$N6*IF(AND(T$4>=$G6,T$4<=$H6),IF($F6="Monthly",$E6,IF(MOD(T$4-$G6,12)=0,$E6,0)),0) | U6: =$N6*IF(AND(U$4>=$G6,U$4<=$H6),IF($F6="Monthly",$E6,IF(MOD(U$4-$G6,12)=0,$E6,0)),0) | V6: =$N6*IF(AND(V$4>=$G6,V$4<=$H6),IF($F6="Monthly",$E6,IF(MOD(V$4-$G6,12)=0,$E6,0)),0) | ... AX6: =$N6*IF(AND(AX$4>=$G6,AX$4<=$H6),IF($F6="Monthly",$E6,IF(MOD(AX$4-$G6,12)=0,$E6,0)),0)
A7: Business email on the brand domain | B7: Tools | C7: 7 | D7: 14 | E7: =C7+'Assumptions'!$C$10*(D7-C7) | F7: Monthly | G7: 1 | H7: 36 | I7: =SUMIF($O$3:$AX$3,1,O7:AX7) | J7: =SUMIF($O$3:$AX$3,2,O7:AX7) | K7: =SUMIF($O$3:$AX$3,3,O7:AX7) | L7: BLIND-SPOTS #4: about $7-$14 a month. | M7: Repo | N7: 1 | O7: =$N7*IF(AND(O$4>=$G7,O$4<=$H7),IF($F7="Monthly",$E7,IF(MOD(O$4-$G7,12)=0,$E7,0)),0) | P7: =$N7*IF(AND(P$4>=$G7,P$4<=$H7),IF($F7="Monthly",$E7,IF(MOD(P$4-$G7,12)=0,$E7,0)),0) | Q7: =$N7*IF(AND(Q$4>=$G7,Q$4<=$H7),IF($F7="Monthly",$E7,IF(MOD(Q$4-$G7,12)=0,$E7,0)),0) | R7: =$N7*IF(AND(R$4>=$G7,R$4<=$H7),IF($F7="Monthly",$E7,IF(MOD(R$4-$G7,12)=0,$E7,0)),0) | S7: =$N7*IF(AND(S$4>=$G7,S$4<=$H7),IF($F7="Monthly",$E7,IF(MOD(S$4-$G7,12)=0,$E7,0)),0) | T7: =$N7*IF(AND(T$4>=$G7,T$4<=$H7),IF($F7="Monthly",$E7,IF(MOD(T$4-$G7,12)=0,$E7,0)),0) | U7: =$N7*IF(AND(U$4>=$G7,U$4<=$H7),IF($F7="Monthly",$E7,IF(MOD(U$4-$G7,12)=0,$E7,0)),0) | V7: =$N7*IF(AND(V$4>=$G7,V$4<=$H7),IF($F7="Monthly",$E7,IF(MOD(V$4-$G7,12)=0,$E7,0)),0) | ... AX7: =$N7*IF(AND(AX$4>=$G7,AX$4<=$H7),IF($F7="Monthly",$E7,IF(MOD(AX$4-$G7,12)=0,$E7,0)),0)
A8: Password manager | B8: Tools | C8: 0 | D8: 40 | E8: =C8+'Assumptions'!$C$10*(D8-C8) | F8: Annual | G8: 1 | H8: 36 | I8: =SUMIF($O$3:$AX$3,1,O8:AX8) | J8: =SUMIF($O$3:$AX$3,2,O8:AX8) | K8: =SUMIF($O$3:$AX$3,3,O8:AX8) | L8: BLIND-SPOTS #4: $0-$40 a year. | M8: Repo | N8: 1 | O8: =$N8*IF(AND(O$4>=$G8,O$4<=$H8),IF($F8="Monthly",$E8,IF(MOD(O$4-$G8,12)=0,$E8,0)),0) | P8: =$N8*IF(AND(P$4>=$G8,P$4<=$H8),IF($F8="Monthly",$E8,IF(MOD(P$4-$G8,12)=0,$E8,0)),0) | Q8: =$N8*IF(AND(Q$4>=$G8,Q$4<=$H8),IF($F8="Monthly",$E8,IF(MOD(Q$4-$G8,12)=0,$E8,0)),0) | R8: =$N8*IF(AND(R$4>=$G8,R$4<=$H8),IF($F8="Monthly",$E8,IF(MOD(R$4-$G8,12)=0,$E8,0)),0) | S8: =$N8*IF(AND(S$4>=$G8,S$4<=$H8),IF($F8="Monthly",$E8,IF(MOD(S$4-$G8,12)=0,$E8,0)),0) | T8: =$N8*IF(AND(T$4>=$G8,T$4<=$H8),IF($F8="Monthly",$E8,IF(MOD(T$4-$G8,12)=0,$E8,0)),0) | U8: =$N8*IF(AND(U$4>=$G8,U$4<=$H8),IF($F8="Monthly",$E8,IF(MOD(U$4-$G8,12)=0,$E8,0)),0) | V8: =$N8*IF(AND(V$4>=$G8,V$4<=$H8),IF($F8="Monthly",$E8,IF(MOD(V$4-$G8,12)=0,$E8,0)),0) | ... AX8: =$N8*IF(AND(AX$4>=$G8,AX$4<=$H8),IF($F8="Monthly",$E8,IF(MOD(AX$4-$G8,12)=0,$E8,0)),0)
A9: Email platform, year 1 (free tiers, then budget) | B9: Email | C9: 0 | D9: 20 | E9: =C9+'Assumptions'!$C$10*(D9-C9) | F9: Monthly | G9: 1 | H9: 12 | I9: =SUMIF($O$3:$AX$3,1,O9:AX9) | J9: =SUMIF($O$3:$AX$3,2,O9:AX9) | K9: =SUMIF($O$3:$AX$3,3,O9:AX9) | L9: MARKETING-PLAYBOOK: Klaviyo free 250 profiles; budget $20/mo. | M9: Repo [VERIFY] | N9: 1 | O9: =$N9*IF(AND(O$4>=$G9,O$4<=$H9),IF($F9="Monthly",$E9,IF(MOD(O$4-$G9,12)=0,$E9,0)),0) | P9: =$N9*IF(AND(P$4>=$G9,P$4<=$H9),IF($F9="Monthly",$E9,IF(MOD(P$4-$G9,12)=0,$E9,0)),0) | Q9: =$N9*IF(AND(Q$4>=$G9,Q$4<=$H9),IF($F9="Monthly",$E9,IF(MOD(Q$4-$G9,12)=0,$E9,0)),0) | R9: =$N9*IF(AND(R$4>=$G9,R$4<=$H9),IF($F9="Monthly",$E9,IF(MOD(R$4-$G9,12)=0,$E9,0)),0) | S9: =$N9*IF(AND(S$4>=$G9,S$4<=$H9),IF($F9="Monthly",$E9,IF(MOD(S$4-$G9,12)=0,$E9,0)),0) | T9: =$N9*IF(AND(T$4>=$G9,T$4<=$H9),IF($F9="Monthly",$E9,IF(MOD(T$4-$G9,12)=0,$E9,0)),0) | U9: =$N9*IF(AND(U$4>=$G9,U$4<=$H9),IF($F9="Monthly",$E9,IF(MOD(U$4-$G9,12)=0,$E9,0)),0) | V9: =$N9*IF(AND(V$4>=$G9,V$4<=$H9),IF($F9="Monthly",$E9,IF(MOD(V$4-$G9,12)=0,$E9,0)),0) | ... AX9: =$N9*IF(AND(AX$4>=$G9,AX$4<=$H9),IF($F9="Monthly",$E9,IF(MOD(AX$4-$G9,12)=0,$E9,0)),0)
A10: Email platform, years 2-3 | B10: Email | C10: 20 | D10: 39 | E10: =C10+'Assumptions'!$C$10*(D10-C10) | F10: Monthly | G10: 13 | H10: 36 | I10: =SUMIF($O$3:$AX$3,1,O10:AX10) | J10: =SUMIF($O$3:$AX$3,2,O10:AX10) | K10: =SUMIF($O$3:$AX$3,3,O10:AX10) | L10: MARKETING-PLAYBOOK: about $20-39/mo later. | M10: Repo [VERIFY] | N10: 1 | O10: =$N10*IF(AND(O$4>=$G10,O$4<=$H10),IF($F10="Monthly",$E10,IF(MOD(O$4-$G10,12)=0,$E10,0)),0) | P10: =$N10*IF(AND(P$4>=$G10,P$4<=$H10),IF($F10="Monthly",$E10,IF(MOD(P$4-$G10,12)=0,$E10,0)),0) | Q10: =$N10*IF(AND(Q$4>=$G10,Q$4<=$H10),IF($F10="Monthly",$E10,IF(MOD(Q$4-$G10,12)=0,$E10,0)),0) | R10: =$N10*IF(AND(R$4>=$G10,R$4<=$H10),IF($F10="Monthly",$E10,IF(MOD(R$4-$G10,12)=0,$E10,0)),0) | S10: =$N10*IF(AND(S$4>=$G10,S$4<=$H10),IF($F10="Monthly",$E10,IF(MOD(S$4-$G10,12)=0,$E10,0)),0) | T10: =$N10*IF(AND(T$4>=$G10,T$4<=$H10),IF($F10="Monthly",$E10,IF(MOD(T$4-$G10,12)=0,$E10,0)),0) | U10: =$N10*IF(AND(U$4>=$G10,U$4<=$H10),IF($F10="Monthly",$E10,IF(MOD(U$4-$G10,12)=0,$E10,0)),0) | V10: =$N10*IF(AND(V$4>=$G10,V$4<=$H10),IF($F10="Monthly",$E10,IF(MOD(V$4-$G10,12)=0,$E10,0)),0) | ... AX10: =$N10*IF(AND(AX$4>=$G10,AX$4<=$H10),IF($F10="Monthly",$E10,IF(MOD(AX$4-$G10,12)=0,$E10,0)),0)
A11: Claude plan that runs the scheduled routines | B11: Automation | C11: 100 | D11: 200 | E11: =C11+'Assumptions'!$C$10*(D11-C11) | F11: Monthly | G11: 1 | H11: 36 | I11: =SUMIF($O$3:$AX$3,1,O11:AX11) | J11: =SUMIF($O$3:$AX$3,2,O11:AX11) | K11: =SUMIF($O$3:$AX$3,3,O11:AX11) | L11: No price in the repo; a higher-usage tier is assumed because routines run weekly (ops/ROUTINE.md). | M11: Assumption [VERIFY] | N11: 1 | O11: =$N11*IF(AND(O$4>=$G11,O$4<=$H11),IF($F11="Monthly",$E11,IF(MOD(O$4-$G11,12)=0,$E11,0)),0) | P11: =$N11*IF(AND(P$4>=$G11,P$4<=$H11),IF($F11="Monthly",$E11,IF(MOD(P$4-$G11,12)=0,$E11,0)),0) | Q11: =$N11*IF(AND(Q$4>=$G11,Q$4<=$H11),IF($F11="Monthly",$E11,IF(MOD(Q$4-$G11,12)=0,$E11,0)),0) | R11: =$N11*IF(AND(R$4>=$G11,R$4<=$H11),IF($F11="Monthly",$E11,IF(MOD(R$4-$G11,12)=0,$E11,0)),0) | S11: =$N11*IF(AND(S$4>=$G11,S$4<=$H11),IF($F11="Monthly",$E11,IF(MOD(S$4-$G11,12)=0,$E11,0)),0) | T11: =$N11*IF(AND(T$4>=$G11,T$4<=$H11),IF($F11="Monthly",$E11,IF(MOD(T$4-$G11,12)=0,$E11,0)),0) | U11: =$N11*IF(AND(U$4>=$G11,U$4<=$H11),IF($F11="Monthly",$E11,IF(MOD(U$4-$G11,12)=0,$E11,0)),0) | V11: =$N11*IF(AND(V$4>=$G11,V$4<=$H11),IF($F11="Monthly",$E11,IF(MOD(V$4-$G11,12)=0,$E11,0)),0) | ... AX11: =$N11*IF(AND(AX$4>=$G11,AX$4<=$H11),IF($F11="Monthly",$E11,IF(MOD(AX$4-$G11,12)=0,$E11,0)),0)
A12: Claude usage-credit cap (hard limit) | B12: Automation | C12: 0 | D12: 25 | E12: =C12+'Assumptions'!$C$10*(D12-C12) | F12: Monthly | G12: 1 | H12: 36 | I12: =SUMIF($O$3:$AX$3,1,O12:AX12) | J12: =SUMIF($O$3:$AX$3,2,O12:AX12) | K12: =SUMIF($O$3:$AX$3,3,O12:AX12) | L12: ops/GAPS-ROUND-2.md G2-06: fixed monthly limit such as $25. | M12: Repo | N12: 1 | O12: =$N12*IF(AND(O$4>=$G12,O$4<=$H12),IF($F12="Monthly",$E12,IF(MOD(O$4-$G12,12)=0,$E12,0)),0) | P12: =$N12*IF(AND(P$4>=$G12,P$4<=$H12),IF($F12="Monthly",$E12,IF(MOD(P$4-$G12,12)=0,$E12,0)),0) | Q12: =$N12*IF(AND(Q$4>=$G12,Q$4<=$H12),IF($F12="Monthly",$E12,IF(MOD(Q$4-$G12,12)=0,$E12,0)),0) | R12: =$N12*IF(AND(R$4>=$G12,R$4<=$H12),IF($F12="Monthly",$E12,IF(MOD(R$4-$G12,12)=0,$E12,0)),0) | S12: =$N12*IF(AND(S$4>=$G12,S$4<=$H12),IF($F12="Monthly",$E12,IF(MOD(S$4-$G12,12)=0,$E12,0)),0) | T12: =$N12*IF(AND(T$4>=$G12,T$4<=$H12),IF($F12="Monthly",$E12,IF(MOD(T$4-$G12,12)=0,$E12,0)),0) | U12: =$N12*IF(AND(U$4>=$G12,U$4<=$H12),IF($F12="Monthly",$E12,IF(MOD(U$4-$G12,12)=0,$E12,0)),0) | V12: =$N12*IF(AND(V$4>=$G12,V$4<=$H12),IF($F12="Monthly",$E12,IF(MOD(V$4-$G12,12)=0,$E12,0)),0) | ... AX12: =$N12*IF(AND(AX$4>=$G12,AX$4<=$H12),IF($F12="Monthly",$E12,IF(MOD(AX$4-$G12,12)=0,$E12,0)),0)
A13: QuickBooks Online (Simple Start to Essentials) | B13: Bookkeeping | C13: 38 | D13: 85 | E13: =C13+'Assumptions'!$C$10*(D13-C13) | F13: Monthly | G13: 1 | H13: 36 | I13: =SUMIF($O$3:$AX$3,1,O13:AX13) | J13: =SUMIF($O$3:$AX$3,2,O13:AX13) | K13: =SUMIF($O$3:$AX$3,3,O13:AX13) | L13: finance/money-and-tax-setup.md: $38 Simple Start; Essentials $75-$85 (UNVERIFIED). | M13: Repo [VERIFY] | N13: 1 | O13: =$N13*IF(AND(O$4>=$G13,O$4<=$H13),IF($F13="Monthly",$E13,IF(MOD(O$4-$G13,12)=0,$E13,0)),0) | P13: =$N13*IF(AND(P$4>=$G13,P$4<=$H13),IF($F13="Monthly",$E13,IF(MOD(P$4-$G13,12)=0,$E13,0)),0) | Q13: =$N13*IF(AND(Q$4>=$G13,Q$4<=$H13),IF($F13="Monthly",$E13,IF(MOD(Q$4-$G13,12)=0,$E13,0)),0) | R13: =$N13*IF(AND(R$4>=$G13,R$4<=$H13),IF($F13="Monthly",$E13,IF(MOD(R$4-$G13,12)=0,$E13,0)),0) | S13: =$N13*IF(AND(S$4>=$G13,S$4<=$H13),IF($F13="Monthly",$E13,IF(MOD(S$4-$G13,12)=0,$E13,0)),0) | T13: =$N13*IF(AND(T$4>=$G13,T$4<=$H13),IF($F13="Monthly",$E13,IF(MOD(T$4-$G13,12)=0,$E13,0)),0) | U13: =$N13*IF(AND(U$4>=$G13,U$4<=$H13),IF($F13="Monthly",$E13,IF(MOD(U$4-$G13,12)=0,$E13,0)),0) | V13: =$N13*IF(AND(V$4>=$G13,V$4<=$H13),IF($F13="Monthly",$E13,IF(MOD(V$4-$G13,12)=0,$E13,0)),0) | ... AX13: =$N13*IF(AND(AX$4>=$G13,AX$4<=$H13),IF($F13="Monthly",$E13,IF(MOD(AX$4-$G13,12)=0,$E13,0)),0)
A14: Link My Books settlement connector (1-3 channels) | B14: Connectors | C14: 21 | D14: 47 | E14: =C14+'Assumptions'!$C$10*(D14-C14) | F14: Monthly | G14: 3 | H14: 36 | I14: =SUMIF($O$3:$AX$3,1,O14:AX14) | J14: =SUMIF($O$3:$AX$3,2,O14:AX14) | K14: =SUMIF($O$3:$AX$3,3,O14:AX14) | L14: money-and-tax-setup: from $21/mo, about $13 per extra channel. | M14: Repo [VERIFY] | N14: 1 | O14: =$N14*IF(AND(O$4>=$G14,O$4<=$H14),IF($F14="Monthly",$E14,IF(MOD(O$4-$G14,12)=0,$E14,0)),0) | P14: =$N14*IF(AND(P$4>=$G14,P$4<=$H14),IF($F14="Monthly",$E14,IF(MOD(P$4-$G14,12)=0,$E14,0)),0) | Q14: =$N14*IF(AND(Q$4>=$G14,Q$4<=$H14),IF($F14="Monthly",$E14,IF(MOD(Q$4-$G14,12)=0,$E14,0)),0) | R14: =$N14*IF(AND(R$4>=$G14,R$4<=$H14),IF($F14="Monthly",$E14,IF(MOD(R$4-$G14,12)=0,$E14,0)),0) | S14: =$N14*IF(AND(S$4>=$G14,S$4<=$H14),IF($F14="Monthly",$E14,IF(MOD(S$4-$G14,12)=0,$E14,0)),0) | T14: =$N14*IF(AND(T$4>=$G14,T$4<=$H14),IF($F14="Monthly",$E14,IF(MOD(T$4-$G14,12)=0,$E14,0)),0) | U14: =$N14*IF(AND(U$4>=$G14,U$4<=$H14),IF($F14="Monthly",$E14,IF(MOD(U$4-$G14,12)=0,$E14,0)),0) | V14: =$N14*IF(AND(V$4>=$G14,V$4<=$H14),IF($F14="Monthly",$E14,IF(MOD(V$4-$G14,12)=0,$E14,0)),0) | ... AX14: =$N14*IF(AND(AX$4>=$G14,AX$4<=$H14),IF($F14="Monthly",$E14,IF(MOD(AX$4-$G14,12)=0,$E14,0)),0)
A15: Buyer-specific PDF stamping | B15: Tools | C15: 0 | D15: 20 | E15: =C15+'Assumptions'!$C$10*(D15-C15) | F15: Monthly | G15: 3 | H15: 36 | I15: =SUMIF($O$3:$AX$3,1,O15:AX15) | J15: =SUMIF($O$3:$AX$3,2,O15:AX15) | K15: =SUMIF($O$3:$AX$3,3,O15:AX15) | L15: PROTECTION-PLAN: about $0-$20/mo. | M15: Repo [VERIFY] | N15: 1 | O15: =$N15*IF(AND(O$4>=$G15,O$4<=$H15),IF($F15="Monthly",$E15,IF(MOD(O$4-$G15,12)=0,$E15,0)),0) | P15: =$N15*IF(AND(P$4>=$G15,P$4<=$H15),IF($F15="Monthly",$E15,IF(MOD(P$4-$G15,12)=0,$E15,0)),0) | Q15: =$N15*IF(AND(Q$4>=$G15,Q$4<=$H15),IF($F15="Monthly",$E15,IF(MOD(Q$4-$G15,12)=0,$E15,0)),0) | R15: =$N15*IF(AND(R$4>=$G15,R$4<=$H15),IF($F15="Monthly",$E15,IF(MOD(R$4-$G15,12)=0,$E15,0)),0) | S15: =$N15*IF(AND(S$4>=$G15,S$4<=$H15),IF($F15="Monthly",$E15,IF(MOD(S$4-$G15,12)=0,$E15,0)),0) | T15: =$N15*IF(AND(T$4>=$G15,T$4<=$H15),IF($F15="Monthly",$E15,IF(MOD(T$4-$G15,12)=0,$E15,0)),0) | U15: =$N15*IF(AND(U$4>=$G15,U$4<=$H15),IF($F15="Monthly",$E15,IF(MOD(U$4-$G15,12)=0,$E15,0)),0) | V15: =$N15*IF(AND(V$4>=$G15,V$4<=$H15),IF($F15="Monthly",$E15,IF(MOD(V$4-$G15,12)=0,$E15,0)),0) | ... AX15: =$N15*IF(AND(AX$4>=$G15,AX$4<=$H15),IF($F15="Monthly",$E15,IF(MOD(AX$4-$G15,12)=0,$E15,0)),0)
A16: Social scheduler | B16: Tools | C16: 0 | D16: 30 | E16: =C16+'Assumptions'!$C$10*(D16-C16) | F16: Monthly | G16: 3 | H16: 36 | I16: =SUMIF($O$3:$AX$3,1,O16:AX16) | J16: =SUMIF($O$3:$AX$3,2,O16:AX16) | K16: =SUMIF($O$3:$AX$3,3,O16:AX16) | L16: Publisher role posts through a scheduler (section 5.3); no price in the repo. | M16: Assumption [VERIFY] | N16: 1 | O16: =$N16*IF(AND(O$4>=$G16,O$4<=$H16),IF($F16="Monthly",$E16,IF(MOD(O$4-$G16,12)=0,$E16,0)),0) | P16: =$N16*IF(AND(P$4>=$G16,P$4<=$H16),IF($F16="Monthly",$E16,IF(MOD(P$4-$G16,12)=0,$E16,0)),0) | Q16: =$N16*IF(AND(Q$4>=$G16,Q$4<=$H16),IF($F16="Monthly",$E16,IF(MOD(Q$4-$G16,12)=0,$E16,0)),0) | R16: =$N16*IF(AND(R$4>=$G16,R$4<=$H16),IF($F16="Monthly",$E16,IF(MOD(R$4-$G16,12)=0,$E16,0)),0) | S16: =$N16*IF(AND(S$4>=$G16,S$4<=$H16),IF($F16="Monthly",$E16,IF(MOD(S$4-$G16,12)=0,$E16,0)),0) | T16: =$N16*IF(AND(T$4>=$G16,T$4<=$H16),IF($F16="Monthly",$E16,IF(MOD(T$4-$G16,12)=0,$E16,0)),0) | U16: =$N16*IF(AND(U$4>=$G16,U$4<=$H16),IF($F16="Monthly",$E16,IF(MOD(U$4-$G16,12)=0,$E16,0)),0) | V16: =$N16*IF(AND(V$4>=$G16,V$4<=$H16),IF($F16="Monthly",$E16,IF(MOD(V$4-$G16,12)=0,$E16,0)),0) | ... AX16: =$N16*IF(AND(AX$4>=$G16,AX$4<=$H16),IF($F16="Monthly",$E16,IF(MOD(AX$4-$G16,12)=0,$E16,0)),0)
A17: Own-site review app | B17: Tools | C17: 0 | D17: 15 | E17: =C17+'Assumptions'!$C$10*(D17-C17) | F17: Monthly | G17: 3 | H17: 36 | I17: =SUMIF($O$3:$AX$3,1,O17:AX17) | J17: =SUMIF($O$3:$AX$3,2,O17:AX17) | K17: =SUMIF($O$3:$AX$3,3,O17:AX17) | L17: Section 4.7 own-site review app; no price in the repo. | M17: Assumption [VERIFY] | N17: 1 | O17: =$N17*IF(AND(O$4>=$G17,O$4<=$H17),IF($F17="Monthly",$E17,IF(MOD(O$4-$G17,12)=0,$E17,0)),0) | P17: =$N17*IF(AND(P$4>=$G17,P$4<=$H17),IF($F17="Monthly",$E17,IF(MOD(P$4-$G17,12)=0,$E17,0)),0) | Q17: =$N17*IF(AND(Q$4>=$G17,Q$4<=$H17),IF($F17="Monthly",$E17,IF(MOD(Q$4-$G17,12)=0,$E17,0)),0) | R17: =$N17*IF(AND(R$4>=$G17,R$4<=$H17),IF($F17="Monthly",$E17,IF(MOD(R$4-$G17,12)=0,$E17,0)),0) | S17: =$N17*IF(AND(S$4>=$G17,S$4<=$H17),IF($F17="Monthly",$E17,IF(MOD(S$4-$G17,12)=0,$E17,0)),0) | T17: =$N17*IF(AND(T$4>=$G17,T$4<=$H17),IF($F17="Monthly",$E17,IF(MOD(T$4-$G17,12)=0,$E17,0)),0) | U17: =$N17*IF(AND(U$4>=$G17,U$4<=$H17),IF($F17="Monthly",$E17,IF(MOD(U$4-$G17,12)=0,$E17,0)),0) | V17: =$N17*IF(AND(V$4>=$G17,V$4<=$H17),IF($F17="Monthly",$E17,IF(MOD(V$4-$G17,12)=0,$E17,0)),0) | ... AX17: =$N17*IF(AND(AX$4>=$G17,AX$4<=$H17),IF($F17="Monthly",$E17,IF(MOD(AX$4-$G17,12)=0,$E17,0)),0)
... A34: Upload assistant for KDP/IngramSpark/TpT packets (switch: when uploads exceed the founder cap) | B34: Contractor | C34: 0 | D34: 200 | E34: =C34+'Assumptions'!$C$10*(D34-C34) | F34: Monthly | G34: 7 | H34: 36 | I34: =SUMIF($O$3:$AX$3,1,O34:AX34) | J34: =SUMIF($O$3:$AX$3,2,O34:AX34) | K34: =SUMIF($O$3:$AX$3,3,O34:AX34) | L34: Section 5.2; not priced in the repo. | M34: Assumption | N34: 0 | O34: =$N34*IF(AND(O$4>=$G34,O$4<=$H34),IF($F34="Monthly",$E34,IF(MOD(O$4-$G34,12)=0,$E34,0)),0) | P34: =$N34*IF(AND(P$4>=$G34,P$4<=$H34),IF($F34="Monthly",$E34,IF(MOD(P$4-$G34,12)=0,$E34,0)),0) | Q34: =$N34*IF(AND(Q$4>=$G34,Q$4<=$H34),IF($F34="Monthly",$E34,IF(MOD(Q$4-$G34,12)=0,$E34,0)),0) | R34: =$N34*IF(AND(R$4>=$G34,R$4<=$H34),IF($F34="Monthly",$E34,IF(MOD(R$4-$G34,12)=0,$E34,0)),0) | S34: =$N34*IF(AND(S$4>=$G34,S$4<=$H34),IF($F34="Monthly",$E34,IF(MOD(S$4-$G34,12)=0,$E34,0)),0) | T34: =$N34*IF(AND(T$4>=$G34,T$4<=$H34),IF($F34="Monthly",$E34,IF(MOD(T$4-$G34,12)=0,$E34,0)),0) | U34: =$N34*IF(AND(U$4>=$G34,U$4<=$H34),IF($F34="Monthly",$E34,IF(MOD(U$4-$G34,12)=0,$E34,0)),0) | V34: =$N34*IF(AND(V$4>=$G34,V$4<=$H34),IF($F34="Monthly",$E34,IF(MOD(V$4-$G34,12)=0,$E34,0)),0) | ... AX34: =$N34*IF(AND(AX$4>=$G34,AX$4<=$H34),IF($F34="Monthly",$E34,IF(MOD(AX$4-$G34,12)=0,$E34,0)),0)
A35: Subtotal | I35: =SUM(I6:I34) | J35: =SUM(J6:J34) | K35: =SUM(K6:K34) | O35: =SUM(O6:O34) | P35: =SUM(P6:P34) | Q35: =SUM(Q6:Q34) | R35: =SUM(R6:R34) | S35: =SUM(S6:S34) | T35: =SUM(T6:T34) | U35: =SUM(U6:U34) | V35: =SUM(V6:V34) | ... AX35: =SUM(AX6:AX34)
A36: Operating contingency | I36: =I35*'Assumptions'!$C$20 | J36: =J35*'Assumptions'!$C$20 | K36: =K35*'Assumptions'!$C$20 | O36: =O35*'Assumptions'!$C$20 | P36: =P35*'Assumptions'!$C$20 | Q36: =Q35*'Assumptions'!$C$20 | R36: =R35*'Assumptions'!$C$20 | S36: =S35*'Assumptions'!$C$20 | T36: =T35*'Assumptions'!$C$20 | U36: =U35*'Assumptions'!$C$20 | V36: =V35*'Assumptions'!$C$20 | ... AX36: =AX35*'Assumptions'!$C$20
A37: Total monthly operating costs | I37: =I35+I36 | J37: =J35+J36 | K37: =K35+K36 | O37: =O35+O36 | P37: =P35+P36 | Q37: =Q35+Q36 | R37: =R35+R36 | S37: =S35+S36 | T37: =T35+T36 | U37: =U35+U36 | V37: =V35+V36 | ... AX37: =AX35+AX36
A39: Wave-specific fixed costs (3PL minimum, Seller Central, retail EDI and insurance uplift) are added in the forecast only when that wave is live.

Sheet 36-Month Forecast
A1: 36-month forecast: three scenarios, driven by traffic -> conversion -> orders -> order value, by channel and wave
A2: Traffic = trend (launch traffic compounded by monthly growth) x seasonality. Conversion ramps up over the review-ramp months. Net contribution = items x blended net per item from Unit Economics. Figures are planning estimates, not promises of income.
A4: Model month # | B4: Unit / note | C4: 1 | D4: 2 | E4: 3 | F4: 4 | G4: 5 | H4: 6 | I4: 7 | J4: 8 | K4: 9 | L4: 10 | M4: 11 | N4: 12 | O4: 13 | P4: 14 | Q4: 15 | R4: 16 | S4: 17 | T4: 18 | U4: 19 | V4: 20 | W4: 21 | X4: 22 | Y4: 23 | Z4: 24 | AA4: 25 | AB4: 26 | AC4: 27 | AD4: 28 | AE4: 29 | AF4: 30 | AG4: 31 | AH4: 32 | AI4: 33 | AJ4: 34 | AK4: 35 | AL4: 36 | AM4: Oct-Sep | AN4: Oct-Sep | AO4: Oct-Sep | AP4: Total
A5: Month | C5: =DATE(YEAR('Assumptions'!$C$8),MONTH('Assumptions'!$C$8)+C4-1,1) | D5: =DATE(YEAR('Assumptions'!$C$8),MONTH('Assumptions'!$C$8)+D4-1,1) | E5: =DATE(YEAR('Assumptions'!$C$8),MONTH('Assumptions'!$C$8)+E4-1,1) | F5: =DATE(YEAR('Assumptions'!$C$8),MONTH('Assumptions'!$C$8)+F4-1,1) | G5: =DATE(YEAR('Assumptions'!$C$8),MONTH('Assumptions'!$C$8)+G4-1,1) | H5: =DATE(YEAR('Assumptions'!$C$8),MONTH('Assumptions'!$C$8)+H4-1,1) | I5: =DATE(YEAR('Assumptions'!$C$8),MONTH('Assumptions'!$C$8)+I4-1,1) | J5: =DATE(YEAR('Assumptions'!$C$8),MONTH('Assumptions'!$C$8)+J4-1,1) | ... AL5: =DATE(YEAR('Assumptions'!$C$8),MONTH('Assumptions'!$C$8)+AL4-1,1) | AM5: Year 1 | AN5: Year 2 | AO5: Year 3 | AP5: 36 months
A6: Model year | C6: =INT((C4-1)/12)+1 | D6: =INT((D4-1)/12)+1 | E6: =INT((E4-1)/12)+1 | F6: =INT((F4-1)/12)+1 | G6: =INT((G4-1)/12)+1 | H6: =INT((H4-1)/12)+1 | I6: =INT((I4-1)/12)+1 | J6: =INT((J4-1)/12)+1 | ... AL6: =INT((AL4-1)/12)+1
A7: Seasonality: consumer | C7: =INDEX('Assumptions'!$C$92:$C$103,MONTH(C5))/AVERAGE('Assumptions'!$C$92:$C$103) | D7: =INDEX('Assumptions'!$C$92:$C$103,MONTH(D5))/AVERAGE('Assumptions'!$C$92:$C$103) | E7: =INDEX('Assumptions'!$C$92:$C$103,MONTH(E5))/AVERAGE('Assumptions'!$C$92:$C$103) | F7: =INDEX('Assumptions'!$C$92:$C$103,MONTH(F5))/AVERAGE('Assumptions'!$C$92:$C$103) | G7: =INDEX('Assumptions'!$C$92:$C$103,MONTH(G5))/AVERAGE('Assumptions'!$C$92:$C$103) | H7: =INDEX('Assumptions'!$C$92:$C$103,MONTH(H5))/AVERAGE('Assumptions'!$C$92:$C$103) | I7: =INDEX('Assumptions'!$C$92:$C$103,MONTH(I5))/AVERAGE('Assumptions'!$C$92:$C$103) | J7: =INDEX('Assumptions'!$C$92:$C$103,MONTH(J5))/AVERAGE('Assumptions'!$C$92:$C$103) | ... AL7: =INDEX('Assumptions'!$C$92:$C$103,MONTH(AL5))/AVERAGE('Assumptions'!$C$92:$C$103)
A8: Seasonality: school / group | C8: =INDEX('Assumptions'!$D$92:$D$103,MONTH(C5))/AVERAGE('Assumptions'!$D$92:$D$103) | D8: =INDEX('Assumptions'!$D$92:$D$103,MONTH(D5))/AVERAGE('Assumptions'!$D$92:$D$103) | E8: =INDEX('Assumptions'!$D$92:$D$103,MONTH(E5))/AVERAGE('Assumptions'!$D$92:$D$103) | F8: =INDEX('Assumptions'!$D$92:$D$103,MONTH(F5))/AVERAGE('Assumptions'!$D$92:$D$103) | G8: =INDEX('Assumptions'!$D$92:$D$103,MONTH(G5))/AVERAGE('Assumptions'!$D$92:$D$103) | H8: =INDEX('Assumptions'!$D$92:$D$103,MONTH(H5))/AVERAGE('Assumptions'!$D$92:$D$103) | I8: =INDEX('Assumptions'!$D$92:$D$103,MONTH(I5))/AVERAGE('Assumptions'!$D$92:$D$103) | J8: =INDEX('Assumptions'!$D$92:$D$103,MONTH(J5))/AVERAGE('Assumptions'!$D$92:$D$103) | ... AL8: =INDEX('Assumptions'!$D$92:$D$103,MONTH(AL5))/AVERAGE('Assumptions'!$D$92:$D$103)
A10: CONSERVATIVE SCENARIO
A11: Board-book print decision month (pre-sale ends), model month # (0 = board book off) | B11: =IF('Assumptions'!$C$164=1,MAX('Assumptions'!$C$165,'Assumptions'!$C$9)+'Assumptions'!$C$72,0)
A12: Pre-sale copies ordered before the print decision (demand) | B12: =IF($B$11=0,0,SUMPRODUCT(($C$4:$AL$4>=MAX('Assumptions'!$C$165,'Assumptions'!$C$9))*($C$4:$AL$4<$B$11)*($C$89:$AL$89)))
A13: Go line: pre-sale copies needed to fund the planned run + print-month costs + 15% buffer (BLIND-SPOTS #16) | B13: =IF($B$11=0,0,ROUNDUP(('Assumptions'!$C$58*'Assumptions'!$C$66+'Retail Readiness Costs'!$H$20)*(1+'Assumptions'!$C$73)/('Assumptions'!$C$57*(1-'Assumptions'!$C$24)-'Assumptions'!$C$25-'Assumptions'!$C$67-'Assumptions'!$C$48),0))
A14: Go (1) / no-go (0): print only if pre-sale copies reach the go line; otherwise refund the pre-sale | B14: =IF(AND($B$11>0,$B$12>=$B$13),1,0)
A15: First offset run = max(planned run, pre-sale x (1 + buffer)), rounded up to 100; 0 if no-go | B15: =IF($B$14=0,0,MAX('Assumptions'!$C$58,ROUNDUP($B$12*(1+'Assumptions'!$C$71)/100,0)*100))
A17: Digital catalog (shared by the own site, Etsy and the merchant of record)
A18: Digital products live | B18: products | C18: =IF(C$4<'Assumptions'!$C$9,0,MIN('Assumptions'!$C$112,'Assumptions'!$C$110+'Assumptions'!$C$111*(C$4-'Assumptions'!$C$9))) | D18: =IF(D$4<'Assumptions'!$C$9,0,MIN('Assumptions'!$C$112,'Assumptions'!$C$110+'Assumptions'!$C$111*(D$4-'Assumptions'!$C$9))) | E18: =IF(E$4<'Assumptions'!$C$9,0,MIN('Assumptions'!$C$112,'Assumptions'!$C$110+'Assumptions'!$C$111*(E$4-'Assumptions'!$C$9))) | F18: =IF(F$4<'Assumptions'!$C$9,0,MIN('Assumptions'!$C$112,'Assumptions'!$C$110+'Assumptions'!$C$111*(F$4-'Assumptions'!$C$9))) | G18: =IF(G$4<'Assumptions'!$C$9,0,MIN('Assumptions'!$C$112,'Assumptions'!$C$110+'Assumptions'!$C$111*(G$4-'Assumptions'!$C$9))) | H18: =IF(H$4<'Assumptions'!$C$9,0,MIN('Assumptions'!$C$112,'Assumptions'!$C$110+'Assumptions'!$C$111*(H$4-'Assumptions'!$C$9))) | I18: =IF(I$4<'Assumptions'!$C$9,0,MIN('Assumptions'!$C$112,'Assumptions'!$C$110+'Assumptions'!$C$111*(I$4-'Assumptions'!$C$9))) | J18: =IF(J$4<'Assumptions'!$C$9,0,MIN('Assumptions'!$C$112,'Assumptions'!$C$110+'Assumptions'!$C$111*(J$4-'Assumptions'!$C$9))) | ... AL18: =IF(AL$4<'Assumptions'!$C$9,0,MIN('Assumptions'!$C$112,'Assumptions'!$C$110+'Assumptions'!$C$111*(AL$4-'Assumptions'!$C$9)))
A19: Own site: printables and PDFs (Shopify)
A20: Active (1 = live) | B20: flag | C20: =IF(AND('Assumptions'!$C$117=1,C$4>=MAX('Assumptions'!$C$118,'Assumptions'!$C$9)),1,0) | D20: =IF(AND('Assumptions'!$C$117=1,D$4>=MAX('Assumptions'!$C$118,'Assumptions'!$C$9)),1,0) | E20: =IF(AND('Assumptions'!$C$117=1,E$4>=MAX('Assumptions'!$C$118,'Assumptions'!$C$9)),1,0) | F20: =IF(AND('Assumptions'!$C$117=1,F$4>=MAX('Assumptions'!$C$118,'Assumptions'!$C$9)),1,0) | G20: =IF(AND('Assumptions'!$C$117=1,G$4>=MAX('Assumptions'!$C$118,'Assumptions'!$C$9)),1,0) | H20: =IF(AND('Assumptions'!$C$117=1,H$4>=MAX('Assumptions'!$C$118,'Assumptions'!$C$9)),1,0) | I20: =IF(AND('Assumptions'!$C$117=1,I$4>=MAX('Assumptions'!$C$118,'Assumptions'!$C$9)),1,0) | J20: =IF(AND('Assumptions'!$C$117=1,J$4>=MAX('Assumptions'!$C$118,'Assumptions'!$C$9)),1,0) | ... AL20: =IF(AND('Assumptions'!$C$117=1,AL$4>=MAX('Assumptions'!$C$118,'Assumptions'!$C$9)),1,0)
A21: Sales-per-product index (1.00 in the launch month) | B21: index | C21: =IF(C20=0,0,1) | D21: =IF(D20=0,0,IF(D$4=MAX('Assumptions'!$C$118,'Assumptions'!$C$9),1,C21*(1+CHOOSE(D$6,'Assumptions'!$C$119,'Assumptions'!$C$120,'Assumptions'!$C$121)))) | E21: =IF(E20=0,0,IF(E$4=MAX('Assumptions'!$C$118,'Assumptions'!$C$9),1,D21*(1+CHOOSE(E$6,'Assumptions'!$C$119,'Assumptions'!$C$120,'Assumptions'!$C$121)))) | F21: =IF(F20=0,0,IF(F$4=MAX('Assumptions'!$C$118,'Assumptions'!$C$9),1,E21*(1+CHOOSE(F$6,'Assumptions'!$C$119,'Assumptions'!$C$120,'Assumptions'!$C$121)))) | G21: =IF(G20=0,0,IF(G$4=MAX('Assumptions'!$C$118,'Assumptions'!$C$9),1,F21*(1+CHOOSE(G$6,'Assumptions'!$C$119,'Assumptions'!$C$120,'Assumptions'!$C$121)))) | H21: =IF(H20=0,0,IF(H$4=MAX('Assumptions'!$C$118,'Assumptions'!$C$9),1,G21*(1+CHOOSE(H$6,'Assumptions'!$C$119,'Assumptions'!$C$120,'Assumptions'!$C$121)))) | I21: =IF(I20=0,0,IF(I$4=MAX('Assumptions'!$C$118,'Assumptions'!$C$9),1,H21*(1+CHOOSE(I$6,'Assumptions'!$C$119,'Assumptions'!$C$120,'Assumptions'!$C$121)))) | J21: =IF(J20=0,0,IF(J$4=MAX('Assumptions'!$C$118,'Assumptions'!$C$9),1,I21*(1+CHOOSE(J$6,'Assumptions'!$C$119,'Assumptions'!$C$120,'Assumptions'!$C$121)))) | K21: =IF(K20=0,0,IF(K$4=MAX('Assumptions'!$C$118,'Assumptions'!$C$9),1,J21*(1+CHOOSE(K$6,'Assumptions'!$C$119,'Assumptions'!$C$120,'Assumptions'!$C$121)))) | ... AL21: =IF(AL20=0,0,IF(AL$4=MAX('Assumptions'!$C$118,'Assumptions'!$C$9),1,AK21*(1+CHOOSE(AL$6,'Assumptions'!$C$119,'Assumptions'!$C$120,'Assumptions'!$C$121))))
A22: Product-months live (products x sales index x season) | B22: prod-mo | C22: =C18*C21*C$7 | D22: =D18*D21*D$7 | E22: =E18*E21*E$7 | F22: =F18*F21*F$7 | G22: =G18*G21*G$7 | H22: =H18*H21*H$7 | I22: =I18*I21*I$7 | J22: =J18*J21*J$7 | ... AL22: =AL18*AL21*AL$7 | AM22: =SUMIF($C$6:$AL$6,1,C22:AL22) | AN22: =SUMIF($C$6:$AL$6,2,C22:AL22) | AO22: =SUMIF($C$6:$AL$6,3,C22:AL22) | AP22: =SUM(C22:AL22)
A23: Orders per product per month (with review ramp) | B23: orders | C23: ='Assumptions'!$C$122*MIN(1,(C$4-MAX('Assumptions'!$C$118,'Assumptions'!$C$9)+1)/'Assumptions'!$C$11)*C20 | D23: ='Assumptions'!$C$122*MIN(1,(D$4-MAX('Assumptions'!$C$118,'Assumptions'!$C$9)+1)/'Assumptions'!$C$11)*D20 | E23: ='Assumptions'!$C$122*MIN(1,(E$4-MAX('Assumptions'!$C$118,'Assumptions'!$C$9)+1)/'Assumptions'!$C$11)*E20 | F23: ='Assumptions'!$C$122*MIN(1,(F$4-MAX('Assumptions'!$C$118,'Assumptions'!$C$9)+1)/'Assumptions'!$C$11)*F20 | G23: ='Assumptions'!$C$122*MIN(1,(G$4-MAX('Assumptions'!$C$118,'Assumptions'!$C$9)+1)/'Assumptions'!$C$11)*G20 | H23: ='Assumptions'!$C$122*MIN(1,(H$4-MAX('Assumptions'!$C$118,'Assumptions'!$C$9)+1)/'Assumptions'!$C$11)*H20 | I23: ='Assumptions'!$C$122*MIN(1,(I$4-MAX('Assumptions'!$C$118,'Assumptions'!$C$9)+1)/'Assumptions'!$C$11)*I20 | J23: ='Assumptions'!$C$122*MIN(1,(J$4-MAX('Assumptions'!$C$118,'Assumptions'!$C$9)+1)/'Assumptions'!$C$11)*J20 | ... AL23: ='Assumptions'!$C$122*MIN(1,(AL$4-MAX('Assumptions'!$C$118,'Assumptions'!$C$9)+1)/'Assumptions'!$C$11)*AL20
A24: Orders | B24: orders | C24: =C22*C23 | D24: =D22*D23 | E24: =E22*E23 | F24: =F22*F23 | G24: =G22*G23 | H24: =H22*H23 | I24: =I22*I23 | J24: =J22*J23 | ... AL24: =AL22*AL23 | AM24: =SUMIF($C$6:$AL$6,1,C24:AL24) | AN24: =SUMIF($C$6:$AL$6,2,C24:AL24) | AO24: =SUMIF($C$6:$AL$6,3,C24:AL24) | AP24: =SUM(C24:AL24)
A25: Items sold | B25: items | C25: =C24*'Assumptions'!$C$123 | D25: =D24*'Assumptions'!$C$123 | E25: =E24*'Assumptions'!$C$123 | F25: =F24*'Assumptions'!$C$123 | G25: =G24*'Assumptions'!$C$123 | H25: =H24*'Assumptions'!$C$123 | I25: =I24*'Assumptions'!$C$123 | J25: =J24*'Assumptions'!$C$123 | ... AL25: =AL24*'Assumptions'!$C$123 | AM25: =SUMIF($C$6:$AL$6,1,C25:AL25) | AN25: =SUMIF($C$6:$AL$6,2,C25:AL25) | AO25: =SUMIF($C$6:$AL$6,3,C25:AL25) | AP25: =SUM(C25:AL25)
A26: Average order value | B26: $ | C26: ='Unit Economics'!$E$49*'Assumptions'!$C$123*C20 | D26: ='Unit Economics'!$E$49*'Assumptions'!$C$123*D20 | E26: ='Unit Economics'!$E$49*'Assumptions'!$C$123*E20 | F26: ='Unit Economics'!$E$49*'Assumptions'!$C$123*F20 | G26: ='Unit Economics'!$E$49*'Assumptions'!$C$123*G20 | H26: ='Unit Economics'!$E$49*'Assumptions'!$C$123*H20 | I26: ='Unit Economics'!$E$49*'Assumptions'!$C$123*I20 | J26: ='Unit Economics'!$E$49*'Assumptions'!$C$123*J20 | ... AL26: ='Unit Economics'!$E$49*'Assumptions'!$C$123*AL20
A27: Gross sales (price paid by customers) | B27: $ | C27: =C25*'Unit Economics'!$E$49 | D27: =D25*'Unit Economics'!$E$49 | E27: =E25*'Unit Economics'!$E$49 | F27: =F25*'Unit Economics'!$E$49 | G27: =G25*'Unit Economics'!$E$49 | H27: =H25*'Unit Economics'!$E$49 | I27: =I25*'Unit Economics'!$E$49 | J27: =J25*'Unit Economics'!$E$49 | ... AL27: =AL25*'Unit Economics'!$E$49 | AM27: =SUMIF($C$6:$AL$6,1,C27:AL27) | AN27: =SUMIF($C$6:$AL$6,2,C27:AL27) | AO27: =SUMIF($C$6:$AL$6,3,C27:AL27) | AP27: =SUM(C27:AL27)
A28: Net contribution to AlphaPlay | B28: $ | C28: =C25*'Unit Economics'!$F$49 | D28: =D25*'Unit Economics'!$F$49 | E28: =E25*'Unit Economics'!$F$49 | F28: =F25*'Unit Economics'!$F$49 | G28: =G25*'Unit Economics'!$F$49 | H28: =H25*'Unit Economics'!$F$49 | I28: =I25*'Unit Economics'!$F$49 | J28: =J25*'Unit Economics'!$F$49 | ... AL28: =AL25*'Unit Economics'!$F$49 | AM28: =SUMIF($C$6:$AL$6,1,C28:AL28) | AN28: =SUMIF($C$6:$AL$6,2,C28:AL28) | AO28: =SUMIF($C$6:$AL$6,3,C28:AL28) | AP28: =SUM(C28:AL28)
A29: Etsy: printables
A30: Active (1 = live) | B30: flag | C30: =IF(AND('Assumptions'!$C$126=1,C$4>=MAX('Assumptions'!$C$127,'Assumptions'!$C$9)),1,0) | D30: =IF(AND('Assumptions'!$C$126=1,D$4>=MAX('Assumptions'!$C$127,'Assumptions'!$C$9)),1,0) | E30: =IF(AND('Assumptions'!$C$126=1,E$4>=MAX('Assumptions'!$C$127,'Assumptions'!$C$9)),1,0) | F30: =IF(AND('Assumptions'!$C$126=1,F$4>=MAX('Assumptions'!$C$127,'Assumptions'!$C$9)),1,0) | G30: =IF(AND('Assumptions'!$C$126=1,G$4>=MAX('Assumptions'!$C$127,'Assumptions'!$C$9)),1,0) | H30: =IF(AND('Assumptions'!$C$126=1,H$4>=MAX('Assumptions'!$C$127,'Assumptions'!$C$9)),1,0) | I30: =IF(AND('Assumptions'!$C$126=1,I$4>=MAX('Assumptions'!$C$127,'Assumptions'!$C$9)),1,0) | J30: =IF(AND('Assumptions'!$C$126=1,J$4>=MAX('Assumptions'!$C$127,'Assumptions'!$C$9)),1,0) | ... AL30: =IF(AND('Assumptions'!$C$126=1,AL$4>=MAX('Assumptions'!$C$127,'Assumptions'!$C$9)),1,0)
A31: Sales-per-product index (1.00 in the launch month) | B31: index | C31: =IF(C30=0,0,1) | D31: =IF(D30=0,0,IF(D$4=MAX('Assumptions'!$C$127,'Assumptions'!$C$9),1,C31*(1+CHOOSE(D$6,'Assumptions'!$C$128,'Assumptions'!$C$129,'Assumptions'!$C$130)))) | E31: =IF(E30=0,0,IF(E$4=MAX('Assumptions'!$C$127,'Assumptions'!$C$9),1,D31*(1+CHOOSE(E$6,'Assumptions'!$C$128,'Assumptions'!$C$129,'Assumptions'!$C$130)))) | F31: =IF(F30=0,0,IF(F$4=MAX('Assumptions'!$C$127,'Assumptions'!$C$9),1,E31*(1+CHOOSE(F$6,'Assumptions'!$C$128,'Assumptions'!$C$129,'Assumptions'!$C$130)))) | G31: =IF(G30=0,0,IF(G$4=MAX('Assumptions'!$C$127,'Assumptions'!$C$9),1,F31*(1+CHOOSE(G$6,'Assumptions'!$C$128,'Assumptions'!$C$129,'Assumptions'!$C$130)))) | H31: =IF(H30=0,0,IF(H$4=MAX('Assumptions'!$C$127,'Assumptions'!$C$9),1,G31*(1+CHOOSE(H$6,'Assumptions'!$C$128,'Assumptions'!$C$129,'Assumptions'!$C$130)))) | I31: =IF(I30=0,0,IF(I$4=MAX('Assumptions'!$C$127,'Assumptions'!$C$9),1,H31*(1+CHOOSE(I$6,'Assumptions'!$C$128,'Assumptions'!$C$129,'Assumptions'!$C$130)))) | J31: =IF(J30=0,0,IF(J$4=MAX('Assumptions'!$C$127,'Assumptions'!$C$9),1,I31*(1+CHOOSE(J$6,'Assumptions'!$C$128,'Assumptions'!$C$129,'Assumptions'!$C$130)))) | K31: =IF(K30=0,0,IF(K$4=MAX('Assumptions'!$C$127,'Assumptions'!$C$9),1,J31*(1+CHOOSE(K$6,'Assumptions'!$C$128,'Assumptions'!$C$129,'Assumptions'!$C$130)))) | ... AL31: =IF(AL30=0,0,IF(AL$4=MAX('Assumptions'!$C$127,'Assumptions'!$C$9),1,AK31*(1+CHOOSE(AL$6,'Assumptions'!$C$128,'Assumptions'!$C$129,'Assumptions'!$C$130))))
A32: Product-months live (products x sales index x season) | B32: prod-mo | C32: =C18*C31*C$7 | D32: =D18*D31*D$7 | E32: =E18*E31*E$7 | F32: =F18*F31*F$7 | G32: =G18*G31*G$7 | H32: =H18*H31*H$7 | I32: =I18*I31*I$7 | J32: =J18*J31*J$7 | ... AL32: =AL18*AL31*AL$7 | AM32: =SUMIF($C$6:$AL$6,1,C32:AL32) | AN32: =SUMIF($C$6:$AL$6,2,C32:AL32) | AO32: =SUMIF($C$6:$AL$6,3,C32:AL32) | AP32: =SUM(C32:AL32)
A33: Orders per product per month (with review ramp) | B33: orders | C33: ='Assumptions'!$C$131*MIN(1,(C$4-MAX('Assumptions'!$C$127,'Assumptions'!$C$9)+1)/'Assumptions'!$C$11)*C30 | D33: ='Assumptions'!$C$131*MIN(1,(D$4-MAX('Assumptions'!$C$127,'Assumptions'!$C$9)+1)/'Assumptions'!$C$11)*D30 | E33: ='Assumptions'!$C$131*MIN(1,(E$4-MAX('Assumptions'!$C$127,'Assumptions'!$C$9)+1)/'Assumptions'!$C$11)*E30 | F33: ='Assumptions'!$C$131*MIN(1,(F$4-MAX('Assumptions'!$C$127,'Assumptions'!$C$9)+1)/'Assumptions'!$C$11)*F30 | G33: ='Assumptions'!$C$131*MIN(1,(G$4-MAX('Assumptions'!$C$127,'Assumptions'!$C$9)+1)/'Assumptions'!$C$11)*G30 | H33: ='Assumptions'!$C$131*MIN(1,(H$4-MAX('Assumptions'!$C$127,'Assumptions'!$C$9)+1)/'Assumptions'!$C$11)*H30 | I33: ='Assumptions'!$C$131*MIN(1,(I$4-MAX('Assumptions'!$C$127,'Assumptions'!$C$9)+1)/'Assumptions'!$C$11)*I30 | J33: ='Assumptions'!$C$131*MIN(1,(J$4-MAX('Assumptions'!$C$127,'Assumptions'!$C$9)+1)/'Assumptions'!$C$11)*J30 | ... AL33: ='Assumptions'!$C$131*MIN(1,(AL$4-MAX('Assumptions'!$C$127,'Assumptions'!$C$9)+1)/'Assumptions'!$C$11)*AL30
A34: Orders | B34: orders | C34: =C32*C33 | D34: =D32*D33 | E34: =E32*E33 | F34: =F32*F33 | G34: =G32*G33 | H34: =H32*H33 | I34: =I32*I33 | J34: =J32*J33 | ... AL34: =AL32*AL33 | AM34: =SUMIF($C$6:$AL$6,1,C34:AL34) | AN34: =SUMIF($C$6:$AL$6,2,C34:AL34) | AO34: =SUMIF($C$6:$AL$6,3,C34:AL34) | AP34: =SUM(C34:AL34)
A35: Items sold | B35: items | C35: =C34*'Assumptions'!$C$132 | D35: =D34*'Assumptions'!$C$132 | E35: =E34*'Assumptions'!$C$132 | F35: =F34*'Assumptions'!$C$132 | G35: =G34*'Assumptions'!$C$132 | H35: =H34*'Assumptions'!$C$132 | I35: =I34*'Assumptions'!$C$132 | J35: =J34*'Assumptions'!$C$132 | ... AL35: =AL34*'Assumptions'!$C$132 | AM35: =SUMIF($C$6:$AL$6,1,C35:AL35) | AN35: =SUMIF($C$6:$AL$6,2,C35:AL35) | AO35: =SUMIF($C$6:$AL$6,3,C35:AL35) | AP35: =SUM(C35:AL35)
A36: Average order value | B36: $ | C36: ='Unit Economics'!$E$50*'Assumptions'!$C$132*C30 | D36: ='Unit Economics'!$E$50*'Assumptions'!$C$132*D30 | E36: ='Unit Economics'!$E$50*'Assumptions'!$C$132*E30 | F36: ='Unit Economics'!$E$50*'Assumptions'!$C$132*F30 | G36: ='Unit Economics'!$E$50*'Assumptions'!$C$132*G30 | H36: ='Unit Economics'!$E$50*'Assumptions'!$C$132*H30 | I36: ='Unit Economics'!$E$50*'Assumptions'!$C$132*I30 | J36: ='Unit Economics'!$E$50*'Assumptions'!$C$132*J30 | ... AL36: ='Unit Economics'!$E$50*'Assumptions'!$C$132*AL30
A37: Gross sales (price paid by customers) | B37: $ | C37: =C35*'Unit Economics'!$E$50 | D37: =D35*'Unit Economics'!$E$50 | E37: =E35*'Unit Economics'!$E$50 | F37: =F35*'Unit Economics'!$E$50 | G37: =G35*'Unit Economics'!$E$50 | H37: =H35*'Unit Economics'!$E$50 | I37: =I35*'Unit Economics'!$E$50 | J37: =J35*'Unit Economics'!$E$50 | ... AL37: =AL35*'Unit Economics'!$E$50 | AM37: =SUMIF($C$6:$AL$6,1,C37:AL37) | AN37: =SUMIF($C$6:$AL$6,2,C37:AL37) | AO37: =SUMIF($C$6:$AL$6,3,C37:AL37) | AP37: =SUM(C37:AL37)
A38: Net contribution to AlphaPlay | B38: $ | C38: =C35*'Unit Economics'!$F$50 | D38: =D35*'Unit Economics'!$F$50 | E38: =E35*'Unit Economics'!$F$50 | F38: =F35*'Unit Economics'!$F$50 | G38: =G35*'Unit Economics'!$F$50 | H38: =H35*'Unit Economics'!$F$50 | I38: =I35*'Unit Economics'!$F$50 | J38: =J35*'Unit Economics'!$F$50 | ... AL38: =AL35*'Unit Economics'!$F$50 | AM38: =SUMIF($C$6:$AL$6,1,C38:AL38) | AN38: =SUMIF($C$6:$AL$6,2,C38:AL38) | AO38: =SUMIF($C$6:$AL$6,3,C38:AL38) | AP38: =SUM(C38:AL38)
A39: Amazon KDP: paperbacks
A40: Active (1 = live) | B40: flag | C40: =IF(AND('Assumptions'!$C$134=1,C$4>=MAX('Assumptions'!$C$135,'Assumptions'!$C$9)),1,0) | D40: =IF(AND('Assumptions'!$C$134=1,D$4>=MAX('Assumptions'!$C$135,'Assumptions'!$C$9)),1,0) | E40: =IF(AND('Assumptions'!$C$134=1,E$4>=MAX('Assumptions'!$C$135,'Assumptions'!$C$9)),1,0) | F40: =IF(AND('Assumptions'!$C$134=1,F$4>=MAX('Assumptions'!$C$135,'Assumptions'!$C$9)),1,0) | G40: =IF(AND('Assumptions'!$C$134=1,G$4>=MAX('Assumptions'!$C$135,'Assumptions'!$C$9)),1,0) | H40: =IF(AND('Assumptions'!$C$134=1,H$4>=MAX('Assumptions'!$C$135,'Assumptions'!$C$9)),1,0) | I40: =IF(AND('Assumptions'!$C$134=1,I$4>=MAX('Assumptions'!$C$135,'Assumptions'!$C$9)),1,0) | J40: =IF(AND('Assumptions'!$C$134=1,J$4>=MAX('Assumptions'!$C$135,'Assumptions'!$C$9)),1,0) | ... AL40: =IF(AND('Assumptions'!$C$134=1,AL$4>=MAX('Assumptions'!$C$135,'Assumptions'!$C$9)),1,0)
A41: Titles live | B41: titles | C41: =IF(C40=0,0,MIN('Assumptions'!$C$138,'Assumptions'!$C$136+'Assumptions'!$C$137*(C$4-MAX('Assumptions'!$C$135,'Assumptions'!$C$9)))) | D41: =IF(D40=0,0,MIN('Assumptions'!$C$138,'Assumptions'!$C$136+'Assumptions'!$C$137*(D$4-MAX('Assumptions'!$C$135,'Assumptions'!$C$9)))) | E41: =IF(E40=0,0,MIN('Assumptions'!$C$138,'Assumptions'!$C$136+'Assumptions'!$C$137*(E$4-MAX('Assumptions'!$C$135,'Assumptions'!$C$9)))) | F41: =IF(F40=0,0,MIN('Assumptions'!$C$138,'Assumptions'!$C$136+'Assumptions'!$C$137*(F$4-MAX('Assumptions'!$C$135,'Assumptions'!$C$9)))) | G41: =IF(G40=0,0,MIN('Assumptions'!$C$138,'Assumptions'!$C$136+'Assumptions'!$C$137*(G$4-MAX('Assumptions'!$C$135,'Assumptions'!$C$9)))) | H41: =IF(H40=0,0,MIN('Assumptions'!$C$138,'Assumptions'!$C$136+'Assumptions'!$C$137*(H$4-MAX('Assumptions'!$C$135,'Assumptions'!$C$9)))) | I41: =IF(I40=0,0,MIN('Assumptions'!$C$138,'Assumptions'!$C$136+'Assumptions'!$C$137*(I$4-MAX('Assumptions'!$C$135,'Assumptions'!$C$9)))) | J41: =IF(J40=0,0,MIN('Assumptions'!$C$138,'Assumptions'!$C$136+'Assumptions'!$C$137*(J$4-MAX('Assumptions'!$C$135,'Assumptions'!$C$9)))) | ... AL41: =IF(AL40=0,0,MIN('Assumptions'!$C$138,'Assumptions'!$C$136+'Assumptions'!$C$137*(AL$4-MAX('Assumptions'!$C$135,'Assumptions'!$C$9))))
A42: Title-months live (titles x season) | B42: title-mo | C42: =C41*C$7 | D42: =D41*D$7 | E42: =E41*E$7 | F42: =F41*F$7 | G42: =G41*G$7 | H42: =H41*H$7 | I42: =I41*I$7 | J42: =J41*J$7 | ... AL42: =AL41*AL$7 | AM42: =SUMIF($C$6:$AL$6,1,C42:AL42) | AN42: =SUMIF($C$6:$AL$6,2,C42:AL42) | AO42: =SUMIF($C$6:$AL$6,3,C42:AL42) | AP42: =SUM(C42:AL42)
A43: Units per title per month (with review ramp) | B43: units | C43: ='Assumptions'!$C$139*MIN(1,(C$4-MAX('Assumptions'!$C$135,'Assumptions'!$C$9)+1)/'Assumptions'!$C$11)*C40 | D43: ='Assumptions'!$C$139*MIN(1,(D$4-MAX('Assumptions'!$C$135,'Assumptions'!$C$9)+1)/'Assumptions'!$C$11)*D40 | E43: ='Assumptions'!$C$139*MIN(1,(E$4-MAX('Assumptions'!$C$135,'Assumptions'!$C$9)+1)/'Assumptions'!$C$11)*E40 | F43: ='Assumptions'!$C$139*MIN(1,(F$4-MAX('Assumptions'!$C$135,'Assumptions'!$C$9)+1)/'Assumptions'!$C$11)*F40 | G43: ='Assumptions'!$C$139*MIN(1,(G$4-MAX('Assumptions'!$C$135,'Assumptions'!$C$9)+1)/'Assumptions'!$C$11)*G40 | H43: ='Assumptions'!$C$139*MIN(1,(H$4-MAX('Assumptions'!$C$135,'Assumptions'!$C$9)+1)/'Assumptions'!$C$11)*H40 | I43: ='Assumptions'!$C$139*MIN(1,(I$4-MAX('Assumptions'!$C$135,'Assumptions'!$C$9)+1)/'Assumptions'!$C$11)*I40 | J43: ='Assumptions'!$C$139*MIN(1,(J$4-MAX('Assumptions'!$C$135,'Assumptions'!$C$9)+1)/'Assumptions'!$C$11)*J40 | ... AL43: ='Assumptions'!$C$139*MIN(1,(AL$4-MAX('Assumptions'!$C$135,'Assumptions'!$C$9)+1)/'Assumptions'!$C$11)*AL40
A44: Orders | B44: orders | C44: =C42*C43 | D44: =D42*D43 | E44: =E42*E43 | F44: =F42*F43 | G44: =G42*G43 | H44: =H42*H43 | I44: =I42*I43 | J44: =J42*J43 | ... AL44: =AL42*AL43 | AM44: =SUMIF($C$6:$AL$6,1,C44:AL44) | AN44: =SUMIF($C$6:$AL$6,2,C44:AL44) | AO44: =SUMIF($C$6:$AL$6,3,C44:AL44) | AP44: =SUM(C44:AL44)
A45: Items sold | B45: items | C45: =C44*'Assumptions'!$C$140 | D45: =D44*'Assumptions'!$C$140 | E45: =E44*'Assumptions'!$C$140 | F45: =F44*'Assumptions'!$C$140 | G45: =G44*'Assumptions'!$C$140 | H45: =H44*'Assumptions'!$C$140 | I45: =I44*'Assumptions'!$C$140 | J45: =J44*'Assumptions'!$C$140 | ... AL45: =AL44*'Assumptions'!$C$140 | AM45: =SUMIF($C$6:$AL$6,1,C45:AL45) | AN45: =SUMIF($C$6:$AL$6,2,C45:AL45) | AO45: =SUMIF($C$6:$AL$6,3,C45:AL45) | AP45: =SUM(C45:AL45)
A46: Average order value | B46: $ | C46: ='Unit Economics'!$E$51*'Assumptions'!$C$140*C40 | D46: ='Unit Economics'!$E$51*'Assumptions'!$C$140*D40 | E46: ='Unit Economics'!$E$51*'Assumptions'!$C$140*E40 | F46: ='Unit Economics'!$E$51*'Assumptions'!$C$140*F40 | G46: ='Unit Economics'!$E$51*'Assumptions'!$C$140*G40 | H46: ='Unit Economics'!$E$51*'Assumptions'!$C$140*H40 | I46: ='Unit Economics'!$E$51*'Assumptions'!$C$140*I40 | J46: ='Unit Economics'!$E$51*'Assumptions'!$C$140*J40 | ... AL46: ='Unit Economics'!$E$51*'Assumptions'!$C$140*AL40
A47: Gross sales (price paid by customers) | B47: $ | C47: =C45*'Unit Economics'!$E$51 | D47: =D45*'Unit Economics'!$E$51 | E47: =E45*'Unit Economics'!$E$51 | F47: =F45*'Unit Economics'!$E$51 | G47: =G45*'Unit Economics'!$E$51 | H47: =H45*'Unit Economics'!$E$51 | I47: =I45*'Unit Economics'!$E$51 | J47: =J45*'Unit Economics'!$E$51 | ... AL47: =AL45*'Unit Economics'!$E$51 | AM47: =SUMIF($C$6:$AL$6,1,C47:AL47) | AN47: =SUMIF($C$6:$AL$6,2,C47:AL47) | AO47: =SUMIF($C$6:$AL$6,3,C47:AL47) | AP47: =SUM(C47:AL47)
A48: Net contribution to AlphaPlay | B48: $ | C48: =C45*'Unit Economics'!$F$51 | D48: =D45*'Unit Economics'!$F$51 | E48: =E45*'Unit Economics'!$F$51 | F48: =F45*'Unit Economics'!$F$51 | G48: =G45*'Unit Economics'!$F$51 | H48: =H45*'Unit Economics'!$F$51 | I48: =I45*'Unit Economics'!$F$51 | J48: =J45*'Unit Economics'!$F$51 | ... AL48: =AL45*'Unit Economics'!$F$51 | AM48: =SUMIF($C$6:$AL$6,1,C48:AL48) | AN48: =SUMIF($C$6:$AL$6,2,C48:AL48) | AO48: =SUMIF($C$6:$AL$6,3,C48:AL48) | AP48: =SUM(C48:AL48)
A49: IngramSpark: paperbacks to bookstores and libraries
A50: Active (1 = live) | B50: flag | C50: =IF(AND('Assumptions'!$C$142=1,C$4>=MAX('Assumptions'!$C$143,'Assumptions'!$C$9)),1,0) | D50: =IF(AND('Assumptions'!$C$142=1,D$4>=MAX('Assumptions'!$C$143,'Assumptions'!$C$9)),1,0) | E50: =IF(AND('Assumptions'!$C$142=1,E$4>=MAX('Assumptions'!$C$143,'Assumptions'!$C$9)),1,0) | F50: =IF(AND('Assumptions'!$C$142=1,F$4>=MAX('Assumptions'!$C$143,'Assumptions'!$C$9)),1,0) | G50: =IF(AND('Assumptions'!$C$142=1,G$4>=MAX('Assumptions'!$C$143,'Assumptions'!$C$9)),1,0) | H50: =IF(AND('Assumptions'!$C$142=1,H$4>=MAX('Assumptions'!$C$143,'Assumptions'!$C$9)),1,0) | I50: =IF(AND('Assumptions'!$C$142=1,I$4>=MAX('Assumptions'!$C$143,'Assumptions'!$C$9)),1,0) | J50: =IF(AND('Assumptions'!$C$142=1,J$4>=MAX('Assumptions'!$C$143,'Assumptions'!$C$9)),1,0) | ... AL50: =IF(AND('Assumptions'!$C$142=1,AL$4>=MAX('Assumptions'!$C$143,'Assumptions'!$C$9)),1,0)
A51: Titles live | B51: titles | C51: =IF(C50=0,0,MIN('Assumptions'!$C$146,'Assumptions'!$C$144+'Assumptions'!$C$145*(C$4-MAX('Assumptions'!$C$143,'Assumptions'!$C$9)))) | D51: =IF(D50=0,0,MIN('Assumptions'!$C$146,'Assumptions'!$C$144+'Assumptions'!$C$145*(D$4-MAX('Assumptions'!$C$143,'Assumptions'!$C$9)))) | E51: =IF(E50=0,0,MIN('Assumptions'!$C$146,'Assumptions'!$C$144+'Assumptions'!$C$145*(E$4-MAX('Assumptions'!$C$143,'Assumptions'!$C$9)))) | F51: =IF(F50=0,0,MIN('Assumptions'!$C$146,'Assumptions'!$C$144+'Assumptions'!$C$145*(F$4-MAX('Assumptions'!$C$143,'Assumptions'!$C$9)))) | G51: =IF(G50=0,0,MIN('Assumptions'!$C$146,'Assumptions'!$C$144+'Assumptions'!$C$145*(G$4-MAX('Assumptions'!$C$143,'Assumptions'!$C$9)))) | H51: =IF(H50=0,0,MIN('Assumptions'!$C$146,'Assumptions'!$C$144+'Assumptions'!$C$145*(H$4-MAX('Assumptions'!$C$143,'Assumptions'!$C$9)))) | I51: =IF(I50=0,0,MIN('Assumptions'!$C$146,'Assumptions'!$C$144+'Assumptions'!$C$145*(I$4-MAX('Assumptions'!$C$143,'Assumptions'!$C$9)))) | J51: =IF(J50=0,0,MIN('Assumptions'!$C$146,'Assumptions'!$C$144+'Assumptions'!$C$145*(J$4-MAX('Assumptions'!$C$143,'Assumptions'!$C$9)))) | ... AL51: =IF(AL50=0,0,MIN('Assumptions'!$C$146,'Assumptions'!$C$144+'Assumptions'!$C$145*(AL$4-MAX('Assumptions'!$C$143,'Assumptions'!$C$9))))
A52: Title-months live (titles x season) | B52: title-mo | C52: =C51*C$7 | D52: =D51*D$7 | E52: =E51*E$7 | F52: =F51*F$7 | G52: =G51*G$7 | H52: =H51*H$7 | I52: =I51*I$7 | J52: =J51*J$7 | ... AL52: =AL51*AL$7 | AM52: =SUMIF($C$6:$AL$6,1,C52:AL52) | AN52: =SUMIF($C$6:$AL$6,2,C52:AL52) | AO52: =SUMIF($C$6:$AL$6,3,C52:AL52) | AP52: =SUM(C52:AL52)
A53: Units per title per month (with review ramp) | B53: units | C53: ='Assumptions'!$C$147*MIN(1,(C$4-MAX('Assumptions'!$C$143,'Assumptions'!$C$9)+1)/'Assumptions'!$C$11)*C50 | D53: ='Assumptions'!$C$147*MIN(1,(D$4-MAX('Assumptions'!$C$143,'Assumptions'!$C$9)+1)/'Assumptions'!$C$11)*D50 | E53: ='Assumptions'!$C$147*MIN(1,(E$4-MAX('Assumptions'!$C$143,'Assumptions'!$C$9)+1)/'Assumptions'!$C$11)*E50 | F53: ='Assumptions'!$C$147*MIN(1,(F$4-MAX('Assumptions'!$C$143,'Assumptions'!$C$9)+1)/'Assumptions'!$C$11)*F50 | G53: ='Assumptions'!$C$147*MIN(1,(G$4-MAX('Assumptions'!$C$143,'Assumptions'!$C$9)+1)/'Assumptions'!$C$11)*G50 | H53: ='Assumptions'!$C$147*MIN(1,(H$4-MAX('Assumptions'!$C$143,'Assumptions'!$C$9)+1)/'Assumptions'!$C$11)*H50 | I53: ='Assumptions'!$C$147*MIN(1,(I$4-MAX('Assumptions'!$C$143,'Assumptions'!$C$9)+1)/'Assumptions'!$C$11)*I50 | J53: ='Assumptions'!$C$147*MIN(1,(J$4-MAX('Assumptions'!$C$143,'Assumptions'!$C$9)+1)/'Assumptions'!$C$11)*J50 | ... AL53: ='Assumptions'!$C$147*MIN(1,(AL$4-MAX('Assumptions'!$C$143,'Assumptions'!$C$9)+1)/'Assumptions'!$C$11)*AL50
A54: Orders | B54: orders | C54: =C52*C53 | D54: =D52*D53 | E54: =E52*E53 | F54: =F52*F53 | G54: =G52*G53 | H54: =H52*H53 | I54: =I52*I53 | J54: =J52*J53 | ... AL54: =AL52*AL53 | AM54: =SUMIF($C$6:$AL$6,1,C54:AL54) | AN54: =SUMIF($C$6:$AL$6,2,C54:AL54) | AO54: =SUMIF($C$6:$AL$6,3,C54:AL54) | AP54: =SUM(C54:AL54)
A55: Items sold | B55: items | C55: =C54*'Assumptions'!$C$148 | D55: =D54*'Assumptions'!$C$148 | E55: =E54*'Assumptions'!$C$148 | F55: =F54*'Assumptions'!$C$148 | G55: =G54*'Assumptions'!$C$148 | H55: =H54*'Assumptions'!$C$148 | I55: =I54*'Assumptions'!$C$148 | J55: =J54*'Assumptions'!$C$148 | ... AL55: =AL54*'Assumptions'!$C$148 | AM55: =SUMIF($C$6:$AL$6,1,C55:AL55) | AN55: =SUMIF($C$6:$AL$6,2,C55:AL55) | AO55: =SUMIF($C$6:$AL$6,3,C55:AL55) | AP55: =SUM(C55:AL55)
A56: Average order value | B56: $ | C56: ='Unit Economics'!$E$52*'Assumptions'!$C$148*C50 | D56: ='Unit Economics'!$E$52*'Assumptions'!$C$148*D50 | E56: ='Unit Economics'!$E$52*'Assumptions'!$C$148*E50 | F56: ='Unit Economics'!$E$52*'Assumptions'!$C$148*F50 | G56: ='Unit Economics'!$E$52*'Assumptions'!$C$148*G50 | H56: ='Unit Economics'!$E$52*'Assumptions'!$C$148*H50 | I56: ='Unit Economics'!$E$52*'Assumptions'!$C$148*I50 | J56: ='Unit Economics'!$E$52*'Assumptions'!$C$148*J50 | ... AL56: ='Unit Economics'!$E$52*'Assumptions'!$C$148*AL50
A57: Gross sales (price paid by customers) | B57: $ | C57: =C55*'Unit Economics'!$E$52 | D57: =D55*'Unit Economics'!$E$52 | E57: =E55*'Unit Economics'!$E$52 | F57: =F55*'Unit Economics'!$E$52 | G57: =G55*'Unit Economics'!$E$52 | H57: =H55*'Unit Economics'!$E$52 | I57: =I55*'Unit Economics'!$E$52 | J57: =J55*'Unit Economics'!$E$52 | ... AL57: =AL55*'Unit Economics'!$E$52 | AM57: =SUMIF($C$6:$AL$6,1,C57:AL57) | AN57: =SUMIF($C$6:$AL$6,2,C57:AL57) | AO57: =SUMIF($C$6:$AL$6,3,C57:AL57) | AP57: =SUM(C57:AL57)
A58: Net contribution to AlphaPlay | B58: $ | C58: =C55*'Unit Economics'!$F$52 | D58: =D55*'Unit Economics'!$F$52 | E58: =E55*'Unit Economics'!$F$52 | F58: =F55*'Unit Economics'!$F$52 | G58: =G55*'Unit Economics'!$F$52 | H58: =H55*'Unit Economics'!$F$52 | I58: =I55*'Unit Economics'!$F$52 | J58: =J55*'Unit Economics'!$F$52 | ... AL58: =AL55*'Unit Economics'!$F$52 | AM58: =SUMIF($C$6:$AL$6,1,C58:AL58) | AN58: =SUMIF($C$6:$AL$6,2,C58:AL58) | AO58: =SUMIF($C$6:$AL$6,3,C58:AL58) | AP58: =SUM(C58:AL58)
A59: International digital via merchant of record (Gumroad)
A60: Active (1 = live) | B60: flag | C60: =IF(AND('Assumptions'!$C$150=1,C$4>=MAX('Assumptions'!$C$151,'Assumptions'!$C$9)),1,0) | D60: =IF(AND('Assumptions'!$C$150=1,D$4>=MAX('Assumptions'!$C$151,'Assumptions'!$C$9)),1,0) | E60: =IF(AND('Assumptions'!$C$150=1,E$4>=MAX('Assumptions'!$C$151,'Assumptions'!$C$9)),1,0) | F60: =IF(AND('Assumptions'!$C$150=1,F$4>=MAX('Assumptions'!$C$151,'Assumptions'!$C$9)),1,0) | G60: =IF(AND('Assumptions'!$C$150=1,G$4>=MAX('Assumptions'!$C$151,'Assumptions'!$C$9)),1,0) | H60: =IF(AND('Assumptions'!$C$150=1,H$4>=MAX('Assumptions'!$C$151,'Assumptions'!$C$9)),1,0) | I60: =IF(AND('Assumptions'!$C$150=1,I$4>=MAX('Assumptions'!$C$151,'Assumptions'!$C$9)),1,0) | J60: =IF(AND('Assumptions'!$C$150=1,J$4>=MAX('Assumptions'!$C$151,'Assumptions'!$C$9)),1,0) | ... AL60: =IF(AND('Assumptions'!$C$150=1,AL$4>=MAX('Assumptions'!$C$151,'Assumptions'!$C$9)),1,0)
A61: Sales-per-product index (1.00 in the launch month) | B61: index | C61: =IF(C60=0,0,1) | D61: =IF(D60=0,0,IF(D$4=MAX('Assumptions'!$C$151,'Assumptions'!$C$9),1,C61*(1+CHOOSE(D$6,'Assumptions'!$C$152,'Assumptions'!$C$153,'Assumptions'!$C$154)))) | E61: =IF(E60=0,0,IF(E$4=MAX('Assumptions'!$C$151,'Assumptions'!$C$9),1,D61*(1+CHOOSE(E$6,'Assumptions'!$C$152,'Assumptions'!$C$153,'Assumptions'!$C$154)))) | F61: =IF(F60=0,0,IF(F$4=MAX('Assumptions'!$C$151,'Assumptions'!$C$9),1,E61*(1+CHOOSE(F$6,'Assumptions'!$C$152,'Assumptions'!$C$153,'Assumptions'!$C$154)))) | G61: =IF(G60=0,0,IF(G$4=MAX('Assumptions'!$C$151,'Assumptions'!$C$9),1,F61*(1+CHOOSE(G$6,'Assumptions'!$C$152,'Assumptions'!$C$153,'Assumptions'!$C$154)))) | H61: =IF(H60=0,0,IF(H$4=MAX('Assumptions'!$C$151,'Assumptions'!$C$9),1,G61*(1+CHOOSE(H$6,'Assumptions'!$C$152,'Assumptions'!$C$153,'Assumptions'!$C$154)))) | I61: =IF(I60=0,0,IF(I$4=MAX('Assumptions'!$C$151,'Assumptions'!$C$9),1,H61*(1+CHOOSE(I$6,'Assumptions'!$C$152,'Assumptions'!$C$153,'Assumptions'!$C$154)))) | J61: =IF(J60=0,0,IF(J$4=MAX('Assumptions'!$C$151,'Assumptions'!$C$9),1,I61*(1+CHOOSE(J$6,'Assumptions'!$C$152,'Assumptions'!$C$153,'Assumptions'!$C$154)))) | K61: =IF(K60=0,0,IF(K$4=MAX('Assumptions'!$C$151,'Assumptions'!$C$9),1,J61*(1+CHOOSE(K$6,'Assumptions'!$C$152,'Assumptions'!$C$153,'Assumptions'!$C$154)))) | ... AL61: =IF(AL60=0,0,IF(AL$4=MAX('Assumptions'!$C$151,'Assumptions'!$C$9),1,AK61*(1+CHOOSE(AL$6,'Assumptions'!$C$152,'Assumptions'!$C$153,'Assumptions'!$C$154))))
A62: Product-months live (products x sales index x season) | B62: prod-mo | C62: =C18*C61*C$7 | D62: =D18*D61*D$7 | E62: =E18*E61*E$7 | F62: =F18*F61*F$7 | G62: =G18*G61*G$7 | H62: =H18*H61*H$7 | I62: =I18*I61*I$7 | J62: =J18*J61*J$7 | ... AL62: =AL18*AL61*AL$7 | AM62: =SUMIF($C$6:$AL$6,1,C62:AL62) | AN62: =SUMIF($C$6:$AL$6,2,C62:AL62) | AO62: =SUMIF($C$6:$AL$6,3,C62:AL62) | AP62: =SUM(C62:AL62)
A63: Orders per product per month (with review ramp) | B63: orders | C63: ='Assumptions'!$C$155*MIN(1,(C$4-MAX('Assumptions'!$C$151,'Assumptions'!$C$9)+1)/'Assumptions'!$C$11)*C60 | D63: ='Assumptions'!$C$155*MIN(1,(D$4-MAX('Assumptions'!$C$151,'Assumptions'!$C$9)+1)/'Assumptions'!$C$11)*D60 | E63: ='Assumptions'!$C$155*MIN(1,(E$4-MAX('Assumptions'!$C$151,'Assumptions'!$C$9)+1)/'Assumptions'!$C$11)*E60 | F63: ='Assumptions'!$C$155*MIN(1,(F$4-MAX('Assumptions'!$C$151,'Assumptions'!$C$9)+1)/'Assumptions'!$C$11)*F60 | G63: ='Assumptions'!$C$155*MIN(1,(G$4-MAX('Assumptions'!$C$151,'Assumptions'!$C$9)+1)/'Assumptions'!$C$11)*G60 | H63: ='Assumptions'!$C$155*MIN(1,(H$4-MAX('Assumptions'!$C$151,'Assumptions'!$C$9)+1)/'Assumptions'!$C$11)*H60 | I63: ='Assumptions'!$C$155*MIN(1,(I$4-MAX('Assumptions'!$C$151,'Assumptions'!$C$9)+1)/'Assumptions'!$C$11)*I60 | J63: ='Assumptions'!$C$155*MIN(1,(J$4-MAX('Assumptions'!$C$151,'Assumptions'!$C$9)+1)/'Assumptions'!$C$11)*J60 | ... AL63: ='Assumptions'!$C$155*MIN(1,(AL$4-MAX('Assumptions'!$C$151,'Assumptions'!$C$9)+1)/'Assumptions'!$C$11)*AL60
A64: Orders | B64: orders | C64: =C62*C63 | D64: =D62*D63 | E64: =E62*E63 | F64: =F62*F63 | G64: =G62*G63 | H64: =H62*H63 | I64: =I62*I63 | J64: =J62*J63 | ... AL64: =AL62*AL63 | AM64: =SUMIF($C$6:$AL$6,1,C64:AL64) | AN64: =SUMIF($C$6:$AL$6,2,C64:AL64) | AO64: =SUMIF($C$6:$AL$6,3,C64:AL64) | AP64: =SUM(C64:AL64)
A65: Items sold | B65: items | C65: =C64*'Assumptions'!$C$156 | D65: =D64*'Assumptions'!$C$156 | E65: =E64*'Assumptions'!$C$156 | F65: =F64*'Assumptions'!$C$156 | G65: =G64*'Assumptions'!$C$156 | H65: =H64*'Assumptions'!$C$156 | I65: =I64*'Assumptions'!$C$156 | J65: =J64*'Assumptions'!$C$156 | ... AL65: =AL64*'Assumptions'!$C$156 | AM65: =SUMIF($C$6:$AL$6,1,C65:AL65) | AN65: =SUMIF($C$6:$AL$6,2,C65:AL65) | AO65: =SUMIF($C$6:$AL$6,3,C65:AL65) | AP65: =SUM(C65:AL65)
A66: Average order value | B66: $ | C66: ='Unit Economics'!$E$53*'Assumptions'!$C$156*C60 | D66: ='Unit Economics'!$E$53*'Assumptions'!$C$156*D60 | E66: ='Unit Economics'!$E$53*'Assumptions'!$C$156*E60 | F66: ='Unit Economics'!$E$53*'Assumptions'!$C$156*F60 | G66: ='Unit Economics'!$E$53*'Assumptions'!$C$156*G60 | H66: ='Unit Economics'!$E$53*'Assumptions'!$C$156*H60 | I66: ='Unit Economics'!$E$53*'Assumptions'!$C$156*I60 | J66: ='Unit Economics'!$E$53*'Assumptions'!$C$156*J60 | ... AL66: ='Unit Economics'!$E$53*'Assumptions'!$C$156*AL60
A67: Gross sales (price paid by customers) | B67: $ | C67: =C65*'Unit Economics'!$E$53 | D67: =D65*'Unit Economics'!$E$53 | E67: =E65*'Unit Economics'!$E$53 | F67: =F65*'Unit Economics'!$E$53 | G67: =G65*'Unit Economics'!$E$53 | H67: =H65*'Unit Economics'!$E$53 | I67: =I65*'Unit Economics'!$E$53 | J67: =J65*'Unit Economics'!$E$53 | ... AL67: =AL65*'Unit Economics'!$E$53 | AM67: =SUMIF($C$6:$AL$6,1,C67:AL67) | AN67: =SUMIF($C$6:$AL$6,2,C67:AL67) | AO67: =SUMIF($C$6:$AL$6,3,C67:AL67) | AP67: =SUM(C67:AL67)
A68: Net contribution to AlphaPlay | B68: $ | C68: =C65*'Unit Economics'!$F$53 | D68: =D65*'Unit Economics'!$F$53 | E68: =E65*'Unit Economics'!$F$53 | F68: =F65*'Unit Economics'!$F$53 | G68: =G65*'Unit Economics'!$F$53 | H68: =H65*'Unit Economics'!$F$53 | I68: =I65*'Unit Economics'!$F$53 | J68: =J65*'Unit Economics'!$F$53 | ... AL68: =AL65*'Unit Economics'!$F$53 | AM68: =SUMIF($C$6:$AL$6,1,C68:AL68) | AN68: =SUMIF($C$6:$AL$6,2,C68:AL68) | AO68: =SUMIF($C$6:$AL$6,3,C68:AL68) | AP68: =SUM(C68:AL68)
A69: 30-Day Screen Reset written course (Wave 2)
A70: Active (1 = live) | B70: flag | C70: =IF(AND('Assumptions'!$C$158=1,C$4>=MAX('Assumptions'!$C$159,'Assumptions'!$C$9)),1,0) | D70: =IF(AND('Assumptions'!$C$158=1,D$4>=MAX('Assumptions'!$C$159,'Assumptions'!$C$9)),1,0) | E70: =IF(AND('Assumptions'!$C$158=1,E$4>=MAX('Assumptions'!$C$159,'Assumptions'!$C$9)),1,0) | F70: =IF(AND('Assumptions'!$C$158=1,F$4>=MAX('Assumptions'!$C$159,'Assumptions'!$C$9)),1,0) | G70: =IF(AND('Assumptions'!$C$158=1,G$4>=MAX('Assumptions'!$C$159,'Assumptions'!$C$9)),1,0) | H70: =IF(AND('Assumptions'!$C$158=1,H$4>=MAX('Assumptions'!$C$159,'Assumptions'!$C$9)),1,0) | I70: =IF(AND('Assumptions'!$C$158=1,I$4>=MAX('Assumptions'!$C$159,'Assumptions'!$C$9)),1,0) | J70: =IF(AND('Assumptions'!$C$158=1,J$4>=MAX('Assumptions'!$C$159,'Assumptions'!$C$9)),1,0) | ... AL70: =IF(AND('Assumptions'!$C$158=1,AL$4>=MAX('Assumptions'!$C$159,'Assumptions'!$C$9)),1,0)
A71: Subscribers reached (list last month x reach) | B71: people | C71: =IF(C70=0,0,0*'Assumptions'!$C$162) | D71: =IF(D70=0,0,C114*'Assumptions'!$C$162) | E71: =IF(E70=0,0,D114*'Assumptions'!$C$162) | F71: =IF(F70=0,0,E114*'Assumptions'!$C$162) | G71: =IF(G70=0,0,F114*'Assumptions'!$C$162) | H71: =IF(H70=0,0,G114*'Assumptions'!$C$162) | I71: =IF(I70=0,0,H114*'Assumptions'!$C$162) | J71: =IF(J70=0,0,I114*'Assumptions'!$C$162) | K71: =IF(K70=0,0,J114*'Assumptions'!$C$162) | ... AL71: =IF(AL70=0,0,AK114*'Assumptions'!$C$162)
A72: Subscribers reached by the offer | B72: visits | C72: =C71*C$7 | D72: =D71*D$7 | E72: =E71*E$7 | F72: =F71*F$7 | G72: =G71*G$7 | H72: =H71*H$7 | I72: =I71*I$7 | J72: =J71*J$7 | ... AL72: =AL71*AL$7 | AM72: =SUMIF($C$6:$AL$6,1,C72:AL72) | AN72: =SUMIF($C$6:$AL$6,2,C72:AL72) | AO72: =SUMIF($C$6:$AL$6,3,C72:AL72) | AP72: =SUM(C72:AL72)
A73: Conversion rate (with review ramp) | B73: % | C73: ='Assumptions'!$C$160*MIN(1,(C$4-MAX('Assumptions'!$C$159,'Assumptions'!$C$9)+1)/'Assumptions'!$C$11)*C70 | D73: ='Assumptions'!$C$160*MIN(1,(D$4-MAX('Assumptions'!$C$159,'Assumptions'!$C$9)+1)/'Assumptions'!$C$11)*D70 | E73: ='Assumptions'!$C$160*MIN(1,(E$4-MAX('Assumptions'!$C$159,'Assumptions'!$C$9)+1)/'Assumptions'!$C$11)*E70 | F73: ='Assumptions'!$C$160*MIN(1,(F$4-MAX('Assumptions'!$C$159,'Assumptions'!$C$9)+1)/'Assumptions'!$C$11)*F70 | G73: ='Assumptions'!$C$160*MIN(1,(G$4-MAX('Assumptions'!$C$159,'Assumptions'!$C$9)+1)/'Assumptions'!$C$11)*G70 | H73: ='Assumptions'!$C$160*MIN(1,(H$4-MAX('Assumptions'!$C$159,'Assumptions'!$C$9)+1)/'Assumptions'!$C$11)*H70 | I73: ='Assumptions'!$C$160*MIN(1,(I$4-MAX('Assumptions'!$C$159,'Assumptions'!$C$9)+1)/'Assumptions'!$C$11)*I70 | J73: ='Assumptions'!$C$160*MIN(1,(J$4-MAX('Assumptions'!$C$159,'Assumptions'!$C$9)+1)/'Assumptions'!$C$11)*J70 | ... AL73: ='Assumptions'!$C$160*MIN(1,(AL$4-MAX('Assumptions'!$C$159,'Assumptions'!$C$9)+1)/'Assumptions'!$C$11)*AL70
A74: Orders | B74: orders | C74: =C72*C73 | D74: =D72*D73 | E74: =E72*E73 | F74: =F72*F73 | G74: =G72*G73 | H74: =H72*H73 | I74: =I72*I73 | J74: =J72*J73 | ... AL74: =AL72*AL73 | AM74: =SUMIF($C$6:$AL$6,1,C74:AL74) | AN74: =SUMIF($C$6:$AL$6,2,C74:AL74) | AO74: =SUMIF($C$6:$AL$6,3,C74:AL74) | AP74: =SUM(C74:AL74)
A75: Items sold | B75: items | C75: =C74*'Assumptions'!$C$161 | D75: =D74*'Assumptions'!$C$161 | E75: =E74*'Assumptions'!$C$161 | F75: =F74*'Assumptions'!$C$161 | G75: =G74*'Assumptions'!$C$161 | H75: =H74*'Assumptions'!$C$161 | I75: =I74*'Assumptions'!$C$161 | J75: =J74*'Assumptions'!$C$161 | ... AL75: =AL74*'Assumptions'!$C$161 | AM75: =SUMIF($C$6:$AL$6,1,C75:AL75) | AN75: =SUMIF($C$6:$AL$6,2,C75:AL75) | AO75: =SUMIF($C$6:$AL$6,3,C75:AL75) | AP75: =SUM(C75:AL75)
A76: Average order value | B76: $ | C76: ='Unit Economics'!$E$54*'Assumptions'!$C$161*C70 | D76: ='Unit Economics'!$E$54*'Assumptions'!$C$161*D70 | E76: ='Unit Economics'!$E$54*'Assumptions'!$C$161*E70 | F76: ='Unit Economics'!$E$54*'Assumptions'!$C$161*F70 | G76: ='Unit Economics'!$E$54*'Assumptions'!$C$161*G70 | H76: ='Unit Economics'!$E$54*'Assumptions'!$C$161*H70 | I76: ='Unit Economics'!$E$54*'Assumptions'!$C$161*I70 | J76: ='Unit Economics'!$E$54*'Assumptions'!$C$161*J70 | ... AL76: ='Unit Economics'!$E$54*'Assumptions'!$C$161*AL70
A77: Gross sales (price paid by customers) | B77: $ | C77: =C75*'Unit Economics'!$E$54 | D77: =D75*'Unit Economics'!$E$54 | E77: =E75*'Unit Economics'!$E$54 | F77: =F75*'Unit Economics'!$E$54 | G77: =G75*'Unit Economics'!$E$54 | H77: =H75*'Unit Economics'!$E$54 | I77: =I75*'Unit Economics'!$E$54 | J77: =J75*'Unit Economics'!$E$54 | ... AL77: =AL75*'Unit Economics'!$E$54 | AM77: =SUMIF($C$6:$AL$6,1,C77:AL77) | AN77: =SUMIF($C$6:$AL$6,2,C77:AL77) | AO77: =SUMIF($C$6:$AL$6,3,C77:AL77) | AP77: =SUM(C77:AL77)
A78: Net contribution to AlphaPlay | B78: $ | C78: =C75*'Unit Economics'!$F$54 | D78: =D75*'Unit Economics'!$F$54 | E78: =E75*'Unit Economics'!$F$54 | F78: =F75*'Unit Economics'!$F$54 | G78: =G75*'Unit Economics'!$F$54 | H78: =H75*'Unit Economics'!$F$54 | I78: =I75*'Unit Economics'!$F$54 | J78: =J75*'Unit Economics'!$F$54 | ... AL78: =AL75*'Unit Economics'!$F$54 | AM78: =SUMIF($C$6:$AL$6,1,C78:AL78) | AN78: =SUMIF($C$6:$AL$6,2,C78:AL78) | AO78: =SUMIF($C$6:$AL$6,3,C78:AL78) | AP78: =SUM(C78:AL78)
A79: Board book: pre-sale, then 3PL and Amazon FBA (gated option; off in base)
A80: Active (1 = live) | B80: flag | C80: =IF(AND('Assumptions'!$C$164=1,C$4>=MAX('Assumptions'!$C$165,'Assumptions'!$C$9)),1,0) | D80: =IF(AND('Assumptions'!$C$164=1,D$4>=MAX('Assumptions'!$C$165,'Assumptions'!$C$9)),1,0) | E80: =IF(AND('Assumptions'!$C$164=1,E$4>=MAX('Assumptions'!$C$165,'Assumptions'!$C$9)),1,0) | F80: =IF(AND('Assumptions'!$C$164=1,F$4>=MAX('Assumptions'!$C$165,'Assumptions'!$C$9)),1,0) | G80: =IF(AND('Assumptions'!$C$164=1,G$4>=MAX('Assumptions'!$C$165,'Assumptions'!$C$9)),1,0) | H80: =IF(AND('Assumptions'!$C$164=1,H$4>=MAX('Assumptions'!$C$165,'Assumptions'!$C$9)),1,0) | I80: =IF(AND('Assumptions'!$C$164=1,I$4>=MAX('Assumptions'!$C$165,'Assumptions'!$C$9)),1,0) | J80: =IF(AND('Assumptions'!$C$164=1,J$4>=MAX('Assumptions'!$C$165,'Assumptions'!$C$9)),1,0) | ... AL80: =IF(AND('Assumptions'!$C$164=1,AL$4>=MAX('Assumptions'!$C$165,'Assumptions'!$C$9)),1,0)
A81: Traffic trend (before seasonality) | B81: visits | C81: =IF(C80=0,0,'Assumptions'!$C$166) | D81: =IF(D80=0,0,IF(D$4=MAX('Assumptions'!$C$165,'Assumptions'!$C$9),'Assumptions'!$C$166,C81*(1+CHOOSE(D$6,'Assumptions'!$C$167,'Assumptions'!$C$168,'Assumptions'!$C$169)))) | E81: =IF(E80=0,0,IF(E$4=MAX('Assumptions'!$C$165,'Assumptions'!$C$9),'Assumptions'!$C$166,D81*(1+CHOOSE(E$6,'Assumptions'!$C$167,'Assumptions'!$C$168,'Assumptions'!$C$169)))) | F81: =IF(F80=0,0,IF(F$4=MAX('Assumptions'!$C$165,'Assumptions'!$C$9),'Assumptions'!$C$166,E81*(1+CHOOSE(F$6,'Assumptions'!$C$167,'Assumptions'!$C$168,'Assumptions'!$C$169)))) | G81: =IF(G80=0,0,IF(G$4=MAX('Assumptions'!$C$165,'Assumptions'!$C$9),'Assumptions'!$C$166,F81*(1+CHOOSE(G$6,'Assumptions'!$C$167,'Assumptions'!$C$168,'Assumptions'!$C$169)))) | H81: =IF(H80=0,0,IF(H$4=MAX('Assumptions'!$C$165,'Assumptions'!$C$9),'Assumptions'!$C$166,G81*(1+CHOOSE(H$6,'Assumptions'!$C$167,'Assumptions'!$C$168,'Assumptions'!$C$169)))) | I81: =IF(I80=0,0,IF(I$4=MAX('Assumptions'!$C$165,'Assumptions'!$C$9),'Assumptions'!$C$166,H81*(1+CHOOSE(I$6,'Assumptions'!$C$167,'Assumptions'!$C$168,'Assumptions'!$C$169)))) | J81: =IF(J80=0,0,IF(J$4=MAX('Assumptions'!$C$165,'Assumptions'!$C$9),'Assumptions'!$C$166,I81*(1+CHOOSE(J$6,'Assumptions'!$C$167,'Assumptions'!$C$168,'Assumptions'!$C$169)))) | K81: =IF(K80=0,0,IF(K$4=MAX('Assumptions'!$C$165,'Assumptions'!$C$9),'Assumptions'!$C$166,J81*(1+CHOOSE(K$6,'Assumptions'!$C$167,'Assumptions'!$C$168,'Assumptions'!$C$169)))) | ... AL81: =IF(AL80=0,0,IF(AL$4=MAX('Assumptions'!$C$165,'Assumptions'!$C$9),'Assumptions'!$C$166,AK81*(1+CHOOSE(AL$6,'Assumptions'!$C$167,'Assumptions'!$C$168,'Assumptions'!$C$169))))
A82: Product-page sessions (site + Amazon) | B82: visits | C82: =C81*C$7 | D82: =D81*D$7 | E82: =E81*E$7 | F82: =F81*F$7 | G82: =G81*G$7 | H82: =H81*H$7 | I82: =I81*I$7 | J82: =J81*J$7 | ... AL82: =AL81*AL$7 | AM82: =SUMIF($C$6:$AL$6,1,C82:AL82) | AN82: =SUMIF($C$6:$AL$6,2,C82:AL82) | AO82: =SUMIF($C$6:$AL$6,3,C82:AL82) | AP82: =SUM(C82:AL82)
A83: Conversion rate (with review ramp) | B83: % | C83: ='Assumptions'!$C$170*MIN(1,(C$4-MAX('Assumptions'!$C$165,'Assumptions'!$C$9)+1)/'Assumptions'!$C$11)*C80 | D83: ='Assumptions'!$C$170*MIN(1,(D$4-MAX('Assumptions'!$C$165,'Assumptions'!$C$9)+1)/'Assumptions'!$C$11)*D80 | E83: ='Assumptions'!$C$170*MIN(1,(E$4-MAX('Assumptions'!$C$165,'Assumptions'!$C$9)+1)/'Assumptions'!$C$11)*E80 | F83: ='Assumptions'!$C$170*MIN(1,(F$4-MAX('Assumptions'!$C$165,'Assumptions'!$C$9)+1)/'Assumptions'!$C$11)*F80 | G83: ='Assumptions'!$C$170*MIN(1,(G$4-MAX('Assumptions'!$C$165,'Assumptions'!$C$9)+1)/'Assumptions'!$C$11)*G80 | H83: ='Assumptions'!$C$170*MIN(1,(H$4-MAX('Assumptions'!$C$165,'Assumptions'!$C$9)+1)/'Assumptions'!$C$11)*H80 | I83: ='Assumptions'!$C$170*MIN(1,(I$4-MAX('Assumptions'!$C$165,'Assumptions'!$C$9)+1)/'Assumptions'!$C$11)*I80 | J83: ='Assumptions'!$C$170*MIN(1,(J$4-MAX('Assumptions'!$C$165,'Assumptions'!$C$9)+1)/'Assumptions'!$C$11)*J80 | ... AL83: ='Assumptions'!$C$170*MIN(1,(AL$4-MAX('Assumptions'!$C$165,'Assumptions'!$C$9)+1)/'Assumptions'!$C$11)*AL80
A84: Orders recognized (x go flag; a missed pre-sale is refunded) | B84: orders | C84: =C82*C83*$B$14 | D84: =D82*D83*$B$14 | E84: =E82*E83*$B$14 | F84: =F82*F83*$B$14 | G84: =G82*G83*$B$14 | H84: =H82*H83*$B$14 | I84: =I82*I83*$B$14 | J84: =J82*J83*$B$14 | ... AL84: =AL82*AL83*$B$14 | AM84: =SUMIF($C$6:$AL$6,1,C84:AL84) | AN84: =SUMIF($C$6:$AL$6,2,C84:AL84) | AO84: =SUMIF($C$6:$AL$6,3,C84:AL84) | AP84: =SUM(C84:AL84)
A85: Items sold | B85: items | C85: =C84*'Assumptions'!$C$171 | D85: =D84*'Assumptions'!$C$171 | E85: =E84*'Assumptions'!$C$171 | F85: =F84*'Assumptions'!$C$171 | G85: =G84*'Assumptions'!$C$171 | H85: =H84*'Assumptions'!$C$171 | I85: =I84*'Assumptions'!$C$171 | J85: =J84*'Assumptions'!$C$171 | ... AL85: =AL84*'Assumptions'!$C$171 | AM85: =SUMIF($C$6:$AL$6,1,C85:AL85) | AN85: =SUMIF($C$6:$AL$6,2,C85:AL85) | AO85: =SUMIF($C$6:$AL$6,3,C85:AL85) | AP85: =SUM(C85:AL85)
A86: Average order value | B86: $ | C86: ='Unit Economics'!$E$55*'Assumptions'!$C$171*C80 | D86: ='Unit Economics'!$E$55*'Assumptions'!$C$171*D80 | E86: ='Unit Economics'!$E$55*'Assumptions'!$C$171*E80 | F86: ='Unit Economics'!$E$55*'Assumptions'!$C$171*F80 | G86: ='Unit Economics'!$E$55*'Assumptions'!$C$171*G80 | H86: ='Unit Economics'!$E$55*'Assumptions'!$C$171*H80 | I86: ='Unit Economics'!$E$55*'Assumptions'!$C$171*I80 | J86: ='Unit Economics'!$E$55*'Assumptions'!$C$171*J80 | ... AL86: ='Unit Economics'!$E$55*'Assumptions'!$C$171*AL80
A87: Gross sales (price paid by customers) | B87: $ | C87: =C85*'Unit Economics'!$E$55 | D87: =D85*'Unit Economics'!$E$55 | E87: =E85*'Unit Economics'!$E$55 | F87: =F85*'Unit Economics'!$E$55 | G87: =G85*'Unit Economics'!$E$55 | H87: =H85*'Unit Economics'!$E$55 | I87: =I85*'Unit Economics'!$E$55 | J87: =J85*'Unit Economics'!$E$55 | ... AL87: =AL85*'Unit Economics'!$E$55 | AM87: =SUMIF($C$6:$AL$6,1,C87:AL87) | AN87: =SUMIF($C$6:$AL$6,2,C87:AL87) | AO87: =SUMIF($C$6:$AL$6,3,C87:AL87) | AP87: =SUM(C87:AL87)
A88: Net contribution to AlphaPlay | B88: $ | C88: =C85*IF(C$4<$B$11,'Unit Economics'!$M$36,'Unit Economics'!$F$55) | D88: =D85*IF(D$4<$B$11,'Unit Economics'!$M$36,'Unit Economics'!$F$55) | E88: =E85*IF(E$4<$B$11,'Unit Economics'!$M$36,'Unit Economics'!$F$55) | F88: =F85*IF(F$4<$B$11,'Unit Economics'!$M$36,'Unit Economics'!$F$55) | G88: =G85*IF(G$4<$B$11,'Unit Economics'!$M$36,'Unit Economics'!$F$55) | H88: =H85*IF(H$4<$B$11,'Unit Economics'!$M$36,'Unit Economics'!$F$55) | I88: =I85*IF(I$4<$B$11,'Unit Economics'!$M$36,'Unit Economics'!$F$55) | J88: =J85*IF(J$4<$B$11,'Unit Economics'!$M$36,'Unit Economics'!$F$55) | ... AL88: =AL85*IF(AL$4<$B$11,'Unit Economics'!$M$36,'Unit Economics'!$F$55) | AM88: =SUMIF($C$6:$AL$6,1,C88:AL88) | AN88: =SUMIF($C$6:$AL$6,2,C88:AL88) | AO88: =SUMIF($C$6:$AL$6,3,C88:AL88) | AP88: =SUM(C88:AL88)
A89: Items ordered (demand before the go / no-go test) | B89: items | C89: =C82*C83*'Assumptions'!$C$171 | D89: =D82*D83*'Assumptions'!$C$171 | E89: =E82*E83*'Assumptions'!$C$171 | F89: =F82*F83*'Assumptions'!$C$171 | G89: =G82*G83*'Assumptions'!$C$171 | H89: =H82*H83*'Assumptions'!$C$171 | I89: =I82*I83*'Assumptions'!$C$171 | J89: =J82*J83*'Assumptions'!$C$171 | ... AL89: =AL82*AL83*'Assumptions'!$C$171 | AM89: =SUMIF($C$6:$AL$6,1,C89:AL89) | AN89: =SUMIF($C$6:$AL$6,2,C89:AL89) | AO89: =SUMIF($C$6:$AL$6,3,C89:AL89) | AP89: =SUM(C89:AL89)
A90: School and group licenses + TPT (overlay only if counsel clears in writing; off in base)
A91: Active (1 = live) | B91: flag | C91: =IF(AND('Assumptions'!$C$173=1,C$4>=MAX('Assumptions'!$C$174,'Assumptions'!$C$9)),1,0) | D91: =IF(AND('Assumptions'!$C$173=1,D$4>=MAX('Assumptions'!$C$174,'Assumptions'!$C$9)),1,0) | E91: =IF(AND('Assumptions'!$C$173=1,E$4>=MAX('Assumptions'!$C$174,'Assumptions'!$C$9)),1,0) | F91: =IF(AND('Assumptions'!$C$173=1,F$4>=MAX('Assumptions'!$C$174,'Assumptions'!$C$9)),1,0) | G91: =IF(AND('Assumptions'!$C$173=1,G$4>=MAX('Assumptions'!$C$174,'Assumptions'!$C$9)),1,0) | H91: =IF(AND('Assumptions'!$C$173=1,H$4>=MAX('Assumptions'!$C$174,'Assumptions'!$C$9)),1,0) | I91: =IF(AND('Assumptions'!$C$173=1,I$4>=MAX('Assumptions'!$C$174,'Assumptions'!$C$9)),1,0) | J91: =IF(AND('Assumptions'!$C$173=1,J$4>=MAX('Assumptions'!$C$174,'Assumptions'!$C$9)),1,0) | ... AL91: =IF(AND('Assumptions'!$C$173=1,AL$4>=MAX('Assumptions'!$C$174,'Assumptions'!$C$9)),1,0)
A92: Traffic trend (before seasonality) | B92: visits | C92: =IF(C91=0,0,'Assumptions'!$C$175) | D92: =IF(D91=0,0,IF(D$4=MAX('Assumptions'!$C$174,'Assumptions'!$C$9),'Assumptions'!$C$175,C92*(1+CHOOSE(D$6,'Assumptions'!$C$176,'Assumptions'!$C$177,'Assumptions'!$C$178)))) | E92: =IF(E91=0,0,IF(E$4=MAX('Assumptions'!$C$174,'Assumptions'!$C$9),'Assumptions'!$C$175,D92*(1+CHOOSE(E$6,'Assumptions'!$C$176,'Assumptions'!$C$177,'Assumptions'!$C$178)))) | F92: =IF(F91=0,0,IF(F$4=MAX('Assumptions'!$C$174,'Assumptions'!$C$9),'Assumptions'!$C$175,E92*(1+CHOOSE(F$6,'Assumptions'!$C$176,'Assumptions'!$C$177,'Assumptions'!$C$178)))) | G92: =IF(G91=0,0,IF(G$4=MAX('Assumptions'!$C$174,'Assumptions'!$C$9),'Assumptions'!$C$175,F92*(1+CHOOSE(G$6,'Assumptions'!$C$176,'Assumptions'!$C$177,'Assumptions'!$C$178)))) | H92: =IF(H91=0,0,IF(H$4=MAX('Assumptions'!$C$174,'Assumptions'!$C$9),'Assumptions'!$C$175,G92*(1+CHOOSE(H$6,'Assumptions'!$C$176,'Assumptions'!$C$177,'Assumptions'!$C$178)))) | I92: =IF(I91=0,0,IF(I$4=MAX('Assumptions'!$C$174,'Assumptions'!$C$9),'Assumptions'!$C$175,H92*(1+CHOOSE(I$6,'Assumptions'!$C$176,'Assumptions'!$C$177,'Assumptions'!$C$178)))) | J92: =IF(J91=0,0,IF(J$4=MAX('Assumptions'!$C$174,'Assumptions'!$C$9),'Assumptions'!$C$175,I92*(1+CHOOSE(J$6,'Assumptions'!$C$176,'Assumptions'!$C$177,'Assumptions'!$C$178)))) | K92: =IF(K91=0,0,IF(K$4=MAX('Assumptions'!$C$174,'Assumptions'!$C$9),'Assumptions'!$C$175,J92*(1+CHOOSE(K$6,'Assumptions'!$C$176,'Assumptions'!$C$177,'Assumptions'!$C$178)))) | ... AL92: =IF(AL91=0,0,IF(AL$4=MAX('Assumptions'!$C$174,'Assumptions'!$C$9),'Assumptions'!$C$175,AK92*(1+CHOOSE(AL$6,'Assumptions'!$C$176,'Assumptions'!$C$177,'Assumptions'!$C$178))))
A93: Schools/orgs page + TPT views | B93: visits | C93: =C92*C$8 | D93: =D92*D$8 | E93: =E92*E$8 | F93: =F92*F$8 | G93: =G92*G$8 | H93: =H92*H$8 | I93: =I92*I$8 | J93: =J92*J$8 | ... AL93: =AL92*AL$8 | AM93: =SUMIF($C$6:$AL$6,1,C93:AL93) | AN93: =SUMIF($C$6:$AL$6,2,C93:AL93) | AO93: =SUMIF($C$6:$AL$6,3,C93:AL93) | AP93: =SUM(C93:AL93)
A94: Conversion rate (with review ramp) | B94: % | C94: ='Assumptions'!$C$179*MIN(1,(C$4-MAX('Assumptions'!$C$174,'Assumptions'!$C$9)+1)/'Assumptions'!$C$11)*C91 | D94: ='Assumptions'!$C$179*MIN(1,(D$4-MAX('Assumptions'!$C$174,'Assumptions'!$C$9)+1)/'Assumptions'!$C$11)*D91 | E94: ='Assumptions'!$C$179*MIN(1,(E$4-MAX('Assumptions'!$C$174,'Assumptions'!$C$9)+1)/'Assumptions'!$C$11)*E91 | F94: ='Assumptions'!$C$179*MIN(1,(F$4-MAX('Assumptions'!$C$174,'Assumptions'!$C$9)+1)/'Assumptions'!$C$11)*F91 | G94: ='Assumptions'!$C$179*MIN(1,(G$4-MAX('Assumptions'!$C$174,'Assumptions'!$C$9)+1)/'Assumptions'!$C$11)*G91 | H94: ='Assumptions'!$C$179*MIN(1,(H$4-MAX('Assumptions'!$C$174,'Assumptions'!$C$9)+1)/'Assumptions'!$C$11)*H91 | I94: ='Assumptions'!$C$179*MIN(1,(I$4-MAX('Assumptions'!$C$174,'Assumptions'!$C$9)+1)/'Assumptions'!$C$11)*I91 | J94: ='Assumptions'!$C$179*MIN(1,(J$4-MAX('Assumptions'!$C$174,'Assumptions'!$C$9)+1)/'Assumptions'!$C$11)*J91 | ... AL94: ='Assumptions'!$C$179*MIN(1,(AL$4-MAX('Assumptions'!$C$174,'Assumptions'!$C$9)+1)/'Assumptions'!$C$11)*AL91
A95: Orders | B95: orders | C95: =C93*C94 | D95: =D93*D94 | E95: =E93*E94 | F95: =F93*F94 | G95: =G93*G94 | H95: =H93*H94 | I95: =I93*I94 | J95: =J93*J94 | ... AL95: =AL93*AL94 | AM95: =SUMIF($C$6:$AL$6,1,C95:AL95) | AN95: =SUMIF($C$6:$AL$6,2,C95:AL95) | AO95: =SUMIF($C$6:$AL$6,3,C95:AL95) | AP95: =SUM(C95:AL95)
A96: Items sold | B96: items | C96: =C95*'Assumptions'!$C$180 | D96: =D95*'Assumptions'!$C$180 | E96: =E95*'Assumptions'!$C$180 | F96: =F95*'Assumptions'!$C$180 | G96: =G95*'Assumptions'!$C$180 | H96: =H95*'Assumptions'!$C$180 | I96: =I95*'Assumptions'!$C$180 | J96: =J95*'Assumptions'!$C$180 | ... AL96: =AL95*'Assumptions'!$C$180 | AM96: =SUMIF($C$6:$AL$6,1,C96:AL96) | AN96: =SUMIF($C$6:$AL$6,2,C96:AL96) | AO96: =SUMIF($C$6:$AL$6,3,C96:AL96) | AP96: =SUM(C96:AL96)
A97: Average order value | B97: $ | C97: ='Unit Economics'!$E$56*'Assumptions'!$C$180*C91 | D97: ='Unit Economics'!$E$56*'Assumptions'!$C$180*D91 | E97: ='Unit Economics'!$E$56*'Assumptions'!$C$180*E91 | F97: ='Unit Economics'!$E$56*'Assumptions'!$C$180*F91 | G97: ='Unit Economics'!$E$56*'Assumptions'!$C$180*G91 | H97: ='Unit Economics'!$E$56*'Assumptions'!$C$180*H91 | I97: ='Unit Economics'!$E$56*'Assumptions'!$C$180*I91 | J97: ='Unit Economics'!$E$56*'Assumptions'!$C$180*J91 | ... AL97: ='Unit Economics'!$E$56*'Assumptions'!$C$180*AL91
A98: Gross sales (price paid by customers) | B98: $ | C98: =C96*'Unit Economics'!$E$56 | D98: =D96*'Unit Economics'!$E$56 | E98: =E96*'Unit Economics'!$E$56 | F98: =F96*'Unit Economics'!$E$56 | G98: =G96*'Unit Economics'!$E$56 | H98: =H96*'Unit Economics'!$E$56 | I98: =I96*'Unit Economics'!$E$56 | J98: =J96*'Unit Economics'!$E$56 | ... AL98: =AL96*'Unit Economics'!$E$56 | AM98: =SUMIF($C$6:$AL$6,1,C98:AL98) | AN98: =SUMIF($C$6:$AL$6,2,C98:AL98) | AO98: =SUMIF($C$6:$AL$6,3,C98:AL98) | AP98: =SUM(C98:AL98)
A99: Net contribution to AlphaPlay | B99: $ | C99: =C96*'Unit Economics'!$F$56 | D99: =D96*'Unit Economics'!$F$56 | E99: =E96*'Unit Economics'!$F$56 | F99: =F96*'Unit Economics'!$F$56 | G99: =G96*'Unit Economics'!$F$56 | H99: =H96*'Unit Economics'!$F$56 | I99: =I96*'Unit Economics'!$F$56 | J99: =J96*'Unit Economics'!$F$56 | ... AL99: =AL96*'Unit Economics'!$F$56 | AM99: =SUMIF($C$6:$AL$6,1,C99:AL99) | AN99: =SUMIF($C$6:$AL$6,2,C99:AL99) | AO99: =SUMIF($C$6:$AL$6,3,C99:AL99) | AP99: =SUM(C99:AL99)
A100: Retail and wholesale: Faire, Walmart Marketplace (off in base)
A101: Active (1 = live) | B101: flag | C101: =IF(AND('Assumptions'!$C$182=1,C$4>=MAX('Assumptions'!$C$183,'Assumptions'!$C$9)),1,0) | D101: =IF(AND('Assumptions'!$C$182=1,D$4>=MAX('Assumptions'!$C$183,'Assumptions'!$C$9)),1,0) | E101: =IF(AND('Assumptions'!$C$182=1,E$4>=MAX('Assumptions'!$C$183,'Assumptions'!$C$9)),1,0) | F101: =IF(AND('Assumptions'!$C$182=1,F$4>=MAX('Assumptions'!$C$183,'Assumptions'!$C$9)),1,0) | G101: =IF(AND('Assumptions'!$C$182=1,G$4>=MAX('Assumptions'!$C$183,'Assumptions'!$C$9)),1,0) | H101: =IF(AND('Assumptions'!$C$182=1,H$4>=MAX('Assumptions'!$C$183,'Assumptions'!$C$9)),1,0) | I101: =IF(AND('Assumptions'!$C$182=1,I$4>=MAX('Assumptions'!$C$183,'Assumptions'!$C$9)),1,0) | J101: =IF(AND('Assumptions'!$C$182=1,J$4>=MAX('Assumptions'!$C$183,'Assumptions'!$C$9)),1,0) | ... AL101: =IF(AND('Assumptions'!$C$182=1,AL$4>=MAX('Assumptions'!$C$183,'Assumptions'!$C$9)),1,0)
A102: Traffic trend (before seasonality) | B102: visits | C102: =IF(C101=0,0,'Assumptions'!$C$184) | D102: =IF(D101=0,0,IF(D$4=MAX('Assumptions'!$C$183,'Assumptions'!$C$9),'Assumptions'!$C$184,C102*(1+CHOOSE(D$6,'Assumptions'!$C$185,'Assumptions'!$C$186,'Assumptions'!$C$187)))) | E102: =IF(E101=0,0,IF(E$4=MAX('Assumptions'!$C$183,'Assumptions'!$C$9),'Assumptions'!$C$184,D102*(1+CHOOSE(E$6,'Assumptions'!$C$185,'Assumptions'!$C$186,'Assumptions'!$C$187)))) | F102: =IF(F101=0,0,IF(F$4=MAX('Assumptions'!$C$183,'Assumptions'!$C$9),'Assumptions'!$C$184,E102*(1+CHOOSE(F$6,'Assumptions'!$C$185,'Assumptions'!$C$186,'Assumptions'!$C$187)))) | G102: =IF(G101=0,0,IF(G$4=MAX('Assumptions'!$C$183,'Assumptions'!$C$9),'Assumptions'!$C$184,F102*(1+CHOOSE(G$6,'Assumptions'!$C$185,'Assumptions'!$C$186,'Assumptions'!$C$187)))) | H102: =IF(H101=0,0,IF(H$4=MAX('Assumptions'!$C$183,'Assumptions'!$C$9),'Assumptions'!$C$184,G102*(1+CHOOSE(H$6,'Assumptions'!$C$185,'Assumptions'!$C$186,'Assumptions'!$C$187)))) | I102: =IF(I101=0,0,IF(I$4=MAX('Assumptions'!$C$183,'Assumptions'!$C$9),'Assumptions'!$C$184,H102*(1+CHOOSE(I$6,'Assumptions'!$C$185,'Assumptions'!$C$186,'Assumptions'!$C$187)))) | J102: =IF(J101=0,0,IF(J$4=MAX('Assumptions'!$C$183,'Assumptions'!$C$9),'Assumptions'!$C$184,I102*(1+CHOOSE(J$6,'Assumptions'!$C$185,'Assumptions'!$C$186,'Assumptions'!$C$187)))) | K102: =IF(K101=0,0,IF(K$4=MAX('Assumptions'!$C$183,'Assumptions'!$C$9),'Assumptions'!$C$184,J102*(1+CHOOSE(K$6,'Assumptions'!$C$185,'Assumptions'!$C$186,'Assumptions'!$C$187)))) | ... AL102: =IF(AL101=0,0,IF(AL$4=MAX('Assumptions'!$C$183,'Assumptions'!$C$9),'Assumptions'!$C$184,AK102*(1+CHOOSE(AL$6,'Assumptions'!$C$185,'Assumptions'!$C$186,'Assumptions'!$C$187))))
A103: Retailer and marketplace views | B103: visits | C103: =C102*C$7 | D103: =D102*D$7 | E103: =E102*E$7 | F103: =F102*F$7 | G103: =G102*G$7 | H103: =H102*H$7 | I103: =I102*I$7 | J103: =J102*J$7 | ... AL103: =AL102*AL$7 | AM103: =SUMIF($C$6:$AL$6,1,C103:AL103) | AN103: =SUMIF($C$6:$AL$6,2,C103:AL103) | AO103: =SUMIF($C$6:$AL$6,3,C103:AL103) | AP103: =SUM(C103:AL103)
...

Sheet Cash Flow
A1: Cash flow: payout delays, inventory purchases, one-time costs and the tax reserve
A2: Marketplace payouts arrive after the sale month (KDP about 60 days, IngramSpark about 90 days; see Assumptions section 4). Costs are negative. Sales tax and VAT are pass-through and excluded. Founder capital goes in whenever the operating account would fall below zero, so the cumulative founder capital row is the funding need. The tax reserve holds 25% of cumulative profit after one-time costs (none while cumulative results are negative); the accountant sets the real figure.
A4: Model month # | C4: ='36-Month Forecast'!C4 | D4: ='36-Month Forecast'!D4 | E4: ='36-Month Forecast'!E4 | F4: ='36-Month Forecast'!F4 | G4: ='36-Month Forecast'!G4 | H4: ='36-Month Forecast'!H4 | I4: ='36-Month Forecast'!I4 | J4: ='36-Month Forecast'!J4 | ... AL4: ='36-Month Forecast'!AL4
A5: Month | C5: ='36-Month Forecast'!C5 | D5: ='36-Month Forecast'!D5 | E5: ='36-Month Forecast'!E5 | F5: ='36-Month Forecast'!F5 | G5: ='36-Month Forecast'!G5 | H5: ='36-Month Forecast'!H5 | I5: ='36-Month Forecast'!I5 | J5: ='36-Month Forecast'!J5 | ... AL5: ='36-Month Forecast'!AL5 | AM5: Year 1 | AN5: Year 2 | AO5: Year 3 | AP5: 36 months
A6: Model year | C6: ='36-Month Forecast'!C6 | D6: ='36-Month Forecast'!D6 | E6: ='36-Month Forecast'!E6 | F6: ='36-Month Forecast'!F6 | G6: ='36-Month Forecast'!G6 | H6: ='36-Month Forecast'!H6 | I6: ='36-Month Forecast'!I6 | J6: ='36-Month Forecast'!J6 | ... AL6: ='36-Month Forecast'!AL6
A8: CONSERVATIVE SCENARIO
A9: Payout: Own site: printables and PDFs (Shopify) | C9: =IF(C$4-'Assumptions'!$C$80>=1,INDEX('36-Month Forecast'!$C$28:$AL$28,1,C$4-'Assumptions'!$C$80)+INDEX('36-Month Forecast'!$C$25:$AL$25,1,C$4-'Assumptions'!$C$80)*'Unit Economics'!$H$49,0) | D9: =IF(D$4-'Assumptions'!$C$80>=1,INDEX('36-Month Forecast'!$C$28:$AL$28,1,D$4-'Assumptions'!$C$80)+INDEX('36-Month Forecast'!$C$25:$AL$25,1,D$4-'Assumptions'!$C$80)*'Unit Economics'!$H$49,0) | E9: =IF(E$4-'Assumptions'!$C$80>=1,INDEX('36-Month Forecast'!$C$28:$AL$28,1,E$4-'Assumptions'!$C$80)+INDEX('36-Month Forecast'!$C$25:$AL$25,1,E$4-'Assumptions'!$C$80)*'Unit Economics'!$H$49,0) | F9: =IF(F$4-'Assumptions'!$C$80>=1,INDEX('36-Month Forecast'!$C$28:$AL$28,1,F$4-'Assumptions'!$C$80)+INDEX('36-Month Forecast'!$C$25:$AL$25,1,F$4-'Assumptions'!$C$80)*'Unit Economics'!$H$49,0) | G9: =IF(G$4-'Assumptions'!$C$80>=1,INDEX('36-Month Forecast'!$C$28:$AL$28,1,G$4-'Assumptions'!$C$80)+INDEX('36-Month Forecast'!$C$25:$AL$25,1,G$4-'Assumptions'!$C$80)*'Unit Economics'!$H$49,0) | H9: =IF(H$4-'Assumptions'!$C$80>=1,INDEX('36-Month Forecast'!$C$28:$AL$28,1,H$4-'Assumptions'!$C$80)+INDEX('36-Month Forecast'!$C$25:$AL$25,1,H$4-'Assumptions'!$C$80)*'Unit Economics'!$H$49,0) | I9: =IF(I$4-'Assumptions'!$C$80>=1,INDEX('36-Month Forecast'!$C$28:$AL$28,1,I$4-'Assumptions'!$C$80)+INDEX('36-Month Forecast'!$C$25:$AL$25,1,I$4-'Assumptions'!$C$80)*'Unit Economics'!$H$49,0) | J9: =IF(J$4-'Assumptions'!$C$80>=1,INDEX('36-Month Forecast'!$C$28:$AL$28,1,J$4-'Assumptions'!$C$80)+INDEX('36-Month Forecast'!$C$25:$AL$25,1,J$4-'Assumptions'!$C$80)*'Unit Economics'!$H$49,0) | ... AL9: =IF(AL$4-'Assumptions'!$C$80>=1,INDEX('36-Month Forecast'!$C$28:$AL$28,1,AL$4-'Assumptions'!$C$80)+INDEX('36-Month Forecast'!$C$25:$AL$25,1,AL$4-'Assumptions'!$C$80)*'Unit Economics'!$H$49,0) | AM9: =SUMIF($C$6:$AL$6,1,C9:AL9) | AN9: =SUMIF($C$6:$AL$6,2,C9:AL9) | AO9: =SUMIF($C$6:$AL$6,3,C9:AL9) | AP9: =SUM(C9:AL9)
A10: Payout: Etsy: printables | C10: =IF(C$4-'Assumptions'!$C$81>=1,INDEX('36-Month Forecast'!$C$38:$AL$38,1,C$4-'Assumptions'!$C$81)+INDEX('36-Month Forecast'!$C$35:$AL$35,1,C$4-'Assumptions'!$C$81)*'Unit Economics'!$H$50,0) | D10: =IF(D$4-'Assumptions'!$C$81>=1,INDEX('36-Month Forecast'!$C$38:$AL$38,1,D$4-'Assumptions'!$C$81)+INDEX('36-Month Forecast'!$C$35:$AL$35,1,D$4-'Assumptions'!$C$81)*'Unit Economics'!$H$50,0) | E10: =IF(E$4-'Assumptions'!$C$81>=1,INDEX('36-Month Forecast'!$C$38:$AL$38,1,E$4-'Assumptions'!$C$81)+INDEX('36-Month Forecast'!$C$35:$AL$35,1,E$4-'Assumptions'!$C$81)*'Unit Economics'!$H$50,0) | F10: =IF(F$4-'Assumptions'!$C$81>=1,INDEX('36-Month Forecast'!$C$38:$AL$38,1,F$4-'Assumptions'!$C$81)+INDEX('36-Month Forecast'!$C$35:$AL$35,1,F$4-'Assumptions'!$C$81)*'Unit Economics'!$H$50,0) | G10: =IF(G$4-'Assumptions'!$C$81>=1,INDEX('36-Month Forecast'!$C$38:$AL$38,1,G$4-'Assumptions'!$C$81)+INDEX('36-Month Forecast'!$C$35:$AL$35,1,G$4-'Assumptions'!$C$81)*'Unit Economics'!$H$50,0) | H10: =IF(H$4-'Assumptions'!$C$81>=1,INDEX('36-Month Forecast'!$C$38:$AL$38,1,H$4-'Assumptions'!$C$81)+INDEX('36-Month Forecast'!$C$35:$AL$35,1,H$4-'Assumptions'!$C$81)*'Unit Economics'!$H$50,0) | I10: =IF(I$4-'Assumptions'!$C$81>=1,INDEX('36-Month Forecast'!$C$38:$AL$38,1,I$4-'Assumptions'!$C$81)+INDEX('36-Month Forecast'!$C$35:$AL$35,1,I$4-'Assumptions'!$C$81)*'Unit Economics'!$H$50,0) | J10: =IF(J$4-'Assumptions'!$C$81>=1,INDEX('36-Month Forecast'!$C$38:$AL$38,1,J$4-'Assumptions'!$C$81)+INDEX('36-Month Forecast'!$C$35:$AL$35,1,J$4-'Assumptions'!$C$81)*'Unit Economics'!$H$50,0) | ... AL10: =IF(AL$4-'Assumptions'!$C$81>=1,INDEX('36-Month Forecast'!$C$38:$AL$38,1,AL$4-'Assumptions'!$C$81)+INDEX('36-Month Forecast'!$C$35:$AL$35,1,AL$4-'Assumptions'!$C$81)*'Unit Economics'!$H$50,0) | AM10: =SUMIF($C$6:$AL$6,1,C10:AL10) | AN10: =SUMIF($C$6:$AL$6,2,C10:AL10) | AO10: =SUMIF($C$6:$AL$6,3,C10:AL10) | AP10: =SUM(C10:AL10)
A11: Payout: Amazon KDP: paperbacks | C11: =IF(C$4-'Assumptions'!$C$82>=1,INDEX('36-Month Forecast'!$C$48:$AL$48,1,C$4-'Assumptions'!$C$82)+INDEX('36-Month Forecast'!$C$45:$AL$45,1,C$4-'Assumptions'!$C$82)*'Unit Economics'!$H$51,0) | D11: =IF(D$4-'Assumptions'!$C$82>=1,INDEX('36-Month Forecast'!$C$48:$AL$48,1,D$4-'Assumptions'!$C$82)+INDEX('36-Month Forecast'!$C$45:$AL$45,1,D$4-'Assumptions'!$C$82)*'Unit Economics'!$H$51,0) | E11: =IF(E$4-'Assumptions'!$C$82>=1,INDEX('36-Month Forecast'!$C$48:$AL$48,1,E$4-'Assumptions'!$C$82)+INDEX('36-Month Forecast'!$C$45:$AL$45,1,E$4-'Assumptions'!$C$82)*'Unit Economics'!$H$51,0) | F11: =IF(F$4-'Assumptions'!$C$82>=1,INDEX('36-Month Forecast'!$C$48:$AL$48,1,F$4-'Assumptions'!$C$82)+INDEX('36-Month Forecast'!$C$45:$AL$45,1,F$4-'Assumptions'!$C$82)*'Unit Economics'!$H$51,0) | G11: =IF(G$4-'Assumptions'!$C$82>=1,INDEX('36-Month Forecast'!$C$48:$AL$48,1,G$4-'Assumptions'!$C$82)+INDEX('36-Month Forecast'!$C$45:$AL$45,1,G$4-'Assumptions'!$C$82)*'Unit Economics'!$H$51,0) | H11: =IF(H$4-'Assumptions'!$C$82>=1,INDEX('36-Month Forecast'!$C$48:$AL$48,1,H$4-'Assumptions'!$C$82)+INDEX('36-Month Forecast'!$C$45:$AL$45,1,H$4-'Assumptions'!$C$82)*'Unit Economics'!$H$51,0) | I11: =IF(I$4-'Assumptions'!$C$82>=1,INDEX('36-Month Forecast'!$C$48:$AL$48,1,I$4-'Assumptions'!$C$82)+INDEX('36-Month Forecast'!$C$45:$AL$45,1,I$4-'Assumptions'!$C$82)*'Unit Economics'!$H$51,0) | J11: =IF(J$4-'Assumptions'!$C$82>=1,INDEX('36-Month Forecast'!$C$48:$AL$48,1,J$4-'Assumptions'!$C$82)+INDEX('36-Month Forecast'!$C$45:$AL$45,1,J$4-'Assumptions'!$C$82)*'Unit Economics'!$H$51,0) | ... AL11: =IF(AL$4-'Assumptions'!$C$82>=1,INDEX('36-Month Forecast'!$C$48:$AL$48,1,AL$4-'Assumptions'!$C$82)+INDEX('36-Month Forecast'!$C$45:$AL$45,1,AL$4-'Assumptions'!$C$82)*'Unit Economics'!$H$51,0) | AM11: =SUMIF($C$6:$AL$6,1,C11:AL11) | AN11: =SUMIF($C$6:$AL$6,2,C11:AL11) | AO11: =SUMIF($C$6:$AL$6,3,C11:AL11) | AP11: =SUM(C11:AL11)
A12: Payout: IngramSpark: paperbacks to bookstores and libraries | C12: =IF(C$4-'Assumptions'!$C$83>=1,INDEX('36-Month Forecast'!$C$58:$AL$58,1,C$4-'Assumptions'!$C$83)+INDEX('36-Month Forecast'!$C$55:$AL$55,1,C$4-'Assumptions'!$C$83)*'Unit Economics'!$H$52,0) | D12: =IF(D$4-'Assumptions'!$C$83>=1,INDEX('36-Month Forecast'!$C$58:$AL$58,1,D$4-'Assumptions'!$C$83)+INDEX('36-Month Forecast'!$C$55:$AL$55,1,D$4-'Assumptions'!$C$83)*'Unit Economics'!$H$52,0) | E12: =IF(E$4-'Assumptions'!$C$83>=1,INDEX('36-Month Forecast'!$C$58:$AL$58,1,E$4-'Assumptions'!$C$83)+INDEX('36-Month Forecast'!$C$55:$AL$55,1,E$4-'Assumptions'!$C$83)*'Unit Economics'!$H$52,0) | F12: =IF(F$4-'Assumptions'!$C$83>=1,INDEX('36-Month Forecast'!$C$58:$AL$58,1,F$4-'Assumptions'!$C$83)+INDEX('36-Month Forecast'!$C$55:$AL$55,1,F$4-'Assumptions'!$C$83)*'Unit Economics'!$H$52,0) | G12: =IF(G$4-'Assumptions'!$C$83>=1,INDEX('36-Month Forecast'!$C$58:$AL$58,1,G$4-'Assumptions'!$C$83)+INDEX('36-Month Forecast'!$C$55:$AL$55,1,G$4-'Assumptions'!$C$83)*'Unit Economics'!$H$52,0) | H12: =IF(H$4-'Assumptions'!$C$83>=1,INDEX('36-Month Forecast'!$C$58:$AL$58,1,H$4-'Assumptions'!$C$83)+INDEX('36-Month Forecast'!$C$55:$AL$55,1,H$4-'Assumptions'!$C$83)*'Unit Economics'!$H$52,0) | I12: =IF(I$4-'Assumptions'!$C$83>=1,INDEX('36-Month Forecast'!$C$58:$AL$58,1,I$4-'Assumptions'!$C$83)+INDEX('36-Month Forecast'!$C$55:$AL$55,1,I$4-'Assumptions'!$C$83)*'Unit Economics'!$H$52,0) | J12: =IF(J$4-'Assumptions'!$C$83>=1,INDEX('36-Month Forecast'!$C$58:$AL$58,1,J$4-'Assumptions'!$C$83)+INDEX('36-Month Forecast'!$C$55:$AL$55,1,J$4-'Assumptions'!$C$83)*'Unit Economics'!$H$52,0) | ... AL12: =IF(AL$4-'Assumptions'!$C$83>=1,INDEX('36-Month Forecast'!$C$58:$AL$58,1,AL$4-'Assumptions'!$C$83)+INDEX('36-Month Forecast'!$C$55:$AL$55,1,AL$4-'Assumptions'!$C$83)*'Unit Economics'!$H$52,0) | AM12: =SUMIF($C$6:$AL$6,1,C12:AL12) | AN12: =SUMIF($C$6:$AL$6,2,C12:AL12) | AO12: =SUMIF($C$6:$AL$6,3,C12:AL12) | AP12: =SUM(C12:AL12)
A13: Payout: International digital via merchant of record (Gumroad) | C13: =IF(C$4-'Assumptions'!$C$84>=1,INDEX('36-Month Forecast'!$C$68:$AL$68,1,C$4-'Assumptions'!$C$84)+INDEX('36-Month Forecast'!$C$65:$AL$65,1,C$4-'Assumptions'!$C$84)*'Unit Economics'!$H$53,0) | D13: =IF(D$4-'Assumptions'!$C$84>=1,INDEX('36-Month Forecast'!$C$68:$AL$68,1,D$4-'Assumptions'!$C$84)+INDEX('36-Month Forecast'!$C$65:$AL$65,1,D$4-'Assumptions'!$C$84)*'Unit Economics'!$H$53,0) | E13: =IF(E$4-'Assumptions'!$C$84>=1,INDEX('36-Month Forecast'!$C$68:$AL$68,1,E$4-'Assumptions'!$C$84)+INDEX('36-Month Forecast'!$C$65:$AL$65,1,E$4-'Assumptions'!$C$84)*'Unit Economics'!$H$53,0) | F13: =IF(F$4-'Assumptions'!$C$84>=1,INDEX('36-Month Forecast'!$C$68:$AL$68,1,F$4-'Assumptions'!$C$84)+INDEX('36-Month Forecast'!$C$65:$AL$65,1,F$4-'Assumptions'!$C$84)*'Unit Economics'!$H$53,0) | G13: =IF(G$4-'Assumptions'!$C$84>=1,INDEX('36-Month Forecast'!$C$68:$AL$68,1,G$4-'Assumptions'!$C$84)+INDEX('36-Month Forecast'!$C$65:$AL$65,1,G$4-'Assumptions'!$C$84)*'Unit Economics'!$H$53,0) | H13: =IF(H$4-'Assumptions'!$C$84>=1,INDEX('36-Month Forecast'!$C$68:$AL$68,1,H$4-'Assumptions'!$C$84)+INDEX('36-Month Forecast'!$C$65:$AL$65,1,H$4-'Assumptions'!$C$84)*'Unit Economics'!$H$53,0) | I13: =IF(I$4-'Assumptions'!$C$84>=1,INDEX('36-Month Forecast'!$C$68:$AL$68,1,I$4-'Assumptions'!$C$84)+INDEX('36-Month Forecast'!$C$65:$AL$65,1,I$4-'Assumptions'!$C$84)*'Unit Economics'!$H$53,0) | J13: =IF(J$4-'Assumptions'!$C$84>=1,INDEX('36-Month Forecast'!$C$68:$AL$68,1,J$4-'Assumptions'!$C$84)+INDEX('36-Month Forecast'!$C$65:$AL$65,1,J$4-'Assumptions'!$C$84)*'Unit Economics'!$H$53,0) | ... AL13: =IF(AL$4-'Assumptions'!$C$84>=1,INDEX('36-Month Forecast'!$C$68:$AL$68,1,AL$4-'Assumptions'!$C$84)+INDEX('36-Month Forecast'!$C$65:$AL$65,1,AL$4-'Assumptions'!$C$84)*'Unit Economics'!$H$53,0) | AM13: =SUMIF($C$6:$AL$6,1,C13:AL13) | AN13: =SUMIF($C$6:$AL$6,2,C13:AL13) | AO13: =SUMIF($C$6:$AL$6,3,C13:AL13) | AP13: =SUM(C13:AL13)
A14: Payout: 30-Day Screen Reset written course (Wave 2) | C14: =IF(C$4-'Assumptions'!$C$85>=1,INDEX('36-Month Forecast'!$C$78:$AL$78,1,C$4-'Assumptions'!$C$85)+INDEX('36-Month Forecast'!$C$75:$AL$75,1,C$4-'Assumptions'!$C$85)*'Unit Economics'!$H$54,0) | D14: =IF(D$4-'Assumptions'!$C$85>=1,INDEX('36-Month Forecast'!$C$78:$AL$78,1,D$4-'Assumptions'!$C$85)+INDEX('36-Month Forecast'!$C$75:$AL$75,1,D$4-'Assumptions'!$C$85)*'Unit Economics'!$H$54,0) | E14: =IF(E$4-'Assumptions'!$C$85>=1,INDEX('36-Month Forecast'!$C$78:$AL$78,1,E$4-'Assumptions'!$C$85)+INDEX('36-Month Forecast'!$C$75:$AL$75,1,E$4-'Assumptions'!$C$85)*'Unit Economics'!$H$54,0) | F14: =IF(F$4-'Assumptions'!$C$85>=1,INDEX('36-Month Forecast'!$C$78:$AL$78,1,F$4-'Assumptions'!$C$85)+INDEX('36-Month Forecast'!$C$75:$AL$75,1,F$4-'Assumptions'!$C$85)*'Unit Economics'!$H$54,0) | G14: =IF(G$4-'Assumptions'!$C$85>=1,INDEX('36-Month Forecast'!$C$78:$AL$78,1,G$4-'Assumptions'!$C$85)+INDEX('36-Month Forecast'!$C$75:$AL$75,1,G$4-'Assumptions'!$C$85)*'Unit Economics'!$H$54,0) | H14: =IF(H$4-'Assumptions'!$C$85>=1,INDEX('36-Month Forecast'!$C$78:$AL$78,1,H$4-'Assumptions'!$C$85)+INDEX('36-Month Forecast'!$C$75:$AL$75,1,H$4-'Assumptions'!$C$85)*'Unit Economics'!$H$54,0) | I14: =IF(I$4-'Assumptions'!$C$85>=1,INDEX('36-Month Forecast'!$C$78:$AL$78,1,I$4-'Assumptions'!$C$85)+INDEX('36-Month Forecast'!$C$75:$AL$75,1,I$4-'Assumptions'!$C$85)*'Unit Economics'!$H$54,0) | J14: =IF(J$4-'Assumptions'!$C$85>=1,INDEX('36-Month Forecast'!$C$78:$AL$78,1,J$4-'Assumptions'!$C$85)+INDEX('36-Month Forecast'!$C$75:$AL$75,1,J$4-'Assumptions'!$C$85)*'Unit Economics'!$H$54,0) | ... AL14: =IF(AL$4-'Assumptions'!$C$85>=1,INDEX('36-Month Forecast'!$C$78:$AL$78,1,AL$4-'Assumptions'!$C$85)+INDEX('36-Month Forecast'!$C$75:$AL$75,1,AL$4-'Assumptions'!$C$85)*'Unit Economics'!$H$54,0) | AM14: =SUMIF($C$6:$AL$6,1,C14:AL14) | AN14: =SUMIF($C$6:$AL$6,2,C14:AL14) | AO14: =SUMIF($C$6:$AL$6,3,C14:AL14) | AP14: =SUM(C14:AL14)
A15: Payout: Board book: pre-sale, then 3PL and Amazon FBA (gated option; off in base) | C15: =IF(C$4-'Assumptions'!$C$86>=1,INDEX('36-Month Forecast'!$C$88:$AL$88,1,C$4-'Assumptions'!$C$86)+INDEX('36-Month Forecast'!$C$85:$AL$85,1,C$4-'Assumptions'!$C$86)*'Unit Economics'!$H$55,0) | D15: =IF(D$4-'Assumptions'!$C$86>=1,INDEX('36-Month Forecast'!$C$88:$AL$88,1,D$4-'Assumptions'!$C$86)+INDEX('36-Month Forecast'!$C$85:$AL$85,1,D$4-'Assumptions'!$C$86)*'Unit Economics'!$H$55,0) | E15: =IF(E$4-'Assumptions'!$C$86>=1,INDEX('36-Month Forecast'!$C$88:$AL$88,1,E$4-'Assumptions'!$C$86)+INDEX('36-Month Forecast'!$C$85:$AL$85,1,E$4-'Assumptions'!$C$86)*'Unit Economics'!$H$55,0) | F15: =IF(F$4-'Assumptions'!$C$86>=1,INDEX('36-Month Forecast'!$C$88:$AL$88,1,F$4-'Assumptions'!$C$86)+INDEX('36-Month Forecast'!$C$85:$AL$85,1,F$4-'Assumptions'!$C$86)*'Unit Economics'!$H$55,0) | G15: =IF(G$4-'Assumptions'!$C$86>=1,INDEX('36-Month Forecast'!$C$88:$AL$88,1,G$4-'Assumptions'!$C$86)+INDEX('36-Month Forecast'!$C$85:$AL$85,1,G$4-'Assumptions'!$C$86)*'Unit Economics'!$H$55,0) | H15: =IF(H$4-'Assumptions'!$C$86>=1,INDEX('36-Month Forecast'!$C$88:$AL$88,1,H$4-'Assumptions'!$C$86)+INDEX('36-Month Forecast'!$C$85:$AL$85,1,H$4-'Assumptions'!$C$86)*'Unit Economics'!$H$55,0) | I15: =IF(I$4-'Assumptions'!$C$86>=1,INDEX('36-Month Forecast'!$C$88:$AL$88,1,I$4-'Assumptions'!$C$86)+INDEX('36-Month Forecast'!$C$85:$AL$85,1,I$4-'Assumptions'!$C$86)*'Unit Economics'!$H$55,0) | J15: =IF(J$4-'Assumptions'!$C$86>=1,INDEX('36-Month Forecast'!$C$88:$AL$88,1,J$4-'Assumptions'!$C$86)+INDEX('36-Month Forecast'!$C$85:$AL$85,1,J$4-'Assumptions'!$C$86)*'Unit Economics'!$H$55,0) | ... AL15: =IF(AL$4-'Assumptions'!$C$86>=1,INDEX('36-Month Forecast'!$C$88:$AL$88,1,AL$4-'Assumptions'!$C$86)+INDEX('36-Month Forecast'!$C$85:$AL$85,1,AL$4-'Assumptions'!$C$86)*'Unit Economics'!$H$55,0) | AM15: =SUMIF($C$6:$AL$6,1,C15:AL15) | AN15: =SUMIF($C$6:$AL$6,2,C15:AL15) | AO15: =SUMIF($C$6:$AL$6,3,C15:AL15) | AP15: =SUM(C15:AL15)
A16: Payout: School and group licenses + TPT (overlay only if counsel clears in writing; off in base) | C16: =IF(C$4-'Assumptions'!$C$87>=1,INDEX('36-Month Forecast'!$C$99:$AL$99,1,C$4-'Assumptions'!$C$87)+INDEX('36-Month Forecast'!$C$96:$AL$96,1,C$4-'Assumptions'!$C$87)*'Unit Economics'!$H$56,0) | D16: =IF(D$4-'Assumptions'!$C$87>=1,INDEX('36-Month Forecast'!$C$99:$AL$99,1,D$4-'Assumptions'!$C$87)+INDEX('36-Month Forecast'!$C$96:$AL$96,1,D$4-'Assumptions'!$C$87)*'Unit Economics'!$H$56,0) | E16: =IF(E$4-'Assumptions'!$C$87>=1,INDEX('36-Month Forecast'!$C$99:$AL$99,1,E$4-'Assumptions'!$C$87)+INDEX('36-Month Forecast'!$C$96:$AL$96,1,E$4-'Assumptions'!$C$87)*'Unit Economics'!$H$56,0) | F16: =IF(F$4-'Assumptions'!$C$87>=1,INDEX('36-Month Forecast'!$C$99:$AL$99,1,F$4-'Assumptions'!$C$87)+INDEX('36-Month Forecast'!$C$96:$AL$96,1,F$4-'Assumptions'!$C$87)*'Unit Economics'!$H$56,0) | G16: =IF(G$4-'Assumptions'!$C$87>=1,INDEX('36-Month Forecast'!$C$99:$AL$99,1,G$4-'Assumptions'!$C$87)+INDEX('36-Month Forecast'!$C$96:$AL$96,1,G$4-'Assumptions'!$C$87)*'Unit Economics'!$H$56,0) | H16: =IF(H$4-'Assumptions'!$C$87>=1,INDEX('36-Month Forecast'!$C$99:$AL$99,1,H$4-'Assumptions'!$C$87)+INDEX('36-Month Forecast'!$C$96:$AL$96,1,H$4-'Assumptions'!$C$87)*'Unit Economics'!$H$56,0) | I16: =IF(I$4-'Assumptions'!$C$87>=1,INDEX('36-Month Forecast'!$C$99:$AL$99,1,I$4-'Assumptions'!$C$87)+INDEX('36-Month Forecast'!$C$96:$AL$96,1,I$4-'Assumptions'!$C$87)*'Unit Economics'!$H$56,0) | J16: =IF(J$4-'Assumptions'!$C$87>=1,INDEX('36-Month Forecast'!$C$99:$AL$99,1,J$4-'Assumptions'!$C$87)+INDEX('36-Month Forecast'!$C$96:$AL$96,1,J$4-'Assumptions'!$C$87)*'Unit Economics'!$H$56,0) | ... AL16: =IF(AL$4-'Assumptions'!$C$87>=1,INDEX('36-Month Forecast'!$C$99:$AL$99,1,AL$4-'Assumptions'!$C$87)+INDEX('36-Month Forecast'!$C$96:$AL$96,1,AL$4-'Assumptions'!$C$87)*'Unit Economics'!$H$56,0) | AM16: =SUMIF($C$6:$AL$6,1,C16:AL16) | AN16: =SUMIF($C$6:$AL$6,2,C16:AL16) | AO16: =SUMIF($C$6:$AL$6,3,C16:AL16) | AP16: =SUM(C16:AL16)
A17: Payout: Retail and wholesale: Faire, Walmart Marketplace (off in base) | C17: =IF(C$4-'Assumptions'!$C$88>=1,INDEX('36-Month Forecast'!$C$109:$AL$109,1,C$4-'Assumptions'!$C$88)+INDEX('36-Month Forecast'!$C$106:$AL$106,1,C$4-'Assumptions'!$C$88)*'Unit Economics'!$H$57,0) | D17: =IF(D$4-'Assumptions'!$C$88>=1,INDEX('36-Month Forecast'!$C$109:$AL$109,1,D$4-'Assumptions'!$C$88)+INDEX('36-Month Forecast'!$C$106:$AL$106,1,D$4-'Assumptions'!$C$88)*'Unit Economics'!$H$57,0) | E17: =IF(E$4-'Assumptions'!$C$88>=1,INDEX('36-Month Forecast'!$C$109:$AL$109,1,E$4-'Assumptions'!$C$88)+INDEX('36-Month Forecast'!$C$106:$AL$106,1,E$4-'Assumptions'!$C$88)*'Unit Economics'!$H$57,0) | F17: =IF(F$4-'Assumptions'!$C$88>=1,INDEX('36-Month Forecast'!$C$109:$AL$109,1,F$4-'Assumptions'!$C$88)+INDEX('36-Month Forecast'!$C$106:$AL$106,1,F$4-'Assumptions'!$C$88)*'Unit Economics'!$H$57,0) | G17: =IF(G$4-'Assumptions'!$C$88>=1,INDEX('36-Month Forecast'!$C$109:$AL$109,1,G$4-'Assumptions'!$C$88)+INDEX('36-Month Forecast'!$C$106:$AL$106,1,G$4-'Assumptions'!$C$88)*'Unit Economics'!$H$57,0) | H17: =IF(H$4-'Assumptions'!$C$88>=1,INDEX('36-Month Forecast'!$C$109:$AL$109,1,H$4-'Assumptions'!$C$88)+INDEX('36-Month Forecast'!$C$106:$AL$106,1,H$4-'Assumptions'!$C$88)*'Unit Economics'!$H$57,0) | I17: =IF(I$4-'Assumptions'!$C$88>=1,INDEX('36-Month Forecast'!$C$109:$AL$109,1,I$4-'Assumptions'!$C$88)+INDEX('36-Month Forecast'!$C$106:$AL$106,1,I$4-'Assumptions'!$C$88)*'Unit Economics'!$H$57,0) | J17: =IF(J$4-'Assumptions'!$C$88>=1,INDEX('36-Month Forecast'!$C$109:$AL$109,1,J$4-'Assumptions'!$C$88)+INDEX('36-Month Forecast'!$C$106:$AL$106,1,J$4-'Assumptions'!$C$88)*'Unit Economics'!$H$57,0) | ... AL17: =IF(AL$4-'Assumptions'!$C$88>=1,INDEX('36-Month Forecast'!$C$109:$AL$109,1,AL$4-'Assumptions'!$C$88)+INDEX('36-Month Forecast'!$C$106:$AL$106,1,AL$4-'Assumptions'!$C$88)*'Unit Economics'!$H$57,0) | AM17: =SUMIF($C$6:$AL$6,1,C17:AL17) | AN17: =SUMIF($C$6:$AL$6,2,C17:AL17) | AO17: =SUMIF($C$6:$AL$6,3,C17:AL17) | AP17: =SUM(C17:AL17)
A18: Total payouts received | C18: =SUM(C9:C17) | D18: =SUM(D9:D17) | E18: =SUM(E9:E17) | F18: =SUM(F9:F17) | G18: =SUM(G9:G17) | H18: =SUM(H9:H17) | I18: =SUM(I9:I17) | J18: =SUM(J9:J17) | ... AL18: =SUM(AL9:AL17) | AM18: =SUMIF($C$6:$AL$6,1,C18:AL18) | AN18: =SUMIF($C$6:$AL$6,2,C18:AL18) | AO18: =SUMIF($C$6:$AL$6,3,C18:AL18) | AP18: =SUM(C18:AL18)
A19: Existing business-card balance paid off (month 1) | C19: =-'Assumptions'!$C$18 | D19: =0 | E19: =0 | F19: =0 | G19: =0 | H19: =0 | I19: =0 | J19: =0 | K19: =0 | ... AL19: =0 | AM19: =SUMIF($C$6:$AL$6,1,C19:AL19) | AN19: =SUMIF($C$6:$AL$6,2,C19:AL19) | AO19: =SUMIF($C$6:$AL$6,3,C19:AL19) | AP19: =SUM(C19:AL19)
A20: Inventory purchases (offset print runs, landed) | C20: =-'36-Month Forecast'!C136 | D20: =-'36-Month Forecast'!D136 | E20: =-'36-Month Forecast'!E136 | F20: =-'36-Month Forecast'!F136 | G20: =-'36-Month Forecast'!G136 | H20: =-'36-Month Forecast'!H136 | I20: =-'36-Month Forecast'!I136 | J20: =-'36-Month Forecast'!J136 | ... AL20: =-'36-Month Forecast'!AL136 | AM20: =SUMIF($C$6:$AL$6,1,C20:AL20) | AN20: =SUMIF($C$6:$AL$6,2,C20:AL20) | AO20: =SUMIF($C$6:$AL$6,3,C20:AL20) | AP20: =SUM(C20:AL20)
A21: Paid advertising | C21: =-'36-Month Forecast'!C123 | D21: =-'36-Month Forecast'!D123 | E21: =-'36-Month Forecast'!E123 | F21: =-'36-Month Forecast'!F123 | G21: =-'36-Month Forecast'!G123 | H21: =-'36-Month Forecast'!H123 | I21: =-'36-Month Forecast'!I123 | J21: =-'36-Month Forecast'!J123 | ... AL21: =-'36-Month Forecast'!AL123 | AM21: =SUMIF($C$6:$AL$6,1,C21:AL21) | AN21: =SUMIF($C$6:$AL$6,2,C21:AL21) | AO21: =SUMIF($C$6:$AL$6,3,C21:AL21) | AP21: =SUM(C21:AL21)
A22: Operating costs | C22: =-'36-Month Forecast'!C124 | D22: =-'36-Month Forecast'!D124 | E22: =-'36-Month Forecast'!E124 | F22: =-'36-Month Forecast'!F124 | G22: =-'36-Month Forecast'!G124 | H22: =-'36-Month Forecast'!H124 | I22: =-'36-Month Forecast'!I124 | J22: =-'36-Month Forecast'!J124 | ... AL22: =-'36-Month Forecast'!AL124 | AM22: =SUMIF($C$6:$AL$6,1,C22:AL22) | AN22: =SUMIF($C$6:$AL$6,2,C22:AL22) | AO22: =SUMIF($C$6:$AL$6,3,C22:AL22) | AP22: =SUM(C22:AL22)
A23: Wave fixed costs | C23: =-'36-Month Forecast'!C125 | D23: =-'36-Month Forecast'!D125 | E23: =-'36-Month Forecast'!E125 | F23: =-'36-Month Forecast'!F125 | G23: =-'36-Month Forecast'!G125 | H23: =-'36-Month Forecast'!H125 | I23: =-'36-Month Forecast'!I125 | J23: =-'36-Month Forecast'!J125 | ... AL23: =-'36-Month Forecast'!AL125 | AM23: =SUMIF($C$6:$AL$6,1,C23:AL23) | AN23: =SUMIF($C$6:$AL$6,2,C23:AL23) | AO23: =SUMIF($C$6:$AL$6,3,C23:AL23) | AP23: =SUM(C23:AL23)
A24: One-time startup costs | C24: =-'36-Month Forecast'!C128 | D24: =-'36-Month Forecast'!D128 | E24: =-'36-Month Forecast'!E128 | F24: =-'36-Month Forecast'!F128 | G24: =-'36-Month Forecast'!G128 | H24: =-'36-Month Forecast'!H128 | I24: =-'36-Month Forecast'!I128 | J24: =-'36-Month Forecast'!J128 | ... AL24: =-'36-Month Forecast'!AL128 | AM24: =SUMIF($C$6:$AL$6,1,C24:AL24) | AN24: =SUMIF($C$6:$AL$6,2,C24:AL24) | AO24: =SUMIF($C$6:$AL$6,3,C24:AL24) | AP24: =SUM(C24:AL24)
A25: One-time wave costs | C25: =-'36-Month Forecast'!C129 | D25: =-'36-Month Forecast'!D129 | E25: =-'36-Month Forecast'!E129 | F25: =-'36-Month Forecast'!F129 | G25: =-'36-Month Forecast'!G129 | H25: =-'36-Month Forecast'!H129 | I25: =-'36-Month Forecast'!I129 | J25: =-'36-Month Forecast'!J129 | ... AL25: =-'36-Month Forecast'!AL129 | AM25: =SUMIF($C$6:$AL$6,1,C25:AL25) | AN25: =SUMIF($C$6:$AL$6,2,C25:AL25) | AO25: =SUMIF($C$6:$AL$6,3,C25:AL25) | AP25: =SUM(C25:AL25)
A26: NET CASH FLOW before tax reserve and founder capital | C26: =SUM(C18:C25) | D26: =SUM(D18:D25) | E26: =SUM(E18:E25) | F26: =SUM(F18:F25) | G26: =SUM(G18:G25) | H26: =SUM(H18:H25) | I26: =SUM(I18:I25) | J26: =SUM(J18:J25) | ... AL26: =SUM(AL18:AL25) | AM26: =SUMIF($C$6:$AL$6,1,C26:AL26) | AN26: =SUMIF($C$6:$AL$6,2,C26:AL26) | AO26: =SUMIF($C$6:$AL$6,3,C26:AL26) | AP26: =SUM(C26:AL26)
A27: Transfer to (-) or from (+) the tax reserve account | C27: =0-C31 | D27: =C31-D31 | E27: =D31-E31 | F27: =E31-F31 | G27: =F31-G31 | H27: =G31-H31 | I27: =H31-I31 | J27: =I31-J31 | K27: =J31-K31 | ... AL27: =AK31-AL31 | AM27: =SUMIF($C$6:$AL$6,1,C27:AL27) | AN27: =SUMIF($C$6:$AL$6,2,C27:AL27) | AO27: =SUMIF($C$6:$AL$6,3,C27:AL27) | AP27: =SUM(C27:AL27)
A28: Operating balance before founder capital | C28: ='Assumptions'!$C$16+C26+C27 | D28: =C30+D26+D27 | E28: =D30+E26+E27 | F28: =E30+F26+F27 | G28: =F30+G26+G27 | H28: =G30+H26+H27 | I28: =H30+I26+I27 | J28: =I30+J26+J27 | K28: =J30+K26+K27 | ... AL28: =AK30+AL26+AL27
A29: FOUNDER CAPITAL IN (planned month-1 amount + any top-up that keeps the balance at zero or above) | C29: ='Assumptions'!$C$17+MAX(0,-(C28+'Assumptions'!$C$17)) | D29: =0+MAX(0,-(D28+0)) | E29: =0+MAX(0,-(E28+0)) | F29: =0+MAX(0,-(F28+0)) | G29: =0+MAX(0,-(G28+0)) | H29: =0+MAX(0,-(H28+0)) | I29: =0+MAX(0,-(I28+0)) | J29: =0+MAX(0,-(J28+0)) | K29: =0+MAX(0,-(K28+0)) | ... AL29: =0+MAX(0,-(AL28+0)) | AM29: =SUMIF($C$6:$AL$6,1,C29:AL29) | AN29: =SUMIF($C$6:$AL$6,2,C29:AL29) | AO29: =SUMIF($C$6:$AL$6,3,C29:AL29) | AP29: =SUM(C29:AL29)
A30: OPERATING ACCOUNT BALANCE (month end) | C30: =C28+C29 | D30: =D28+D29 | E30: =E28+E29 | F30: =F28+F29 | G30: =G28+G29 | H30: =H28+H29 | I30: =I28+I29 | J30: =J28+J29 | ... AL30: =AL28+AL29 | AM30: =N30 | AN30: =Z30 | AO30: =AL30 | AP30: =AL30
A31: Tax reserve account balance (25% of cumulative profit after one-time costs, if positive) | C31: ='Assumptions'!$C$15*MAX(0,'36-Month Forecast'!C131) | D31: ='Assumptions'!$C$15*MAX(0,'36-Month Forecast'!D131) | E31: ='Assumptions'!$C$15*MAX(0,'36-Month Forecast'!E131) | F31: ='Assumptions'!$C$15*MAX(0,'36-Month Forecast'!F131) | G31: ='Assumptions'!$C$15*MAX(0,'36-Month Forecast'!G131) | H31: ='Assumptions'!$C$15*MAX(0,'36-Month Forecast'!H131) | I31: ='Assumptions'!$C$15*MAX(0,'36-Month Forecast'!I131) | J31: ='Assumptions'!$C$15*MAX(0,'36-Month Forecast'!J131) | ... AL31: ='Assumptions'!$C$15*MAX(0,'36-Month Forecast'!AL131) | AM31: =N31 | AN31: =Z31 | AO31: =AL31 | AP31: =AL31
A32: Total cash (both accounts) | C32: =C30+C31 | D32: =D30+D31 | E32: =E30+E31 | F32: =F30+F31 | G32: =G30+G31 | H32: =H30+H31 | I32: =I30+I31 | J32: =J30+J31 | ... AL32: =AL30+AL31 | AM32: =N32 | AN32: =Z32 | AO32: =AL32 | AP32: =AL32
A33: CUMULATIVE FOUNDER CAPITAL (the funding need) | C33: =C29 | D33: =D29+C33 | E33: =E29+D33 | F33: =F29+E33 | G33: =G29+F33 | H33: =H29+G33 | I33: =I29+H33 | J33: =J29+I33 | K33: =K29+J33 | ... AL33: =AL29+AK33 | AM33: =N33 | AN33: =Z33 | AO33: =AL33 | AP33: =AL33
A34: Reserve target (months x fixed costs incl. ads) | C34: ='Assumptions'!$C$21*('36-Month Forecast'!C124+'36-Month Forecast'!C125+'36-Month Forecast'!C123) | D34: ='Assumptions'!$C$21*('36-Month Forecast'!D124+'36-Month Forecast'!D125+'36-Month Forecast'!D123) | E34: ='Assumptions'!$C$21*('36-Month Forecast'!E124+'36-Month Forecast'!E125+'36-Month Forecast'!E123) | F34: ='Assumptions'!$C$21*('36-Month Forecast'!F124+'36-Month Forecast'!F125+'36-Month Forecast'!F123) | G34: ='Assumptions'!$C$21*('36-Month Forecast'!G124+'36-Month Forecast'!G125+'36-Month Forecast'!G123) | H34: ='Assumptions'!$C$21*('36-Month Forecast'!H124+'36-Month Forecast'!H125+'36-Month Forecast'!H123) | I34: ='Assumptions'!$C$21*('36-Month Forecast'!I124+'36-Month Forecast'!I125+'36-Month Forecast'!I123) | J34: ='Assumptions'!$C$21*('36-Month Forecast'!J124+'36-Month Forecast'!J125+'36-Month Forecast'!J123) | ... AL34: ='Assumptions'!$C$21*('36-Month Forecast'!AL124+'36-Month Forecast'!AL125+'36-Month Forecast'!AL123) | AM34: =N34 | AN34: =Z34 | AO34: =AL34 | AP34: =AL34
A35: Operating balance above / (below) reserve target | C35: =C30-C34 | D35: =D30-D34 | E35: =E30-E34 | F35: =F30-F34 | G35: =G30-G34 | H35: =H30-H34 | I35: =I30-I34 | J35: =J30-J34 | ... AL35: =AL30-AL34 | AM35: =N35 | AN35: =Z35 | AO35: =AL35 | AP35: =AL35
A36: Helper: month # if founder capital goes in | C36: =IF(C29>0.5,C$4,"") | D36: =IF(D29>0.5,D$4,"") | E36: =IF(E29>0.5,E$4,"") | F36: =IF(F29>0.5,F$4,"") | G36: =IF(G29>0.5,G$4,"") | H36: =IF(H29>0.5,H$4,"") | I36: =IF(I29>0.5,I$4,"") | J36: =IF(J29>0.5,J$4,"") | ... AL36: =IF(AL29>0.5,AL$4,"")
A37: Helper: month # if cumulative founder capital is above the household-money cap | C37: =IF(C33>'Assumptions'!$C$19,C$4,"") | D37: =IF(D33>'Assumptions'!$C$19,D$4,"") | E37: =IF(E33>'Assumptions'!$C$19,E$4,"") | F37: =IF(F33>'Assumptions'!$C$19,F$4,"") | G37: =IF(G33>'Assumptions'!$C$19,G$4,"") | H37: =IF(H33>'Assumptions'!$C$19,H$4,"") | I37: =IF(I33>'Assumptions'!$C$19,I$4,"") | J37: =IF(J33>'Assumptions'!$C$19,J$4,"") | ... AL37: =IF(AL33>'Assumptions'!$C$19,AL$4,"")
A39: EXPECTED SCENARIO
A40: Payout: Own site: printables and PDFs (Shopify) | C40: =IF(C$4-'Assumptions'!$C$80>=1,INDEX('36-Month Forecast'!$C$162:$AL$162,1,C$4-'Assumptions'!$C$80)+INDEX('36-Month Forecast'!$C$159:$AL$159,1,C$4-'Assumptions'!$C$80)*'Unit Economics'!$H$49,0) | D40: =IF(D$4-'Assumptions'!$C$80>=1,INDEX('36-Month Forecast'!$C$162:$AL$162,1,D$4-'Assumptions'!$C$80)+INDEX('36-Month Forecast'!$C$159:$AL$159,1,D$4-'Assumptions'!$C$80)*'Unit Economics'!$H$49,0) | E40: =IF(E$4-'Assumptions'!$C$80>=1,INDEX('36-Month Forecast'!$C$162:$AL$162,1,E$4-'Assumptions'!$C$80)+INDEX('36-Month Forecast'!$C$159:$AL$159,1,E$4-'Assumptions'!$C$80)*'Unit Economics'!$H$49,0) | F40: =IF(F$4-'Assumptions'!$C$80>=1,INDEX('36-Month Forecast'!$C$162:$AL$162,1,F$4-'Assumptions'!$C$80)+INDEX('36-Month Forecast'!$C$159:$AL$159,1,F$4-'Assumptions'!$C$80)*'Unit Economics'!$H$49,0) | G40: =IF(G$4-'Assumptions'!$C$80>=1,INDEX('36-Month Forecast'!$C$162:$AL$162,1,G$4-'Assumptions'!$C$80)+INDEX('36-Month Forecast'!$C$159:$AL$159,1,G$4-'Assumptions'!$C$80)*'Unit Economics'!$H$49,0) | H40: =IF(H$4-'Assumptions'!$C$80>=1,INDEX('36-Month Forecast'!$C$162:$AL$162,1,H$4-'Assumptions'!$C$80)+INDEX('36-Month Forecast'!$C$159:$AL$159,1,H$4-'Assumptions'!$C$80)*'Unit Economics'!$H$49,0) | I40: =IF(I$4-'Assumptions'!$C$80>=1,INDEX('36-Month Forecast'!$C$162:$AL$162,1,I$4-'Assumptions'!$C$80)+INDEX('36-Month Forecast'!$C$159:$AL$159,1,I$4-'Assumptions'!$C$80)*'Unit Economics'!$H$49,0) | J40: =IF(J$4-'Assumptions'!$C$80>=1,INDEX('36-Month Forecast'!$C$162:$AL$162,1,J$4-'Assumptions'!$C$80)+INDEX('36-Month Forecast'!$C$159:$AL$159,1,J$4-'Assumptions'!$C$80)*'Unit Economics'!$H$49,0) | ... AL40: =IF(AL$4-'Assumptions'!$C$80>=1,INDEX('36-Month Forecast'!$C$162:$AL$162,1,AL$4-'Assumptions'!$C$80)+INDEX('36-Month Forecast'!$C$159:$AL$159,1,AL$4-'Assumptions'!$C$80)*'Unit Economics'!$H$49,0) | AM40: =SUMIF($C$6:$AL$6,1,C40:AL40) | AN40: =SUMIF($C$6:$AL$6,2,C40:AL40) | AO40: =SUMIF($C$6:$AL$6,3,C40:AL40) | AP40: =SUM(C40:AL40)
A41: Payout: Etsy: printables | C41: =IF(C$4-'Assumptions'!$C$81>=1,INDEX('36-Month Forecast'!$C$172:$AL$172,1,C$4-'Assumptions'!$C$81)+INDEX('36-Month Forecast'!$C$169:$AL$169,1,C$4-'Assumptions'!$C$81)*'Unit Economics'!$H$50,0) | D41: =IF(D$4-'Assumptions'!$C$81>=1,INDEX('36-Month Forecast'!$C$172:$AL$172,1,D$4-'Assumptions'!$C$81)+INDEX('36-Month Forecast'!$C$169:$AL$169,1,D$4-'Assumptions'!$C$81)*'Unit Economics'!$H$50,0) | E41: =IF(E$4-'Assumptions'!$C$81>=1,INDEX('36-Month Forecast'!$C$172:$AL$172,1,E$4-'Assumptions'!$C$81)+INDEX('36-Month Forecast'!$C$169:$AL$169,1,E$4-'Assumptions'!$C$81)*'Unit Economics'!$H$50,0) | F41: =IF(F$4-'Assumptions'!$C$81>=1,INDEX('36-Month Forecast'!$C$172:$AL$172,1,F$4-'Assumptions'!$C$81)+INDEX('36-Month Forecast'!$C$169:$AL$169,1,F$4-'Assumptions'!$C$81)*'Unit Economics'!$H$50,0) | G41: =IF(G$4-'Assumptions'!$C$81>=1,INDEX('36-Month Forecast'!$C$172:$AL$172,1,G$4-'Assumptions'!$C$81)+INDEX('36-Month Forecast'!$C$169:$AL$169,1,G$4-'Assumptions'!$C$81)*'Unit Economics'!$H$50,0) | H41: =IF(H$4-'Assumptions'!$C$81>=1,INDEX('36-Month Forecast'!$C$172:$AL$172,1,H$4-'Assumptions'!$C$81)+INDEX('36-Month Forecast'!$C$169:$AL$169,1,H$4-'Assumptions'!$C$81)*'Unit Economics'!$H$50,0) | I41: =IF(I$4-'Assumptions'!$C$81>=1,INDEX('36-Month Forecast'!$C$172:$AL$172,1,I$4-'Assumptions'!$C$81)+INDEX('36-Month Forecast'!$C$169:$AL$169,1,I$4-'Assumptions'!$C$81)*'Unit Economics'!$H$50,0) | J41: =IF(J$4-'Assumptions'!$C$81>=1,INDEX('36-Month Forecast'!$C$172:$AL$172,1,J$4-'Assumptions'!$C$81)+INDEX('36-Month Forecast'!$C$169:$AL$169,1,J$4-'Assumptions'!$C$81)*'Unit Economics'!$H$50,0) | ... AL41: =IF(AL$4-'Assumptions'!$C$81>=1,INDEX('36-Month Forecast'!$C$172:$AL$172,1,AL$4-'Assumptions'!$C$81)+INDEX('36-Month Forecast'!$C$169:$AL$169,1,AL$4-'Assumptions'!$C$81)*'Unit Economics'!$H$50,0) | AM41: =SUMIF($C$6:$AL$6,1,C41:AL41) | AN41: =SUMIF($C$6:$AL$6,2,C41:AL41) | AO41: =SUMIF($C$6:$AL$6,3,C41:AL41) | AP41: =SUM(C41:AL41)
A42: Payout: Amazon KDP: paperbacks | C42: =IF(C$4-'Assumptions'!$C$82>=1,INDEX('36-Month Forecast'!$C$182:$AL$182,1,C$4-'Assumptions'!$C$82)+INDEX('36-Month Forecast'!$C$179:$AL$179,1,C$4-'Assumptions'!$C$82)*'Unit Economics'!$H$51,0) | D42: =IF(D$4-'Assumptions'!$C$82>=1,INDEX('36-Month Forecast'!$C$182:$AL$182,1,D$4-'Assumptions'!$C$82)+INDEX('36-Month Forecast'!$C$179:$AL$179,1,D$4-'Assumptions'!$C$82)*'Unit Economics'!$H$51,0) | E42: =IF(E$4-'Assumptions'!$C$82>=1,INDEX('36-Month Forecast'!$C$182:$AL$182,1,E$4-'Assumptions'!$C$82)+INDEX('36-Month Forecast'!$C$179:$AL$179,1,E$4-'Assumptions'!$C$82)*'Unit Economics'!$H$51,0) | F42: =IF(F$4-'Assumptions'!$C$82>=1,INDEX('36-Month Forecast'!$C$182:$AL$182,1,F$4-'Assumptions'!$C$82)+INDEX('36-Month Forecast'!$C$179:$AL$179,1,F$4-'Assumptions'!$C$82)*'Unit Economics'!$H$51,0) | G42: =IF(G$4-'Assumptions'!$C$82>=1,INDEX('36-Month Forecast'!$C$182:$AL$182,1,G$4-'Assumptions'!$C$82)+INDEX('36-Month Forecast'!$C$179:$AL$179,1,G$4-'Assumptions'!$C$82)*'Unit Economics'!$H$51,0) | H42: =IF(H$4-'Assumptions'!$C$82>=1,INDEX('36-Month Forecast'!$C$182:$AL$182,1,H$4-'Assumptions'!$C$82)+INDEX('36-Month Forecast'!$C$179:$AL$179,1,H$4-'Assumptions'!$C$82)*'Unit Economics'!$H$51,0) | I42: =IF(I$4-'Assumptions'!$C$82>=1,INDEX('36-Month Forecast'!$C$182:$AL$182,1,I$4-'Assumptions'!$C$82)+INDEX('36-Month Forecast'!$C$179:$AL$179,1,I$4-'Assumptions'!$C$82)*'Unit Economics'!$H$51,0) | J42: =IF(J$4-'Assumptions'!$C$82>=1,INDEX('36-Month Forecast'!$C$182:$AL$182,1,J$4-'Assumptions'!$C$82)+INDEX('36-Month Forecast'!$C$179:$AL$179,1,J$4-'Assumptions'!$C$82)*'Unit Economics'!$H$51,0) | ... AL42: =IF(AL$4-'Assumptions'!$C$82>=1,INDEX('36-Month Forecast'!$C$182:$AL$182,1,AL$4-'Assumptions'!$C$82)+INDEX('36-Month Forecast'!$C$179:$AL$179,1,AL$4-'Assumptions'!$C$82)*'Unit Economics'!$H$51,0) | AM42: =SUMIF($C$6:$AL$6,1,C42:AL42) | AN42: =SUMIF($C$6:$AL$6,2,C42:AL42) | AO42: =SUMIF($C$6:$AL$6,3,C42:AL42) | AP42: =SUM(C42:AL42)
A43: Payout: IngramSpark: paperbacks to bookstores and libraries | C43: =IF(C$4-'Assumptions'!$C$83>=1,INDEX('36-Month Forecast'!$C$192:$AL$192,1,C$4-'Assumptions'!$C$83)+INDEX('36-Month Forecast'!$C$189:$AL$189,1,C$4-'Assumptions'!$C$83)*'Unit Economics'!$H$52,0) | D43: =IF(D$4-'Assumptions'!$C$83>=1,INDEX('36-Month Forecast'!$C$192:$AL$192,1,D$4-'Assumptions'!$C$83)+INDEX('36-Month Forecast'!$C$189:$AL$189,1,D$4-'Assumptions'!$C$83)*'Unit Economics'!$H$52,0) | E43: =IF(E$4-'Assumptions'!$C$83>=1,INDEX('36-Month Forecast'!$C$192:$AL$192,1,E$4-'Assumptions'!$C$83)+INDEX('36-Month Forecast'!$C$189:$AL$189,1,E$4-'Assumptions'!$C$83)*'Unit Economics'!$H$52,0) | F43: =IF(F$4-'Assumptions'!$C$83>=1,INDEX('36-Month Forecast'!$C$192:$AL$192,1,F$4-'Assumptions'!$C$83)+INDEX('36-Month Forecast'!$C$189:$AL$189,1,F$4-'Assumptions'!$C$83)*'Unit Economics'!$H$52,0) | G43: =IF(G$4-'Assumptions'!$C$83>=1,INDEX('36-Month Forecast'!$C$192:$AL$192,1,G$4-'Assumptions'!$C$83)+INDEX('36-Month Forecast'!$C$189:$AL$189,1,G$4-'Assumptions'!$C$83)*'Unit Economics'!$H$52,0) | H43: =IF(H$4-'Assumptions'!$C$83>=1,INDEX('36-Month Forecast'!$C$192:$AL$192,1,H$4-'Assumptions'!$C$83)+INDEX('36-Month Forecast'!$C$189:$AL$189,1,H$4-'Assumptions'!$C$83)*'Unit Economics'!$H$52,0) | I43: =IF(I$4-'Assumptions'!$C$83>=1,INDEX('36-Month Forecast'!$C$192:$AL$192,1,I$4-'Assumptions'!$C$83)+INDEX('36-Month Forecast'!$C$189:$AL$189,1,I$4-'Assumptions'!$C$83)*'Unit Economics'!$H$52,0) | J43: =IF(J$4-'Assumptions'!$C$83>=1,INDEX('36-Month Forecast'!$C$192:$AL$192,1,J$4-'Assumptions'!$C$83)+INDEX('36-Month Forecast'!$C$189:$AL$189,1,J$4-'Assumptions'!$C$83)*'Unit Economics'!$H$52,0) | ... AL43: =IF(AL$4-'Assumptions'!$C$83>=1,INDEX('36-Month Forecast'!$C$192:$AL$192,1,AL$4-'Assumptions'!$C$83)+INDEX('36-Month Forecast'!$C$189:$AL$189,1,AL$4-'Assumptions'!$C$83)*'Unit Economics'!$H$52,0) | AM43: =SUMIF($C$6:$AL$6,1,C43:AL43) | AN43: =SUMIF($C$6:$AL$6,2,C43:AL43) | AO43: =SUMIF($C$6:$AL$6,3,C43:AL43) | AP43: =SUM(C43:AL43)
A44: Payout: International digital via merchant of record (Gumroad) | C44: =IF(C$4-'Assumptions'!$C$84>=1,INDEX('36-Month Forecast'!$C$202:$AL$202,1,C$4-'Assumptions'!$C$84)+INDEX('36-Month Forecast'!$C$199:$AL$199,1,C$4-'Assumptions'!$C$84)*'Unit Economics'!$H$53,0) | D44: =IF(D$4-'Assumptions'!$C$84>=1,INDEX('36-Month Forecast'!$C$202:$AL$202,1,D$4-'Assumptions'!$C$84)+INDEX('36-Month Forecast'!$C$199:$AL$199,1,D$4-'Assumptions'!$C$84)*'Unit Economics'!$H$53,0) | E44: =IF(E$4-'Assumptions'!$C$84>=1,INDEX('36-Month Forecast'!$C$202:$AL$202,1,E$4-'Assumptions'!$C$84)+INDEX('36-Month Forecast'!$C$199:$AL$199,1,E$4-'Assumptions'!$C$84)*'Unit Economics'!$H$53,0) | F44: =IF(F$4-'Assumptions'!$C$84>=1,INDEX('36-Month Forecast'!$C$202:$AL$202,1,F$4-'Assumptions'!$C$84)+INDEX('36-Month Forecast'!$C$199:$AL$199,1,F$4-'Assumptions'!$C$84)*'Unit Economics'!$H$53,0) | G44: =IF(G$4-'Assumptions'!$C$84>=1,INDEX('36-Month Forecast'!$C$202:$AL$202,1,G$4-'Assumptions'!$C$84)+INDEX('36-Month Forecast'!$C$199:$AL$199,1,G$4-'Assumptions'!$C$84)*'Unit Economics'!$H$53,0) | H44: =IF(H$4-'Assumptions'!$C$84>=1,INDEX('36-Month Forecast'!$C$202:$AL$202,1,H$4-'Assumptions'!$C$84)+INDEX('36-Month Forecast'!$C$199:$AL$199,1,H$4-'Assumptions'!$C$84)*'Unit Economics'!$H$53,0) | I44: =IF(I$4-'Assumptions'!$C$84>=1,INDEX('36-Month Forecast'!$C$202:$AL$202,1,I$4-'Assumptions'!$C$84)+INDEX('36-Month Forecast'!$C$199:$AL$199,1,I$4-'Assumptions'!$C$84)*'Unit Economics'!$H$53,0) | J44: =IF(J$4-'Assumptions'!$C$84>=1,INDEX('36-Month Forecast'!$C$202:$AL$202,1,J$4-'Assumptions'!$C$84)+INDEX('36-Month Forecast'!$C$199:$AL$199,1,J$4-'Assumptions'!$C$84)*'Unit Economics'!$H$53,0) | ... AL44: =IF(AL$4-'Assumptions'!$C$84>=1,INDEX('36-Month Forecast'!$C$202:$AL$202,1,AL$4-'Assumptions'!$C$84)+INDEX('36-Month Forecast'!$C$199:$AL$199,1,AL$4-'Assumptions'!$C$84)*'Unit Economics'!$H$53,0) | AM44: =SUMIF($C$6:$AL$6,1,C44:AL44) | AN44: =SUMIF($C$6:$AL$6,2,C44:AL44) | AO44: =SUMIF($C$6:$AL$6,3,C44:AL44) | AP44: =SUM(C44:AL44)
A45: Payout: 30-Day Screen Reset written course (Wave 2) | C45: =IF(C$4-'Assumptions'!$C$85>=1,INDEX('36-Month Forecast'!$C$212:$AL$212,1,C$4-'Assumptions'!$C$85)+INDEX('36-Month Forecast'!$C$209:$AL$209,1,C$4-'Assumptions'!$C$85)*'Unit Economics'!$H$54,0) | D45: =IF(D$4-'Assumptions'!$C$85>=1,INDEX('36-Month Forecast'!$C$212:$AL$212,1,D$4-'Assumptions'!$C$85)+INDEX('36-Month Forecast'!$C$209:$AL$209,1,D$4-'Assumptions'!$C$85)*'Unit Economics'!$H$54,0) | E45: =IF(E$4-'Assumptions'!$C$85>=1,INDEX('36-Month Forecast'!$C$212:$AL$212,1,E$4-'Assumptions'!$C$85)+INDEX('36-Month Forecast'!$C$209:$AL$209,1,E$4-'Assumptions'!$C$85)*'Unit Economics'!$H$54,0) | F45: =IF(F$4-'Assumptions'!$C$85>=1,INDEX('36-Month Forecast'!$C$212:$AL$212,1,F$4-'Assumptions'!$C$85)+INDEX('36-Month Forecast'!$C$209:$AL$209,1,F$4-'Assumptions'!$C$85)*'Unit Economics'!$H$54,0) | G45: =IF(G$4-'Assumptions'!$C$85>=1,INDEX('36-Month Forecast'!$C$212:$AL$212,1,G$4-'Assumptions'!$C$85)+INDEX('36-Month Forecast'!$C$209:$AL$209,1,G$4-'Assumptions'!$C$85)*'Unit Economics'!$H$54,0) | H45: =IF(H$4-'Assumptions'!$C$85>=1,INDEX('36-Month Forecast'!$C$212:$AL$212,1,H$4-'Assumptions'!$C$85)+INDEX('36-Month Forecast'!$C$209:$AL$209,1,H$4-'Assumptions'!$C$85)*'Unit Economics'!$H$54,0) | I45: =IF(I$4-'Assumptions'!$C$85>=1,INDEX('36-Month Forecast'!$C$212:$AL$212,1,I$4-'Assumptions'!$C$85)+INDEX('36-Month Forecast'!$C$209:$AL$209,1,I$4-'Assumptions'!$C$85)*'Unit Economics'!$H$54,0) | J45: =IF(J$4-'Assumptions'!$C$85>=1,INDEX('36-Month Forecast'!$C$212:$AL$212,1,J$4-'Assumptions'!$C$85)+INDEX('36-Month Forecast'!$C$209:$AL$209,1,J$4-'Assumptions'!$C$85)*'Unit Economics'!$H$54,0) | ... AL45: =IF(AL$4-'Assumptions'!$C$85>=1,INDEX('36-Month Forecast'!$C$212:$AL$212,1,AL$4-'Assumptions'!$C$85)+INDEX('36-Month Forecast'!$C$209:$AL$209,1,AL$4-'Assumptions'!$C$85)*'Unit Economics'!$H$54,0) | AM45: =SUMIF($C$6:$AL$6,1,C45:AL45) | AN45: =SUMIF($C$6:$AL$6,2,C45:AL45) | AO45: =SUMIF($C$6:$AL$6,3,C45:AL45) | AP45: =SUM(C45:AL45)
A46: Payout: Board book: pre-sale, then 3PL and Amazon FBA (gated option; off in base) | C46: =IF(C$4-'Assumptions'!$C$86>=1,INDEX('36-Month Forecast'!$C$222:$AL$222,1,C$4-'Assumptions'!$C$86)+INDEX('36-Month Forecast'!$C$219:$AL$219,1,C$4-'Assumptions'!$C$86)*'Unit Economics'!$H$55,0) | D46: =IF(D$4-'Assumptions'!$C$86>=1,INDEX('36-Month Forecast'!$C$222:$AL$222,1,D$4-'Assumptions'!$C$86)+INDEX('36-Month Forecast'!$C$219:$AL$219,1,D$4-'Assumptions'!$C$86)*'Unit Economics'!$H$55,0) | E46: =IF(E$4-'Assumptions'!$C$86>=1,INDEX('36-Month Forecast'!$C$222:$AL$222,1,E$4-'Assumptions'!$C$86)+INDEX('36-Month Forecast'!$C$219:$AL$219,1,E$4-'Assumptions'!$C$86)*'Unit Economics'!$H$55,0) | F46: =IF(F$4-'Assumptions'!$C$86>=1,INDEX('36-Month Forecast'!$C$222:$AL$222,1,F$4-'Assumptions'!$C$86)+INDEX('36-Month Forecast'!$C$219:$AL$219,1,F$4-'Assumptions'!$C$86)*'Unit Economics'!$H$55,0) | G46: =IF(G$4-'Assumptions'!$C$86>=1,INDEX('36-Month Forecast'!$C$222:$AL$222,1,G$4-'Assumptions'!$C$86)+INDEX('36-Month Forecast'!$C$219:$AL$219,1,G$4-'Assumptions'!$C$86)*'Unit Economics'!$H$55,0) | H46: =IF(H$4-'Assumptions'!$C$86>=1,INDEX('36-Month Forecast'!$C$222:$AL$222,1,H$4-'Assumptions'!$C$86)+INDEX('36-Month Forecast'!$C$219:$AL$219,1,H$4-'Assumptions'!$C$86)*'Unit Economics'!$H$55,0) | I46: =IF(I$4-'Assumptions'!$C$86>=1,INDEX('36-Month Forecast'!$C$222:$AL$222,1,I$4-'Assumptions'!$C$86)+INDEX('36-Month Forecast'!$C$219:$AL$219,1,I$4-'Assumptions'!$C$86)*'Unit Economics'!$H$55,0) | J46: =IF(J$4-'Assumptions'!$C$86>=1,INDEX('36-Month Forecast'!$C$222:$AL$222,1,J$4-'Assumptions'!$C$86)+INDEX('36-Month Forecast'!$C$219:$AL$219,1,J$4-'Assumptions'!$C$86)*'Unit Economics'!$H$55,0) | ... AL46: =IF(AL$4-'Assumptions'!$C$86>=1,INDEX('36-Month Forecast'!$C$222:$AL$222,1,AL$4-'Assumptions'!$C$86)+INDEX('36-Month Forecast'!$C$219:$AL$219,1,AL$4-'Assumptions'!$C$86)*'Unit Economics'!$H$55,0) | AM46: =SUMIF($C$6:$AL$6,1,C46:AL46) | AN46: =SUMIF($C$6:$AL$6,2,C46:AL46) | AO46: =SUMIF($C$6:$AL$6,3,C46:AL46) | AP46: =SUM(C46:AL46)
A47: Payout: School and group licenses + TPT (overlay only if counsel clears in writing; off in base) | C47: =IF(C$4-'Assumptions'!$C$87>=1,INDEX('36-Month Forecast'!$C$233:$AL$233,1,C$4-'Assumptions'!$C$87)+INDEX('36-Month Forecast'!$C$230:$AL$230,1,C$4-'Assumptions'!$C$87)*'Unit Economics'!$H$56,0) | D47: =IF(D$4-'Assumptions'!$C$87>=1,INDEX('36-Month Forecast'!$C$233:$AL$233,1,D$4-'Assumptions'!$C$87)+INDEX('36-Month Forecast'!$C$230:$AL$230,1,D$4-'Assumptions'!$C$87)*'Unit Economics'!$H$56,0) | E47: =IF(E$4-'Assumptions'!$C$87>=1,INDEX('36-Month Forecast'!$C$233:$AL$233,1,E$4-'Assumptions'!$C$87)+INDEX('36-Month Forecast'!$C$230:$AL$230,1,E$4-'Assumptions'!$C$87)*'Unit Economics'!$H$56,0) | F47: =IF(F$4-'Assumptions'!$C$87>=1,INDEX('36-Month Forecast'!$C$233:$AL$233,1,F$4-'Assumptions'!$C$87)+INDEX('36-Month Forecast'!$C$230:$AL$230,1,F$4-'Assumptions'!$C$87)*'Unit Economics'!$H$56,0) | G47: =IF(G$4-'Assumptions'!$C$87>=1,INDEX('36-Month Forecast'!$C$233:$AL$233,1,G$4-'Assumptions'!$C$87)+INDEX('36-Month Forecast'!$C$230:$AL$230,1,G$4-'Assumptions'!$C$87)*'Unit Economics'!$H$56,0) | H47: =IF(H$4-'Assumptions'!$C$87>=1,INDEX('36-Month Forecast'!$C$233:$AL$233,1,H$4-'Assumptions'!$C$87)+INDEX('36-Month Forecast'!$C$230:$AL$230,1,H$4-'Assumptions'!$C$87)*'Unit Economics'!$H$56,0) | I47: =IF(I$4-'Assumptions'!$C$87>=1,INDEX('36-Month Forecast'!$C$233:$AL$233,1,I$4-'Assumptions'!$C$87)+INDEX('36-Month Forecast'!$C$230:$AL$230,1,I$4-'Assumptions'!$C$87)*'Unit Economics'!$H$56,0) | J47: =IF(J$4-'Assumptions'!$C$87>=1,INDEX('36-Month Forecast'!$C$233:$AL$233,1,J$4-'Assumptions'!$C$87)+INDEX('36-Month Forecast'!$C$230:$AL$230,1,J$4-'Assumptions'!$C$87)*'Unit Economics'!$H$56,0) | ... AL47: =IF(AL$4-'Assumptions'!$C$87>=1,INDEX('36-Month Forecast'!$C$233:$AL$233,1,AL$4-'Assumptions'!$C$87)+INDEX('36-Month Forecast'!$C$230:$AL$230,1,AL$4-'Assumptions'!$C$87)*'Unit Economics'!$H$56,0) | AM47: =SUMIF($C$6:$AL$6,1,C47:AL47) | AN47: =SUMIF($C$6:$AL$6,2,C47:AL47) | AO47: =SUMIF($C$6:$AL$6,3,C47:AL47) | AP47: =SUM(C47:AL47)
A48: Payout: Retail and wholesale: Faire, Walmart Marketplace (off in base) | C48: =IF(C$4-'Assumptions'!$C$88>=1,INDEX('36-Month Forecast'!$C$243:$AL$243,1,C$4-'Assumptions'!$C$88)+INDEX('36-Month Forecast'!$C$240:$AL$240,1,C$4-'Assumptions'!$C$88)*'Unit Economics'!$H$57,0) | D48: =IF(D$4-'Assumptions'!$C$88>=1,INDEX('36-Month Forecast'!$C$243:$AL$243,1,D$4-'Assumptions'!$C$88)+INDEX('36-Month Forecast'!$C$240:$AL$240,1,D$4-'Assumptions'!$C$88)*'Unit Economics'!$H$57,0) | E48: =IF(E$4-'Assumptions'!$C$88>=1,INDEX('36-Month Forecast'!$C$243:$AL$243,1,E$4-'Assumptions'!$C$88)+INDEX('36-Month Forecast'!$C$240:$AL$240,1,E$4-'Assumptions'!$C$88)*'Unit Economics'!$H$57,0) | F48: =IF(F$4-'Assumptions'!$C$88>=1,INDEX('36-Month Forecast'!$C$243:$AL$243,1,F$4-'Assumptions'!$C$88)+INDEX('36-Month Forecast'!$C$240:$AL$240,1,F$4-'Assumptions'!$C$88)*'Unit Economics'!$H$57,0) | G48: =IF(G$4-'Assumptions'!$C$88>=1,INDEX('36-Month Forecast'!$C$243:$AL$243,1,G$4-'Assumptions'!$C$88)+INDEX('36-Month Forecast'!$C$240:$AL$240,1,G$4-'Assumptions'!$C$88)*'Unit Economics'!$H$57,0) | H48: =IF(H$4-'Assumptions'!$C$88>=1,INDEX('36-Month Forecast'!$C$243:$AL$243,1,H$4-'Assumptions'!$C$88)+INDEX('36-Month Forecast'!$C$240:$AL$240,1,H$4-'Assumptions'!$C$88)*'Unit Economics'!$H$57,0) | I48: =IF(I$4-'Assumptions'!$C$88>=1,INDEX('36-Month Forecast'!$C$243:$AL$243,1,I$4-'Assumptions'!$C$88)+INDEX('36-Month Forecast'!$C$240:$AL$240,1,I$4-'Assumptions'!$C$88)*'Unit Economics'!$H$57,0) | J48: =IF(J$4-'Assumptions'!$C$88>=1,INDEX('36-Month Forecast'!$C$243:$AL$243,1,J$4-'Assumptions'!$C$88)+INDEX('36-Month Forecast'!$C$240:$AL$240,1,J$4-'Assumptions'!$C$88)*'Unit Economics'!$H$57,0) | ... AL48: =IF(AL$4-'Assumptions'!$C$88>=1,INDEX('36-Month Forecast'!$C$243:$AL$243,1,AL$4-'Assumptions'!$C$88)+INDEX('36-Month Forecast'!$C$240:$AL$240,1,AL$4-'Assumptions'!$C$88)*'Unit Economics'!$H$57,0) | AM48: =SUMIF($C$6:$AL$6,1,C48:AL48) | AN48: =SUMIF($C$6:$AL$6,2,C48:AL48) | AO48: =SUMIF($C$6:$AL$6,3,C48:AL48) | AP48: =SUM(C48:AL48)
A49: Total payouts received | C49: =SUM(C40:C48) | D49: =SUM(D40:D48) | E49: =SUM(E40:E48) | F49: =SUM(F40:F48) | G49: =SUM(G40:G48) | H49: =SUM(H40:H48) | I49: =SUM(I40:I48) | J49: =SUM(J40:J48) | ... AL49: =SUM(AL40:AL48) | AM49: =SUMIF($C$6:$AL$6,1,C49:AL49) | AN49: =SUMIF($C$6:$AL$6,2,C49:AL49) | AO49: =SUMIF($C$6:$AL$6,3,C49:AL49) | AP49: =SUM(C49:AL49)
A50: Existing business-card balance paid off (month 1) | C50: =-'Assumptions'!$C$18 | D50: =0 | E50: =0 | F50: =0 | G50: =0 | H50: =0 | I50: =0 | J50: =0 | K50: =0 | ... AL50: =0 | AM50: =SUMIF($C$6:$AL$6,1,C50:AL50) | AN50: =SUMIF($C$6:$AL$6,2,C50:AL50) | AO50: =SUMIF($C$6:$AL$6,3,C50:AL50) | AP50: =SUM(C50:AL50)
A51: Inventory purchases (offset print runs, landed) | C51: =-'36-Month Forecast'!C270 | D51: =-'36-Month Forecast'!D270 | E51: =-'36-Month Forecast'!E270 | F51: =-'36-Month Forecast'!F270 | G51: =-'36-Month Forecast'!G270 | H51: =-'36-Month Forecast'!H270 | I51: =-'36-Month Forecast'!I270 | J51: =-'36-Month Forecast'!J270 | ... AL51: =-'36-Month Forecast'!AL270 | AM51: =SUMIF($C$6:$AL$6,1,C51:AL51) | AN51: =SUMIF($C$6:$AL$6,2,C51:AL51) | AO51: =SUMIF($C$6:$AL$6,3,C51:AL51) | AP51: =SUM(C51:AL51)
A52: Paid advertising | C52: =-'36-Month Forecast'!C257 | D52: =-'36-Month Forecast'!D257 | E52: =-'36-Month Forecast'!E257 | F52: =-'36-Month Forecast'!F257 | G52: =-'36-Month Forecast'!G257 | H52: =-'36-Month Forecast'!H257 | I52: =-'36-Month Forecast'!I257 | J52: =-'36-Month Forecast'!J257 | ... AL52: =-'36-Month Forecast'!AL257 | AM52: =SUMIF($C$6:$AL$6,1,C52:AL52) | AN52: =SUMIF($C$6:$AL$6,2,C52:AL52) | AO52: =SUMIF($C$6:$AL$6,3,C52:AL52) | AP52: =SUM(C52:AL52)
A53: Operating costs | C53: =-'36-Month Forecast'!C258 | D53: =-'36-Month Forecast'!D258 | E53: =-'36-Month Forecast'!E258 | F53: =-'36-Month Forecast'!F258 | G53: =-'36-Month Forecast'!G258 | H53: =-'36-Month Forecast'!H258 | I53: =-'36-Month Forecast'!I258 | J53: =-'36-Month Forecast'!J258 | ... AL53: =-'36-Month Forecast'!AL258 | AM53: =SUMIF($C$6:$AL$6,1,C53:AL53) | AN53: =SUMIF($C$6:$AL$6,2,C53:AL53) | AO53: =SUMIF($C$6:$AL$6,3,C53:AL53) | AP53: =SUM(C53:AL53)
A54: Wave fixed costs | C54: =-'36-Month Forecast'!C259 | D54: =-'36-Month Forecast'!D259 | E54: =-'36-Month Forecast'!E259 | F54: =-'36-Month Forecast'!F259 | G54: =-'36-Month Forecast'!G259 | H54: =-'36-Month Forecast'!H259 | I54: =-'36-Month Forecast'!I259 | J54: =-'36-Month Forecast'!J259 | ... AL54: =-'36-Month Forecast'!AL259 | AM54: =SUMIF($C$6:$AL$6,1,C54:AL54) | AN54: =SUMIF($C$6:$AL$6,2,C54:AL54) | AO54: =SUMIF($C$6:$AL$6,3,C54:AL54) | AP54: =SUM(C54:AL54)
A55: One-time startup costs | C55: =-'36-Month Forecast'!C262 | D55: =-'36-Month Forecast'!D262 | E55: =-'36-Month Forecast'!E262 | F55: =-'36-Month Forecast'!F262 | G55: =-'36-Month Forecast'!G262 | H55: =-'36-Month Forecast'!H262 | I55: =-'36-Month Forecast'!I262 | J55: =-'36-Month Forecast'!J262 | ... AL55: =-'36-Month Forecast'!AL262 | AM55: =SUMIF($C$6:$AL$6,1,C55:AL55) | AN55: =SUMIF($C$6:$AL$6,2,C55:AL55) | AO55: =SUMIF($C$6:$AL$6,3,C55:AL55) | AP55: =SUM(C55:AL55)
A56: One-time wave costs | C56: =-'36-Month Forecast'!C263 | D56: =-'36-Month Forecast'!D263 | E56: =-'36-Month Forecast'!E263 | F56: =-'36-Month Forecast'!F263 | G56: =-'36-Month Forecast'!G263 | H56: =-'36-Month Forecast'!H263 | I56: =-'36-Month Forecast'!I263 | J56: =-'36-Month Forecast'!J263 | ... AL56: =-'36-Month Forecast'!AL263 | AM56: =SUMIF($C$6:$AL$6,1,C56:AL56) | AN56: =SUMIF($C$6:$AL$6,2,C56:AL56) | AO56: =SUMIF($C$6:$AL$6,3,C56:AL56) | AP56: =SUM(C56:AL56)
A57: NET CASH FLOW before tax reserve and founder capital | C57: =SUM(C49:C56) | D57: =SUM(D49:D56) | E57: =SUM(E49:E56) | F57: =SUM(F49:F56) | G57: =SUM(G49:G56) | H57: =SUM(H49:H56) | I57: =SUM(I49:I56) | J57: =SUM(J49:J56) | ... AL57: =SUM(AL49:AL56) | AM57: =SUMIF($C$6:$AL$6,1,C57:AL57) | AN57: =SUMIF($C$6:$AL$6,2,C57:AL57) | AO57: =SUMIF($C$6:$AL$6,3,C57:AL57) | AP57: =SUM(C57:AL57)
A58: Transfer to (-) or from (+) the tax reserve account | C58: =0-C62 | D58: =C62-D62 | E58: =D62-E62 | F58: =E62-F62 | G58: =F62-G62 | H58: =G62-H62 | I58: =H62-I62 | J58: =I62-J62 | K58: =J62-K62 | ... AL58: =AK62-AL62 | AM58: =SUMIF($C$6:$AL$6,1,C58:AL58) | AN58: =SUMIF($C$6:$AL$6,2,C58:AL58) | AO58: =SUMIF($C$6:$AL$6,3,C58:AL58) | AP58: =SUM(C58:AL58)
A59: Operating balance before founder capital | C59: ='Assumptions'!$C$16+C57+C58 | D59: =C61+D57+D58 | E59: =D61+E57+E58 | F59: =E61+F57+F58 | G59: =F61+G57+G58 | H59: =G61+H57+H58 | I59: =H61+I57+I58 | J59: =I61+J57+J58 | K59: =J61+K57+K58 | ... AL59: =AK61+AL57+AL58
A60: FOUNDER CAPITAL IN (planned month-1 amount + any top-up that keeps the balance at zero or above) | C60: ='Assumptions'!$C$17+MAX(0,-(C59+'Assumptions'!$C$17)) | D60: =0+MAX(0,-(D59+0)) | E60: =0+MAX(0,-(E59+0)) | F60: =0+MAX(0,-(F59+0)) | G60: =0+MAX(0,-(G59+0)) | H60: =0+MAX(0,-(H59+0)) | I60: =0+MAX(0,-(I59+0)) | J60: =0+MAX(0,-(J59+0)) | K60: =0+MAX(0,-(K59+0)) | ... AL60: =0+MAX(0,-(AL59+0)) | AM60: =SUMIF($C$6:$AL$6,1,C60:AL60) | AN60: =SUMIF($C$6:$AL$6,2,C60:AL60) | AO60: =SUMIF($C$6:$AL$6,3,C60:AL60) | AP60: =SUM(C60:AL60)
A61: OPERATING ACCOUNT BALANCE (month end) | C61: =C59+C60 | D61: =D59+D60 | E61: =E59+E60 | F61: =F59+F60 | G61: =G59+G60 | H61: =H59+H60 | I61: =I59+I60 | J61: =J59+J60 | ... AL61: =AL59+AL60 | AM61: =N61 | AN61: =Z61 | AO61: =AL61 | AP61: =AL61
A62: Tax reserve account balance (25% of cumulative profit after one-time costs, if positive) | C62: ='Assumptions'!$C$15*MAX(0,'36-Month Forecast'!C265) | D62: ='Assumptions'!$C$15*MAX(0,'36-Month Forecast'!D265) | E62: ='Assumptions'!$C$15*MAX(0,'36-Month Forecast'!E265) | F62: ='Assumptions'!$C$15*MAX(0,'36-Month Forecast'!F265) | G62: ='Assumptions'!$C$15*MAX(0,'36-Month Forecast'!G265) | H62: ='Assumptions'!$C$15*MAX(0,'36-Month Forecast'!H265) | I62: ='Assumptions'!$C$15*MAX(0,'36-Month Forecast'!I265) | J62: ='Assumptions'!$C$15*MAX(0,'36-Month Forecast'!J265) | ... AL62: ='Assumptions'!$C$15*MAX(0,'36-Month Forecast'!AL265) | AM62: =N62 | AN62: =Z62 | AO62: =AL62 | AP62: =AL62
A63: Total cash (both accounts) | C63: =C61+C62 | D63: =D61+D62 | E63: =E61+E62 | F63: =F61+F62 | G63: =G61+G62 | H63: =H61+H62 | I63: =I61+I62 | J63: =J61+J62 | ... AL63: =AL61+AL62 | AM63: =N63 | AN63: =Z63 | AO63: =AL63 | AP63: =AL63
A64: CUMULATIVE FOUNDER CAPITAL (the funding need) | C64: =C60 | D64: =D60+C64 | E64: =E60+D64 | F64: =F60+E64 | G64: =G60+F64 | H64: =H60+G64 | I64: =I60+H64 | J64: =J60+I64 | K64: =K60+J64 | ... AL64: =AL60+AK64 | AM64: =N64 | AN64: =Z64 | AO64: =AL64 | AP64: =AL64
A65: Reserve target (months x fixed costs incl. ads) | C65: ='Assumptions'!$C$21*('36-Month Forecast'!C258+'36-Month Forecast'!C259+'36-Month Forecast'!C257) | D65: ='Assumptions'!$C$21*('36-Month Forecast'!D258+'36-Month Forecast'!D259+'36-Month Forecast'!D257) | E65: ='Assumptions'!$C$21*('36-Month Forecast'!E258+'36-Month Forecast'!E259+'36-Month Forecast'!E257) | F65: ='Assumptions'!$C$21*('36-Month Forecast'!F258+'36-Month Forecast'!F259+'36-Month Forecast'!F257) | G65: ='Assumptions'!$C$21*('36-Month Forecast'!G258+'36-Month Forecast'!G259+'36-Month Forecast'!G257) | H65: ='Assumptions'!$C$21*('36-Month Forecast'!H258+'36-Month Forecast'!H259+'36-Month Forecast'!H257) | I65: ='Assumptions'!$C$21*('36-Month Forecast'!I258+'36-Month Forecast'!I259+'36-Month Forecast'!I257) | J65: ='Assumptions'!$C$21*('36-Month Forecast'!J258+'36-Month Forecast'!J259+'36-Month Forecast'!J257) | ... AL65: ='Assumptions'!$C$21*('36-Month Forecast'!AL258+'36-Month Forecast'!AL259+'36-Month Forecast'!AL257) | AM65: =N65 | AN65: =Z65 | AO65: =AL65 | AP65: =AL65
A66: Operating balance above / (below) reserve target | C66: =C61-C65 | D66: =D61-D65 | E66: =E61-E65 | F66: =F61-F65 | G66: =G61-G65 | H66: =H61-H65 | I66: =I61-I65 | J66: =J61-J65 | ... AL66: =AL61-AL65 | AM66: =N66 | AN66: =Z66 | AO66: =AL66 | AP66: =AL66
A67: Helper: month # if founder capital goes in | C67: =IF(C60>0.5,C$4,"") | D67: =IF(D60>0.5,D$4,"") | E67: =IF(E60>0.5,E$4,"") | F67: =IF(F60>0.5,F$4,"") | G67: =IF(G60>0.5,G$4,"") | H67: =IF(H60>0.5,H$4,"") | I67: =IF(I60>0.5,I$4,"") | J67: =IF(J60>0.5,J$4,"") | ... AL67: =IF(AL60>0.5,AL$4,"")
A68: Helper: month # if cumulative founder capital is above the household-money cap | C68: =IF(C64>'Assumptions'!$C$19,C$4,"") | D68: =IF(D64>'Assumptions'!$C$19,D$4,"") | E68: =IF(E64>'Assumptions'!$C$19,E$4,"") | F68: =IF(F64>'Assumptions'!$C$19,F$4,"") | G68: =IF(G64>'Assumptions'!$C$19,G$4,"") | H68: =IF(H64>'Assumptions'!$C$19,H$4,"") | I68: =IF(I64>'Assumptions'!$C$19,I$4,"") | J68: =IF(J64>'Assumptions'!$C$19,J$4,"") | ... AL68: =IF(AL64>'Assumptions'!$C$19,AL$4,"")
A70: STRONG SCENARIO
A71: Payout: Own site: printables and PDFs (Shopify) | C71: =IF(C$4-'Assumptions'!$C$80>=1,INDEX('36-Month Forecast'!$C$296:$AL$296,1,C$4-'Assumptions'!$C$80)+INDEX('36-Month Forecast'!$C$293:$AL$293,1,C$4-'Assumptions'!$C$80)*'Unit Economics'!$H$49,0) | D71: =IF(D$4-'Assumptions'!$C$80>=1,INDEX('36-Month Forecast'!$C$296:$AL$296,1,D$4-'Assumptions'!$C$80)+INDEX('36-Month Forecast'!$C$293:$AL$293,1,D$4-'Assumptions'!$C$80)*'Unit Economics'!$H$49,0) | E71: =IF(E$4-'Assumptions'!$C$80>=1,INDEX('36-Month Forecast'!$C$296:$AL$296,1,E$4-'Assumptions'!$C$80)+INDEX('36-Month Forecast'!$C$293:$AL$293,1,E$4-'Assumptions'!$C$80)*'Unit Economics'!$H$49,0) | F71: =IF(F$4-'Assumptions'!$C$80>=1,INDEX('36-Month Forecast'!$C$296:$AL$296,1,F$4-'Assumptions'!$C$80)+INDEX('36-Month Forecast'!$C$293:$AL$293,1,F$4-'Assumptions'!$C$80)*'Unit Economics'!$H$49,0) | G71: =IF(G$4-'Assumptions'!$C$80>=1,INDEX('36-Month Forecast'!$C$296:$AL$296,1,G$4-'Assumptions'!$C$80)+INDEX('36-Month Forecast'!$C$293:$AL$293,1,G$4-'Assumptions'!$C$80)*'Unit Economics'!$H$49,0) | H71: =IF(H$4-'Assumptions'!$C$80>=1,INDEX('36-Month Forecast'!$C$296:$AL$296,1,H$4-'Assumptions'!$C$80)+INDEX('36-Month Forecast'!$C$293:$AL$293,1,H$4-'Assumptions'!$C$80)*'Unit Economics'!$H$49,0) | I71: =IF(I$4-'Assumptions'!$C$80>=1,INDEX('36-Month Forecast'!$C$296:$AL$296,1,I$4-'Assumptions'!$C$80)+INDEX('36-Month Forecast'!$C$293:$AL$293,1,I$4-'Assumptions'!$C$80)*'Unit Economics'!$H$49,0) | J71: =IF(J$4-'Assumptions'!$C$80>=1,INDEX('36-Month Forecast'!$C$296:$AL$296,1,J$4-'Assumptions'!$C$80)+INDEX('36-Month Forecast'!$C$293:$AL$293,1,J$4-'Assumptions'!$C$80)*'Unit Economics'!$H$49,0) | ... AL71: =IF(AL$4-'Assumptions'!$C$80>=1,INDEX('36-Month Forecast'!$C$296:$AL$296,1,AL$4-'Assumptions'!$C$80)+INDEX('36-Month Forecast'!$C$293:$AL$293,1,AL$4-'Assumptions'!$C$80)*'Unit Economics'!$H$49,0) | AM71: =SUMIF($C$6:$AL$6,1,C71:AL71) | AN71: =SUMIF($C$6:$AL$6,2,C71:AL71) | AO71: =SUMIF($C$6:$AL$6,3,C71:AL71) | AP71: =SUM(C71:AL71)
A72: Payout: Etsy: printables | C72: =IF(C$4-'Assumptions'!$C$81>=1,INDEX('36-Month Forecast'!$C$306:$AL$306,1,C$4-'Assumptions'!$C$81)+INDEX('36-Month Forecast'!$C$303:$AL$303,1,C$4-'Assumptions'!$C$81)*'Unit Economics'!$H$50,0) | D72: =IF(D$4-'Assumptions'!$C$81>=1,INDEX('36-Month Forecast'!$C$306:$AL$306,1,D$4-'Assumptions'!$C$81)+INDEX('36-Month Forecast'!$C$303:$AL$303,1,D$4-'Assumptions'!$C$81)*'Unit Economics'!$H$50,0) | E72: =IF(E$4-'Assumptions'!$C$81>=1,INDEX('36-Month Forecast'!$C$306:$AL$306,1,E$4-'Assumptions'!$C$81)+INDEX('36-Month Forecast'!$C$303:$AL$303,1,E$4-'Assumptions'!$C$81)*'Unit Economics'!$H$50,0) | F72: =IF(F$4-'Assumptions'!$C$81>=1,INDEX('36-Month Forecast'!$C$306:$AL$306,1,F$4-'Assumptions'!$C$81)+INDEX('36-Month Forecast'!$C$303:$AL$303,1,F$4-'Assumptions'!$C$81)*'Unit Economics'!$H$50,0) | G72: =IF(G$4-'Assumptions'!$C$81>=1,INDEX('36-Month Forecast'!$C$306:$AL$306,1,G$4-'Assumptions'!$C$81)+INDEX('36-Month Forecast'!$C$303:$AL$303,1,G$4-'Assumptions'!$C$81)*'Unit Economics'!$H$50,0) | H72: =IF(H$4-'Assumptions'!$C$81>=1,INDEX('36-Month Forecast'!$C$306:$AL$306,1,H$4-'Assumptions'!$C$81)+INDEX('36-Month Forecast'!$C$303:$AL$303,1,H$4-'Assumptions'!$C$81)*'Unit Economics'!$H$50,0) | I72: =IF(I$4-'Assumptions'!$C$81>=1,INDEX('36-Month Forecast'!$C$306:$AL$306,1,I$4-'Assumptions'!$C$81)+INDEX('36-Month Forecast'!$C$303:$AL$303,1,I$4-'Assumptions'!$C$81)*'Unit Economics'!$H$50,0) | J72: =IF(J$4-'Assumptions'!$C$81>=1,INDEX('36-Month Forecast'!$C$306:$AL$306,1,J$4-'Assumptions'!$C$81)+INDEX('36-Month Forecast'!$C$303:$AL$303,1,J$4-'Assumptions'!$C$81)*'Unit Economics'!$H$50,0) | ... AL72: =IF(AL$4-'Assumptions'!$C$81>=1,INDEX('36-Month Forecast'!$C$306:$AL$306,1,AL$4-'Assumptions'!$C$81)+INDEX('36-Month Forecast'!$C$303:$AL$303,1,AL$4-'Assumptions'!$C$81)*'Unit Economics'!$H$50,0) | AM72: =SUMIF($C$6:$AL$6,1,C72:AL72) | AN72: =SUMIF($C$6:$AL$6,2,C72:AL72) | AO72: =SUMIF($C$6:$AL$6,3,C72:AL72) | AP72: =SUM(C72:AL72)
A73: Payout: Amazon KDP: paperbacks | C73: =IF(C$4-'Assumptions'!$C$82>=1,INDEX('36-Month Forecast'!$C$316:$AL$316,1,C$4-'Assumptions'!$C$82)+INDEX('36-Month Forecast'!$C$313:$AL$313,1,C$4-'Assumptions'!$C$82)*'Unit Economics'!$H$51,0) | D73: =IF(D$4-'Assumptions'!$C$82>=1,INDEX('36-Month Forecast'!$C$316:$AL$316,1,D$4-'Assumptions'!$C$82)+INDEX('36-Month Forecast'!$C$313:$AL$313,1,D$4-'Assumptions'!$C$82)*'Unit Economics'!$H$51,0) | E73: =IF(E$4-'Assumptions'!$C$82>=1,INDEX('36-Month Forecast'!$C$316:$AL$316,1,E$4-'Assumptions'!$C$82)+INDEX('36-Month Forecast'!$C$313:$AL$313,1,E$4-'Assumptions'!$C$82)*'Unit Economics'!$H$51,0) | F73: =IF(F$4-'Assumptions'!$C$82>=1,INDEX('36-Month Forecast'!$C$316:$AL$316,1,F$4-'Assumptions'!$C$82)+INDEX('36-Month Forecast'!$C$313:$AL$313,1,F$4-'Assumptions'!$C$82)*'Unit Economics'!$H$51,0) | G73: =IF(G$4-'Assumptions'!$C$82>=1,INDEX('36-Month Forecast'!$C$316:$AL$316,1,G$4-'Assumptions'!$C$82)+INDEX('36-Month Forecast'!$C$313:$AL$313,1,G$4-'Assumptions'!$C$82)*'Unit Economics'!$H$51,0) | H73: =IF(H$4-'Assumptions'!$C$82>=1,INDEX('36-Month Forecast'!$C$316:$AL$316,1,H$4-'Assumptions'!$C$82)+INDEX('36-Month Forecast'!$C$313:$AL$313,1,H$4-'Assumptions'!$C$82)*'Unit Economics'!$H$51,0) | I73: =IF(I$4-'Assumptions'!$C$82>=1,INDEX('36-Month Forecast'!$C$316:$AL$316,1,I$4-'Assumptions'!$C$82)+INDEX('36-Month Forecast'!$C$313:$AL$313,1,I$4-'Assumptions'!$C$82)*'Unit Economics'!$H$51,0) | J73: =IF(J$4-'Assumptions'!$C$82>=1,INDEX('36-Month Forecast'!$C$316:$AL$316,1,J$4-'Assumptions'!$C$82)+INDEX('36-Month Forecast'!$C$313:$AL$313,1,J$4-'Assumptions'!$C$82)*'Unit Economics'!$H$51,0) | ... AL73: =IF(AL$4-'Assumptions'!$C$82>=1,INDEX('36-Month Forecast'!$C$316:$AL$316,1,AL$4-'Assumptions'!$C$82)+INDEX('36-Month Forecast'!$C$313:$AL$313,1,AL$4-'Assumptions'!$C$82)*'Unit Economics'!$H$51,0) | AM73: =SUMIF($C$6:$AL$6,1,C73:AL73) | AN73: =SUMIF($C$6:$AL$6,2,C73:AL73) | AO73: =SUMIF($C$6:$AL$6,3,C73:AL73) | AP73: =SUM(C73:AL73)
A74: Payout: IngramSpark: paperbacks to bookstores and libraries | C74: =IF(C$4-'Assumptions'!$C$83>=1,INDEX('36-Month Forecast'!$C$326:$AL$326,1,C$4-'Assumptions'!$C$83)+INDEX('36-Month Forecast'!$C$323:$AL$323,1,C$4-'Assumptions'!$C$83)*'Unit Economics'!$H$52,0) | D74: =IF(D$4-'Assumptions'!$C$83>=1,INDEX('36-Month Forecast'!$C$326:$AL$326,1,D$4-'Assumptions'!$C$83)+INDEX('36-Month Forecast'!$C$323:$AL$323,1,D$4-'Assumptions'!$C$83)*'Unit Economics'!$H$52,0) | E74: =IF(E$4-'Assumptions'!$C$83>=1,INDEX('36-Month Forecast'!$C$326:$AL$326,1,E$4-'Assumptions'!$C$83)+INDEX('36-Month Forecast'!$C$323:$AL$323,1,E$4-'Assumptions'!$C$83)*'Unit Economics'!$H$52,0) | F74: =IF(F$4-'Assumptions'!$C$83>=1,INDEX('36-Month Forecast'!$C$326:$AL$326,1,F$4-'Assumptions'!$C$83)+INDEX('36-Month Forecast'!$C$323:$AL$323,1,F$4-'Assumptions'!$C$83)*'Unit Economics'!$H$52,0) | G74: =IF(G$4-'Assumptions'!$C$83>=1,INDEX('36-Month Forecast'!$C$326:$AL$326,1,G$4-'Assumptions'!$C$83)+INDEX('36-Month Forecast'!$C$323:$AL$323,1,G$4-'Assumptions'!$C$83)*'Unit Economics'!$H$52,0) | H74: =IF(H$4-'Assumptions'!$C$83>=1,INDEX('36-Month Forecast'!$C$326:$AL$326,1,H$4-'Assumptions'!$C$83)+INDEX('36-Month Forecast'!$C$323:$AL$323,1,H$4-'Assumptions'!$C$83)*'Unit Economics'!$H$52,0) | I74: =IF(I$4-'Assumptions'!$C$83>=1,INDEX('36-Month Forecast'!$C$326:$AL$326,1,I$4-'Assumptions'!$C$83)+INDEX('36-Month Forecast'!$C$323:$AL$323,1,I$4-'Assumptions'!$C$83)*'Unit Economics'!$H$52,0) | J74: =IF(J$4-'Assumptions'!$C$83>=1,INDEX('36-Month Forecast'!$C$326:$AL$326,1,J$4-'Assumptions'!$C$83)+INDEX('36-Month Forecast'!$C$323:$AL$323,1,J$4-'Assumptions'!$C$83)*'Unit Economics'!$H$52,0) | ... AL74: =IF(AL$4-'Assumptions'!$C$83>=1,INDEX('36-Month Forecast'!$C$326:$AL$326,1,AL$4-'Assumptions'!$C$83)+INDEX('36-Month Forecast'!$C$323:$AL$323,1,AL$4-'Assumptions'!$C$83)*'Unit Economics'!$H$52,0) | AM74: =SUMIF($C$6:$AL$6,1,C74:AL74) | AN74: =SUMIF($C$6:$AL$6,2,C74:AL74) | AO74: =SUMIF($C$6:$AL$6,3,C74:AL74) | AP74: =SUM(C74:AL74)
A75: Payout: International digital via merchant of record (Gumroad) | C75: =IF(C$4-'Assumptions'!$C$84>=1,INDEX('36-Month Forecast'!$C$336:$AL$336,1,C$4-'Assumptions'!$C$84)+INDEX('36-Month Forecast'!$C$333:$AL$333,1,C$4-'Assumptions'!$C$84)*'Unit Economics'!$H$53,0) | D75: =IF(D$4-'Assumptions'!$C$84>=1,INDEX('36-Month Forecast'!$C$336:$AL$336,1,D$4-'Assumptions'!$C$84)+INDEX('36-Month Forecast'!$C$333:$AL$333,1,D$4-'Assumptions'!$C$84)*'Unit Economics'!$H$53,0) | E75: =IF(E$4-'Assumptions'!$C$84>=1,INDEX('36-Month Forecast'!$C$336:$AL$336,1,E$4-'Assumptions'!$C$84)+INDEX('36-Month Forecast'!$C$333:$AL$333,1,E$4-'Assumptions'!$C$84)*'Unit Economics'!$H$53,0) | F75: =IF(F$4-'Assumptions'!$C$84>=1,INDEX('36-Month Forecast'!$C$336:$AL$336,1,F$4-'Assumptions'!$C$84)+INDEX('36-Month Forecast'!$C$333:$AL$333,1,F$4-'Assumptions'!$C$84)*'Unit Economics'!$H$53,0) | G75: =IF(G$4-'Assumptions'!$C$84>=1,INDEX('36-Month Forecast'!$C$336:$AL$336,1,G$4-'Assumptions'!$C$84)+INDEX('36-Month Forecast'!$C$333:$AL$333,1,G$4-'Assumptions'!$C$84)*'Unit Economics'!$H$53,0) | H75: =IF(H$4-'Assumptions'!$C$84>=1,INDEX('36-Month Forecast'!$C$336:$AL$336,1,H$4-'Assumptions'!$C$84)+INDEX('36-Month Forecast'!$C$333:$AL$333,1,H$4-'Assumptions'!$C$84)*'Unit Economics'!$H$53,0) | I75: =IF(I$4-'Assumptions'!$C$84>=1,INDEX('36-Month Forecast'!$C$336:$AL$336,1,I$4-'Assumptions'!$C$84)+INDEX('36-Month Forecast'!$C$333:$AL$333,1,I$4-'Assumptions'!$C$84)*'Unit Economics'!$H$53,0) | J75: =IF(J$4-'Assumptions'!$C$84>=1,INDEX('36-Month Forecast'!$C$336:$AL$336,1,J$4-'Assumptions'!$C$84)+INDEX('36-Month Forecast'!$C$333:$AL$333,1,J$4-'Assumptions'!$C$84)*'Unit Economics'!$H$53,0) | ... AL75: =IF(AL$4-'Assumptions'!$C$84>=1,INDEX('36-Month Forecast'!$C$336:$AL$336,1,AL$4-'Assumptions'!$C$84)+INDEX('36-Month Forecast'!$C$333:$AL$333,1,AL$4-'Assumptions'!$C$84)*'Unit Economics'!$H$53,0) | AM75: =SUMIF($C$6:$AL$6,1,C75:AL75) | AN75: =SUMIF($C$6:$AL$6,2,C75:AL75) | AO75: =SUMIF($C$6:$AL$6,3,C75:AL75) | AP75: =SUM(C75:AL75)
