Workbook

Sheet README
A1: Play Before Pixels - Bookkeeping Workbook, tax year 2026
A2: AlphaPlay LLC d/b/a Play Before Pixels | built September 27, 2026 | companion guide: /home/user/playbeforepixels/finance/money-and-tax-setup.md
A5: What this workbook is for
A6: QuickBooks Online (or Xero, if your accountant prefers it) is the official set of books. This workbook is your working log and your accountant's cross-check. Use it to:
A7: 1. Log the channels no connector covers: KDP, IngramSpark, Teachers Pay Teachers, Faire, the merchant of record, affiliates, direct invoices and events. Until QBO and Link My Books are live, log every channel here.
A8: 2. Tick every payout against a deposit in business checking (Payouts Reconciliation).
A9: 3. Work out the Maryland sales-tax return numbers (Sales Tax) and the quarterly estimate placeholders (Quarterly Estimates).
A10: 4. Keep the mileage log and the accountant checklist in one place.
A12: The monthly routine (about 30 minutes, first week of each month)
A13: 1. Download each platform's monthly statement and save it to the accountant folder (sub-folder YYYY-MM).
A14: 2. Sales Log: one row per channel per month for marketplaces and royalties; one row per order for direct sales.
A15: 3. Expenses: one row per receipt not already in QBO; pick the category from the drop-down.
... A39: Tabs
A40: Chart of Accounts | B40: The accounts to set up in QBO/Xero, the drop-down lists, and the Channel map showing how every shop's money reaches the books.
A41: Sales Log | B41: Sales by channel. Net payout is a formula.
A42: Expenses | B42: Costs, with category drop-down from the Chart of Accounts and a 1099-NEC watch column.
A43: Payouts Reconciliation | B43: Each platform payout matched to a bank deposit.
A44: Channel Summary | B44: Gross, fees, net and payouts by channel and month (formulas only). Tax year input in B3.
A45: Sales Tax | B45: Maryland taxable sales and tax you collected, with marketplace-collected sales excluded. Monthly, quarterly and annual.
A46: Quarterly Estimates | B46: Profit by IRS estimate period, SE-tax placeholder, set-aside, due dates and payment records.
A47: Mileage & Event Log | B47: Business trips and events. (The requested name 'Mileage/Event log' uses '/', which Excel does not allow in tab names.)
A48: Accountant Packet | B48: Monthly, quarterly and year-end checklist with a Status drop-down.
A50: Verification status - read this
A51: No fee, rate, threshold or deadline in this workbook was confirmed against a primary source on September 27, 2026: irs.gov, marylandtaxes.gov and the platform sites were unreachable from the research environment. Items are marked UNVERIFIED. Weekdays of due dates were computed. Your accountant confirms or replaces every rate in a yellow cell.
A53: Next year
A54: Save a copy as PlayBeforePixels_Bookkeeping_2027.xlsx, change the tax year on Channel Summary B3, type the 2027 due dates on Quarterly Estimates, clear the 2026 rows, and reset the Accountant Packet statuses.

Sheet Chart of Accounts
A1: Chart of Accounts - AlphaPlay LLC d/b/a Play Before Pixels
A2: Set these accounts up in QuickBooks Online (or Xero) with these numbers and names. The tax-line column is a suggestion only (UNVERIFIED): your accountant sets the final mapping. The drop-down lists used on the other tabs live in columns H-I, and the channel map below the chart feeds every Channel drop-down.
A4: Account # | B4: Account name | C4: Type | D4: Tax-line suggestion (UNVERIFIED) | E4: What goes here | F4: How it gets posted | H4: Expense categories (drop-down source) | I4: Income accounts (drop-down source)
A5: 1000 | B5: Business checking (AlphaPlay LLC d/b/a Play Before Pixels) | C5: Bank | D5: Balance sheet | E5: The hub. Every shop, royalty and invoice payout lands here. Pays the card, the tax reserve and taxes. | F5: Bank feed | H5: 1200 Inventory - author copies & stock | I5: 4000 Book royalties - KDP
A6: 1010 | B6: Tax reserve savings | C6: Bank | D6: Balance sheet | E6: Set-aside % of each payout (accountant sets it) plus 100% of Maryland sales tax you collect. | F6: Bank feed (record as transfers) | H6: 5000 COGS - books & stock sold | I6: 4010 Book compensation - IngramSpark
A7: 1020 | B7: PayPal Business | C7: Bank (clearing) | D7: Balance sheet | E7: PayPal sales and platform payouts sitting in PayPal before you transfer them to checking. | F7: PayPal connection or Synder (method UNVERIFIED) | H7: 5100 COGS - POD fulfillment (Printful) | I7: 4100 Sales - digital downloads (printables)
A8: 1030 | B8: Stripe clearing | C8: Clearing | D8: Balance sheet | E8: Stripe gross sales less Stripe fees until the payout reaches checking. | F8: Monthly entry from Stripe Payout Reconciliation report | H8: 5200 Shipping & postage (outbound orders) | I8: 4150 Sales - teacher resource pack
A9: 1040 | B9: Marketplace clearing (connector) | C9: Clearing | D9: Balance sheet | E9: Settlements posted by Link My Books (Etsy, TikTok Shop, Shopify) until the deposit clears. | F9: Link My Books | H9: 5300 COGS - card deck & print runs | I9: 4200 Sales - books sold direct
A10: 1100 | B10: KDP receivable | C10: Receivable | D10: Balance sheet | E10: KDP royalties earned but not yet paid (paid about 60 days after month end, UNVERIFIED). | F10: Monthly journal entry from KDP royalty report | H10: 5400 Packaging & order supplies | I10: 4250 Sales - card deck
A11: 1110 | B11: IngramSpark receivable | C11: Receivable | D11: Balance sheet | E11: IngramSpark compensation earned but not yet paid (about 90 days, UNVERIFIED). | F11: Monthly journal entry from compensation report | H11: 6000 Marketplace & platform fees | I11: 4300 Sales - POD merch
A12: 1120 | B12: Other platform receivables | C12: Receivable | D12: Balance sheet | E12: TpT, Faire, merchant-of-record and affiliate earnings not yet paid. | F12: Monthly journal entry or bank-feed coding | H12: 6050 Payment processing fees | I12: 4400 Sales - online course
A13: 1130 | B13: Accounts receivable - invoices | C13: Receivable | D13: Balance sheet | E13: Unpaid coaching, workshop and B2B/school invoices. | F13: QBO/Xero invoices | H13: 6100 Advertising & marketing | I13: 4500 Coaching (services)
A14: 1200 | B14: Inventory - author copies & stock | C14: Inventory | D14: Balance sheet; becomes COGS when sold | E14: Author copies (KDP, IngramSpark), card-deck stock and event stock. NOT an expense when bought. | F14: Card feed; accountant moves sold units to 5000 | H14: 6200 Software & subscriptions | I14: 4510 Workshops - live delivery
A15: 2000 | B15: Business credit card | C15: Credit card | D15: Balance sheet | E15: Every business charge. Paid in full from 1000 only. | F15: Card feed | H15: 6300 Publishing costs (ISBNs, proofs, revisions) | I15: 4520 Workshop kits - licenses
... A20: 3110 | B20: Owner draw - federal estimated tax | C20: Equity | D20: Not a business expense (disregarded LLC) | E20: Form 1040-ES payments made from the tax reserve. | F20: Bank feed | H20: 6700 Bank & card fees | I20: 4950 Interest income
A21: 3120 | B21: Owner draw - Maryland estimated tax | C21: Equity | D21: Not a business expense (UNVERIFIED; accountant confirms) | E21: Maryland individual estimated payments (Form PV / 502D). | F21: Bank feed | H21: 6800 Research books & education
A22: 3900 | B22: Owner equity / retained earnings | C22: Equity | D22: Balance sheet | E22: Year-end roll-forward (automatic in QBO/Xero). | F22: Automatic | H22: 6850 Workshop & event costs
A23: 4000 | B23: Book royalties - KDP | C23: Income | D23: Sch C line 1 gross receipts (UNVERIFIED; accountant confirms) | E23: KDP royalties (print cost is already netted out by Amazon). | F23: Monthly journal entry: Dr 1100 / Cr 4000 | H23: 6900 Vehicle - mileage, parking & tolls
A24: 4010 | B24: Book compensation - IngramSpark | C24: Income | D24: Sch C line 1 (UNVERIFIED) | E24: IngramSpark publisher compensation. | F24: Monthly journal entry: Dr 1110 / Cr 4010 | H24: 6950 Travel (lodging, fares)
A25: 4100 | B25: Sales - digital downloads (printables) | C25: Income | D25: Sch C line 1 (UNVERIFIED) | E25: Printables sold on Etsy, TpT, the website or a merchant of record. | F25: Connector or monthly entry | H25: 6960 Business meals
A26: 4150 | B26: Sales - teacher resource pack | C26: Income | D26: Sch C line 1 (UNVERIFIED) | E26: Teacher resource pack (mostly TpT). | F26: Monthly entry from TpT report | H26: 7000 Ask My Accountant
A27: 4200 | B27: Sales - books sold direct | C27: Income | D27: Sch C line 1 (UNVERIFIED) | E27: Signed books and author copies you sell yourself (website, events, Etsy, TikTok). | F27: Connector, Stripe or invoice
A28: 4250 | B28: Sales - card deck | C28: Income | D28: Sch C line 1 (UNVERIFIED) | E28: The card deck on any channel. | F28: Connector, Stripe or invoice
A29: 4300 | B29: Sales - POD merch | C29: Income | D29: Sch C line 1 (UNVERIFIED) | E29: Tees, totes, mugs, stickers, onesies (fulfilled by Printful). | F29: Connector
A30: 4400 | B30: Sales - online course | C30: Income | D30: Sch C line 1 (UNVERIFIED) | E30: Course sales (merchant of record, or Stripe for US buyers). | F30: Monthly entry from payout report
A31: 4500 | B31: Coaching (services) | C31: Income | D31: Sch C line 1 (UNVERIFIED) | E31: Parent coaching (audio or written). | F31: Stripe / invoice
A32: 4510 | B32: Workshops - live delivery | C32: Income | D32: Sch C line 1 (UNVERIFIED) | E32: Workshops you deliver (audio or in person). | F32: Stripe / invoice
A33: 4520 | B33: Workshop kits - licenses | C33: Income | D33: Sch C line 1 (UNVERIFIED) | E33: Host-it-yourself kits sold as downloads (possibly taxable digital product in MD, UNVERIFIED). | F33: Stripe, merchant of record or invoice
A34: 4600 | B34: Wholesale & group/B2B sales | C34: Income | D34: Sch C line 1 (UNVERIFIED) | E34: Faire wholesale, school/PTA/group orders. | F34: Monthly entry (Faire) or invoice
A35: 4700 | B35: Affiliate income | C35: Income | D35: Sch C line 1 or other income (accountant decides) | E35: Amazon Associates and Bookshop.org commissions. | F35: Code the deposit in the bank feed
A36: 4800 | B36: Shipping charged to customers | C36: Income | D36: Sch C line 1 (UNVERIFIED) | E36: Shipping buyers paid you. | F36: Connector or entry
A37: 4900 | B37: Refunds & returns | C37: Contra-income | D37: Sch C line 2 returns & allowances (UNVERIFIED) | E37: Refunds you gave (connector splits these out). | F37: Connector or entry
A38: 4950 | B38: Interest income | C38: Other income | D38: Usually not Sch C (accountant decides) | E38: Bank interest (1099-INT if $10 or more, UNVERIFIED). | F38: Bank feed
... A60: 7000 | B60: Ask My Accountant | C60: Suspense | D60: Must be empty at year end | E60: Anything you are unsure of. Add a note. Clear before year end. | F60: Any
A63: Channel map - how every shop's money reaches the books
A64: Column A feeds every Channel drop-down in this workbook. Timing, fees and tax forms are UNVERIFIED (no primary source was reachable on Sept 27, 2026). Check the source URL on the day you sign up.
A65: Channel | B65: What sells there | C65: Who collects sales tax | D65: Payout rail & timing (UNVERIFIED) | E65: Income account(s) | F65: Fee account | G65: How it reaches QBO/Xero | H65: Monthly report to save | I65: Tax form you may receive (UNVERIFIED) | J65: Check at (source)
A66: Amazon KDP | B66: Paperback & hardcover picture books, ebooks (board books are NOT a KDP format, UNVERIFIED) | C66: Amazon is the seller; not on your MD return (UNVERIFIED) | D66: EFT to 1000, ~60 days after month end, per marketplace | E66: 4000 | F66: None (print cost netted in royalty) | G66: Monthly journal entry Dr 1100 / Cr 4000; clear on deposit | H66: Royalty + Payments reports | I66: 1099-MISC (royalty threshold $10) | J66: https://kdp.amazon.com/en_US/help/topic/G200641050
A67: IngramSpark | B67: Hardcover & paperback for bookstores, libraries, schools | C67: The retailer (your print orders are costs) | D67: To 1000, ~90 days after month end | E67: 4010 | F67: Your print orders -> 1200 via card | G67: Monthly journal entry Dr 1110 / Cr 4010 | H67: Compensation report | I67: 1099-MISC possible | J67: https://www.ingramspark.com/
A68: Etsy | B68: Printables, card deck, Printful merch, signed books | C68: Etsy (marketplace facilitator; also EU/UK VAT on downloads) | D68: Etsy Payments deposit to 1000: daily/weekly/biweekly/monthly (you choose) | E68: 4100 / 4250 / 4300 / 4200 + 4800 | F68: 6000-Etsy | G68: Link My Books -> QBO | H68: Monthly CSV statement | I68: 1099-K (federal >$20,000 and >200; MD reported $600) | J68: https://www.etsy.com/legal/fees/
A69: Teachers Pay Teachers | B69: Teacher resource pack, classroom printables | C69: TpT (marketplace facilitator) | D69: Monthly; historically via PayPal | E69: 4150 / 4100 | F69: 6000-TpT | G69: Monthly journal entry; PayPal leg is a transfer | H69: Sales report | I69: 1099-K possible | J69: https://www.teacherspayteachers.com/
A70: TikTok Shop | B70: Merch, card deck, books you ship (NO digital goods) | C70: TikTok (marketplace facilitator) | D70: Settles to 1000 some days after delivery | E70: 4300 / 4250 / 4200 | F70: 6000-TikTok | G70: Link My Books -> QBO | H70: Settlement statements | I70: 1099-K (federal >$20,000 and >200; MD reported $600) | J70: https://seller-us.tiktok.com/
A71: Shopify (website store) | B71: Books direct, Printful merch, card deck, US digital downloads | C71: YOU collect on Maryland orders (watch other states' nexus) | D71: Shopify Payments payout to 1000 | E71: 4200 / 4250 / 4300 / 4100 + 4800 | F71: 6050 (plan fee -> 6200) | G71: Link My Books or A2X -> QBO; tax -> 2200 | H71: Payouts report | I71: 1099-K (federal >$20,000 and >200; MD reported $600) | J71: https://www.shopify.com/pricing
A72: Stripe (website & invoices) | B72: Coaching, workshop deposits & invoices, B2B/school orders, US-only course/downloads | C72: YOU collect where taxable | D72: ~2 business days rolling after a delayed first payout | E72: 4500 / 4510 / 4520 / 4600 / 4400 | F72: 6050 | G72: Match payout in bank feed + monthly entry from Payout Reconciliation report | H72: Payout Reconciliation report | I72: 1099-K (MD reported $600) | J72: https://stripe.com/pricing
A73: PayPal Business | B73: Invoices for PayPal buyers; receives some platform payouts | C73: YOU collect on your own sales | D73: Sits in PayPal until you transfer to 1000 | E73: Per product | F73: 6050 | G73: PayPal as a bank-type account in QBO (method UNVERIFIED); platform payouts = transfers | H73: Monthly statement | I73: 1099-K (MD reported $600) | J73: https://www.paypal.com/us/business/paypal-business-fees
A74: Meta shop (FB/IG) | B74: Same catalog as the website | C74: Follows the checkout (website -> you) | D74: No separate payout if checkout is on your site | E74: Log under Shopify/Stripe | F74: Log under Shopify/Stripe | G74: Nothing extra if checkout is on your site | H74: None | I74: None if website checkout | J74: https://www.facebook.com/business/help
A75: Faire (wholesale) | B75: Books, card deck, merch at wholesale to shops | C75: Resale certificates collected by Faire | D75: Paid shortly after shipment | E75: 4600 | F75: 6000-Faire | G75: Monthly journal entry (Synder later) | H75: Payout reports (proof of exempt wholesale sales) | I75: 1099-K possible | J75: https://www.faire.com/
A76: Merchant of record | B76: Worldwide printables, online course, workshop kits (Lemon Squeezy, Gumroad or course-platform MoR) | C76: The MoR (EU/UK VAT and most US states) | D76: Per MoR payout schedule | E76: 4100 / 4400 / 4520 | F76: 6000-MoR | G76: Monthly journal entry from payout statement (gross vs net: accountant decides) | H76: Payout statement | I76: UNVERIFIED | J76: https://taxation-customs.ec.europa.eu/taxation/vat/vat-e-commerce_en
... A79: Direct (check / ACH / cash) | B79: School, PTA and group orders paid by check or ACH; event cash | C79: YOU collect on taxable MD sales | D79: Deposit straight to 1000 | E79: 4600 / 4200 / 4510 | F79: None | G79: QBO invoice + bank feed | H79: Deposit record | I79: None (still income) | J79: https://www.marylandtaxes.gov/business/sales-use/index.php
A81: Suppliers and notes (not sales channels, so not in the drop-down)
A82: Printful | B82: Cost, not a channel. Charges the business card per order -> 5100 COGS - POD fulfillment and 5200 Shipping. Upload a Maryland resale certificate so Printful does not charge sales tax on fulfillment (UNVERIFIED). Ask for CPSIA certificates for onesies/kids' items. Source: https://www.printful.com/
A83: "Amazon storefront" | B83: The amazon.com/shop/<name> storefront belongs to the Amazon Influencer Program, which needs a social following; the brand kit's faceless rule says skip it. Your Amazon presence is the Author Central page + KDP book pages (paid through KDP) and Associates links (paid through Associates).
A84: Bank & card | B84: One checking (1000), one tax reserve (1010), one card (2000). Never personal money. Source: https://www.sba.gov/business-guide/launch-your-business/open-business-bank-account

Sheet Sales Log
A1: Sales Log
A2: Direct sales (website, Stripe, invoices, events): one row per order. Marketplaces and royalties (Etsy, TikTok, TpT, KDP, IngramSpark, Faire, merchant of record, affiliates): one row per channel per month from the monthly statement. Net payout is a formula. Grey italic EXAMPLE rows are excluded from every total - delete them when you start.
A4: Date | B4: Channel | C4: Order ID | D4: Product | E4: SKU | F4: Qty | G4: Gross | H4: Platform fees | I4: Shipping charged | J4: Sales tax collected | K4: Tax collected by marketplace? (Y/N) | L4: Net payout | M4: Buyer state / country | N4: Taxable in MD? (Y/N) | O4: Income account | P4: Payout ref (date or ID) | Q4: Notes | R4: Example row
A5: 46298 | B5: Etsy | C5: EXAMPLE-ETSY-2026-10 | D5: EXAMPLE - October Etsy statement (monthly summary row) | E5: various | F5: 18 | G5: 142 | H5: 21.5 | I5: 12 | J5: 9.8 | K5: Y | L5: =IF(G5="","",G5-H5+I5+IF(K5="N",J5,0)) -> 132.5 | M5: Various | O5: 4100 Sales - digital downloads (printables) | P5: Etsy deposit 11/01/2026 | Q5: EXAMPLE - made-up amounts to show the format | R5: EXAMPLE
A6: 46303 | B6: Shopify (website store) | C6: EXAMPLE-#1001 | D6: EXAMPLE - Play Before Pixels card deck | E6: PBP-DECK-01 | F6: 1 | G6: 24 | H6: 1 | I6: 5 | J6: 1.44 | K6: N | L6: =IF(G6="","",G6-H6+I6+IF(K6="N",J6,0)) -> 29.44 | M6: MD | N6: Y | O6: 4250 Sales - card deck | P6: Shopify payout 10/10/2026 | Q6: EXAMPLE - you collected MD tax, so it is in the payout and goes to 2200 | R6: EXAMPLE
A7: 46310 | B7: Stripe (website & invoices) | C7: EXAMPLE-INV-0001 | D7: EXAMPLE - Parent coaching session (audio) | E7: COACH-60 | F7: 1 | G7: 95 | H7: 3.06 | I7: 0 | J7: 0 | K7: N | L7: =IF(G7="","",G7-H7+I7+IF(K7="N",J7,0)) -> 91.94 | M7: MD | N7: N | O7: 4500 Coaching (services) | P7: Stripe payout 10/17/2026 | Q7: EXAMPLE - live coaching generally not taxable in MD (UNVERIFIED) | R7: EXAMPLE
A8: 46326 | B8: Amazon KDP | C8: EXAMPLE-KDP-2026-10-US | D8: EXAMPLE - October royalties, amazon.com | E8: all titles | F8: 12 | G8: 38.4 | H8: 0 | I8: 0 | J8: 0 | K8: Y | L8: =IF(G8="","",G8-H8+I8+IF(K8="N",J8,0)) -> 38.4 | M8: Various | O8: 4000 Book royalties - KDP | P8: Expected ~12/29/2026 | Q8: EXAMPLE - royalty earned; post Dr 1100 / Cr 4000 | R8: EXAMPLE
L9: =IF(G9="","",G9-H9+I9+IF(K9="N",J9,0))
L10: =IF(G10="","",G10-H10+I10+IF(K10="N",J10,0))
L11: =IF(G11="","",G11-H11+I11+IF(K11="N",J11,0))
L12: =IF(G12="","",G12-H12+I12+IF(K12="N",J12,0))
L13: =IF(G13="","",G13-H13+I13+IF(K13="N",J13,0))
L14: =IF(G14="","",G14-H14+I14+IF(K14="N",J14,0))
L15: =IF(G15="","",G15-H15+I15+IF(K15="N",J15,0))
L16: =IF(G16="","",G16-H16+I16+IF(K16="N",J16,0))
L17: =IF(G17="","",G17-H17+I17+IF(K17="N",J17,0))
L18: =IF(G18="","",G18-H18+I18+IF(K18="N",J18,0))
L19: =IF(G19="","",G19-H19+I19+IF(K19="N",J19,0))
L20: =IF(G20="","",G20-H20+I20+IF(K20="N",J20,0))
... L1004: =IF(G1004="","",G1004-H1004+I1004+IF(K1004="N",J1004,0))

Sheet Expenses
A1: Expenses
A2: Every cost the business pays: one row per receipt. Pick the category from the drop-down (it comes from the Chart of Accounts). Fees a platform already deducted from a payout go in the Sales Log, not here. Owner draws and tax payments are NOT expenses - never log them here.
A4: Date | B4: Vendor | C4: Category | D4: Amount | E4: Paid with | F4: Receipt link | G4: Notes | H4: 1099 contractor? (Y/N) | I4: W-9 on file? (Y/N) | J4: 1099-NEC watch | K4: Example row
A5: 46297 | B5: Printful | C5: 5100 COGS - POD fulfillment (Printful) | D5: 14.25 | E5: Business credit card | F5: https://drive.example/receipts/printful-1002 | G5: EXAMPLE - tee for an Etsy order (made-up amount) | H5: N | J5: =IF(AND(H5="Y",E5="Business checking (debit/ACH/check)"),"Counts toward 1099-NEC",IF(H5="Y","Paid by card/PayPal - 1099-K side","")) | K5: EXAMPLE
A6: 46301 | B6: IngramSpark | C6: 1200 Inventory - author copies & stock | D6: 60 | E6: Business credit card | F6: https://drive.example/receipts/ingram-1006 | G6: EXAMPLE - author copies for a school order (inventory) | H6: N | J6: =IF(AND(H6="Y",E6="Business checking (debit/ACH/check)"),"Counts toward 1099-NEC",IF(H6="Y","Paid by card/PayPal - 1099-K side","")) | K6: EXAMPLE
A7: 46315 | B7: EXAMPLE Illustrator (contractor) | C7: 6500 Contract labor (1099 watch) | D7: 400 | E7: Business checking (debit/ACH/check) | F7: https://drive.example/receipts/illustrator-inv-7 | G7: EXAMPLE - spot illustrations; W-9 collected first | H7: Y | I7: Y | J7: =IF(AND(H7="Y",E7="Business checking (debit/ACH/check)"),"Counts toward 1099-NEC",IF(H7="Y","Paid by card/PayPal - 1099-K side","")) -> Counts toward 1099-NEC | K7: EXAMPLE
J8: =IF(AND(H8="Y",E8="Business checking (debit/ACH/check)"),"Counts toward 1099-NEC",IF(H8="Y","Paid by card/PayPal - 1099-K side",""))
J9: =IF(AND(H9="Y",E9="Business checking (debit/ACH/check)"),"Counts toward 1099-NEC",IF(H9="Y","Paid by card/PayPal - 1099-K side",""))
J10: =IF(AND(H10="Y",E10="Business checking (debit/ACH/check)"),"Counts toward 1099-NEC",IF(H10="Y","Paid by card/PayPal - 1099-K side",""))
J11: =IF(AND(H11="Y",E11="Business checking (debit/ACH/check)"),"Counts toward 1099-NEC",IF(H11="Y","Paid by card/PayPal - 1099-K side",""))
J12: =IF(AND(H12="Y",E12="Business checking (debit/ACH/check)"),"Counts toward 1099-NEC",IF(H12="Y","Paid by card/PayPal - 1099-K side",""))
J13: =IF(AND(H13="Y",E13="Business checking (debit/ACH/check)"),"Counts toward 1099-NEC",IF(H13="Y","Paid by card/PayPal - 1099-K side",""))
J14: =IF(AND(H14="Y",E14="Business checking (debit/ACH/check)"),"Counts toward 1099-NEC",IF(H14="Y","Paid by card/PayPal - 1099-K side",""))
J15: =IF(AND(H15="Y",E15="Business checking (debit/ACH/check)"),"Counts toward 1099-NEC",IF(H15="Y","Paid by card/PayPal - 1099-K side",""))
J16: =IF(AND(H16="Y",E16="Business checking (debit/ACH/check)"),"Counts toward 1099-NEC",IF(H16="Y","Paid by card/PayPal - 1099-K side",""))
J17: =IF(AND(H17="Y",E17="Business checking (debit/ACH/check)"),"Counts toward 1099-NEC",IF(H17="Y","Paid by card/PayPal - 1099-K side",""))
J18: =IF(AND(H18="Y",E18="Business checking (debit/ACH/check)"),"Counts toward 1099-NEC",IF(H18="Y","Paid by card/PayPal - 1099-K side",""))
J19: =IF(AND(H19="Y",E19="Business checking (debit/ACH/check)"),"Counts toward 1099-NEC",IF(H19="Y","Paid by card/PayPal - 1099-K side",""))
... J1004: =IF(AND(H1004="Y",E1004="Business checking (debit/ACH/check)"),"Counts toward 1099-NEC",IF(H1004="Y","Paid by card/PayPal - 1099-K side",""))

Sheet Payouts Reconciliation
A1: Payouts Reconciliation
A2: One row per payout. Type what the platform says it paid, then the deposit you see on the business checking statement. Bank deposit match turns MATCHED, CHECK or WAITING. A platform payout routed through PayPal is a transfer, not new income: log the platform payout here and match it to the PayPal-to-checking transfer.
A4: Channel | B4: Payout date | C4: Amount | D4: Payout / settlement ID | E4: Period start | F4: Period end | G4: Bank deposit date | H4: Bank deposit amount | I4: Difference | J4: Bank deposit match | K4: Sales Log net for period | L4: Posted in QBO/Xero? (Y/N) | M4: Report saved (link) | N4: Notes | O4: Example row
A5: Etsy | B5: 46327 | C5: 132.5 | D5: EXAMPLE-ETSY-DEP-1101 | E5: 46296 | F5: 46326 | G5: 46329 | H5: 132.5 | I5: =IF(OR(C5="",H5=""),"",C5-H5) -> 0 | J5: =IF(C5="","",IF(H5="","WAITING",IF(ABS(C5-H5)<0.005,"MATCHED","CHECK"))) -> MATCHED | K5: =IF(OR(A5="",E5="",F5=""),"",SUMIFS('Sales Log'!$L$5:$L$1004,'Sales Log'!$B$5:$B$1004,A5,'Sales Log'!$A$5:$A$1004,">="&E5,'Sales Log'!$A$5:$A$1004,"<="&F5,'Sales Log'!$R$5:$R$1004,IF(O5="EXAMPLE","EXAMPLE","<>EXAMPLE"))) -> 132.5 | L5: Y | M5: https://drive.example/etsy/2026-10.csv | N5: EXAMPLE | O5: EXAMPLE
A6: Shopify (website store) | B6: 46305 | C6: 29.44 | D6: EXAMPLE-SHOP-PO-1010 | E6: 46303 | F6: 46303 | G6: 46308 | H6: 29.4 | I6: =IF(OR(C6="",H6=""),"",C6-H6) -> 0.04 | J6: =IF(C6="","",IF(H6="","WAITING",IF(ABS(C6-H6)<0.005,"MATCHED","CHECK"))) -> CHECK | K6: =IF(OR(A6="",E6="",F6=""),"",SUMIFS('Sales Log'!$L$5:$L$1004,'Sales Log'!$B$5:$B$1004,A6,'Sales Log'!$A$5:$A$1004,">="&E6,'Sales Log'!$A$5:$A$1004,"<="&F6,'Sales Log'!$R$5:$R$1004,IF(O6="EXAMPLE","EXAMPLE","<>EXAMPLE"))) -> 29.44 | L6: N | N6: EXAMPLE - 4 cents off: find out why | O6: EXAMPLE
A7: Amazon KDP | B7: 46385 | C7: 38.4 | D7: EXAMPLE-KDP-EFT | E7: 46296 | F7: 46326 | I7: =IF(OR(C7="",H7=""),"",C7-H7) | J7: =IF(C7="","",IF(H7="","WAITING",IF(ABS(C7-H7)<0.005,"MATCHED","CHECK"))) -> WAITING | K7: =IF(OR(A7="",E7="",F7=""),"",SUMIFS('Sales Log'!$L$5:$L$1004,'Sales Log'!$B$5:$B$1004,A7,'Sales Log'!$A$5:$A$1004,">="&E7,'Sales Log'!$A$5:$A$1004,"<="&F7,'Sales Log'!$R$5:$R$1004,IF(O7="EXAMPLE","EXAMPLE","<>EXAMPLE"))) -> 38.4 | L7: N | N7: EXAMPLE - not arrived yet | O7: EXAMPLE
I8: =IF(OR(C8="",H8=""),"",C8-H8) | J8: =IF(C8="","",IF(H8="","WAITING",IF(ABS(C8-H8)<0.005,"MATCHED","CHECK"))) | K8: =IF(OR(A8="",E8="",F8=""),"",SUMIFS('Sales Log'!$L$5:$L$1004,'Sales Log'!$B$5:$B$1004,A8,'Sales Log'!$A$5:$A$1004,">="&E8,'Sales Log'!$A$5:$A$1004,"<="&F8,'Sales Log'!$R$5:$R$1004,IF(O8="EXAMPLE","EXAMPLE","<>EXAMPLE")))
I9: =IF(OR(C9="",H9=""),"",C9-H9) | J9: =IF(C9="","",IF(H9="","WAITING",IF(ABS(C9-H9)<0.005,"MATCHED","CHECK"))) | K9: =IF(OR(A9="",E9="",F9=""),"",SUMIFS('Sales Log'!$L$5:$L$1004,'Sales Log'!$B$5:$B$1004,A9,'Sales Log'!$A$5:$A$1004,">="&E9,'Sales Log'!$A$5:$A$1004,"<="&F9,'Sales Log'!$R$5:$R$1004,IF(O9="EXAMPLE","EXAMPLE","<>EXAMPLE")))
I10: =IF(OR(C10="",H10=""),"",C10-H10) | J10: =IF(C10="","",IF(H10="","WAITING",IF(ABS(C10-H10)<0.005,"MATCHED","CHECK"))) | K10: =IF(OR(A10="",E10="",F10=""),"",SUMIFS('Sales Log'!$L$5:$L$1004,'Sales Log'!$B$5:$B$1004,A10,'Sales Log'!$A$5:$A$1004,">="&E10,'Sales Log'!$A$5:$A$1004,"<="&F10,'Sales Log'!$R$5:$R$1004,IF(O10="EXAMPLE","EXAMPLE","<>EXAMPLE")))
I11: =IF(OR(C11="",H11=""),"",C11-H11) | J11: =IF(C11="","",IF(H11="","WAITING",IF(ABS(C11-H11)<0.005,"MATCHED","CHECK"))) | K11: =IF(OR(A11="",E11="",F11=""),"",SUMIFS('Sales Log'!$L$5:$L$1004,'Sales Log'!$B$5:$B$1004,A11,'Sales Log'!$A$5:$A$1004,">="&E11,'Sales Log'!$A$5:$A$1004,"<="&F11,'Sales Log'!$R$5:$R$1004,IF(O11="EXAMPLE","EXAMPLE","<>EXAMPLE")))
I12: =IF(OR(C12="",H12=""),"",C12-H12) | J12: =IF(C12="","",IF(H12="","WAITING",IF(ABS(C12-H12)<0.005,"MATCHED","CHECK"))) | K12: =IF(OR(A12="",E12="",F12=""),"",SUMIFS('Sales Log'!$L$5:$L$1004,'Sales Log'!$B$5:$B$1004,A12,'Sales Log'!$A$5:$A$1004,">="&E12,'Sales Log'!$A$5:$A$1004,"<="&F12,'Sales Log'!$R$5:$R$1004,IF(O12="EXAMPLE","EXAMPLE","<>EXAMPLE")))
I13: =IF(OR(C13="",H13=""),"",C13-H13) | J13: =IF(C13="","",IF(H13="","WAITING",IF(ABS(C13-H13)<0.005,"MATCHED","CHECK"))) | K13: =IF(OR(A13="",E13="",F13=""),"",SUMIFS('Sales Log'!$L$5:$L$1004,'Sales Log'!$B$5:$B$1004,A13,'Sales Log'!$A$5:$A$1004,">="&E13,'Sales Log'!$A$5:$A$1004,"<="&F13,'Sales Log'!$R$5:$R$1004,IF(O13="EXAMPLE","EXAMPLE","<>EXAMPLE")))
I14: =IF(OR(C14="",H14=""),"",C14-H14) | J14: =IF(C14="","",IF(H14="","WAITING",IF(ABS(C14-H14)<0.005,"MATCHED","CHECK"))) | K14: =IF(OR(A14="",E14="",F14=""),"",SUMIFS('Sales Log'!$L$5:$L$1004,'Sales Log'!$B$5:$B$1004,A14,'Sales Log'!$A$5:$A$1004,">="&E14,'Sales Log'!$A$5:$A$1004,"<="&F14,'Sales Log'!$R$5:$R$1004,IF(O14="EXAMPLE","EXAMPLE","<>EXAMPLE")))
I15: =IF(OR(C15="",H15=""),"",C15-H15) | J15: =IF(C15="","",IF(H15="","WAITING",IF(ABS(C15-H15)<0.005,"MATCHED","CHECK"))) | K15: =IF(OR(A15="",E15="",F15=""),"",SUMIFS('Sales Log'!$L$5:$L$1004,'Sales Log'!$B$5:$B$1004,A15,'Sales Log'!$A$5:$A$1004,">="&E15,'Sales Log'!$A$5:$A$1004,"<="&F15,'Sales Log'!$R$5:$R$1004,IF(O15="EXAMPLE","EXAMPLE","<>EXAMPLE")))
I16: =IF(OR(C16="",H16=""),"",C16-H16) | J16: =IF(C16="","",IF(H16="","WAITING",IF(ABS(C16-H16)<0.005,"MATCHED","CHECK"))) | K16: =IF(OR(A16="",E16="",F16=""),"",SUMIFS('Sales Log'!$L$5:$L$1004,'Sales Log'!$B$5:$B$1004,A16,'Sales Log'!$A$5:$A$1004,">="&E16,'Sales Log'!$A$5:$A$1004,"<="&F16,'Sales Log'!$R$5:$R$1004,IF(O16="EXAMPLE","EXAMPLE","<>EXAMPLE")))
I17: =IF(OR(C17="",H17=""),"",C17-H17) | J17: =IF(C17="","",IF(H17="","WAITING",IF(ABS(C17-H17)<0.005,"MATCHED","CHECK"))) | K17: =IF(OR(A17="",E17="",F17=""),"",SUMIFS('Sales Log'!$L$5:$L$1004,'Sales Log'!$B$5:$B$1004,A17,'Sales Log'!$A$5:$A$1004,">="&E17,'Sales Log'!$A$5:$A$1004,"<="&F17,'Sales Log'!$R$5:$R$1004,IF(O17="EXAMPLE","EXAMPLE","<>EXAMPLE")))
I18: =IF(OR(C18="",H18=""),"",C18-H18) | J18: =IF(C18="","",IF(H18="","WAITING",IF(ABS(C18-H18)<0.005,"MATCHED","CHECK"))) | K18: =IF(OR(A18="",E18="",F18=""),"",SUMIFS('Sales Log'!$L$5:$L$1004,'Sales Log'!$B$5:$B$1004,A18,'Sales Log'!$A$5:$A$1004,">="&E18,'Sales Log'!$A$5:$A$1004,"<="&F18,'Sales Log'!$R$5:$R$1004,IF(O18="EXAMPLE","EXAMPLE","<>EXAMPLE")))
I19: =IF(OR(C19="",H19=""),"",C19-H19) | J19: =IF(C19="","",IF(H19="","WAITING",IF(ABS(C19-H19)<0.005,"MATCHED","CHECK"))) | K19: =IF(OR(A19="",E19="",F19=""),"",SUMIFS('Sales Log'!$L$5:$L$1004,'Sales Log'!$B$5:$B$1004,A19,'Sales Log'!$A$5:$A$1004,">="&E19,'Sales Log'!$A$5:$A$1004,"<="&F19,'Sales Log'!$R$5:$R$1004,IF(O19="EXAMPLE","EXAMPLE","<>EXAMPLE")))
... I504: =IF(OR(C504="",H504=""),"",C504-H504) | J504: =IF(C504="","",IF(H504="","WAITING",IF(ABS(C504-H504)<0.005,"MATCHED","CHECK"))) | K504: =IF(OR(A504="",E504="",F504=""),"",SUMIFS('Sales Log'!$L$5:$L$1004,'Sales Log'!$B$5:$B$1004,A504,'Sales Log'!$A$5:$A$1004,">="&E504,'Sales Log'!$A$5:$A$1004,"<="&F504,'Sales Log'!$R$5:$R$1004,IF(O504="EXAMPLE","EXAMPLE","<>EXAMPLE")))

Sheet Channel Summary
A1: Channel Summary
A2: Everything on this tab is a formula (SUMIFS by channel and month) - do not type in the grey/white grid. Change the tax year in B3 to reuse the workbook next year. EXAMPLE rows are excluded.
A3: Tax year | B3: 2026
A5: Gross sales (before fees; excludes shipping and sales tax)
A6: Channel | B6: =DATE($B$3,1,1) -> 46023 | C6: =DATE($B$3,2,1) -> 46054 | D6: =DATE($B$3,3,1) -> 46082 | E6: =DATE($B$3,4,1) -> 46113 | F6: =DATE($B$3,5,1) -> 46143 | G6: =DATE($B$3,6,1) -> 46174 | H6: =DATE($B$3,7,1) -> 46204 | I6: =DATE($B$3,8,1) -> 46235 | J6: =DATE($B$3,9,1) -> 46266 | K6: =DATE($B$3,10,1) -> 46296 | L6: =DATE($B$3,11,1) -> 46327 | M6: =DATE($B$3,12,1) -> 46357 | N6: Total
A7: ='Chart of Accounts'!$A$66 -> Amazon KDP | B7: =SUMIFS('Sales Log'!$G$5:$G$1004,'Sales Log'!$A$5:$A$1004,">="&B$6,'Sales Log'!$A$5:$A$1004,"<"&DATE(YEAR(B$6),MONTH(B$6)+1,1),'Sales Log'!$B$5:$B$1004,$A7,'Sales Log'!$R$5:$R$1004,"<>EXAMPLE") -> 0 | C7: =SUMIFS('Sales Log'!$G$5:$G$1004,'Sales Log'!$A$5:$A$1004,">="&C$6,'Sales Log'!$A$5:$A$1004,"<"&DATE(YEAR(C$6),MONTH(C$6)+1,1),'Sales Log'!$B$5:$B$1004,$A7,'Sales Log'!$R$5:$R$1004,"<>EXAMPLE") -> 0 | D7: =SUMIFS('Sales Log'!$G$5:$G$1004,'Sales Log'!$A$5:$A$1004,">="&D$6,'Sales Log'!$A$5:$A$1004,"<"&DATE(YEAR(D$6),MONTH(D$6)+1,1),'Sales Log'!$B$5:$B$1004,$A7,'Sales Log'!$R$5:$R$1004,"<>EXAMPLE") -> 0 | E7: =SUMIFS('Sales Log'!$G$5:$G$1004,'Sales Log'!$A$5:$A$1004,">="&E$6,'Sales Log'!$A$5:$A$1004,"<"&DATE(YEAR(E$6),MONTH(E$6)+1,1),'Sales Log'!$B$5:$B$1004,$A7,'Sales Log'!$R$5:$R$1004,"<>EXAMPLE") -> 0 | F7: =SUMIFS('Sales Log'!$G$5:$G$1004,'Sales Log'!$A$5:$A$1004,">="&F$6,'Sales Log'!$A$5:$A$1004,"<"&DATE(YEAR(F$6),MONTH(F$6)+1,1),'Sales Log'!$B$5:$B$1004,$A7,'Sales Log'!$R$5:$R$1004,"<>EXAMPLE") -> 0 | G7: =SUMIFS('Sales Log'!$G$5:$G$1004,'Sales Log'!$A$5:$A$1004,">="&G$6,'Sales Log'!$A$5:$A$1004,"<"&DATE(YEAR(G$6),MONTH(G$6)+1,1),'Sales Log'!$B$5:$B$1004,$A7,'Sales Log'!$R$5:$R$1004,"<>EXAMPLE") -> 0 | H7: =SUMIFS('Sales Log'!$G$5:$G$1004,'Sales Log'!$A$5:$A$1004,">="&H$6,'Sales Log'!$A$5:$A$1004,"<"&DATE(YEAR(H$6),MONTH(H$6)+1,1),'Sales Log'!$B$5:$B$1004,$A7,'Sales Log'!$R$5:$R$1004,"<>EXAMPLE") -> 0 | I7: =SUMIFS('Sales Log'!$G$5:$G$1004,'Sales Log'!$A$5:$A$1004,">="&I$6,'Sales Log'!$A$5:$A$1004,"<"&DATE(YEAR(I$6),MONTH(I$6)+1,1),'Sales Log'!$B$5:$B$1004,$A7,'Sales Log'!$R$5:$R$1004,"<>EXAMPLE") -> 0 | ... M7: =SUMIFS('Sales Log'!$G$5:$G$1004,'Sales Log'!$A$5:$A$1004,">="&M$6,'Sales Log'!$A$5:$A$1004,"<"&DATE(YEAR(M$6),MONTH(M$6)+1,1),'Sales Log'!$B$5:$B$1004,$A7,'Sales Log'!$R$5:$R$1004,"<>EXAMPLE") -> 0 | N7: =SUM(B7:M7) -> 0
A8: ='Chart of Accounts'!$A$67 -> IngramSpark | B8: =SUMIFS('Sales Log'!$G$5:$G$1004,'Sales Log'!$A$5:$A$1004,">="&B$6,'Sales Log'!$A$5:$A$1004,"<"&DATE(YEAR(B$6),MONTH(B$6)+1,1),'Sales Log'!$B$5:$B$1004,$A8,'Sales Log'!$R$5:$R$1004,"<>EXAMPLE") -> 0 | C8: =SUMIFS('Sales Log'!$G$5:$G$1004,'Sales Log'!$A$5:$A$1004,">="&C$6,'Sales Log'!$A$5:$A$1004,"<"&DATE(YEAR(C$6),MONTH(C$6)+1,1),'Sales Log'!$B$5:$B$1004,$A8,'Sales Log'!$R$5:$R$1004,"<>EXAMPLE") -> 0 | D8: =SUMIFS('Sales Log'!$G$5:$G$1004,'Sales Log'!$A$5:$A$1004,">="&D$6,'Sales Log'!$A$5:$A$1004,"<"&DATE(YEAR(D$6),MONTH(D$6)+1,1),'Sales Log'!$B$5:$B$1004,$A8,'Sales Log'!$R$5:$R$1004,"<>EXAMPLE") -> 0 | E8: =SUMIFS('Sales Log'!$G$5:$G$1004,'Sales Log'!$A$5:$A$1004,">="&E$6,'Sales Log'!$A$5:$A$1004,"<"&DATE(YEAR(E$6),MONTH(E$6)+1,1),'Sales Log'!$B$5:$B$1004,$A8,'Sales Log'!$R$5:$R$1004,"<>EXAMPLE") -> 0 | F8: =SUMIFS('Sales Log'!$G$5:$G$1004,'Sales Log'!$A$5:$A$1004,">="&F$6,'Sales Log'!$A$5:$A$1004,"<"&DATE(YEAR(F$6),MONTH(F$6)+1,1),'Sales Log'!$B$5:$B$1004,$A8,'Sales Log'!$R$5:$R$1004,"<>EXAMPLE") -> 0 | G8: =SUMIFS('Sales Log'!$G$5:$G$1004,'Sales Log'!$A$5:$A$1004,">="&G$6,'Sales Log'!$A$5:$A$1004,"<"&DATE(YEAR(G$6),MONTH(G$6)+1,1),'Sales Log'!$B$5:$B$1004,$A8,'Sales Log'!$R$5:$R$1004,"<>EXAMPLE") -> 0 | H8: =SUMIFS('Sales Log'!$G$5:$G$1004,'Sales Log'!$A$5:$A$1004,">="&H$6,'Sales Log'!$A$5:$A$1004,"<"&DATE(YEAR(H$6),MONTH(H$6)+1,1),'Sales Log'!$B$5:$B$1004,$A8,'Sales Log'!$R$5:$R$1004,"<>EXAMPLE") -> 0 | I8: =SUMIFS('Sales Log'!$G$5:$G$1004,'Sales Log'!$A$5:$A$1004,">="&I$6,'Sales Log'!$A$5:$A$1004,"<"&DATE(YEAR(I$6),MONTH(I$6)+1,1),'Sales Log'!$B$5:$B$1004,$A8,'Sales Log'!$R$5:$R$1004,"<>EXAMPLE") -> 0 | ... M8: =SUMIFS('Sales Log'!$G$5:$G$1004,'Sales Log'!$A$5:$A$1004,">="&M$6,'Sales Log'!$A$5:$A$1004,"<"&DATE(YEAR(M$6),MONTH(M$6)+1,1),'Sales Log'!$B$5:$B$1004,$A8,'Sales Log'!$R$5:$R$1004,"<>EXAMPLE") -> 0 | N8: =SUM(B8:M8) -> 0
A9: ='Chart of Accounts'!$A$68 -> Etsy | B9: =SUMIFS('Sales Log'!$G$5:$G$1004,'Sales Log'!$A$5:$A$1004,">="&B$6,'Sales Log'!$A$5:$A$1004,"<"&DATE(YEAR(B$6),MONTH(B$6)+1,1),'Sales Log'!$B$5:$B$1004,$A9,'Sales Log'!$R$5:$R$1004,"<>EXAMPLE") -> 0 | C9: =SUMIFS('Sales Log'!$G$5:$G$1004,'Sales Log'!$A$5:$A$1004,">="&C$6,'Sales Log'!$A$5:$A$1004,"<"&DATE(YEAR(C$6),MONTH(C$6)+1,1),'Sales Log'!$B$5:$B$1004,$A9,'Sales Log'!$R$5:$R$1004,"<>EXAMPLE") -> 0 | D9: =SUMIFS('Sales Log'!$G$5:$G$1004,'Sales Log'!$A$5:$A$1004,">="&D$6,'Sales Log'!$A$5:$A$1004,"<"&DATE(YEAR(D$6),MONTH(D$6)+1,1),'Sales Log'!$B$5:$B$1004,$A9,'Sales Log'!$R$5:$R$1004,"<>EXAMPLE") -> 0 | E9: =SUMIFS('Sales Log'!$G$5:$G$1004,'Sales Log'!$A$5:$A$1004,">="&E$6,'Sales Log'!$A$5:$A$1004,"<"&DATE(YEAR(E$6),MONTH(E$6)+1,1),'Sales Log'!$B$5:$B$1004,$A9,'Sales Log'!$R$5:$R$1004,"<>EXAMPLE") -> 0 | F9: =SUMIFS('Sales Log'!$G$5:$G$1004,'Sales Log'!$A$5:$A$1004,">="&F$6,'Sales Log'!$A$5:$A$1004,"<"&DATE(YEAR(F$6),MONTH(F$6)+1,1),'Sales Log'!$B$5:$B$1004,$A9,'Sales Log'!$R$5:$R$1004,"<>EXAMPLE") -> 0 | G9: =SUMIFS('Sales Log'!$G$5:$G$1004,'Sales Log'!$A$5:$A$1004,">="&G$6,'Sales Log'!$A$5:$A$1004,"<"&DATE(YEAR(G$6),MONTH(G$6)+1,1),'Sales Log'!$B$5:$B$1004,$A9,'Sales Log'!$R$5:$R$1004,"<>EXAMPLE") -> 0 | H9: =SUMIFS('Sales Log'!$G$5:$G$1004,'Sales Log'!$A$5:$A$1004,">="&H$6,'Sales Log'!$A$5:$A$1004,"<"&DATE(YEAR(H$6),MONTH(H$6)+1,1),'Sales Log'!$B$5:$B$1004,$A9,'Sales Log'!$R$5:$R$1004,"<>EXAMPLE") -> 0 | I9: =SUMIFS('Sales Log'!$G$5:$G$1004,'Sales Log'!$A$5:$A$1004,">="&I$6,'Sales Log'!$A$5:$A$1004,"<"&DATE(YEAR(I$6),MONTH(I$6)+1,1),'Sales Log'!$B$5:$B$1004,$A9,'Sales Log'!$R$5:$R$1004,"<>EXAMPLE") -> 0 | ... M9: =SUMIFS('Sales Log'!$G$5:$G$1004,'Sales Log'!$A$5:$A$1004,">="&M$6,'Sales Log'!$A$5:$A$1004,"<"&DATE(YEAR(M$6),MONTH(M$6)+1,1),'Sales Log'!$B$5:$B$1004,$A9,'Sales Log'!$R$5:$R$1004,"<>EXAMPLE") -> 0 | N9: =SUM(B9:M9) -> 0
A10: ='Chart of Accounts'!$A$69 -> Teachers Pay Teachers | B10: =SUMIFS('Sales Log'!$G$5:$G$1004,'Sales Log'!$A$5:$A$1004,">="&B$6,'Sales Log'!$A$5:$A$1004,"<"&DATE(YEAR(B$6),MONTH(B$6)+1,1),'Sales Log'!$B$5:$B$1004,$A10,'Sales Log'!$R$5:$R$1004,"<>EXAMPLE") -> 0 | C10: =SUMIFS('Sales Log'!$G$5:$G$1004,'Sales Log'!$A$5:$A$1004,">="&C$6,'Sales Log'!$A$5:$A$1004,"<"&DATE(YEAR(C$6),MONTH(C$6)+1,1),'Sales Log'!$B$5:$B$1004,$A10,'Sales Log'!$R$5:$R$1004,"<>EXAMPLE") -> 0 | D10: =SUMIFS('Sales Log'!$G$5:$G$1004,'Sales Log'!$A$5:$A$1004,">="&D$6,'Sales Log'!$A$5:$A$1004,"<"&DATE(YEAR(D$6),MONTH(D$6)+1,1),'Sales Log'!$B$5:$B$1004,$A10,'Sales Log'!$R$5:$R$1004,"<>EXAMPLE") -> 0 | E10: =SUMIFS('Sales Log'!$G$5:$G$1004,'Sales Log'!$A$5:$A$1004,">="&E$6,'Sales Log'!$A$5:$A$1004,"<"&DATE(YEAR(E$6),MONTH(E$6)+1,1),'Sales Log'!$B$5:$B$1004,$A10,'Sales Log'!$R$5:$R$1004,"<>EXAMPLE") -> 0 | F10: =SUMIFS('Sales Log'!$G$5:$G$1004,'Sales Log'!$A$5:$A$1004,">="&F$6,'Sales Log'!$A$5:$A$1004,"<"&DATE(YEAR(F$6),MONTH(F$6)+1,1),'Sales Log'!$B$5:$B$1004,$A10,'Sales Log'!$R$5:$R$1004,"<>EXAMPLE") -> 0 | G10: =SUMIFS('Sales Log'!$G$5:$G$1004,'Sales Log'!$A$5:$A$1004,">="&G$6,'Sales Log'!$A$5:$A$1004,"<"&DATE(YEAR(G$6),MONTH(G$6)+1,1),'Sales Log'!$B$5:$B$1004,$A10,'Sales Log'!$R$5:$R$1004,"<>EXAMPLE") -> 0 | H10: =SUMIFS('Sales Log'!$G$5:$G$1004,'Sales Log'!$A$5:$A$1004,">="&H$6,'Sales Log'!$A$5:$A$1004,"<"&DATE(YEAR(H$6),MONTH(H$6)+1,1),'Sales Log'!$B$5:$B$1004,$A10,'Sales Log'!$R$5:$R$1004,"<>EXAMPLE") -> 0 | I10: =SUMIFS('Sales Log'!$G$5:$G$1004,'Sales Log'!$A$5:$A$1004,">="&I$6,'Sales Log'!$A$5:$A$1004,"<"&DATE(YEAR(I$6),MONTH(I$6)+1,1),'Sales Log'!$B$5:$B$1004,$A10,'Sales Log'!$R$5:$R$1004,"<>EXAMPLE") -> 0 | ... M10: =SUMIFS('Sales Log'!$G$5:$G$1004,'Sales Log'!$A$5:$A$1004,">="&M$6,'Sales Log'!$A$5:$A$1004,"<"&DATE(YEAR(M$6),MONTH(M$6)+1,1),'Sales Log'!$B$5:$B$1004,$A10,'Sales Log'!$R$5:$R$1004,"<>EXAMPLE") -> 0 | N10: =SUM(B10:M10) -> 0
A11: ='Chart of Accounts'!$A$70 -> TikTok Shop | B11: =SUMIFS('Sales Log'!$G$5:$G$1004,'Sales Log'!$A$5:$A$1004,">="&B$6,'Sales Log'!$A$5:$A$1004,"<"&DATE(YEAR(B$6),MONTH(B$6)+1,1),'Sales Log'!$B$5:$B$1004,$A11,'Sales Log'!$R$5:$R$1004,"<>EXAMPLE") -> 0 | C11: =SUMIFS('Sales Log'!$G$5:$G$1004,'Sales Log'!$A$5:$A$1004,">="&C$6,'Sales Log'!$A$5:$A$1004,"<"&DATE(YEAR(C$6),MONTH(C$6)+1,1),'Sales Log'!$B$5:$B$1004,$A11,'Sales Log'!$R$5:$R$1004,"<>EXAMPLE") -> 0 | D11: =SUMIFS('Sales Log'!$G$5:$G$1004,'Sales Log'!$A$5:$A$1004,">="&D$6,'Sales Log'!$A$5:$A$1004,"<"&DATE(YEAR(D$6),MONTH(D$6)+1,1),'Sales Log'!$B$5:$B$1004,$A11,'Sales Log'!$R$5:$R$1004,"<>EXAMPLE") -> 0 | E11: =SUMIFS('Sales Log'!$G$5:$G$1004,'Sales Log'!$A$5:$A$1004,">="&E$6,'Sales Log'!$A$5:$A$1004,"<"&DATE(YEAR(E$6),MONTH(E$6)+1,1),'Sales Log'!$B$5:$B$1004,$A11,'Sales Log'!$R$5:$R$1004,"<>EXAMPLE") -> 0 | F11: =SUMIFS('Sales Log'!$G$5:$G$1004,'Sales Log'!$A$5:$A$1004,">="&F$6,'Sales Log'!$A$5:$A$1004,"<"&DATE(YEAR(F$6),MONTH(F$6)+1,1),'Sales Log'!$B$5:$B$1004,$A11,'Sales Log'!$R$5:$R$1004,"<>EXAMPLE") -> 0 | G11: =SUMIFS('Sales Log'!$G$5:$G$1004,'Sales Log'!$A$5:$A$1004,">="&G$6,'Sales Log'!$A$5:$A$1004,"<"&DATE(YEAR(G$6),MONTH(G$6)+1,1),'Sales Log'!$B$5:$B$1004,$A11,'Sales Log'!$R$5:$R$1004,"<>EXAMPLE") -> 0 | H11: =SUMIFS('Sales Log'!$G$5:$G$1004,'Sales Log'!$A$5:$A$1004,">="&H$6,'Sales Log'!$A$5:$A$1004,"<"&DATE(YEAR(H$6),MONTH(H$6)+1,1),'Sales Log'!$B$5:$B$1004,$A11,'Sales Log'!$R$5:$R$1004,"<>EXAMPLE") -> 0 | I11: =SUMIFS('Sales Log'!$G$5:$G$1004,'Sales Log'!$A$5:$A$1004,">="&I$6,'Sales Log'!$A$5:$A$1004,"<"&DATE(YEAR(I$6),MONTH(I$6)+1,1),'Sales Log'!$B$5:$B$1004,$A11,'Sales Log'!$R$5:$R$1004,"<>EXAMPLE") -> 0 | ... M11: =SUMIFS('Sales Log'!$G$5:$G$1004,'Sales Log'!$A$5:$A$1004,">="&M$6,'Sales Log'!$A$5:$A$1004,"<"&DATE(YEAR(M$6),MONTH(M$6)+1,1),'Sales Log'!$B$5:$B$1004,$A11,'Sales Log'!$R$5:$R$1004,"<>EXAMPLE") -> 0 | N11: =SUM(B11:M11) -> 0
A12: ='Chart of Accounts'!$A$71 -> Shopify (website store) | B12: =SUMIFS('Sales Log'!$G$5:$G$1004,'Sales Log'!$A$5:$A$1004,">="&B$6,'Sales Log'!$A$5:$A$1004,"<"&DATE(YEAR(B$6),MONTH(B$6)+1,1),'Sales Log'!$B$5:$B$1004,$A12,'Sales Log'!$R$5:$R$1004,"<>EXAMPLE") -> 0 | C12: =SUMIFS('Sales Log'!$G$5:$G$1004,'Sales Log'!$A$5:$A$1004,">="&C$6,'Sales Log'!$A$5:$A$1004,"<"&DATE(YEAR(C$6),MONTH(C$6)+1,1),'Sales Log'!$B$5:$B$1004,$A12,'Sales Log'!$R$5:$R$1004,"<>EXAMPLE") -> 0 | D12: =SUMIFS('Sales Log'!$G$5:$G$1004,'Sales Log'!$A$5:$A$1004,">="&D$6,'Sales Log'!$A$5:$A$1004,"<"&DATE(YEAR(D$6),MONTH(D$6)+1,1),'Sales Log'!$B$5:$B$1004,$A12,'Sales Log'!$R$5:$R$1004,"<>EXAMPLE") -> 0 | E12: =SUMIFS('Sales Log'!$G$5:$G$1004,'Sales Log'!$A$5:$A$1004,">="&E$6,'Sales Log'!$A$5:$A$1004,"<"&DATE(YEAR(E$6),MONTH(E$6)+1,1),'Sales Log'!$B$5:$B$1004,$A12,'Sales Log'!$R$5:$R$1004,"<>EXAMPLE") -> 0 | F12: =SUMIFS('Sales Log'!$G$5:$G$1004,'Sales Log'!$A$5:$A$1004,">="&F$6,'Sales Log'!$A$5:$A$1004,"<"&DATE(YEAR(F$6),MONTH(F$6)+1,1),'Sales Log'!$B$5:$B$1004,$A12,'Sales Log'!$R$5:$R$1004,"<>EXAMPLE") -> 0 | G12: =SUMIFS('Sales Log'!$G$5:$G$1004,'Sales Log'!$A$5:$A$1004,">="&G$6,'Sales Log'!$A$5:$A$1004,"<"&DATE(YEAR(G$6),MONTH(G$6)+1,1),'Sales Log'!$B$5:$B$1004,$A12,'Sales Log'!$R$5:$R$1004,"<>EXAMPLE") -> 0 | H12: =SUMIFS('Sales Log'!$G$5:$G$1004,'Sales Log'!$A$5:$A$1004,">="&H$6,'Sales Log'!$A$5:$A$1004,"<"&DATE(YEAR(H$6),MONTH(H$6)+1,1),'Sales Log'!$B$5:$B$1004,$A12,'Sales Log'!$R$5:$R$1004,"<>EXAMPLE") -> 0 | I12: =SUMIFS('Sales Log'!$G$5:$G$1004,'Sales Log'!$A$5:$A$1004,">="&I$6,'Sales Log'!$A$5:$A$1004,"<"&DATE(YEAR(I$6),MONTH(I$6)+1,1),'Sales Log'!$B$5:$B$1004,$A12,'Sales Log'!$R$5:$R$1004,"<>EXAMPLE") -> 0 | ... M12: =SUMIFS('Sales Log'!$G$5:$G$1004,'Sales Log'!$A$5:$A$1004,">="&M$6,'Sales Log'!$A$5:$A$1004,"<"&DATE(YEAR(M$6),MONTH(M$6)+1,1),'Sales Log'!$B$5:$B$1004,$A12,'Sales Log'!$R$5:$R$1004,"<>EXAMPLE") -> 0 | N12: =SUM(B12:M12) -> 0
A13: ='Chart of Accounts'!$A$72 -> Stripe (website & invoices) | B13: =SUMIFS('Sales Log'!$G$5:$G$1004,'Sales Log'!$A$5:$A$1004,">="&B$6,'Sales Log'!$A$5:$A$1004,"<"&DATE(YEAR(B$6),MONTH(B$6)+1,1),'Sales Log'!$B$5:$B$1004,$A13,'Sales Log'!$R$5:$R$1004,"<>EXAMPLE") -> 0 | C13: =SUMIFS('Sales Log'!$G$5:$G$1004,'Sales Log'!$A$5:$A$1004,">="&C$6,'Sales Log'!$A$5:$A$1004,"<"&DATE(YEAR(C$6),MONTH(C$6)+1,1),'Sales Log'!$B$5:$B$1004,$A13,'Sales Log'!$R$5:$R$1004,"<>EXAMPLE") -> 0 | D13: =SUMIFS('Sales Log'!$G$5:$G$1004,'Sales Log'!$A$5:$A$1004,">="&D$6,'Sales Log'!$A$5:$A$1004,"<"&DATE(YEAR(D$6),MONTH(D$6)+1,1),'Sales Log'!$B$5:$B$1004,$A13,'Sales Log'!$R$5:$R$1004,"<>EXAMPLE") -> 0 | E13: =SUMIFS('Sales Log'!$G$5:$G$1004,'Sales Log'!$A$5:$A$1004,">="&E$6,'Sales Log'!$A$5:$A$1004,"<"&DATE(YEAR(E$6),MONTH(E$6)+1,1),'Sales Log'!$B$5:$B$1004,$A13,'Sales Log'!$R$5:$R$1004,"<>EXAMPLE") -> 0 | F13: =SUMIFS('Sales Log'!$G$5:$G$1004,'Sales Log'!$A$5:$A$1004,">="&F$6,'Sales Log'!$A$5:$A$1004,"<"&DATE(YEAR(F$6),MONTH(F$6)+1,1),'Sales Log'!$B$5:$B$1004,$A13,'Sales Log'!$R$5:$R$1004,"<>EXAMPLE") -> 0 | G13: =SUMIFS('Sales Log'!$G$5:$G$1004,'Sales Log'!$A$5:$A$1004,">="&G$6,'Sales Log'!$A$5:$A$1004,"<"&DATE(YEAR(G$6),MONTH(G$6)+1,1),'Sales Log'!$B$5:$B$1004,$A13,'Sales Log'!$R$5:$R$1004,"<>EXAMPLE") -> 0 | H13: =SUMIFS('Sales Log'!$G$5:$G$1004,'Sales Log'!$A$5:$A$1004,">="&H$6,'Sales Log'!$A$5:$A$1004,"<"&DATE(YEAR(H$6),MONTH(H$6)+1,1),'Sales Log'!$B$5:$B$1004,$A13,'Sales Log'!$R$5:$R$1004,"<>EXAMPLE") -> 0 | I13: =SUMIFS('Sales Log'!$G$5:$G$1004,'Sales Log'!$A$5:$A$1004,">="&I$6,'Sales Log'!$A$5:$A$1004,"<"&DATE(YEAR(I$6),MONTH(I$6)+1,1),'Sales Log'!$B$5:$B$1004,$A13,'Sales Log'!$R$5:$R$1004,"<>EXAMPLE") -> 0 | ... M13: =SUMIFS('Sales Log'!$G$5:$G$1004,'Sales Log'!$A$5:$A$1004,">="&M$6,'Sales Log'!$A$5:$A$1004,"<"&DATE(YEAR(M$6),MONTH(M$6)+1,1),'Sales Log'!$B$5:$B$1004,$A13,'Sales Log'!$R$5:$R$1004,"<>EXAMPLE") -> 0 | N13: =SUM(B13:M13) -> 0
A14: ='Chart of Accounts'!$A$73 -> PayPal Business | B14: =SUMIFS('Sales Log'!$G$5:$G$1004,'Sales Log'!$A$5:$A$1004,">="&B$6,'Sales Log'!$A$5:$A$1004,"<"&DATE(YEAR(B$6),MONTH(B$6)+1,1),'Sales Log'!$B$5:$B$1004,$A14,'Sales Log'!$R$5:$R$1004,"<>EXAMPLE") -> 0 | C14: =SUMIFS('Sales Log'!$G$5:$G$1004,'Sales Log'!$A$5:$A$1004,">="&C$6,'Sales Log'!$A$5:$A$1004,"<"&DATE(YEAR(C$6),MONTH(C$6)+1,1),'Sales Log'!$B$5:$B$1004,$A14,'Sales Log'!$R$5:$R$1004,"<>EXAMPLE") -> 0 | D14: =SUMIFS('Sales Log'!$G$5:$G$1004,'Sales Log'!$A$5:$A$1004,">="&D$6,'Sales Log'!$A$5:$A$1004,"<"&DATE(YEAR(D$6),MONTH(D$6)+1,1),'Sales Log'!$B$5:$B$1004,$A14,'Sales Log'!$R$5:$R$1004,"<>EXAMPLE") -> 0 | E14: =SUMIFS('Sales Log'!$G$5:$G$1004,'Sales Log'!$A$5:$A$1004,">="&E$6,'Sales Log'!$A$5:$A$1004,"<"&DATE(YEAR(E$6),MONTH(E$6)+1,1),'Sales Log'!$B$5:$B$1004,$A14,'Sales Log'!$R$5:$R$1004,"<>EXAMPLE") -> 0 | F14: =SUMIFS('Sales Log'!$G$5:$G$1004,'Sales Log'!$A$5:$A$1004,">="&F$6,'Sales Log'!$A$5:$A$1004,"<"&DATE(YEAR(F$6),MONTH(F$6)+1,1),'Sales Log'!$B$5:$B$1004,$A14,'Sales Log'!$R$5:$R$1004,"<>EXAMPLE") -> 0 | G14: =SUMIFS('Sales Log'!$G$5:$G$1004,'Sales Log'!$A$5:$A$1004,">="&G$6,'Sales Log'!$A$5:$A$1004,"<"&DATE(YEAR(G$6),MONTH(G$6)+1,1),'Sales Log'!$B$5:$B$1004,$A14,'Sales Log'!$R$5:$R$1004,"<>EXAMPLE") -> 0 | H14: =SUMIFS('Sales Log'!$G$5:$G$1004,'Sales Log'!$A$5:$A$1004,">="&H$6,'Sales Log'!$A$5:$A$1004,"<"&DATE(YEAR(H$6),MONTH(H$6)+1,1),'Sales Log'!$B$5:$B$1004,$A14,'Sales Log'!$R$5:$R$1004,"<>EXAMPLE") -> 0 | I14: =SUMIFS('Sales Log'!$G$5:$G$1004,'Sales Log'!$A$5:$A$1004,">="&I$6,'Sales Log'!$A$5:$A$1004,"<"&DATE(YEAR(I$6),MONTH(I$6)+1,1),'Sales Log'!$B$5:$B$1004,$A14,'Sales Log'!$R$5:$R$1004,"<>EXAMPLE") -> 0 | ... M14: =SUMIFS('Sales Log'!$G$5:$G$1004,'Sales Log'!$A$5:$A$1004,">="&M$6,'Sales Log'!$A$5:$A$1004,"<"&DATE(YEAR(M$6),MONTH(M$6)+1,1),'Sales Log'!$B$5:$B$1004,$A14,'Sales Log'!$R$5:$R$1004,"<>EXAMPLE") -> 0 | N14: =SUM(B14:M14) -> 0
A15: ='Chart of Accounts'!$A$74 -> Meta shop (FB/IG) | B15: =SUMIFS('Sales Log'!$G$5:$G$1004,'Sales Log'!$A$5:$A$1004,">="&B$6,'Sales Log'!$A$5:$A$1004,"<"&DATE(YEAR(B$6),MONTH(B$6)+1,1),'Sales Log'!$B$5:$B$1004,$A15,'Sales Log'!$R$5:$R$1004,"<>EXAMPLE") -> 0 | C15: =SUMIFS('Sales Log'!$G$5:$G$1004,'Sales Log'!$A$5:$A$1004,">="&C$6,'Sales Log'!$A$5:$A$1004,"<"&DATE(YEAR(C$6),MONTH(C$6)+1,1),'Sales Log'!$B$5:$B$1004,$A15,'Sales Log'!$R$5:$R$1004,"<>EXAMPLE") -> 0 | D15: =SUMIFS('Sales Log'!$G$5:$G$1004,'Sales Log'!$A$5:$A$1004,">="&D$6,'Sales Log'!$A$5:$A$1004,"<"&DATE(YEAR(D$6),MONTH(D$6)+1,1),'Sales Log'!$B$5:$B$1004,$A15,'Sales Log'!$R$5:$R$1004,"<>EXAMPLE") -> 0 | E15: =SUMIFS('Sales Log'!$G$5:$G$1004,'Sales Log'!$A$5:$A$1004,">="&E$6,'Sales Log'!$A$5:$A$1004,"<"&DATE(YEAR(E$6),MONTH(E$6)+1,1),'Sales Log'!$B$5:$B$1004,$A15,'Sales Log'!$R$5:$R$1004,"<>EXAMPLE") -> 0 | F15: =SUMIFS('Sales Log'!$G$5:$G$1004,'Sales Log'!$A$5:$A$1004,">="&F$6,'Sales Log'!$A$5:$A$1004,"<"&DATE(YEAR(F$6),MONTH(F$6)+1,1),'Sales Log'!$B$5:$B$1004,$A15,'Sales Log'!$R$5:$R$1004,"<>EXAMPLE") -> 0 | G15: =SUMIFS('Sales Log'!$G$5:$G$1004,'Sales Log'!$A$5:$A$1004,">="&G$6,'Sales Log'!$A$5:$A$1004,"<"&DATE(YEAR(G$6),MONTH(G$6)+1,1),'Sales Log'!$B$5:$B$1004,$A15,'Sales Log'!$R$5:$R$1004,"<>EXAMPLE") -> 0 | H15: =SUMIFS('Sales Log'!$G$5:$G$1004,'Sales Log'!$A$5:$A$1004,">="&H$6,'Sales Log'!$A$5:$A$1004,"<"&DATE(YEAR(H$6),MONTH(H$6)+1,1),'Sales Log'!$B$5:$B$1004,$A15,'Sales Log'!$R$5:$R$1004,"<>EXAMPLE") -> 0 | I15: =SUMIFS('Sales Log'!$G$5:$G$1004,'Sales Log'!$A$5:$A$1004,">="&I$6,'Sales Log'!$A$5:$A$1004,"<"&DATE(YEAR(I$6),MONTH(I$6)+1,1),'Sales Log'!$B$5:$B$1004,$A15,'Sales Log'!$R$5:$R$1004,"<>EXAMPLE") -> 0 | ... M15: =SUMIFS('Sales Log'!$G$5:$G$1004,'Sales Log'!$A$5:$A$1004,">="&M$6,'Sales Log'!$A$5:$A$1004,"<"&DATE(YEAR(M$6),MONTH(M$6)+1,1),'Sales Log'!$B$5:$B$1004,$A15,'Sales Log'!$R$5:$R$1004,"<>EXAMPLE") -> 0 | N15: =SUM(B15:M15) -> 0
A16: ='Chart of Accounts'!$A$75 -> Faire (wholesale) | B16: =SUMIFS('Sales Log'!$G$5:$G$1004,'Sales Log'!$A$5:$A$1004,">="&B$6,'Sales Log'!$A$5:$A$1004,"<"&DATE(YEAR(B$6),MONTH(B$6)+1,1),'Sales Log'!$B$5:$B$1004,$A16,'Sales Log'!$R$5:$R$1004,"<>EXAMPLE") -> 0 | C16: =SUMIFS('Sales Log'!$G$5:$G$1004,'Sales Log'!$A$5:$A$1004,">="&C$6,'Sales Log'!$A$5:$A$1004,"<"&DATE(YEAR(C$6),MONTH(C$6)+1,1),'Sales Log'!$B$5:$B$1004,$A16,'Sales Log'!$R$5:$R$1004,"<>EXAMPLE") -> 0 | D16: =SUMIFS('Sales Log'!$G$5:$G$1004,'Sales Log'!$A$5:$A$1004,">="&D$6,'Sales Log'!$A$5:$A$1004,"<"&DATE(YEAR(D$6),MONTH(D$6)+1,1),'Sales Log'!$B$5:$B$1004,$A16,'Sales Log'!$R$5:$R$1004,"<>EXAMPLE") -> 0 | E16: =SUMIFS('Sales Log'!$G$5:$G$1004,'Sales Log'!$A$5:$A$1004,">="&E$6,'Sales Log'!$A$5:$A$1004,"<"&DATE(YEAR(E$6),MONTH(E$6)+1,1),'Sales Log'!$B$5:$B$1004,$A16,'Sales Log'!$R$5:$R$1004,"<>EXAMPLE") -> 0 | F16: =SUMIFS('Sales Log'!$G$5:$G$1004,'Sales Log'!$A$5:$A$1004,">="&F$6,'Sales Log'!$A$5:$A$1004,"<"&DATE(YEAR(F$6),MONTH(F$6)+1,1),'Sales Log'!$B$5:$B$1004,$A16,'Sales Log'!$R$5:$R$1004,"<>EXAMPLE") -> 0 | G16: =SUMIFS('Sales Log'!$G$5:$G$1004,'Sales Log'!$A$5:$A$1004,">="&G$6,'Sales Log'!$A$5:$A$1004,"<"&DATE(YEAR(G$6),MONTH(G$6)+1,1),'Sales Log'!$B$5:$B$1004,$A16,'Sales Log'!$R$5:$R$1004,"<>EXAMPLE") -> 0 | H16: =SUMIFS('Sales Log'!$G$5:$G$1004,'Sales Log'!$A$5:$A$1004,">="&H$6,'Sales Log'!$A$5:$A$1004,"<"&DATE(YEAR(H$6),MONTH(H$6)+1,1),'Sales Log'!$B$5:$B$1004,$A16,'Sales Log'!$R$5:$R$1004,"<>EXAMPLE") -> 0 | I16: =SUMIFS('Sales Log'!$G$5:$G$1004,'Sales Log'!$A$5:$A$1004,">="&I$6,'Sales Log'!$A$5:$A$1004,"<"&DATE(YEAR(I$6),MONTH(I$6)+1,1),'Sales Log'!$B$5:$B$1004,$A16,'Sales Log'!$R$5:$R$1004,"<>EXAMPLE") -> 0 | ... M16: =SUMIFS('Sales Log'!$G$5:$G$1004,'Sales Log'!$A$5:$A$1004,">="&M$6,'Sales Log'!$A$5:$A$1004,"<"&DATE(YEAR(M$6),MONTH(M$6)+1,1),'Sales Log'!$B$5:$B$1004,$A16,'Sales Log'!$R$5:$R$1004,"<>EXAMPLE") -> 0 | N16: =SUM(B16:M16) -> 0
A17: ='Chart of Accounts'!$A$76 -> Merchant of record | B17: =SUMIFS('Sales Log'!$G$5:$G$1004,'Sales Log'!$A$5:$A$1004,">="&B$6,'Sales Log'!$A$5:$A$1004,"<"&DATE(YEAR(B$6),MONTH(B$6)+1,1),'Sales Log'!$B$5:$B$1004,$A17,'Sales Log'!$R$5:$R$1004,"<>EXAMPLE") -> 0 | C17: =SUMIFS('Sales Log'!$G$5:$G$1004,'Sales Log'!$A$5:$A$1004,">="&C$6,'Sales Log'!$A$5:$A$1004,"<"&DATE(YEAR(C$6),MONTH(C$6)+1,1),'Sales Log'!$B$5:$B$1004,$A17,'Sales Log'!$R$5:$R$1004,"<>EXAMPLE") -> 0 | D17: =SUMIFS('Sales Log'!$G$5:$G$1004,'Sales Log'!$A$5:$A$1004,">="&D$6,'Sales Log'!$A$5:$A$1004,"<"&DATE(YEAR(D$6),MONTH(D$6)+1,1),'Sales Log'!$B$5:$B$1004,$A17,'Sales Log'!$R$5:$R$1004,"<>EXAMPLE") -> 0 | E17: =SUMIFS('Sales Log'!$G$5:$G$1004,'Sales Log'!$A$5:$A$1004,">="&E$6,'Sales Log'!$A$5:$A$1004,"<"&DATE(YEAR(E$6),MONTH(E$6)+1,1),'Sales Log'!$B$5:$B$1004,$A17,'Sales Log'!$R$5:$R$1004,"<>EXAMPLE") -> 0 | F17: =SUMIFS('Sales Log'!$G$5:$G$1004,'Sales Log'!$A$5:$A$1004,">="&F$6,'Sales Log'!$A$5:$A$1004,"<"&DATE(YEAR(F$6),MONTH(F$6)+1,1),'Sales Log'!$B$5:$B$1004,$A17,'Sales Log'!$R$5:$R$1004,"<>EXAMPLE") -> 0 | G17: =SUMIFS('Sales Log'!$G$5:$G$1004,'Sales Log'!$A$5:$A$1004,">="&G$6,'Sales Log'!$A$5:$A$1004,"<"&DATE(YEAR(G$6),MONTH(G$6)+1,1),'Sales Log'!$B$5:$B$1004,$A17,'Sales Log'!$R$5:$R$1004,"<>EXAMPLE") -> 0 | H17: =SUMIFS('Sales Log'!$G$5:$G$1004,'Sales Log'!$A$5:$A$1004,">="&H$6,'Sales Log'!$A$5:$A$1004,"<"&DATE(YEAR(H$6),MONTH(H$6)+1,1),'Sales Log'!$B$5:$B$1004,$A17,'Sales Log'!$R$5:$R$1004,"<>EXAMPLE") -> 0 | I17: =SUMIFS('Sales Log'!$G$5:$G$1004,'Sales Log'!$A$5:$A$1004,">="&I$6,'Sales Log'!$A$5:$A$1004,"<"&DATE(YEAR(I$6),MONTH(I$6)+1,1),'Sales Log'!$B$5:$B$1004,$A17,'Sales Log'!$R$5:$R$1004,"<>EXAMPLE") -> 0 | ... M17: =SUMIFS('Sales Log'!$G$5:$G$1004,'Sales Log'!$A$5:$A$1004,">="&M$6,'Sales Log'!$A$5:$A$1004,"<"&DATE(YEAR(M$6),MONTH(M$6)+1,1),'Sales Log'!$B$5:$B$1004,$A17,'Sales Log'!$R$5:$R$1004,"<>EXAMPLE") -> 0 | N17: =SUM(B17:M17) -> 0
A18: ='Chart of Accounts'!$A$77 -> Amazon Associates | B18: =SUMIFS('Sales Log'!$G$5:$G$1004,'Sales Log'!$A$5:$A$1004,">="&B$6,'Sales Log'!$A$5:$A$1004,"<"&DATE(YEAR(B$6),MONTH(B$6)+1,1),'Sales Log'!$B$5:$B$1004,$A18,'Sales Log'!$R$5:$R$1004,"<>EXAMPLE") -> 0 | C18: =SUMIFS('Sales Log'!$G$5:$G$1004,'Sales Log'!$A$5:$A$1004,">="&C$6,'Sales Log'!$A$5:$A$1004,"<"&DATE(YEAR(C$6),MONTH(C$6)+1,1),'Sales Log'!$B$5:$B$1004,$A18,'Sales Log'!$R$5:$R$1004,"<>EXAMPLE") -> 0 | D18: =SUMIFS('Sales Log'!$G$5:$G$1004,'Sales Log'!$A$5:$A$1004,">="&D$6,'Sales Log'!$A$5:$A$1004,"<"&DATE(YEAR(D$6),MONTH(D$6)+1,1),'Sales Log'!$B$5:$B$1004,$A18,'Sales Log'!$R$5:$R$1004,"<>EXAMPLE") -> 0 | E18: =SUMIFS('Sales Log'!$G$5:$G$1004,'Sales Log'!$A$5:$A$1004,">="&E$6,'Sales Log'!$A$5:$A$1004,"<"&DATE(YEAR(E$6),MONTH(E$6)+1,1),'Sales Log'!$B$5:$B$1004,$A18,'Sales Log'!$R$5:$R$1004,"<>EXAMPLE") -> 0 | F18: =SUMIFS('Sales Log'!$G$5:$G$1004,'Sales Log'!$A$5:$A$1004,">="&F$6,'Sales Log'!$A$5:$A$1004,"<"&DATE(YEAR(F$6),MONTH(F$6)+1,1),'Sales Log'!$B$5:$B$1004,$A18,'Sales Log'!$R$5:$R$1004,"<>EXAMPLE") -> 0 | G18: =SUMIFS('Sales Log'!$G$5:$G$1004,'Sales Log'!$A$5:$A$1004,">="&G$6,'Sales Log'!$A$5:$A$1004,"<"&DATE(YEAR(G$6),MONTH(G$6)+1,1),'Sales Log'!$B$5:$B$1004,$A18,'Sales Log'!$R$5:$R$1004,"<>EXAMPLE") -> 0 | H18: =SUMIFS('Sales Log'!$G$5:$G$1004,'Sales Log'!$A$5:$A$1004,">="&H$6,'Sales Log'!$A$5:$A$1004,"<"&DATE(YEAR(H$6),MONTH(H$6)+1,1),'Sales Log'!$B$5:$B$1004,$A18,'Sales Log'!$R$5:$R$1004,"<>EXAMPLE") -> 0 | I18: =SUMIFS('Sales Log'!$G$5:$G$1004,'Sales Log'!$A$5:$A$1004,">="&I$6,'Sales Log'!$A$5:$A$1004,"<"&DATE(YEAR(I$6),MONTH(I$6)+1,1),'Sales Log'!$B$5:$B$1004,$A18,'Sales Log'!$R$5:$R$1004,"<>EXAMPLE") -> 0 | ... M18: =SUMIFS('Sales Log'!$G$5:$G$1004,'Sales Log'!$A$5:$A$1004,">="&M$6,'Sales Log'!$A$5:$A$1004,"<"&DATE(YEAR(M$6),MONTH(M$6)+1,1),'Sales Log'!$B$5:$B$1004,$A18,'Sales Log'!$R$5:$R$1004,"<>EXAMPLE") -> 0 | N18: =SUM(B18:M18) -> 0
A19: ='Chart of Accounts'!$A$78 -> Bookshop.org | B19: =SUMIFS('Sales Log'!$G$5:$G$1004,'Sales Log'!$A$5:$A$1004,">="&B$6,'Sales Log'!$A$5:$A$1004,"<"&DATE(YEAR(B$6),MONTH(B$6)+1,1),'Sales Log'!$B$5:$B$1004,$A19,'Sales Log'!$R$5:$R$1004,"<>EXAMPLE") -> 0 | C19: =SUMIFS('Sales Log'!$G$5:$G$1004,'Sales Log'!$A$5:$A$1004,">="&C$6,'Sales Log'!$A$5:$A$1004,"<"&DATE(YEAR(C$6),MONTH(C$6)+1,1),'Sales Log'!$B$5:$B$1004,$A19,'Sales Log'!$R$5:$R$1004,"<>EXAMPLE") -> 0 | D19: =SUMIFS('Sales Log'!$G$5:$G$1004,'Sales Log'!$A$5:$A$1004,">="&D$6,'Sales Log'!$A$5:$A$1004,"<"&DATE(YEAR(D$6),MONTH(D$6)+1,1),'Sales Log'!$B$5:$B$1004,$A19,'Sales Log'!$R$5:$R$1004,"<>EXAMPLE") -> 0 | E19: =SUMIFS('Sales Log'!$G$5:$G$1004,'Sales Log'!$A$5:$A$1004,">="&E$6,'Sales Log'!$A$5:$A$1004,"<"&DATE(YEAR(E$6),MONTH(E$6)+1,1),'Sales Log'!$B$5:$B$1004,$A19,'Sales Log'!$R$5:$R$1004,"<>EXAMPLE") -> 0 | F19: =SUMIFS('Sales Log'!$G$5:$G$1004,'Sales Log'!$A$5:$A$1004,">="&F$6,'Sales Log'!$A$5:$A$1004,"<"&DATE(YEAR(F$6),MONTH(F$6)+1,1),'Sales Log'!$B$5:$B$1004,$A19,'Sales Log'!$R$5:$R$1004,"<>EXAMPLE") -> 0 | G19: =SUMIFS('Sales Log'!$G$5:$G$1004,'Sales Log'!$A$5:$A$1004,">="&G$6,'Sales Log'!$A$5:$A$1004,"<"&DATE(YEAR(G$6),MONTH(G$6)+1,1),'Sales Log'!$B$5:$B$1004,$A19,'Sales Log'!$R$5:$R$1004,"<>EXAMPLE") -> 0 | H19: =SUMIFS('Sales Log'!$G$5:$G$1004,'Sales Log'!$A$5:$A$1004,">="&H$6,'Sales Log'!$A$5:$A$1004,"<"&DATE(YEAR(H$6),MONTH(H$6)+1,1),'Sales Log'!$B$5:$B$1004,$A19,'Sales Log'!$R$5:$R$1004,"<>EXAMPLE") -> 0 | I19: =SUMIFS('Sales Log'!$G$5:$G$1004,'Sales Log'!$A$5:$A$1004,">="&I$6,'Sales Log'!$A$5:$A$1004,"<"&DATE(YEAR(I$6),MONTH(I$6)+1,1),'Sales Log'!$B$5:$B$1004,$A19,'Sales Log'!$R$5:$R$1004,"<>EXAMPLE") -> 0 | ... M19: =SUMIFS('Sales Log'!$G$5:$G$1004,'Sales Log'!$A$5:$A$1004,">="&M$6,'Sales Log'!$A$5:$A$1004,"<"&DATE(YEAR(M$6),MONTH(M$6)+1,1),'Sales Log'!$B$5:$B$1004,$A19,'Sales Log'!$R$5:$R$1004,"<>EXAMPLE") -> 0 | N19: =SUM(B19:M19) -> 0
A20: ='Chart of Accounts'!$A$79 -> Direct (check / ACH / cash) | B20: =SUMIFS('Sales Log'!$G$5:$G$1004,'Sales Log'!$A$5:$A$1004,">="&B$6,'Sales Log'!$A$5:$A$1004,"<"&DATE(YEAR(B$6),MONTH(B$6)+1,1),'Sales Log'!$B$5:$B$1004,$A20,'Sales Log'!$R$5:$R$1004,"<>EXAMPLE") -> 0 | C20: =SUMIFS('Sales Log'!$G$5:$G$1004,'Sales Log'!$A$5:$A$1004,">="&C$6,'Sales Log'!$A$5:$A$1004,"<"&DATE(YEAR(C$6),MONTH(C$6)+1,1),'Sales Log'!$B$5:$B$1004,$A20,'Sales Log'!$R$5:$R$1004,"<>EXAMPLE") -> 0 | D20: =SUMIFS('Sales Log'!$G$5:$G$1004,'Sales Log'!$A$5:$A$1004,">="&D$6,'Sales Log'!$A$5:$A$1004,"<"&DATE(YEAR(D$6),MONTH(D$6)+1,1),'Sales Log'!$B$5:$B$1004,$A20,'Sales Log'!$R$5:$R$1004,"<>EXAMPLE") -> 0 | E20: =SUMIFS('Sales Log'!$G$5:$G$1004,'Sales Log'!$A$5:$A$1004,">="&E$6,'Sales Log'!$A$5:$A$1004,"<"&DATE(YEAR(E$6),MONTH(E$6)+1,1),'Sales Log'!$B$5:$B$1004,$A20,'Sales Log'!$R$5:$R$1004,"<>EXAMPLE") -> 0 | F20: =SUMIFS('Sales Log'!$G$5:$G$1004,'Sales Log'!$A$5:$A$1004,">="&F$6,'Sales Log'!$A$5:$A$1004,"<"&DATE(YEAR(F$6),MONTH(F$6)+1,1),'Sales Log'!$B$5:$B$1004,$A20,'Sales Log'!$R$5:$R$1004,"<>EXAMPLE") -> 0 | G20: =SUMIFS('Sales Log'!$G$5:$G$1004,'Sales Log'!$A$5:$A$1004,">="&G$6,'Sales Log'!$A$5:$A$1004,"<"&DATE(YEAR(G$6),MONTH(G$6)+1,1),'Sales Log'!$B$5:$B$1004,$A20,'Sales Log'!$R$5:$R$1004,"<>EXAMPLE") -> 0 | H20: =SUMIFS('Sales Log'!$G$5:$G$1004,'Sales Log'!$A$5:$A$1004,">="&H$6,'Sales Log'!$A$5:$A$1004,"<"&DATE(YEAR(H$6),MONTH(H$6)+1,1),'Sales Log'!$B$5:$B$1004,$A20,'Sales Log'!$R$5:$R$1004,"<>EXAMPLE") -> 0 | I20: =SUMIFS('Sales Log'!$G$5:$G$1004,'Sales Log'!$A$5:$A$1004,">="&I$6,'Sales Log'!$A$5:$A$1004,"<"&DATE(YEAR(I$6),MONTH(I$6)+1,1),'Sales Log'!$B$5:$B$1004,$A20,'Sales Log'!$R$5:$R$1004,"<>EXAMPLE") -> 0 | ... M20: =SUMIFS('Sales Log'!$G$5:$G$1004,'Sales Log'!$A$5:$A$1004,">="&M$6,'Sales Log'!$A$5:$A$1004,"<"&DATE(YEAR(M$6),MONTH(M$6)+1,1),'Sales Log'!$B$5:$B$1004,$A20,'Sales Log'!$R$5:$R$1004,"<>EXAMPLE") -> 0 | N20: =SUM(B20:M20) -> 0
A21: Total | B21: =SUM(B7:B20) -> 0 | C21: =SUM(C7:C20) -> 0 | D21: =SUM(D7:D20) -> 0 | E21: =SUM(E7:E20) -> 0 | F21: =SUM(F7:F20) -> 0 | G21: =SUM(G7:G20) -> 0 | H21: =SUM(H7:H20) -> 0 | I21: =SUM(I7:I20) -> 0 | ... N21: =SUM(N7:N20) -> 0
A24: Platform fees deducted
A25: Channel | B25: =DATE($B$3,1,1) -> 46023 | C25: =DATE($B$3,2,1) -> 46054 | D25: =DATE($B$3,3,1) -> 46082 | E25: =DATE($B$3,4,1) -> 46113 | F25: =DATE($B$3,5,1) -> 46143 | G25: =DATE($B$3,6,1) -> 46174 | H25: =DATE($B$3,7,1) -> 46204 | I25: =DATE($B$3,8,1) -> 46235 | J25: =DATE($B$3,9,1) -> 46266 | K25: =DATE($B$3,10,1) -> 46296 | L25: =DATE($B$3,11,1) -> 46327 | M25: =DATE($B$3,12,1) -> 46357 | N25: Total
A26: ='Chart of Accounts'!$A$66 -> Amazon KDP | B26: =SUMIFS('Sales Log'!$H$5:$H$1004,'Sales Log'!$A$5:$A$1004,">="&B$25,'Sales Log'!$A$5:$A$1004,"<"&DATE(YEAR(B$25),MONTH(B$25)+1,1),'Sales Log'!$B$5:$B$1004,$A26,'Sales Log'!$R$5:$R$1004,"<>EXAMPLE") -> 0 | C26: =SUMIFS('Sales Log'!$H$5:$H$1004,'Sales Log'!$A$5:$A$1004,">="&C$25,'Sales Log'!$A$5:$A$1004,"<"&DATE(YEAR(C$25),MONTH(C$25)+1,1),'Sales Log'!$B$5:$B$1004,$A26,'Sales Log'!$R$5:$R$1004,"<>EXAMPLE") -> 0 | D26: =SUMIFS('Sales Log'!$H$5:$H$1004,'Sales Log'!$A$5:$A$1004,">="&D$25,'Sales Log'!$A$5:$A$1004,"<"&DATE(YEAR(D$25),MONTH(D$25)+1,1),'Sales Log'!$B$5:$B$1004,$A26,'Sales Log'!$R$5:$R$1004,"<>EXAMPLE") -> 0 | E26: =SUMIFS('Sales Log'!$H$5:$H$1004,'Sales Log'!$A$5:$A$1004,">="&E$25,'Sales Log'!$A$5:$A$1004,"<"&DATE(YEAR(E$25),MONTH(E$25)+1,1),'Sales Log'!$B$5:$B$1004,$A26,'Sales Log'!$R$5:$R$1004,"<>EXAMPLE") -> 0 | F26: =SUMIFS('Sales Log'!$H$5:$H$1004,'Sales Log'!$A$5:$A$1004,">="&F$25,'Sales Log'!$A$5:$A$1004,"<"&DATE(YEAR(F$25),MONTH(F$25)+1,1),'Sales Log'!$B$5:$B$1004,$A26,'Sales Log'!$R$5:$R$1004,"<>EXAMPLE") -> 0 | G26: =SUMIFS('Sales Log'!$H$5:$H$1004,'Sales Log'!$A$5:$A$1004,">="&G$25,'Sales Log'!$A$5:$A$1004,"<"&DATE(YEAR(G$25),MONTH(G$25)+1,1),'Sales Log'!$B$5:$B$1004,$A26,'Sales Log'!$R$5:$R$1004,"<>EXAMPLE") -> 0 | H26: =SUMIFS('Sales Log'!$H$5:$H$1004,'Sales Log'!$A$5:$A$1004,">="&H$25,'Sales Log'!$A$5:$A$1004,"<"&DATE(YEAR(H$25),MONTH(H$25)+1,1),'Sales Log'!$B$5:$B$1004,$A26,'Sales Log'!$R$5:$R$1004,"<>EXAMPLE") -> 0 | I26: =SUMIFS('Sales Log'!$H$5:$H$1004,'Sales Log'!$A$5:$A$1004,">="&I$25,'Sales Log'!$A$5:$A$1004,"<"&DATE(YEAR(I$25),MONTH(I$25)+1,1),'Sales Log'!$B$5:$B$1004,$A26,'Sales Log'!$R$5:$R$1004,"<>EXAMPLE") -> 0 | ... M26: =SUMIFS('Sales Log'!$H$5:$H$1004,'Sales Log'!$A$5:$A$1004,">="&M$25,'Sales Log'!$A$5:$A$1004,"<"&DATE(YEAR(M$25),MONTH(M$25)+1,1),'Sales Log'!$B$5:$B$1004,$A26,'Sales Log'!$R$5:$R$1004,"<>EXAMPLE") -> 0 | N26: =SUM(B26:M26) -> 0
A27: ='Chart of Accounts'!$A$67 -> IngramSpark | B27: =SUMIFS('Sales Log'!$H$5:$H$1004,'Sales Log'!$A$5:$A$1004,">="&B$25,'Sales Log'!$A$5:$A$1004,"<"&DATE(YEAR(B$25),MONTH(B$25)+1,1),'Sales Log'!$B$5:$B$1004,$A27,'Sales Log'!$R$5:$R$1004,"<>EXAMPLE") -> 0 | C27: =SUMIFS('Sales Log'!$H$5:$H$1004,'Sales Log'!$A$5:$A$1004,">="&C$25,'Sales Log'!$A$5:$A$1004,"<"&DATE(YEAR(C$25),MONTH(C$25)+1,1),'Sales Log'!$B$5:$B$1004,$A27,'Sales Log'!$R$5:$R$1004,"<>EXAMPLE") -> 0 | D27: =SUMIFS('Sales Log'!$H$5:$H$1004,'Sales Log'!$A$5:$A$1004,">="&D$25,'Sales Log'!$A$5:$A$1004,"<"&DATE(YEAR(D$25),MONTH(D$25)+1,1),'Sales Log'!$B$5:$B$1004,$A27,'Sales Log'!$R$5:$R$1004,"<>EXAMPLE") -> 0 | E27: =SUMIFS('Sales Log'!$H$5:$H$1004,'Sales Log'!$A$5:$A$1004,">="&E$25,'Sales Log'!$A$5:$A$1004,"<"&DATE(YEAR(E$25),MONTH(E$25)+1,1),'Sales Log'!$B$5:$B$1004,$A27,'Sales Log'!$R$5:$R$1004,"<>EXAMPLE") -> 0 | F27: =SUMIFS('Sales Log'!$H$5:$H$1004,'Sales Log'!$A$5:$A$1004,">="&F$25,'Sales Log'!$A$5:$A$1004,"<"&DATE(YEAR(F$25),MONTH(F$25)+1,1),'Sales Log'!$B$5:$B$1004,$A27,'Sales Log'!$R$5:$R$1004,"<>EXAMPLE") -> 0 | G27: =SUMIFS('Sales Log'!$H$5:$H$1004,'Sales Log'!$A$5:$A$1004,">="&G$25,'Sales Log'!$A$5:$A$1004,"<"&DATE(YEAR(G$25),MONTH(G$25)+1,1),'Sales Log'!$B$5:$B$1004,$A27,'Sales Log'!$R$5:$R$1004,"<>EXAMPLE") -> 0 | H27: =SUMIFS('Sales Log'!$H$5:$H$1004,'Sales Log'!$A$5:$A$1004,">="&H$25,'Sales Log'!$A$5:$A$1004,"<"&DATE(YEAR(H$25),MONTH(H$25)+1,1),'Sales Log'!$B$5:$B$1004,$A27,'Sales Log'!$R$5:$R$1004,"<>EXAMPLE") -> 0 | I27: =SUMIFS('Sales Log'!$H$5:$H$1004,'Sales Log'!$A$5:$A$1004,">="&I$25,'Sales Log'!$A$5:$A$1004,"<"&DATE(YEAR(I$25),MONTH(I$25)+1,1),'Sales Log'!$B$5:$B$1004,$A27,'Sales Log'!$R$5:$R$1004,"<>EXAMPLE") -> 0 | ... M27: =SUMIFS('Sales Log'!$H$5:$H$1004,'Sales Log'!$A$5:$A$1004,">="&M$25,'Sales Log'!$A$5:$A$1004,"<"&DATE(YEAR(M$25),MONTH(M$25)+1,1),'Sales Log'!$B$5:$B$1004,$A27,'Sales Log'!$R$5:$R$1004,"<>EXAMPLE") -> 0 | N27: =SUM(B27:M27) -> 0
A28: ='Chart of Accounts'!$A$68 -> Etsy | B28: =SUMIFS('Sales Log'!$H$5:$H$1004,'Sales Log'!$A$5:$A$1004,">="&B$25,'Sales Log'!$A$5:$A$1004,"<"&DATE(YEAR(B$25),MONTH(B$25)+1,1),'Sales Log'!$B$5:$B$1004,$A28,'Sales Log'!$R$5:$R$1004,"<>EXAMPLE") -> 0 | C28: =SUMIFS('Sales Log'!$H$5:$H$1004,'Sales Log'!$A$5:$A$1004,">="&C$25,'Sales Log'!$A$5:$A$1004,"<"&DATE(YEAR(C$25),MONTH(C$25)+1,1),'Sales Log'!$B$5:$B$1004,$A28,'Sales Log'!$R$5:$R$1004,"<>EXAMPLE") -> 0 | D28: =SUMIFS('Sales Log'!$H$5:$H$1004,'Sales Log'!$A$5:$A$1004,">="&D$25,'Sales Log'!$A$5:$A$1004,"<"&DATE(YEAR(D$25),MONTH(D$25)+1,1),'Sales Log'!$B$5:$B$1004,$A28,'Sales Log'!$R$5:$R$1004,"<>EXAMPLE") -> 0 | E28: =SUMIFS('Sales Log'!$H$5:$H$1004,'Sales Log'!$A$5:$A$1004,">="&E$25,'Sales Log'!$A$5:$A$1004,"<"&DATE(YEAR(E$25),MONTH(E$25)+1,1),'Sales Log'!$B$5:$B$1004,$A28,'Sales Log'!$R$5:$R$1004,"<>EXAMPLE") -> 0 | F28: =SUMIFS('Sales Log'!$H$5:$H$1004,'Sales Log'!$A$5:$A$1004,">="&F$25,'Sales Log'!$A$5:$A$1004,"<"&DATE(YEAR(F$25),MONTH(F$25)+1,1),'Sales Log'!$B$5:$B$1004,$A28,'Sales Log'!$R$5:$R$1004,"<>EXAMPLE") -> 0 | G28: =SUMIFS('Sales Log'!$H$5:$H$1004,'Sales Log'!$A$5:$A$1004,">="&G$25,'Sales Log'!$A$5:$A$1004,"<"&DATE(YEAR(G$25),MONTH(G$25)+1,1),'Sales Log'!$B$5:$B$1004,$A28,'Sales Log'!$R$5:$R$1004,"<>EXAMPLE") -> 0 | H28: =SUMIFS('Sales Log'!$H$5:$H$1004,'Sales Log'!$A$5:$A$1004,">="&H$25,'Sales Log'!$A$5:$A$1004,"<"&DATE(YEAR(H$25),MONTH(H$25)+1,1),'Sales Log'!$B$5:$B$1004,$A28,'Sales Log'!$R$5:$R$1004,"<>EXAMPLE") -> 0 | I28: =SUMIFS('Sales Log'!$H$5:$H$1004,'Sales Log'!$A$5:$A$1004,">="&I$25,'Sales Log'!$A$5:$A$1004,"<"&DATE(YEAR(I$25),MONTH(I$25)+1,1),'Sales Log'!$B$5:$B$1004,$A28,'Sales Log'!$R$5:$R$1004,"<>EXAMPLE") -> 0 | ... M28: =SUMIFS('Sales Log'!$H$5:$H$1004,'Sales Log'!$A$5:$A$1004,">="&M$25,'Sales Log'!$A$5:$A$1004,"<"&DATE(YEAR(M$25),MONTH(M$25)+1,1),'Sales Log'!$B$5:$B$1004,$A28,'Sales Log'!$R$5:$R$1004,"<>EXAMPLE") -> 0 | N28: =SUM(B28:M28) -> 0
A29: ='Chart of Accounts'!$A$69 -> Teachers Pay Teachers | B29: =SUMIFS('Sales Log'!$H$5:$H$1004,'Sales Log'!$A$5:$A$1004,">="&B$25,'Sales Log'!$A$5:$A$1004,"<"&DATE(YEAR(B$25),MONTH(B$25)+1,1),'Sales Log'!$B$5:$B$1004,$A29,'Sales Log'!$R$5:$R$1004,"<>EXAMPLE") -> 0 | C29: =SUMIFS('Sales Log'!$H$5:$H$1004,'Sales Log'!$A$5:$A$1004,">="&C$25,'Sales Log'!$A$5:$A$1004,"<"&DATE(YEAR(C$25),MONTH(C$25)+1,1),'Sales Log'!$B$5:$B$1004,$A29,'Sales Log'!$R$5:$R$1004,"<>EXAMPLE") -> 0 | D29: =SUMIFS('Sales Log'!$H$5:$H$1004,'Sales Log'!$A$5:$A$1004,">="&D$25,'Sales Log'!$A$5:$A$1004,"<"&DATE(YEAR(D$25),MONTH(D$25)+1,1),'Sales Log'!$B$5:$B$1004,$A29,'Sales Log'!$R$5:$R$1004,"<>EXAMPLE") -> 0 | E29: =SUMIFS('Sales Log'!$H$5:$H$1004,'Sales Log'!$A$5:$A$1004,">="&E$25,'Sales Log'!$A$5:$A$1004,"<"&DATE(YEAR(E$25),MONTH(E$25)+1,1),'Sales Log'!$B$5:$B$1004,$A29,'Sales Log'!$R$5:$R$1004,"<>EXAMPLE") -> 0 | F29: =SUMIFS('Sales Log'!$H$5:$H$1004,'Sales Log'!$A$5:$A$1004,">="&F$25,'Sales Log'!$A$5:$A$1004,"<"&DATE(YEAR(F$25),MONTH(F$25)+1,1),'Sales Log'!$B$5:$B$1004,$A29,'Sales Log'!$R$5:$R$1004,"<>EXAMPLE") -> 0 | G29: =SUMIFS('Sales Log'!$H$5:$H$1004,'Sales Log'!$A$5:$A$1004,">="&G$25,'Sales Log'!$A$5:$A$1004,"<"&DATE(YEAR(G$25),MONTH(G$25)+1,1),'Sales Log'!$B$5:$B$1004,$A29,'Sales Log'!$R$5:$R$1004,"<>EXAMPLE") -> 0 | H29: =SUMIFS('Sales Log'!$H$5:$H$1004,'Sales Log'!$A$5:$A$1004,">="&H$25,'Sales Log'!$A$5:$A$1004,"<"&DATE(YEAR(H$25),MONTH(H$25)+1,1),'Sales Log'!$B$5:$B$1004,$A29,'Sales Log'!$R$5:$R$1004,"<>EXAMPLE") -> 0 | I29: =SUMIFS('Sales Log'!$H$5:$H$1004,'Sales Log'!$A$5:$A$1004,">="&I$25,'Sales Log'!$A$5:$A$1004,"<"&DATE(YEAR(I$25),MONTH(I$25)+1,1),'Sales Log'!$B$5:$B$1004,$A29,'Sales Log'!$R$5:$R$1004,"<>EXAMPLE") -> 0 | ... M29: =SUMIFS('Sales Log'!$H$5:$H$1004,'Sales Log'!$A$5:$A$1004,">="&M$25,'Sales Log'!$A$5:$A$1004,"<"&DATE(YEAR(M$25),MONTH(M$25)+1,1),'Sales Log'!$B$5:$B$1004,$A29,'Sales Log'!$R$5:$R$1004,"<>EXAMPLE") -> 0 | N29: =SUM(B29:M29) -> 0
A30: ='Chart of Accounts'!$A$70 -> TikTok Shop | B30: =SUMIFS('Sales Log'!$H$5:$H$1004,'Sales Log'!$A$5:$A$1004,">="&B$25,'Sales Log'!$A$5:$A$1004,"<"&DATE(YEAR(B$25),MONTH(B$25)+1,1),'Sales Log'!$B$5:$B$1004,$A30,'Sales Log'!$R$5:$R$1004,"<>EXAMPLE") -> 0 | C30: =SUMIFS('Sales Log'!$H$5:$H$1004,'Sales Log'!$A$5:$A$1004,">="&C$25,'Sales Log'!$A$5:$A$1004,"<"&DATE(YEAR(C$25),MONTH(C$25)+1,1),'Sales Log'!$B$5:$B$1004,$A30,'Sales Log'!$R$5:$R$1004,"<>EXAMPLE") -> 0 | D30: =SUMIFS('Sales Log'!$H$5:$H$1004,'Sales Log'!$A$5:$A$1004,">="&D$25,'Sales Log'!$A$5:$A$1004,"<"&DATE(YEAR(D$25),MONTH(D$25)+1,1),'Sales Log'!$B$5:$B$1004,$A30,'Sales Log'!$R$5:$R$1004,"<>EXAMPLE") -> 0 | E30: =SUMIFS('Sales Log'!$H$5:$H$1004,'Sales Log'!$A$5:$A$1004,">="&E$25,'Sales Log'!$A$5:$A$1004,"<"&DATE(YEAR(E$25),MONTH(E$25)+1,1),'Sales Log'!$B$5:$B$1004,$A30,'Sales Log'!$R$5:$R$1004,"<>EXAMPLE") -> 0 | F30: =SUMIFS('Sales Log'!$H$5:$H$1004,'Sales Log'!$A$5:$A$1004,">="&F$25,'Sales Log'!$A$5:$A$1004,"<"&DATE(YEAR(F$25),MONTH(F$25)+1,1),'Sales Log'!$B$5:$B$1004,$A30,'Sales Log'!$R$5:$R$1004,"<>EXAMPLE") -> 0 | G30: =SUMIFS('Sales Log'!$H$5:$H$1004,'Sales Log'!$A$5:$A$1004,">="&G$25,'Sales Log'!$A$5:$A$1004,"<"&DATE(YEAR(G$25),MONTH(G$25)+1,1),'Sales Log'!$B$5:$B$1004,$A30,'Sales Log'!$R$5:$R$1004,"<>EXAMPLE") -> 0 | H30: =SUMIFS('Sales Log'!$H$5:$H$1004,'Sales Log'!$A$5:$A$1004,">="&H$25,'Sales Log'!$A$5:$A$1004,"<"&DATE(YEAR(H$25),MONTH(H$25)+1,1),'Sales Log'!$B$5:$B$1004,$A30,'Sales Log'!$R$5:$R$1004,"<>EXAMPLE") -> 0 | I30: =SUMIFS('Sales Log'!$H$5:$H$1004,'Sales Log'!$A$5:$A$1004,">="&I$25,'Sales Log'!$A$5:$A$1004,"<"&DATE(YEAR(I$25),MONTH(I$25)+1,1),'Sales Log'!$B$5:$B$1004,$A30,'Sales Log'!$R$5:$R$1004,"<>EXAMPLE") -> 0 | ... M30: =SUMIFS('Sales Log'!$H$5:$H$1004,'Sales Log'!$A$5:$A$1004,">="&M$25,'Sales Log'!$A$5:$A$1004,"<"&DATE(YEAR(M$25),MONTH(M$25)+1,1),'Sales Log'!$B$5:$B$1004,$A30,'Sales Log'!$R$5:$R$1004,"<>EXAMPLE") -> 0 | N30: =SUM(B30:M30) -> 0
A31: ='Chart of Accounts'!$A$71 -> Shopify (website store) | B31: =SUMIFS('Sales Log'!$H$5:$H$1004,'Sales Log'!$A$5:$A$1004,">="&B$25,'Sales Log'!$A$5:$A$1004,"<"&DATE(YEAR(B$25),MONTH(B$25)+1,1),'Sales Log'!$B$5:$B$1004,$A31,'Sales Log'!$R$5:$R$1004,"<>EXAMPLE") -> 0 | C31: =SUMIFS('Sales Log'!$H$5:$H$1004,'Sales Log'!$A$5:$A$1004,">="&C$25,'Sales Log'!$A$5:$A$1004,"<"&DATE(YEAR(C$25),MONTH(C$25)+1,1),'Sales Log'!$B$5:$B$1004,$A31,'Sales Log'!$R$5:$R$1004,"<>EXAMPLE") -> 0 | D31: =SUMIFS('Sales Log'!$H$5:$H$1004,'Sales Log'!$A$5:$A$1004,">="&D$25,'Sales Log'!$A$5:$A$1004,"<"&DATE(YEAR(D$25),MONTH(D$25)+1,1),'Sales Log'!$B$5:$B$1004,$A31,'Sales Log'!$R$5:$R$1004,"<>EXAMPLE") -> 0 | E31: =SUMIFS('Sales Log'!$H$5:$H$1004,'Sales Log'!$A$5:$A$1004,">="&E$25,'Sales Log'!$A$5:$A$1004,"<"&DATE(YEAR(E$25),MONTH(E$25)+1,1),'Sales Log'!$B$5:$B$1004,$A31,'Sales Log'!$R$5:$R$1004,"<>EXAMPLE") -> 0 | F31: =SUMIFS('Sales Log'!$H$5:$H$1004,'Sales Log'!$A$5:$A$1004,">="&F$25,'Sales Log'!$A$5:$A$1004,"<"&DATE(YEAR(F$25),MONTH(F$25)+1,1),'Sales Log'!$B$5:$B$1004,$A31,'Sales Log'!$R$5:$R$1004,"<>EXAMPLE") -> 0 | G31: =SUMIFS('Sales Log'!$H$5:$H$1004,'Sales Log'!$A$5:$A$1004,">="&G$25,'Sales Log'!$A$5:$A$1004,"<"&DATE(YEAR(G$25),MONTH(G$25)+1,1),'Sales Log'!$B$5:$B$1004,$A31,'Sales Log'!$R$5:$R$1004,"<>EXAMPLE") -> 0 | H31: =SUMIFS('Sales Log'!$H$5:$H$1004,'Sales Log'!$A$5:$A$1004,">="&H$25,'Sales Log'!$A$5:$A$1004,"<"&DATE(YEAR(H$25),MONTH(H$25)+1,1),'Sales Log'!$B$5:$B$1004,$A31,'Sales Log'!$R$5:$R$1004,"<>EXAMPLE") -> 0 | I31: =SUMIFS('Sales Log'!$H$5:$H$1004,'Sales Log'!$A$5:$A$1004,">="&I$25,'Sales Log'!$A$5:$A$1004,"<"&DATE(YEAR(I$25),MONTH(I$25)+1,1),'Sales Log'!$B$5:$B$1004,$A31,'Sales Log'!$R$5:$R$1004,"<>EXAMPLE") -> 0 | ... M31: =SUMIFS('Sales Log'!$H$5:$H$1004,'Sales Log'!$A$5:$A$1004,">="&M$25,'Sales Log'!$A$5:$A$1004,"<"&DATE(YEAR(M$25),MONTH(M$25)+1,1),'Sales Log'!$B$5:$B$1004,$A31,'Sales Log'!$R$5:$R$1004,"<>EXAMPLE") -> 0 | N31: =SUM(B31:M31) -> 0
A32: ='Chart of Accounts'!$A$72 -> Stripe (website & invoices) | B32: =SUMIFS('Sales Log'!$H$5:$H$1004,'Sales Log'!$A$5:$A$1004,">="&B$25,'Sales Log'!$A$5:$A$1004,"<"&DATE(YEAR(B$25),MONTH(B$25)+1,1),'Sales Log'!$B$5:$B$1004,$A32,'Sales Log'!$R$5:$R$1004,"<>EXAMPLE") -> 0 | C32: =SUMIFS('Sales Log'!$H$5:$H$1004,'Sales Log'!$A$5:$A$1004,">="&C$25,'Sales Log'!$A$5:$A$1004,"<"&DATE(YEAR(C$25),MONTH(C$25)+1,1),'Sales Log'!$B$5:$B$1004,$A32,'Sales Log'!$R$5:$R$1004,"<>EXAMPLE") -> 0 | D32: =SUMIFS('Sales Log'!$H$5:$H$1004,'Sales Log'!$A$5:$A$1004,">="&D$25,'Sales Log'!$A$5:$A$1004,"<"&DATE(YEAR(D$25),MONTH(D$25)+1,1),'Sales Log'!$B$5:$B$1004,$A32,'Sales Log'!$R$5:$R$1004,"<>EXAMPLE") -> 0 | E32: =SUMIFS('Sales Log'!$H$5:$H$1004,'Sales Log'!$A$5:$A$1004,">="&E$25,'Sales Log'!$A$5:$A$1004,"<"&DATE(YEAR(E$25),MONTH(E$25)+1,1),'Sales Log'!$B$5:$B$1004,$A32,'Sales Log'!$R$5:$R$1004,"<>EXAMPLE") -> 0 | F32: =SUMIFS('Sales Log'!$H$5:$H$1004,'Sales Log'!$A$5:$A$1004,">="&F$25,'Sales Log'!$A$5:$A$1004,"<"&DATE(YEAR(F$25),MONTH(F$25)+1,1),'Sales Log'!$B$5:$B$1004,$A32,'Sales Log'!$R$5:$R$1004,"<>EXAMPLE") -> 0 | G32: =SUMIFS('Sales Log'!$H$5:$H$1004,'Sales Log'!$A$5:$A$1004,">="&G$25,'Sales Log'!$A$5:$A$1004,"<"&DATE(YEAR(G$25),MONTH(G$25)+1,1),'Sales Log'!$B$5:$B$1004,$A32,'Sales Log'!$R$5:$R$1004,"<>EXAMPLE") -> 0 | H32: =SUMIFS('Sales Log'!$H$5:$H$1004,'Sales Log'!$A$5:$A$1004,">="&H$25,'Sales Log'!$A$5:$A$1004,"<"&DATE(YEAR(H$25),MONTH(H$25)+1,1),'Sales Log'!$B$5:$B$1004,$A32,'Sales Log'!$R$5:$R$1004,"<>EXAMPLE") -> 0 | I32: =SUMIFS('Sales Log'!$H$5:$H$1004,'Sales Log'!$A$5:$A$1004,">="&I$25,'Sales Log'!$A$5:$A$1004,"<"&DATE(YEAR(I$25),MONTH(I$25)+1,1),'Sales Log'!$B$5:$B$1004,$A32,'Sales Log'!$R$5:$R$1004,"<>EXAMPLE") -> 0 | ... M32: =SUMIFS('Sales Log'!$H$5:$H$1004,'Sales Log'!$A$5:$A$1004,">="&M$25,'Sales Log'!$A$5:$A$1004,"<"&DATE(YEAR(M$25),MONTH(M$25)+1,1),'Sales Log'!$B$5:$B$1004,$A32,'Sales Log'!$R$5:$R$1004,"<>EXAMPLE") -> 0 | N32: =SUM(B32:M32) -> 0
A33: ='Chart of Accounts'!$A$73 -> PayPal Business | B33: =SUMIFS('Sales Log'!$H$5:$H$1004,'Sales Log'!$A$5:$A$1004,">="&B$25,'Sales Log'!$A$5:$A$1004,"<"&DATE(YEAR(B$25),MONTH(B$25)+1,1),'Sales Log'!$B$5:$B$1004,$A33,'Sales Log'!$R$5:$R$1004,"<>EXAMPLE") -> 0 | C33: =SUMIFS('Sales Log'!$H$5:$H$1004,'Sales Log'!$A$5:$A$1004,">="&C$25,'Sales Log'!$A$5:$A$1004,"<"&DATE(YEAR(C$25),MONTH(C$25)+1,1),'Sales Log'!$B$5:$B$1004,$A33,'Sales Log'!$R$5:$R$1004,"<>EXAMPLE") -> 0 | D33: =SUMIFS('Sales Log'!$H$5:$H$1004,'Sales Log'!$A$5:$A$1004,">="&D$25,'Sales Log'!$A$5:$A$1004,"<"&DATE(YEAR(D$25),MONTH(D$25)+1,1),'Sales Log'!$B$5:$B$1004,$A33,'Sales Log'!$R$5:$R$1004,"<>EXAMPLE") -> 0 | E33: =SUMIFS('Sales Log'!$H$5:$H$1004,'Sales Log'!$A$5:$A$1004,">="&E$25,'Sales Log'!$A$5:$A$1004,"<"&DATE(YEAR(E$25),MONTH(E$25)+1,1),'Sales Log'!$B$5:$B$1004,$A33,'Sales Log'!$R$5:$R$1004,"<>EXAMPLE") -> 0 | F33: =SUMIFS('Sales Log'!$H$5:$H$1004,'Sales Log'!$A$5:$A$1004,">="&F$25,'Sales Log'!$A$5:$A$1004,"<"&DATE(YEAR(F$25),MONTH(F$25)+1,1),'Sales Log'!$B$5:$B$1004,$A33,'Sales Log'!$R$5:$R$1004,"<>EXAMPLE") -> 0 | G33: =SUMIFS('Sales Log'!$H$5:$H$1004,'Sales Log'!$A$5:$A$1004,">="&G$25,'Sales Log'!$A$5:$A$1004,"<"&DATE(YEAR(G$25),MONTH(G$25)+1,1),'Sales Log'!$B$5:$B$1004,$A33,'Sales Log'!$R$5:$R$1004,"<>EXAMPLE") -> 0 | H33: =SUMIFS('Sales Log'!$H$5:$H$1004,'Sales Log'!$A$5:$A$1004,">="&H$25,'Sales Log'!$A$5:$A$1004,"<"&DATE(YEAR(H$25),MONTH(H$25)+1,1),'Sales Log'!$B$5:$B$1004,$A33,'Sales Log'!$R$5:$R$1004,"<>EXAMPLE") -> 0 | I33: =SUMIFS('Sales Log'!$H$5:$H$1004,'Sales Log'!$A$5:$A$1004,">="&I$25,'Sales Log'!$A$5:$A$1004,"<"&DATE(YEAR(I$25),MONTH(I$25)+1,1),'Sales Log'!$B$5:$B$1004,$A33,'Sales Log'!$R$5:$R$1004,"<>EXAMPLE") -> 0 | ... M33: =SUMIFS('Sales Log'!$H$5:$H$1004,'Sales Log'!$A$5:$A$1004,">="&M$25,'Sales Log'!$A$5:$A$1004,"<"&DATE(YEAR(M$25),MONTH(M$25)+1,1),'Sales Log'!$B$5:$B$1004,$A33,'Sales Log'!$R$5:$R$1004,"<>EXAMPLE") -> 0 | N33: =SUM(B33:M33) -> 0
A34: ='Chart of Accounts'!$A$74 -> Meta shop (FB/IG) | B34: =SUMIFS('Sales Log'!$H$5:$H$1004,'Sales Log'!$A$5:$A$1004,">="&B$25,'Sales Log'!$A$5:$A$1004,"<"&DATE(YEAR(B$25),MONTH(B$25)+1,1),'Sales Log'!$B$5:$B$1004,$A34,'Sales Log'!$R$5:$R$1004,"<>EXAMPLE") -> 0 | C34: =SUMIFS('Sales Log'!$H$5:$H$1004,'Sales Log'!$A$5:$A$1004,">="&C$25,'Sales Log'!$A$5:$A$1004,"<"&DATE(YEAR(C$25),MONTH(C$25)+1,1),'Sales Log'!$B$5:$B$1004,$A34,'Sales Log'!$R$5:$R$1004,"<>EXAMPLE") -> 0 | D34: =SUMIFS('Sales Log'!$H$5:$H$1004,'Sales Log'!$A$5:$A$1004,">="&D$25,'Sales Log'!$A$5:$A$1004,"<"&DATE(YEAR(D$25),MONTH(D$25)+1,1),'Sales Log'!$B$5:$B$1004,$A34,'Sales Log'!$R$5:$R$1004,"<>EXAMPLE") -> 0 | E34: =SUMIFS('Sales Log'!$H$5:$H$1004,'Sales Log'!$A$5:$A$1004,">="&E$25,'Sales Log'!$A$5:$A$1004,"<"&DATE(YEAR(E$25),MONTH(E$25)+1,1),'Sales Log'!$B$5:$B$1004,$A34,'Sales Log'!$R$5:$R$1004,"<>EXAMPLE") -> 0 | F34: =SUMIFS('Sales Log'!$H$5:$H$1004,'Sales Log'!$A$5:$A$1004,">="&F$25,'Sales Log'!$A$5:$A$1004,"<"&DATE(YEAR(F$25),MONTH(F$25)+1,1),'Sales Log'!$B$5:$B$1004,$A34,'Sales Log'!$R$5:$R$1004,"<>EXAMPLE") -> 0 | G34: =SUMIFS('Sales Log'!$H$5:$H$1004,'Sales Log'!$A$5:$A$1004,">="&G$25,'Sales Log'!$A$5:$A$1004,"<"&DATE(YEAR(G$25),MONTH(G$25)+1,1),'Sales Log'!$B$5:$B$1004,$A34,'Sales Log'!$R$5:$R$1004,"<>EXAMPLE") -> 0 | H34: =SUMIFS('Sales Log'!$H$5:$H$1004,'Sales Log'!$A$5:$A$1004,">="&H$25,'Sales Log'!$A$5:$A$1004,"<"&DATE(YEAR(H$25),MONTH(H$25)+1,1),'Sales Log'!$B$5:$B$1004,$A34,'Sales Log'!$R$5:$R$1004,"<>EXAMPLE") -> 0 | I34: =SUMIFS('Sales Log'!$H$5:$H$1004,'Sales Log'!$A$5:$A$1004,">="&I$25,'Sales Log'!$A$5:$A$1004,"<"&DATE(YEAR(I$25),MONTH(I$25)+1,1),'Sales Log'!$B$5:$B$1004,$A34,'Sales Log'!$R$5:$R$1004,"<>EXAMPLE") -> 0 | ... M34: =SUMIFS('Sales Log'!$H$5:$H$1004,'Sales Log'!$A$5:$A$1004,">="&M$25,'Sales Log'!$A$5:$A$1004,"<"&DATE(YEAR(M$25),MONTH(M$25)+1,1),'Sales Log'!$B$5:$B$1004,$A34,'Sales Log'!$R$5:$R$1004,"<>EXAMPLE") -> 0 | N34: =SUM(B34:M34) -> 0
A35: ='Chart of Accounts'!$A$75 -> Faire (wholesale) | B35: =SUMIFS('Sales Log'!$H$5:$H$1004,'Sales Log'!$A$5:$A$1004,">="&B$25,'Sales Log'!$A$5:$A$1004,"<"&DATE(YEAR(B$25),MONTH(B$25)+1,1),'Sales Log'!$B$5:$B$1004,$A35,'Sales Log'!$R$5:$R$1004,"<>EXAMPLE") -> 0 | C35: =SUMIFS('Sales Log'!$H$5:$H$1004,'Sales Log'!$A$5:$A$1004,">="&C$25,'Sales Log'!$A$5:$A$1004,"<"&DATE(YEAR(C$25),MONTH(C$25)+1,1),'Sales Log'!$B$5:$B$1004,$A35,'Sales Log'!$R$5:$R$1004,"<>EXAMPLE") -> 0 | D35: =SUMIFS('Sales Log'!$H$5:$H$1004,'Sales Log'!$A$5:$A$1004,">="&D$25,'Sales Log'!$A$5:$A$1004,"<"&DATE(YEAR(D$25),MONTH(D$25)+1,1),'Sales Log'!$B$5:$B$1004,$A35,'Sales Log'!$R$5:$R$1004,"<>EXAMPLE") -> 0 | E35: =SUMIFS('Sales Log'!$H$5:$H$1004,'Sales Log'!$A$5:$A$1004,">="&E$25,'Sales Log'!$A$5:$A$1004,"<"&DATE(YEAR(E$25),MONTH(E$25)+1,1),'Sales Log'!$B$5:$B$1004,$A35,'Sales Log'!$R$5:$R$1004,"<>EXAMPLE") -> 0 | F35: =SUMIFS('Sales Log'!$H$5:$H$1004,'Sales Log'!$A$5:$A$1004,">="&F$25,'Sales Log'!$A$5:$A$1004,"<"&DATE(YEAR(F$25),MONTH(F$25)+1,1),'Sales Log'!$B$5:$B$1004,$A35,'Sales Log'!$R$5:$R$1004,"<>EXAMPLE") -> 0 | G35: =SUMIFS('Sales Log'!$H$5:$H$1004,'Sales Log'!$A$5:$A$1004,">="&G$25,'Sales Log'!$A$5:$A$1004,"<"&DATE(YEAR(G$25),MONTH(G$25)+1,1),'Sales Log'!$B$5:$B$1004,$A35,'Sales Log'!$R$5:$R$1004,"<>EXAMPLE") -> 0 | H35: =SUMIFS('Sales Log'!$H$5:$H$1004,'Sales Log'!$A$5:$A$1004,">="&H$25,'Sales Log'!$A$5:$A$1004,"<"&DATE(YEAR(H$25),MONTH(H$25)+1,1),'Sales Log'!$B$5:$B$1004,$A35,'Sales Log'!$R$5:$R$1004,"<>EXAMPLE") -> 0 | I35: =SUMIFS('Sales Log'!$H$5:$H$1004,'Sales Log'!$A$5:$A$1004,">="&I$25,'Sales Log'!$A$5:$A$1004,"<"&DATE(YEAR(I$25),MONTH(I$25)+1,1),'Sales Log'!$B$5:$B$1004,$A35,'Sales Log'!$R$5:$R$1004,"<>EXAMPLE") -> 0 | ... M35: =SUMIFS('Sales Log'!$H$5:$H$1004,'Sales Log'!$A$5:$A$1004,">="&M$25,'Sales Log'!$A$5:$A$1004,"<"&DATE(YEAR(M$25),MONTH(M$25)+1,1),'Sales Log'!$B$5:$B$1004,$A35,'Sales Log'!$R$5:$R$1004,"<>EXAMPLE") -> 0 | N35: =SUM(B35:M35) -> 0
A36: ='Chart of Accounts'!$A$76 -> Merchant of record | B36: =SUMIFS('Sales Log'!$H$5:$H$1004,'Sales Log'!$A$5:$A$1004,">="&B$25,'Sales Log'!$A$5:$A$1004,"<"&DATE(YEAR(B$25),MONTH(B$25)+1,1),'Sales Log'!$B$5:$B$1004,$A36,'Sales Log'!$R$5:$R$1004,"<>EXAMPLE") -> 0 | C36: =SUMIFS('Sales Log'!$H$5:$H$1004,'Sales Log'!$A$5:$A$1004,">="&C$25,'Sales Log'!$A$5:$A$1004,"<"&DATE(YEAR(C$25),MONTH(C$25)+1,1),'Sales Log'!$B$5:$B$1004,$A36,'Sales Log'!$R$5:$R$1004,"<>EXAMPLE") -> 0 | D36: =SUMIFS('Sales Log'!$H$5:$H$1004,'Sales Log'!$A$5:$A$1004,">="&D$25,'Sales Log'!$A$5:$A$1004,"<"&DATE(YEAR(D$25),MONTH(D$25)+1,1),'Sales Log'!$B$5:$B$1004,$A36,'Sales Log'!$R$5:$R$1004,"<>EXAMPLE") -> 0 | E36: =SUMIFS('Sales Log'!$H$5:$H$1004,'Sales Log'!$A$5:$A$1004,">="&E$25,'Sales Log'!$A$5:$A$1004,"<"&DATE(YEAR(E$25),MONTH(E$25)+1,1),'Sales Log'!$B$5:$B$1004,$A36,'Sales Log'!$R$5:$R$1004,"<>EXAMPLE") -> 0 | F36: =SUMIFS('Sales Log'!$H$5:$H$1004,'Sales Log'!$A$5:$A$1004,">="&F$25,'Sales Log'!$A$5:$A$1004,"<"&DATE(YEAR(F$25),MONTH(F$25)+1,1),'Sales Log'!$B$5:$B$1004,$A36,'Sales Log'!$R$5:$R$1004,"<>EXAMPLE") -> 0 | G36: =SUMIFS('Sales Log'!$H$5:$H$1004,'Sales Log'!$A$5:$A$1004,">="&G$25,'Sales Log'!$A$5:$A$1004,"<"&DATE(YEAR(G$25),MONTH(G$25)+1,1),'Sales Log'!$B$5:$B$1004,$A36,'Sales Log'!$R$5:$R$1004,"<>EXAMPLE") -> 0 | H36: =SUMIFS('Sales Log'!$H$5:$H$1004,'Sales Log'!$A$5:$A$1004,">="&H$25,'Sales Log'!$A$5:$A$1004,"<"&DATE(YEAR(H$25),MONTH(H$25)+1,1),'Sales Log'!$B$5:$B$1004,$A36,'Sales Log'!$R$5:$R$1004,"<>EXAMPLE") -> 0 | I36: =SUMIFS('Sales Log'!$H$5:$H$1004,'Sales Log'!$A$5:$A$1004,">="&I$25,'Sales Log'!$A$5:$A$1004,"<"&DATE(YEAR(I$25),MONTH(I$25)+1,1),'Sales Log'!$B$5:$B$1004,$A36,'Sales Log'!$R$5:$R$1004,"<>EXAMPLE") -> 0 | ... M36: =SUMIFS('Sales Log'!$H$5:$H$1004,'Sales Log'!$A$5:$A$1004,">="&M$25,'Sales Log'!$A$5:$A$1004,"<"&DATE(YEAR(M$25),MONTH(M$25)+1,1),'Sales Log'!$B$5:$B$1004,$A36,'Sales Log'!$R$5:$R$1004,"<>EXAMPLE") -> 0 | N36: =SUM(B36:M36) -> 0
A37: ='Chart of Accounts'!$A$77 -> Amazon Associates | B37: =SUMIFS('Sales Log'!$H$5:$H$1004,'Sales Log'!$A$5:$A$1004,">="&B$25,'Sales Log'!$A$5:$A$1004,"<"&DATE(YEAR(B$25),MONTH(B$25)+1,1),'Sales Log'!$B$5:$B$1004,$A37,'Sales Log'!$R$5:$R$1004,"<>EXAMPLE") -> 0 | C37: =SUMIFS('Sales Log'!$H$5:$H$1004,'Sales Log'!$A$5:$A$1004,">="&C$25,'Sales Log'!$A$5:$A$1004,"<"&DATE(YEAR(C$25),MONTH(C$25)+1,1),'Sales Log'!$B$5:$B$1004,$A37,'Sales Log'!$R$5:$R$1004,"<>EXAMPLE") -> 0 | D37: =SUMIFS('Sales Log'!$H$5:$H$1004,'Sales Log'!$A$5:$A$1004,">="&D$25,'Sales Log'!$A$5:$A$1004,"<"&DATE(YEAR(D$25),MONTH(D$25)+1,1),'Sales Log'!$B$5:$B$1004,$A37,'Sales Log'!$R$5:$R$1004,"<>EXAMPLE") -> 0 | E37: =SUMIFS('Sales Log'!$H$5:$H$1004,'Sales Log'!$A$5:$A$1004,">="&E$25,'Sales Log'!$A$5:$A$1004,"<"&DATE(YEAR(E$25),MONTH(E$25)+1,1),'Sales Log'!$B$5:$B$1004,$A37,'Sales Log'!$R$5:$R$1004,"<>EXAMPLE") -> 0 | F37: =SUMIFS('Sales Log'!$H$5:$H$1004,'Sales Log'!$A$5:$A$1004,">="&F$25,'Sales Log'!$A$5:$A$1004,"<"&DATE(YEAR(F$25),MONTH(F$25)+1,1),'Sales Log'!$B$5:$B$1004,$A37,'Sales Log'!$R$5:$R$1004,"<>EXAMPLE") -> 0 | G37: =SUMIFS('Sales Log'!$H$5:$H$1004,'Sales Log'!$A$5:$A$1004,">="&G$25,'Sales Log'!$A$5:$A$1004,"<"&DATE(YEAR(G$25),MONTH(G$25)+1,1),'Sales Log'!$B$5:$B$1004,$A37,'Sales Log'!$R$5:$R$1004,"<>EXAMPLE") -> 0 | H37: =SUMIFS('Sales Log'!$H$5:$H$1004,'Sales Log'!$A$5:$A$1004,">="&H$25,'Sales Log'!$A$5:$A$1004,"<"&DATE(YEAR(H$25),MONTH(H$25)+1,1),'Sales Log'!$B$5:$B$1004,$A37,'Sales Log'!$R$5:$R$1004,"<>EXAMPLE") -> 0 | I37: =SUMIFS('Sales Log'!$H$5:$H$1004,'Sales Log'!$A$5:$A$1004,">="&I$25,'Sales Log'!$A$5:$A$1004,"<"&DATE(YEAR(I$25),MONTH(I$25)+1,1),'Sales Log'!$B$5:$B$1004,$A37,'Sales Log'!$R$5:$R$1004,"<>EXAMPLE") -> 0 | ... M37: =SUMIFS('Sales Log'!$H$5:$H$1004,'Sales Log'!$A$5:$A$1004,">="&M$25,'Sales Log'!$A$5:$A$1004,"<"&DATE(YEAR(M$25),MONTH(M$25)+1,1),'Sales Log'!$B$5:$B$1004,$A37,'Sales Log'!$R$5:$R$1004,"<>EXAMPLE") -> 0 | N37: =SUM(B37:M37) -> 0
A38: ='Chart of Accounts'!$A$78 -> Bookshop.org | B38: =SUMIFS('Sales Log'!$H$5:$H$1004,'Sales Log'!$A$5:$A$1004,">="&B$25,'Sales Log'!$A$5:$A$1004,"<"&DATE(YEAR(B$25),MONTH(B$25)+1,1),'Sales Log'!$B$5:$B$1004,$A38,'Sales Log'!$R$5:$R$1004,"<>EXAMPLE") -> 0 | C38: =SUMIFS('Sales Log'!$H$5:$H$1004,'Sales Log'!$A$5:$A$1004,">="&C$25,'Sales Log'!$A$5:$A$1004,"<"&DATE(YEAR(C$25),MONTH(C$25)+1,1),'Sales Log'!$B$5:$B$1004,$A38,'Sales Log'!$R$5:$R$1004,"<>EXAMPLE") -> 0 | D38: =SUMIFS('Sales Log'!$H$5:$H$1004,'Sales Log'!$A$5:$A$1004,">="&D$25,'Sales Log'!$A$5:$A$1004,"<"&DATE(YEAR(D$25),MONTH(D$25)+1,1),'Sales Log'!$B$5:$B$1004,$A38,'Sales Log'!$R$5:$R$1004,"<>EXAMPLE") -> 0 | E38: =SUMIFS('Sales Log'!$H$5:$H$1004,'Sales Log'!$A$5:$A$1004,">="&E$25,'Sales Log'!$A$5:$A$1004,"<"&DATE(YEAR(E$25),MONTH(E$25)+1,1),'Sales Log'!$B$5:$B$1004,$A38,'Sales Log'!$R$5:$R$1004,"<>EXAMPLE") -> 0 | F38: =SUMIFS('Sales Log'!$H$5:$H$1004,'Sales Log'!$A$5:$A$1004,">="&F$25,'Sales Log'!$A$5:$A$1004,"<"&DATE(YEAR(F$25),MONTH(F$25)+1,1),'Sales Log'!$B$5:$B$1004,$A38,'Sales Log'!$R$5:$R$1004,"<>EXAMPLE") -> 0 | G38: =SUMIFS('Sales Log'!$H$5:$H$1004,'Sales Log'!$A$5:$A$1004,">="&G$25,'Sales Log'!$A$5:$A$1004,"<"&DATE(YEAR(G$25),MONTH(G$25)+1,1),'Sales Log'!$B$5:$B$1004,$A38,'Sales Log'!$R$5:$R$1004,"<>EXAMPLE") -> 0 | H38: =SUMIFS('Sales Log'!$H$5:$H$1004,'Sales Log'!$A$5:$A$1004,">="&H$25,'Sales Log'!$A$5:$A$1004,"<"&DATE(YEAR(H$25),MONTH(H$25)+1,1),'Sales Log'!$B$5:$B$1004,$A38,'Sales Log'!$R$5:$R$1004,"<>EXAMPLE") -> 0 | I38: =SUMIFS('Sales Log'!$H$5:$H$1004,'Sales Log'!$A$5:$A$1004,">="&I$25,'Sales Log'!$A$5:$A$1004,"<"&DATE(YEAR(I$25),MONTH(I$25)+1,1),'Sales Log'!$B$5:$B$1004,$A38,'Sales Log'!$R$5:$R$1004,"<>EXAMPLE") -> 0 | ... M38: =SUMIFS('Sales Log'!$H$5:$H$1004,'Sales Log'!$A$5:$A$1004,">="&M$25,'Sales Log'!$A$5:$A$1004,"<"&DATE(YEAR(M$25),MONTH(M$25)+1,1),'Sales Log'!$B$5:$B$1004,$A38,'Sales Log'!$R$5:$R$1004,"<>EXAMPLE") -> 0 | N38: =SUM(B38:M38) -> 0
A39: ='Chart of Accounts'!$A$79 -> Direct (check / ACH / cash) | B39: =SUMIFS('Sales Log'!$H$5:$H$1004,'Sales Log'!$A$5:$A$1004,">="&B$25,'Sales Log'!$A$5:$A$1004,"<"&DATE(YEAR(B$25),MONTH(B$25)+1,1),'Sales Log'!$B$5:$B$1004,$A39,'Sales Log'!$R$5:$R$1004,"<>EXAMPLE") -> 0 | C39: =SUMIFS('Sales Log'!$H$5:$H$1004,'Sales Log'!$A$5:$A$1004,">="&C$25,'Sales Log'!$A$5:$A$1004,"<"&DATE(YEAR(C$25),MONTH(C$25)+1,1),'Sales Log'!$B$5:$B$1004,$A39,'Sales Log'!$R$5:$R$1004,"<>EXAMPLE") -> 0 | D39: =SUMIFS('Sales Log'!$H$5:$H$1004,'Sales Log'!$A$5:$A$1004,">="&D$25,'Sales Log'!$A$5:$A$1004,"<"&DATE(YEAR(D$25),MONTH(D$25)+1,1),'Sales Log'!$B$5:$B$1004,$A39,'Sales Log'!$R$5:$R$1004,"<>EXAMPLE") -> 0 | E39: =SUMIFS('Sales Log'!$H$5:$H$1004,'Sales Log'!$A$5:$A$1004,">="&E$25,'Sales Log'!$A$5:$A$1004,"<"&DATE(YEAR(E$25),MONTH(E$25)+1,1),'Sales Log'!$B$5:$B$1004,$A39,'Sales Log'!$R$5:$R$1004,"<>EXAMPLE") -> 0 | F39: =SUMIFS('Sales Log'!$H$5:$H$1004,'Sales Log'!$A$5:$A$1004,">="&F$25,'Sales Log'!$A$5:$A$1004,"<"&DATE(YEAR(F$25),MONTH(F$25)+1,1),'Sales Log'!$B$5:$B$1004,$A39,'Sales Log'!$R$5:$R$1004,"<>EXAMPLE") -> 0 | G39: =SUMIFS('Sales Log'!$H$5:$H$1004,'Sales Log'!$A$5:$A$1004,">="&G$25,'Sales Log'!$A$5:$A$1004,"<"&DATE(YEAR(G$25),MONTH(G$25)+1,1),'Sales Log'!$B$5:$B$1004,$A39,'Sales Log'!$R$5:$R$1004,"<>EXAMPLE") -> 0 | H39: =SUMIFS('Sales Log'!$H$5:$H$1004,'Sales Log'!$A$5:$A$1004,">="&H$25,'Sales Log'!$A$5:$A$1004,"<"&DATE(YEAR(H$25),MONTH(H$25)+1,1),'Sales Log'!$B$5:$B$1004,$A39,'Sales Log'!$R$5:$R$1004,"<>EXAMPLE") -> 0 | I39: =SUMIFS('Sales Log'!$H$5:$H$1004,'Sales Log'!$A$5:$A$1004,">="&I$25,'Sales Log'!$A$5:$A$1004,"<"&DATE(YEAR(I$25),MONTH(I$25)+1,1),'Sales Log'!$B$5:$B$1004,$A39,'Sales Log'!$R$5:$R$1004,"<>EXAMPLE") -> 0 | ... M39: =SUMIFS('Sales Log'!$H$5:$H$1004,'Sales Log'!$A$5:$A$1004,">="&M$25,'Sales Log'!$A$5:$A$1004,"<"&DATE(YEAR(M$25),MONTH(M$25)+1,1),'Sales Log'!$B$5:$B$1004,$A39,'Sales Log'!$R$5:$R$1004,"<>EXAMPLE") -> 0 | N39: =SUM(B39:M39) -> 0
A40: Total | B40: =SUM(B26:B39) -> 0 | C40: =SUM(C26:C39) -> 0 | D40: =SUM(D26:D39) -> 0 | E40: =SUM(E26:E39) -> 0 | F40: =SUM(F26:F39) -> 0 | G40: =SUM(G26:G39) -> 0 | H40: =SUM(H26:H39) -> 0 | I40: =SUM(I26:I39) -> 0 | ... N40: =SUM(N26:N39) -> 0
A43: Net payout (from Sales Log)
A44: Channel | B44: =DATE($B$3,1,1) -> 46023 | C44: =DATE($B$3,2,1) -> 46054 | D44: =DATE($B$3,3,1) -> 46082 | E44: =DATE($B$3,4,1) -> 46113 | F44: =DATE($B$3,5,1) -> 46143 | G44: =DATE($B$3,6,1) -> 46174 | H44: =DATE($B$3,7,1) -> 46204 | I44: =DATE($B$3,8,1) -> 46235 | J44: =DATE($B$3,9,1) -> 46266 | K44: =DATE($B$3,10,1) -> 46296 | L44: =DATE($B$3,11,1) -> 46327 | M44: =DATE($B$3,12,1) -> 46357 | N44: Total
A45: ='Chart of Accounts'!$A$66 -> Amazon KDP | B45: =SUMIFS('Sales Log'!$L$5:$L$1004,'Sales Log'!$A$5:$A$1004,">="&B$44,'Sales Log'!$A$5:$A$1004,"<"&DATE(YEAR(B$44),MONTH(B$44)+1,1),'Sales Log'!$B$5:$B$1004,$A45,'Sales Log'!$R$5:$R$1004,"<>EXAMPLE") -> 0 | C45: =SUMIFS('Sales Log'!$L$5:$L$1004,'Sales Log'!$A$5:$A$1004,">="&C$44,'Sales Log'!$A$5:$A$1004,"<"&DATE(YEAR(C$44),MONTH(C$44)+1,1),'Sales Log'!$B$5:$B$1004,$A45,'Sales Log'!$R$5:$R$1004,"<>EXAMPLE") -> 0 | D45: =SUMIFS('Sales Log'!$L$5:$L$1004,'Sales Log'!$A$5:$A$1004,">="&D$44,'Sales Log'!$A$5:$A$1004,"<"&DATE(YEAR(D$44),MONTH(D$44)+1,1),'Sales Log'!$B$5:$B$1004,$A45,'Sales Log'!$R$5:$R$1004,"<>EXAMPLE") -> 0 | E45: =SUMIFS('Sales Log'!$L$5:$L$1004,'Sales Log'!$A$5:$A$1004,">="&E$44,'Sales Log'!$A$5:$A$1004,"<"&DATE(YEAR(E$44),MONTH(E$44)+1,1),'Sales Log'!$B$5:$B$1004,$A45,'Sales Log'!$R$5:$R$1004,"<>EXAMPLE") -> 0 | F45: =SUMIFS('Sales Log'!$L$5:$L$1004,'Sales Log'!$A$5:$A$1004,">="&F$44,'Sales Log'!$A$5:$A$1004,"<"&DATE(YEAR(F$44),MONTH(F$44)+1,1),'Sales Log'!$B$5:$B$1004,$A45,'Sales Log'!$R$5:$R$1004,"<>EXAMPLE") -> 0 | G45: =SUMIFS('Sales Log'!$L$5:$L$1004,'Sales Log'!$A$5:$A$1004,">="&G$44,'Sales Log'!$A$5:$A$1004,"<"&DATE(YEAR(G$44),MONTH(G$44)+1,1),'Sales Log'!$B$5:$B$1004,$A45,'Sales Log'!$R$5:$R$1004,"<>EXAMPLE") -> 0 | H45: =SUMIFS('Sales Log'!$L$5:$L$1004,'Sales Log'!$A$5:$A$1004,">="&H$44,'Sales Log'!$A$5:$A$1004,"<"&DATE(YEAR(H$44),MONTH(H$44)+1,1),'Sales Log'!$B$5:$B$1004,$A45,'Sales Log'!$R$5:$R$1004,"<>EXAMPLE") -> 0 | I45: =SUMIFS('Sales Log'!$L$5:$L$1004,'Sales Log'!$A$5:$A$1004,">="&I$44,'Sales Log'!$A$5:$A$1004,"<"&DATE(YEAR(I$44),MONTH(I$44)+1,1),'Sales Log'!$B$5:$B$1004,$A45,'Sales Log'!$R$5:$R$1004,"<>EXAMPLE") -> 0 | ... M45: =SUMIFS('Sales Log'!$L$5:$L$1004,'Sales Log'!$A$5:$A$1004,">="&M$44,'Sales Log'!$A$5:$A$1004,"<"&DATE(YEAR(M$44),MONTH(M$44)+1,1),'Sales Log'!$B$5:$B$1004,$A45,'Sales Log'!$R$5:$R$1004,"<>EXAMPLE") -> 0 | N45: =SUM(B45:M45) -> 0
A46: ='Chart of Accounts'!$A$67 -> IngramSpark | B46: =SUMIFS('Sales Log'!$L$5:$L$1004,'Sales Log'!$A$5:$A$1004,">="&B$44,'Sales Log'!$A$5:$A$1004,"<"&DATE(YEAR(B$44),MONTH(B$44)+1,1),'Sales Log'!$B$5:$B$1004,$A46,'Sales Log'!$R$5:$R$1004,"<>EXAMPLE") -> 0 | C46: =SUMIFS('Sales Log'!$L$5:$L$1004,'Sales Log'!$A$5:$A$1004,">="&C$44,'Sales Log'!$A$5:$A$1004,"<"&DATE(YEAR(C$44),MONTH(C$44)+1,1),'Sales Log'!$B$5:$B$1004,$A46,'Sales Log'!$R$5:$R$1004,"<>EXAMPLE") -> 0 | D46: =SUMIFS('Sales Log'!$L$5:$L$1004,'Sales Log'!$A$5:$A$1004,">="&D$44,'Sales Log'!$A$5:$A$1004,"<"&DATE(YEAR(D$44),MONTH(D$44)+1,1),'Sales Log'!$B$5:$B$1004,$A46,'Sales Log'!$R$5:$R$1004,"<>EXAMPLE") -> 0 | E46: =SUMIFS('Sales Log'!$L$5:$L$1004,'Sales Log'!$A$5:$A$1004,">="&E$44,'Sales Log'!$A$5:$A$1004,"<"&DATE(YEAR(E$44),MONTH(E$44)+1,1),'Sales Log'!$B$5:$B$1004,$A46,'Sales Log'!$R$5:$R$1004,"<>EXAMPLE") -> 0 | F46: =SUMIFS('Sales Log'!$L$5:$L$1004,'Sales Log'!$A$5:$A$1004,">="&F$44,'Sales Log'!$A$5:$A$1004,"<"&DATE(YEAR(F$44),MONTH(F$44)+1,1),'Sales Log'!$B$5:$B$1004,$A46,'Sales Log'!$R$5:$R$1004,"<>EXAMPLE") -> 0 | G46: =SUMIFS('Sales Log'!$L$5:$L$1004,'Sales Log'!$A$5:$A$1004,">="&G$44,'Sales Log'!$A$5:$A$1004,"<"&DATE(YEAR(G$44),MONTH(G$44)+1,1),'Sales Log'!$B$5:$B$1004,$A46,'Sales Log'!$R$5:$R$1004,"<>EXAMPLE") -> 0 | H46: =SUMIFS('Sales Log'!$L$5:$L$1004,'Sales Log'!$A$5:$A$1004,">="&H$44,'Sales Log'!$A$5:$A$1004,"<"&DATE(YEAR(H$44),MONTH(H$44)+1,1),'Sales Log'!$B$5:$B$1004,$A46,'Sales Log'!$R$5:$R$1004,"<>EXAMPLE") -> 0 | I46: =SUMIFS('Sales Log'!$L$5:$L$1004,'Sales Log'!$A$5:$A$1004,">="&I$44,'Sales Log'!$A$5:$A$1004,"<"&DATE(YEAR(I$44),MONTH(I$44)+1,1),'Sales Log'!$B$5:$B$1004,$A46,'Sales Log'!$R$5:$R$1004,"<>EXAMPLE") -> 0 | ... M46: =SUMIFS('Sales Log'!$L$5:$L$1004,'Sales Log'!$A$5:$A$1004,">="&M$44,'Sales Log'!$A$5:$A$1004,"<"&DATE(YEAR(M$44),MONTH(M$44)+1,1),'Sales Log'!$B$5:$B$1004,$A46,'Sales Log'!$R$5:$R$1004,"<>EXAMPLE") -> 0 | N46: =SUM(B46:M46) -> 0
A47: ='Chart of Accounts'!$A$68 -> Etsy | B47: =SUMIFS('Sales Log'!$L$5:$L$1004,'Sales Log'!$A$5:$A$1004,">="&B$44,'Sales Log'!$A$5:$A$1004,"<"&DATE(YEAR(B$44),MONTH(B$44)+1,1),'Sales Log'!$B$5:$B$1004,$A47,'Sales Log'!$R$5:$R$1004,"<>EXAMPLE") -> 0 | C47: =SUMIFS('Sales Log'!$L$5:$L$1004,'Sales Log'!$A$5:$A$1004,">="&C$44,'Sales Log'!$A$5:$A$1004,"<"&DATE(YEAR(C$44),MONTH(C$44)+1,1),'Sales Log'!$B$5:$B$1004,$A47,'Sales Log'!$R$5:$R$1004,"<>EXAMPLE") -> 0 | D47: =SUMIFS('Sales Log'!$L$5:$L$1004,'Sales Log'!$A$5:$A$1004,">="&D$44,'Sales Log'!$A$5:$A$1004,"<"&DATE(YEAR(D$44),MONTH(D$44)+1,1),'Sales Log'!$B$5:$B$1004,$A47,'Sales Log'!$R$5:$R$1004,"<>EXAMPLE") -> 0 | E47: =SUMIFS('Sales Log'!$L$5:$L$1004,'Sales Log'!$A$5:$A$1004,">="&E$44,'Sales Log'!$A$5:$A$1004,"<"&DATE(YEAR(E$44),MONTH(E$44)+1,1),'Sales Log'!$B$5:$B$1004,$A47,'Sales Log'!$R$5:$R$1004,"<>EXAMPLE") -> 0 | F47: =SUMIFS('Sales Log'!$L$5:$L$1004,'Sales Log'!$A$5:$A$1004,">="&F$44,'Sales Log'!$A$5:$A$1004,"<"&DATE(YEAR(F$44),MONTH(F$44)+1,1),'Sales Log'!$B$5:$B$1004,$A47,'Sales Log'!$R$5:$R$1004,"<>EXAMPLE") -> 0 | G47: =SUMIFS('Sales Log'!$L$5:$L$1004,'Sales Log'!$A$5:$A$1004,">="&G$44,'Sales Log'!$A$5:$A$1004,"<"&DATE(YEAR(G$44),MONTH(G$44)+1,1),'Sales Log'!$B$5:$B$1004,$A47,'Sales Log'!$R$5:$R$1004,"<>EXAMPLE") -> 0 | H47: =SUMIFS('Sales Log'!$L$5:$L$1004,'Sales Log'!$A$5:$A$1004,">="&H$44,'Sales Log'!$A$5:$A$1004,"<"&DATE(YEAR(H$44),MONTH(H$44)+1,1),'Sales Log'!$B$5:$B$1004,$A47,'Sales Log'!$R$5:$R$1004,"<>EXAMPLE") -> 0 | I47: =SUMIFS('Sales Log'!$L$5:$L$1004,'Sales Log'!$A$5:$A$1004,">="&I$44,'Sales Log'!$A$5:$A$1004,"<"&DATE(YEAR(I$44),MONTH(I$44)+1,1),'Sales Log'!$B$5:$B$1004,$A47,'Sales Log'!$R$5:$R$1004,"<>EXAMPLE") -> 0 | ... M47: =SUMIFS('Sales Log'!$L$5:$L$1004,'Sales Log'!$A$5:$A$1004,">="&M$44,'Sales Log'!$A$5:$A$1004,"<"&DATE(YEAR(M$44),MONTH(M$44)+1,1),'Sales Log'!$B$5:$B$1004,$A47,'Sales Log'!$R$5:$R$1004,"<>EXAMPLE") -> 0 | N47: =SUM(B47:M47) -> 0
A48: ='Chart of Accounts'!$A$69 -> Teachers Pay Teachers | B48: =SUMIFS('Sales Log'!$L$5:$L$1004,'Sales Log'!$A$5:$A$1004,">="&B$44,'Sales Log'!$A$5:$A$1004,"<"&DATE(YEAR(B$44),MONTH(B$44)+1,1),'Sales Log'!$B$5:$B$1004,$A48,'Sales Log'!$R$5:$R$1004,"<>EXAMPLE") -> 0 | C48: =SUMIFS('Sales Log'!$L$5:$L$1004,'Sales Log'!$A$5:$A$1004,">="&C$44,'Sales Log'!$A$5:$A$1004,"<"&DATE(YEAR(C$44),MONTH(C$44)+1,1),'Sales Log'!$B$5:$B$1004,$A48,'Sales Log'!$R$5:$R$1004,"<>EXAMPLE") -> 0 | D48: =SUMIFS('Sales Log'!$L$5:$L$1004,'Sales Log'!$A$5:$A$1004,">="&D$44,'Sales Log'!$A$5:$A$1004,"<"&DATE(YEAR(D$44),MONTH(D$44)+1,1),'Sales Log'!$B$5:$B$1004,$A48,'Sales Log'!$R$5:$R$1004,"<>EXAMPLE") -> 0 | E48: =SUMIFS('Sales Log'!$L$5:$L$1004,'Sales Log'!$A$5:$A$1004,">="&E$44,'Sales Log'!$A$5:$A$1004,"<"&DATE(YEAR(E$44),MONTH(E$44)+1,1),'Sales Log'!$B$5:$B$1004,$A48,'Sales Log'!$R$5:$R$1004,"<>EXAMPLE") -> 0 | F48: =SUMIFS('Sales Log'!$L$5:$L$1004,'Sales Log'!$A$5:$A$1004,">="&F$44,'Sales Log'!$A$5:$A$1004,"<"&DATE(YEAR(F$44),MONTH(F$44)+1,1),'Sales Log'!$B$5:$B$1004,$A48,'Sales Log'!$R$5:$R$1004,"<>EXAMPLE") -> 0 | G48: =SUMIFS('Sales Log'!$L$5:$L$1004,'Sales Log'!$A$5:$A$1004,">="&G$44,'Sales Log'!$A$5:$A$1004,"<"&DATE(YEAR(G$44),MONTH(G$44)+1,1),'Sales Log'!$B$5:$B$1004,$A48,'Sales Log'!$R$5:$R$1004,"<>EXAMPLE") -> 0 | H48: =SUMIFS('Sales Log'!$L$5:$L$1004,'Sales Log'!$A$5:$A$1004,">="&H$44,'Sales Log'!$A$5:$A$1004,"<"&DATE(YEAR(H$44),MONTH(H$44)+1,1),'Sales Log'!$B$5:$B$1004,$A48,'Sales Log'!$R$5:$R$1004,"<>EXAMPLE") -> 0 | I48: =SUMIFS('Sales Log'!$L$5:$L$1004,'Sales Log'!$A$5:$A$1004,">="&I$44,'Sales Log'!$A$5:$A$1004,"<"&DATE(YEAR(I$44),MONTH(I$44)+1,1),'Sales Log'!$B$5:$B$1004,$A48,'Sales Log'!$R$5:$R$1004,"<>EXAMPLE") -> 0 | ... M48: =SUMIFS('Sales Log'!$L$5:$L$1004,'Sales Log'!$A$5:$A$1004,">="&M$44,'Sales Log'!$A$5:$A$1004,"<"&DATE(YEAR(M$44),MONTH(M$44)+1,1),'Sales Log'!$B$5:$B$1004,$A48,'Sales Log'!$R$5:$R$1004,"<>EXAMPLE") -> 0 | N48: =SUM(B48:M48) -> 0
A49: ='Chart of Accounts'!$A$70 -> TikTok Shop | B49: =SUMIFS('Sales Log'!$L$5:$L$1004,'Sales Log'!$A$5:$A$1004,">="&B$44,'Sales Log'!$A$5:$A$1004,"<"&DATE(YEAR(B$44),MONTH(B$44)+1,1),'Sales Log'!$B$5:$B$1004,$A49,'Sales Log'!$R$5:$R$1004,"<>EXAMPLE") -> 0 | C49: =SUMIFS('Sales Log'!$L$5:$L$1004,'Sales Log'!$A$5:$A$1004,">="&C$44,'Sales Log'!$A$5:$A$1004,"<"&DATE(YEAR(C$44),MONTH(C$44)+1,1),'Sales Log'!$B$5:$B$1004,$A49,'Sales Log'!$R$5:$R$1004,"<>EXAMPLE") -> 0 | D49: =SUMIFS('Sales Log'!$L$5:$L$1004,'Sales Log'!$A$5:$A$1004,">="&D$44,'Sales Log'!$A$5:$A$1004,"<"&DATE(YEAR(D$44),MONTH(D$44)+1,1),'Sales Log'!$B$5:$B$1004,$A49,'Sales Log'!$R$5:$R$1004,"<>EXAMPLE") -> 0 | E49: =SUMIFS('Sales Log'!$L$5:$L$1004,'Sales Log'!$A$5:$A$1004,">="&E$44,'Sales Log'!$A$5:$A$1004,"<"&DATE(YEAR(E$44),MONTH(E$44)+1,1),'Sales Log'!$B$5:$B$1004,$A49,'Sales Log'!$R$5:$R$1004,"<>EXAMPLE") -> 0 | F49: =SUMIFS('Sales Log'!$L$5:$L$1004,'Sales Log'!$A$5:$A$1004,">="&F$44,'Sales Log'!$A$5:$A$1004,"<"&DATE(YEAR(F$44),MONTH(F$44)+1,1),'Sales Log'!$B$5:$B$1004,$A49,'Sales Log'!$R$5:$R$1004,"<>EXAMPLE") -> 0 | G49: =SUMIFS('Sales Log'!$L$5:$L$1004,'Sales Log'!$A$5:$A$1004,">="&G$44,'Sales Log'!$A$5:$A$1004,"<"&DATE(YEAR(G$44),MONTH(G$44)+1,1),'Sales Log'!$B$5:$B$1004,$A49,'Sales Log'!$R$5:$R$1004,"<>EXAMPLE") -> 0 | H49: =SUMIFS('Sales Log'!$L$5:$L$1004,'Sales Log'!$A$5:$A$1004,">="&H$44,'Sales Log'!$A$5:$A$1004,"<"&DATE(YEAR(H$44),MONTH(H$44)+1,1),'Sales Log'!$B$5:$B$1004,$A49,'Sales Log'!$R$5:$R$1004,"<>EXAMPLE") -> 0 | I49: =SUMIFS('Sales Log'!$L$5:$L$1004,'Sales Log'!$A$5:$A$1004,">="&I$44,'Sales Log'!$A$5:$A$1004,"<"&DATE(YEAR(I$44),MONTH(I$44)+1,1),'Sales Log'!$B$5:$B$1004,$A49,'Sales Log'!$R$5:$R$1004,"<>EXAMPLE") -> 0 | ... M49: =SUMIFS('Sales Log'!$L$5:$L$1004,'Sales Log'!$A$5:$A$1004,">="&M$44,'Sales Log'!$A$5:$A$1004,"<"&DATE(YEAR(M$44),MONTH(M$44)+1,1),'Sales Log'!$B$5:$B$1004,$A49,'Sales Log'!$R$5:$R$1004,"<>EXAMPLE") -> 0 | N49: =SUM(B49:M49) -> 0
A50: ='Chart of Accounts'!$A$71 -> Shopify (website store) | B50: =SUMIFS('Sales Log'!$L$5:$L$1004,'Sales Log'!$A$5:$A$1004,">="&B$44,'Sales Log'!$A$5:$A$1004,"<"&DATE(YEAR(B$44),MONTH(B$44)+1,1),'Sales Log'!$B$5:$B$1004,$A50,'Sales Log'!$R$5:$R$1004,"<>EXAMPLE") -> 0 | C50: =SUMIFS('Sales Log'!$L$5:$L$1004,'Sales Log'!$A$5:$A$1004,">="&C$44,'Sales Log'!$A$5:$A$1004,"<"&DATE(YEAR(C$44),MONTH(C$44)+1,1),'Sales Log'!$B$5:$B$1004,$A50,'Sales Log'!$R$5:$R$1004,"<>EXAMPLE") -> 0 | D50: =SUMIFS('Sales Log'!$L$5:$L$1004,'Sales Log'!$A$5:$A$1004,">="&D$44,'Sales Log'!$A$5:$A$1004,"<"&DATE(YEAR(D$44),MONTH(D$44)+1,1),'Sales Log'!$B$5:$B$1004,$A50,'Sales Log'!$R$5:$R$1004,"<>EXAMPLE") -> 0 | E50: =SUMIFS('Sales Log'!$L$5:$L$1004,'Sales Log'!$A$5:$A$1004,">="&E$44,'Sales Log'!$A$5:$A$1004,"<"&DATE(YEAR(E$44),MONTH(E$44)+1,1),'Sales Log'!$B$5:$B$1004,$A50,'Sales Log'!$R$5:$R$1004,"<>EXAMPLE") -> 0 | F50: =SUMIFS('Sales Log'!$L$5:$L$1004,'Sales Log'!$A$5:$A$1004,">="&F$44,'Sales Log'!$A$5:$A$1004,"<"&DATE(YEAR(F$44),MONTH(F$44)+1,1),'Sales Log'!$B$5:$B$1004,$A50,'Sales Log'!$R$5:$R$1004,"<>EXAMPLE") -> 0 | G50: =SUMIFS('Sales Log'!$L$5:$L$1004,'Sales Log'!$A$5:$A$1004,">="&G$44,'Sales Log'!$A$5:$A$1004,"<"&DATE(YEAR(G$44),MONTH(G$44)+1,1),'Sales Log'!$B$5:$B$1004,$A50,'Sales Log'!$R$5:$R$1004,"<>EXAMPLE") -> 0 | H50: =SUMIFS('Sales Log'!$L$5:$L$1004,'Sales Log'!$A$5:$A$1004,">="&H$44,'Sales Log'!$A$5:$A$1004,"<"&DATE(YEAR(H$44),MONTH(H$44)+1,1),'Sales Log'!$B$5:$B$1004,$A50,'Sales Log'!$R$5:$R$1004,"<>EXAMPLE") -> 0 | I50: =SUMIFS('Sales Log'!$L$5:$L$1004,'Sales Log'!$A$5:$A$1004,">="&I$44,'Sales Log'!$A$5:$A$1004,"<"&DATE(YEAR(I$44),MONTH(I$44)+1,1),'Sales Log'!$B$5:$B$1004,$A50,'Sales Log'!$R$5:$R$1004,"<>EXAMPLE") -> 0 | ... M50: =SUMIFS('Sales Log'!$L$5:$L$1004,'Sales Log'!$A$5:$A$1004,">="&M$44,'Sales Log'!$A$5:$A$1004,"<"&DATE(YEAR(M$44),MONTH(M$44)+1,1),'Sales Log'!$B$5:$B$1004,$A50,'Sales Log'!$R$5:$R$1004,"<>EXAMPLE") -> 0 | N50: =SUM(B50:M50) -> 0
A51: ='Chart of Accounts'!$A$72 -> Stripe (website & invoices) | B51: =SUMIFS('Sales Log'!$L$5:$L$1004,'Sales Log'!$A$5:$A$1004,">="&B$44,'Sales Log'!$A$5:$A$1004,"<"&DATE(YEAR(B$44),MONTH(B$44)+1,1),'Sales Log'!$B$5:$B$1004,$A51,'Sales Log'!$R$5:$R$1004,"<>EXAMPLE") -> 0 | C51: =SUMIFS('Sales Log'!$L$5:$L$1004,'Sales Log'!$A$5:$A$1004,">="&C$44,'Sales Log'!$A$5:$A$1004,"<"&DATE(YEAR(C$44),MONTH(C$44)+1,1),'Sales Log'!$B$5:$B$1004,$A51,'Sales Log'!$R$5:$R$1004,"<>EXAMPLE") -> 0 | D51: =SUMIFS('Sales Log'!$L$5:$L$1004,'Sales Log'!$A$5:$A$1004,">="&D$44,'Sales Log'!$A$5:$A$1004,"<"&DATE(YEAR(D$44),MONTH(D$44)+1,1),'Sales Log'!$B$5:$B$1004,$A51,'Sales Log'!$R$5:$R$1004,"<>EXAMPLE") -> 0 | E51: =SUMIFS('Sales Log'!$L$5:$L$1004,'Sales Log'!$A$5:$A$1004,">="&E$44,'Sales Log'!$A$5:$A$1004,"<"&DATE(YEAR(E$44),MONTH(E$44)+1,1),'Sales Log'!$B$5:$B$1004,$A51,'Sales Log'!$R$5:$R$1004,"<>EXAMPLE") -> 0 | F51: =SUMIFS('Sales Log'!$L$5:$L$1004,'Sales Log'!$A$5:$A$1004,">="&F$44,'Sales Log'!$A$5:$A$1004,"<"&DATE(YEAR(F$44),MONTH(F$44)+1,1),'Sales Log'!$B$5:$B$1004,$A51,'Sales Log'!$R$5:$R$1004,"<>EXAMPLE") -> 0 | G51: =SUMIFS('Sales Log'!$L$5:$L$1004,'Sales Log'!$A$5:$A$1004,">="&G$44,'Sales Log'!$A$5:$A$1004,"<"&DATE(YEAR(G$44),MONTH(G$44)+1,1),'Sales Log'!$B$5:$B$1004,$A51,'Sales Log'!$R$5:$R$1004,"<>EXAMPLE") -> 0 | H51: =SUMIFS('Sales Log'!$L$5:$L$1004,'Sales Log'!$A$5:$A$1004,">="&H$44,'Sales Log'!$A$5:$A$1004,"<"&DATE(YEAR(H$44),MONTH(H$44)+1,1),'Sales Log'!$B$5:$B$1004,$A51,'Sales Log'!$R$5:$R$1004,"<>EXAMPLE") -> 0 | I51: =SUMIFS('Sales Log'!$L$5:$L$1004,'Sales Log'!$A$5:$A$1004,">="&I$44,'Sales Log'!$A$5:$A$1004,"<"&DATE(YEAR(I$44),MONTH(I$44)+1,1),'Sales Log'!$B$5:$B$1004,$A51,'Sales Log'!$R$5:$R$1004,"<>EXAMPLE") -> 0 | ... M51: =SUMIFS('Sales Log'!$L$5:$L$1004,'Sales Log'!$A$5:$A$1004,">="&M$44,'Sales Log'!$A$5:$A$1004,"<"&DATE(YEAR(M$44),MONTH(M$44)+1,1),'Sales Log'!$B$5:$B$1004,$A51,'Sales Log'!$R$5:$R$1004,"<>EXAMPLE") -> 0 | N51: =SUM(B51:M51) -> 0
A52: ='Chart of Accounts'!$A$73 -> PayPal Business | B52: =SUMIFS('Sales Log'!$L$5:$L$1004,'Sales Log'!$A$5:$A$1004,">="&B$44,'Sales Log'!$A$5:$A$1004,"<"&DATE(YEAR(B$44),MONTH(B$44)+1,1),'Sales Log'!$B$5:$B$1004,$A52,'Sales Log'!$R$5:$R$1004,"<>EXAMPLE") -> 0 | C52: =SUMIFS('Sales Log'!$L$5:$L$1004,'Sales Log'!$A$5:$A$1004,">="&C$44,'Sales Log'!$A$5:$A$1004,"<"&DATE(YEAR(C$44),MONTH(C$44)+1,1),'Sales Log'!$B$5:$B$1004,$A52,'Sales Log'!$R$5:$R$1004,"<>EXAMPLE") -> 0 | D52: =SUMIFS('Sales Log'!$L$5:$L$1004,'Sales Log'!$A$5:$A$1004,">="&D$44,'Sales Log'!$A$5:$A$1004,"<"&DATE(YEAR(D$44),MONTH(D$44)+1,1),'Sales Log'!$B$5:$B$1004,$A52,'Sales Log'!$R$5:$R$1004,"<>EXAMPLE") -> 0 | E52: =SUMIFS('Sales Log'!$L$5:$L$1004,'Sales Log'!$A$5:$A$1004,">="&E$44,'Sales Log'!$A$5:$A$1004,"<"&DATE(YEAR(E$44),MONTH(E$44)+1,1),'Sales Log'!$B$5:$B$1004,$A52,'Sales Log'!$R$5:$R$1004,"<>EXAMPLE") -> 0 | F52: =SUMIFS('Sales Log'!$L$5:$L$1004,'Sales Log'!$A$5:$A$1004,">="&F$44,'Sales Log'!$A$5:$A$1004,"<"&DATE(YEAR(F$44),MONTH(F$44)+1,1),'Sales Log'!$B$5:$B$1004,$A52,'Sales Log'!$R$5:$R$1004,"<>EXAMPLE") -> 0 | G52: =SUMIFS('Sales Log'!$L$5:$L$1004,'Sales Log'!$A$5:$A$1004,">="&G$44,'Sales Log'!$A$5:$A$1004,"<"&DATE(YEAR(G$44),MONTH(G$44)+1,1),'Sales Log'!$B$5:$B$1004,$A52,'Sales Log'!$R$5:$R$1004,"<>EXAMPLE") -> 0 | H52: =SUMIFS('Sales Log'!$L$5:$L$1004,'Sales Log'!$A$5:$A$1004,">="&H$44,'Sales Log'!$A$5:$A$1004,"<"&DATE(YEAR(H$44),MONTH(H$44)+1,1),'Sales Log'!$B$5:$B$1004,$A52,'Sales Log'!$R$5:$R$1004,"<>EXAMPLE") -> 0 | I52: =SUMIFS('Sales Log'!$L$5:$L$1004,'Sales Log'!$A$5:$A$1004,">="&I$44,'Sales Log'!$A$5:$A$1004,"<"&DATE(YEAR(I$44),MONTH(I$44)+1,1),'Sales Log'!$B$5:$B$1004,$A52,'Sales Log'!$R$5:$R$1004,"<>EXAMPLE") -> 0 | ... M52: =SUMIFS('Sales Log'!$L$5:$L$1004,'Sales Log'!$A$5:$A$1004,">="&M$44,'Sales Log'!$A$5:$A$1004,"<"&DATE(YEAR(M$44),MONTH(M$44)+1,1),'Sales Log'!$B$5:$B$1004,$A52,'Sales Log'!$R$5:$R$1004,"<>EXAMPLE") -> 0 | N52: =SUM(B52:M52) -> 0
A53: ='Chart of Accounts'!$A$74 -> Meta shop (FB/IG) | B53: =SUMIFS('Sales Log'!$L$5:$L$1004,'Sales Log'!$A$5:$A$1004,">="&B$44,'Sales Log'!$A$5:$A$1004,"<"&DATE(YEAR(B$44),MONTH(B$44)+1,1),'Sales Log'!$B$5:$B$1004,$A53,'Sales Log'!$R$5:$R$1004,"<>EXAMPLE") -> 0 | C53: =SUMIFS('Sales Log'!$L$5:$L$1004,'Sales Log'!$A$5:$A$1004,">="&C$44,'Sales Log'!$A$5:$A$1004,"<"&DATE(YEAR(C$44),MONTH(C$44)+1,1),'Sales Log'!$B$5:$B$1004,$A53,'Sales Log'!$R$5:$R$1004,"<>EXAMPLE") -> 0 | D53: =SUMIFS('Sales Log'!$L$5:$L$1004,'Sales Log'!$A$5:$A$1004,">="&D$44,'Sales Log'!$A$5:$A$1004,"<"&DATE(YEAR(D$44),MONTH(D$44)+1,1),'Sales Log'!$B$5:$B$1004,$A53,'Sales Log'!$R$5:$R$1004,"<>EXAMPLE") -> 0 | E53: =SUMIFS('Sales Log'!$L$5:$L$1004,'Sales Log'!$A$5:$A$1004,">="&E$44,'Sales Log'!$A$5:$A$1004,"<"&DATE(YEAR(E$44),MONTH(E$44)+1,1),'Sales Log'!$B$5:$B$1004,$A53,'Sales Log'!$R$5:$R$1004,"<>EXAMPLE") -> 0 | F53: =SUMIFS('Sales Log'!$L$5:$L$1004,'Sales Log'!$A$5:$A$1004,">="&F$44,'Sales Log'!$A$5:$A$1004,"<"&DATE(YEAR(F$44),MONTH(F$44)+1,1),'Sales Log'!$B$5:$B$1004,$A53,'Sales Log'!$R$5:$R$1004,"<>EXAMPLE") -> 0 | G53: =SUMIFS('Sales Log'!$L$5:$L$1004,'Sales Log'!$A$5:$A$1004,">="&G$44,'Sales Log'!$A$5:$A$1004,"<"&DATE(YEAR(G$44),MONTH(G$44)+1,1),'Sales Log'!$B$5:$B$1004,$A53,'Sales Log'!$R$5:$R$1004,"<>EXAMPLE") -> 0 | H53: =SUMIFS('Sales Log'!$L$5:$L$1004,'Sales Log'!$A$5:$A$1004,">="&H$44,'Sales Log'!$A$5:$A$1004,"<"&DATE(YEAR(H$44),MONTH(H$44)+1,1),'Sales Log'!$B$5:$B$1004,$A53,'Sales Log'!$R$5:$R$1004,"<>EXAMPLE") -> 0 | I53: =SUMIFS('Sales Log'!$L$5:$L$1004,'Sales Log'!$A$5:$A$1004,">="&I$44,'Sales Log'!$A$5:$A$1004,"<"&DATE(YEAR(I$44),MONTH(I$44)+1,1),'Sales Log'!$B$5:$B$1004,$A53,'Sales Log'!$R$5:$R$1004,"<>EXAMPLE") -> 0 | ... M53: =SUMIFS('Sales Log'!$L$5:$L$1004,'Sales Log'!$A$5:$A$1004,">="&M$44,'Sales Log'!$A$5:$A$1004,"<"&DATE(YEAR(M$44),MONTH(M$44)+1,1),'Sales Log'!$B$5:$B$1004,$A53,'Sales Log'!$R$5:$R$1004,"<>EXAMPLE") -> 0 | N53: =SUM(B53:M53) -> 0
A54: ='Chart of Accounts'!$A$75 -> Faire (wholesale) | B54: =SUMIFS('Sales Log'!$L$5:$L$1004,'Sales Log'!$A$5:$A$1004,">="&B$44,'Sales Log'!$A$5:$A$1004,"<"&DATE(YEAR(B$44),MONTH(B$44)+1,1),'Sales Log'!$B$5:$B$1004,$A54,'Sales Log'!$R$5:$R$1004,"<>EXAMPLE") -> 0 | C54: =SUMIFS('Sales Log'!$L$5:$L$1004,'Sales Log'!$A$5:$A$1004,">="&C$44,'Sales Log'!$A$5:$A$1004,"<"&DATE(YEAR(C$44),MONTH(C$44)+1,1),'Sales Log'!$B$5:$B$1004,$A54,'Sales Log'!$R$5:$R$1004,"<>EXAMPLE") -> 0 | D54: =SUMIFS('Sales Log'!$L$5:$L$1004,'Sales Log'!$A$5:$A$1004,">="&D$44,'Sales Log'!$A$5:$A$1004,"<"&DATE(YEAR(D$44),MONTH(D$44)+1,1),'Sales Log'!$B$5:$B$1004,$A54,'Sales Log'!$R$5:$R$1004,"<>EXAMPLE") -> 0 | E54: =SUMIFS('Sales Log'!$L$5:$L$1004,'Sales Log'!$A$5:$A$1004,">="&E$44,'Sales Log'!$A$5:$A$1004,"<"&DATE(YEAR(E$44),MONTH(E$44)+1,1),'Sales Log'!$B$5:$B$1004,$A54,'Sales Log'!$R$5:$R$1004,"<>EXAMPLE") -> 0 | F54: =SUMIFS('Sales Log'!$L$5:$L$1004,'Sales Log'!$A$5:$A$1004,">="&F$44,'Sales Log'!$A$5:$A$1004,"<"&DATE(YEAR(F$44),MONTH(F$44)+1,1),'Sales Log'!$B$5:$B$1004,$A54,'Sales Log'!$R$5:$R$1004,"<>EXAMPLE") -> 0 | G54: =SUMIFS('Sales Log'!$L$5:$L$1004,'Sales Log'!$A$5:$A$1004,">="&G$44,'Sales Log'!$A$5:$A$1004,"<"&DATE(YEAR(G$44),MONTH(G$44)+1,1),'Sales Log'!$B$5:$B$1004,$A54,'Sales Log'!$R$5:$R$1004,"<>EXAMPLE") -> 0 | H54: =SUMIFS('Sales Log'!$L$5:$L$1004,'Sales Log'!$A$5:$A$1004,">="&H$44,'Sales Log'!$A$5:$A$1004,"<"&DATE(YEAR(H$44),MONTH(H$44)+1,1),'Sales Log'!$B$5:$B$1004,$A54,'Sales Log'!$R$5:$R$1004,"<>EXAMPLE") -> 0 | I54: =SUMIFS('Sales Log'!$L$5:$L$1004,'Sales Log'!$A$5:$A$1004,">="&I$44,'Sales Log'!$A$5:$A$1004,"<"&DATE(YEAR(I$44),MONTH(I$44)+1,1),'Sales Log'!$B$5:$B$1004,$A54,'Sales Log'!$R$5:$R$1004,"<>EXAMPLE") -> 0 | ... M54: =SUMIFS('Sales Log'!$L$5:$L$1004,'Sales Log'!$A$5:$A$1004,">="&M$44,'Sales Log'!$A$5:$A$1004,"<"&DATE(YEAR(M$44),MONTH(M$44)+1,1),'Sales Log'!$B$5:$B$1004,$A54,'Sales Log'!$R$5:$R$1004,"<>EXAMPLE") -> 0 | N54: =SUM(B54:M54) -> 0
A55: ='Chart of Accounts'!$A$76 -> Merchant of record | B55: =SUMIFS('Sales Log'!$L$5:$L$1004,'Sales Log'!$A$5:$A$1004,">="&B$44,'Sales Log'!$A$5:$A$1004,"<"&DATE(YEAR(B$44),MONTH(B$44)+1,1),'Sales Log'!$B$5:$B$1004,$A55,'Sales Log'!$R$5:$R$1004,"<>EXAMPLE") -> 0 | C55: =SUMIFS('Sales Log'!$L$5:$L$1004,'Sales Log'!$A$5:$A$1004,">="&C$44,'Sales Log'!$A$5:$A$1004,"<"&DATE(YEAR(C$44),MONTH(C$44)+1,1),'Sales Log'!$B$5:$B$1004,$A55,'Sales Log'!$R$5:$R$1004,"<>EXAMPLE") -> 0 | D55: =SUMIFS('Sales Log'!$L$5:$L$1004,'Sales Log'!$A$5:$A$1004,">="&D$44,'Sales Log'!$A$5:$A$1004,"<"&DATE(YEAR(D$44),MONTH(D$44)+1,1),'Sales Log'!$B$5:$B$1004,$A55,'Sales Log'!$R$5:$R$1004,"<>EXAMPLE") -> 0 | E55: =SUMIFS('Sales Log'!$L$5:$L$1004,'Sales Log'!$A$5:$A$1004,">="&E$44,'Sales Log'!$A$5:$A$1004,"<"&DATE(YEAR(E$44),MONTH(E$44)+1,1),'Sales Log'!$B$5:$B$1004,$A55,'Sales Log'!$R$5:$R$1004,"<>EXAMPLE") -> 0 | F55: =SUMIFS('Sales Log'!$L$5:$L$1004,'Sales Log'!$A$5:$A$1004,">="&F$44,'Sales Log'!$A$5:$A$1004,"<"&DATE(YEAR(F$44),MONTH(F$44)+1,1),'Sales Log'!$B$5:$B$1004,$A55,'Sales Log'!$R$5:$R$1004,"<>EXAMPLE") -> 0 | G55: =SUMIFS('Sales Log'!$L$5:$L$1004,'Sales Log'!$A$5:$A$1004,">="&G$44,'Sales Log'!$A$5:$A$1004,"<"&DATE(YEAR(G$44),MONTH(G$44)+1,1),'Sales Log'!$B$5:$B$1004,$A55,'Sales Log'!$R$5:$R$1004,"<>EXAMPLE") -> 0 | H55: =SUMIFS('Sales Log'!$L$5:$L$1004,'Sales Log'!$A$5:$A$1004,">="&H$44,'Sales Log'!$A$5:$A$1004,"<"&DATE(YEAR(H$44),MONTH(H$44)+1,1),'Sales Log'!$B$5:$B$1004,$A55,'Sales Log'!$R$5:$R$1004,"<>EXAMPLE") -> 0 | I55: =SUMIFS('Sales Log'!$L$5:$L$1004,'Sales Log'!$A$5:$A$1004,">="&I$44,'Sales Log'!$A$5:$A$1004,"<"&DATE(YEAR(I$44),MONTH(I$44)+1,1),'Sales Log'!$B$5:$B$1004,$A55,'Sales Log'!$R$5:$R$1004,"<>EXAMPLE") -> 0 | ... M55: =SUMIFS('Sales Log'!$L$5:$L$1004,'Sales Log'!$A$5:$A$1004,">="&M$44,'Sales Log'!$A$5:$A$1004,"<"&DATE(YEAR(M$44),MONTH(M$44)+1,1),'Sales Log'!$B$5:$B$1004,$A55,'Sales Log'!$R$5:$R$1004,"<>EXAMPLE") -> 0 | N55: =SUM(B55:M55) -> 0
A56: ='Chart of Accounts'!$A$77 -> Amazon Associates | B56: =SUMIFS('Sales Log'!$L$5:$L$1004,'Sales Log'!$A$5:$A$1004,">="&B$44,'Sales Log'!$A$5:$A$1004,"<"&DATE(YEAR(B$44),MONTH(B$44)+1,1),'Sales Log'!$B$5:$B$1004,$A56,'Sales Log'!$R$5:$R$1004,"<>EXAMPLE") -> 0 | C56: =SUMIFS('Sales Log'!$L$5:$L$1004,'Sales Log'!$A$5:$A$1004,">="&C$44,'Sales Log'!$A$5:$A$1004,"<"&DATE(YEAR(C$44),MONTH(C$44)+1,1),'Sales Log'!$B$5:$B$1004,$A56,'Sales Log'!$R$5:$R$1004,"<>EXAMPLE") -> 0 | D56: =SUMIFS('Sales Log'!$L$5:$L$1004,'Sales Log'!$A$5:$A$1004,">="&D$44,'Sales Log'!$A$5:$A$1004,"<"&DATE(YEAR(D$44),MONTH(D$44)+1,1),'Sales Log'!$B$5:$B$1004,$A56,'Sales Log'!$R$5:$R$1004,"<>EXAMPLE") -> 0 | E56: =SUMIFS('Sales Log'!$L$5:$L$1004,'Sales Log'!$A$5:$A$1004,">="&E$44,'Sales Log'!$A$5:$A$1004,"<"&DATE(YEAR(E$44),MONTH(E$44)+1,1),'Sales Log'!$B$5:$B$1004,$A56,'Sales Log'!$R$5:$R$1004,"<>EXAMPLE") -> 0 | F56: =SUMIFS('Sales Log'!$L$5:$L$1004,'Sales Log'!$A$5:$A$1004,">="&F$44,'Sales Log'!$A$5:$A$1004,"<"&DATE(YEAR(F$44),MONTH(F$44)+1,1),'Sales Log'!$B$5:$B$1004,$A56,'Sales Log'!$R$5:$R$1004,"<>EXAMPLE") -> 0 | G56: =SUMIFS('Sales Log'!$L$5:$L$1004,'Sales Log'!$A$5:$A$1004,">="&G$44,'Sales Log'!$A$5:$A$1004,"<"&DATE(YEAR(G$44),MONTH(G$44)+1,1),'Sales Log'!$B$5:$B$1004,$A56,'Sales Log'!$R$5:$R$1004,"<>EXAMPLE") -> 0 | H56: =SUMIFS('Sales Log'!$L$5:$L$1004,'Sales Log'!$A$5:$A$1004,">="&H$44,'Sales Log'!$A$5:$A$1004,"<"&DATE(YEAR(H$44),MONTH(H$44)+1,1),'Sales Log'!$B$5:$B$1004,$A56,'Sales Log'!$R$5:$R$1004,"<>EXAMPLE") -> 0 | I56: =SUMIFS('Sales Log'!$L$5:$L$1004,'Sales Log'!$A$5:$A$1004,">="&I$44,'Sales Log'!$A$5:$A$1004,"<"&DATE(YEAR(I$44),MONTH(I$44)+1,1),'Sales Log'!$B$5:$B$1004,$A56,'Sales Log'!$R$5:$R$1004,"<>EXAMPLE") -> 0 | ... M56: =SUMIFS('Sales Log'!$L$5:$L$1004,'Sales Log'!$A$5:$A$1004,">="&M$44,'Sales Log'!$A$5:$A$1004,"<"&DATE(YEAR(M$44),MONTH(M$44)+1,1),'Sales Log'!$B$5:$B$1004,$A56,'Sales Log'!$R$5:$R$1004,"<>EXAMPLE") -> 0 | N56: =SUM(B56:M56) -> 0
A57: ='Chart of Accounts'!$A$78 -> Bookshop.org | B57: =SUMIFS('Sales Log'!$L$5:$L$1004,'Sales Log'!$A$5:$A$1004,">="&B$44,'Sales Log'!$A$5:$A$1004,"<"&DATE(YEAR(B$44),MONTH(B$44)+1,1),'Sales Log'!$B$5:$B$1004,$A57,'Sales Log'!$R$5:$R$1004,"<>EXAMPLE") -> 0 | C57: =SUMIFS('Sales Log'!$L$5:$L$1004,'Sales Log'!$A$5:$A$1004,">="&C$44,'Sales Log'!$A$5:$A$1004,"<"&DATE(YEAR(C$44),MONTH(C$44)+1,1),'Sales Log'!$B$5:$B$1004,$A57,'Sales Log'!$R$5:$R$1004,"<>EXAMPLE") -> 0 | D57: =SUMIFS('Sales Log'!$L$5:$L$1004,'Sales Log'!$A$5:$A$1004,">="&D$44,'Sales Log'!$A$5:$A$1004,"<"&DATE(YEAR(D$44),MONTH(D$44)+1,1),'Sales Log'!$B$5:$B$1004,$A57,'Sales Log'!$R$5:$R$1004,"<>EXAMPLE") -> 0 | E57: =SUMIFS('Sales Log'!$L$5:$L$1004,'Sales Log'!$A$5:$A$1004,">="&E$44,'Sales Log'!$A$5:$A$1004,"<"&DATE(YEAR(E$44),MONTH(E$44)+1,1),'Sales Log'!$B$5:$B$1004,$A57,'Sales Log'!$R$5:$R$1004,"<>EXAMPLE") -> 0 | F57: =SUMIFS('Sales Log'!$L$5:$L$1004,'Sales Log'!$A$5:$A$1004,">="&F$44,'Sales Log'!$A$5:$A$1004,"<"&DATE(YEAR(F$44),MONTH(F$44)+1,1),'Sales Log'!$B$5:$B$1004,$A57,'Sales Log'!$R$5:$R$1004,"<>EXAMPLE") -> 0 | G57: =SUMIFS('Sales Log'!$L$5:$L$1004,'Sales Log'!$A$5:$A$1004,">="&G$44,'Sales Log'!$A$5:$A$1004,"<"&DATE(YEAR(G$44),MONTH(G$44)+1,1),'Sales Log'!$B$5:$B$1004,$A57,'Sales Log'!$R$5:$R$1004,"<>EXAMPLE") -> 0 | H57: =SUMIFS('Sales Log'!$L$5:$L$1004,'Sales Log'!$A$5:$A$1004,">="&H$44,'Sales Log'!$A$5:$A$1004,"<"&DATE(YEAR(H$44),MONTH(H$44)+1,1),'Sales Log'!$B$5:$B$1004,$A57,'Sales Log'!$R$5:$R$1004,"<>EXAMPLE") -> 0 | I57: =SUMIFS('Sales Log'!$L$5:$L$1004,'Sales Log'!$A$5:$A$1004,">="&I$44,'Sales Log'!$A$5:$A$1004,"<"&DATE(YEAR(I$44),MONTH(I$44)+1,1),'Sales Log'!$B$5:$B$1004,$A57,'Sales Log'!$R$5:$R$1004,"<>EXAMPLE") -> 0 | ... M57: =SUMIFS('Sales Log'!$L$5:$L$1004,'Sales Log'!$A$5:$A$1004,">="&M$44,'Sales Log'!$A$5:$A$1004,"<"&DATE(YEAR(M$44),MONTH(M$44)+1,1),'Sales Log'!$B$5:$B$1004,$A57,'Sales Log'!$R$5:$R$1004,"<>EXAMPLE") -> 0 | N57: =SUM(B57:M57) -> 0
A58: ='Chart of Accounts'!$A$79 -> Direct (check / ACH / cash) | B58: =SUMIFS('Sales Log'!$L$5:$L$1004,'Sales Log'!$A$5:$A$1004,">="&B$44,'Sales Log'!$A$5:$A$1004,"<"&DATE(YEAR(B$44),MONTH(B$44)+1,1),'Sales Log'!$B$5:$B$1004,$A58,'Sales Log'!$R$5:$R$1004,"<>EXAMPLE") -> 0 | C58: =SUMIFS('Sales Log'!$L$5:$L$1004,'Sales Log'!$A$5:$A$1004,">="&C$44,'Sales Log'!$A$5:$A$1004,"<"&DATE(YEAR(C$44),MONTH(C$44)+1,1),'Sales Log'!$B$5:$B$1004,$A58,'Sales Log'!$R$5:$R$1004,"<>EXAMPLE") -> 0 | D58: =SUMIFS('Sales Log'!$L$5:$L$1004,'Sales Log'!$A$5:$A$1004,">="&D$44,'Sales Log'!$A$5:$A$1004,"<"&DATE(YEAR(D$44),MONTH(D$44)+1,1),'Sales Log'!$B$5:$B$1004,$A58,'Sales Log'!$R$5:$R$1004,"<>EXAMPLE") -> 0 | E58: =SUMIFS('Sales Log'!$L$5:$L$1004,'Sales Log'!$A$5:$A$1004,">="&E$44,'Sales Log'!$A$5:$A$1004,"<"&DATE(YEAR(E$44),MONTH(E$44)+1,1),'Sales Log'!$B$5:$B$1004,$A58,'Sales Log'!$R$5:$R$1004,"<>EXAMPLE") -> 0 | F58: =SUMIFS('Sales Log'!$L$5:$L$1004,'Sales Log'!$A$5:$A$1004,">="&F$44,'Sales Log'!$A$5:$A$1004,"<"&DATE(YEAR(F$44),MONTH(F$44)+1,1),'Sales Log'!$B$5:$B$1004,$A58,'Sales Log'!$R$5:$R$1004,"<>EXAMPLE") -> 0 | G58: =SUMIFS('Sales Log'!$L$5:$L$1004,'Sales Log'!$A$5:$A$1004,">="&G$44,'Sales Log'!$A$5:$A$1004,"<"&DATE(YEAR(G$44),MONTH(G$44)+1,1),'Sales Log'!$B$5:$B$1004,$A58,'Sales Log'!$R$5:$R$1004,"<>EXAMPLE") -> 0 | H58: =SUMIFS('Sales Log'!$L$5:$L$1004,'Sales Log'!$A$5:$A$1004,">="&H$44,'Sales Log'!$A$5:$A$1004,"<"&DATE(YEAR(H$44),MONTH(H$44)+1,1),'Sales Log'!$B$5:$B$1004,$A58,'Sales Log'!$R$5:$R$1004,"<>EXAMPLE") -> 0 | I58: =SUMIFS('Sales Log'!$L$5:$L$1004,'Sales Log'!$A$5:$A$1004,">="&I$44,'Sales Log'!$A$5:$A$1004,"<"&DATE(YEAR(I$44),MONTH(I$44)+1,1),'Sales Log'!$B$5:$B$1004,$A58,'Sales Log'!$R$5:$R$1004,"<>EXAMPLE") -> 0 | ... M58: =SUMIFS('Sales Log'!$L$5:$L$1004,'Sales Log'!$A$5:$A$1004,">="&M$44,'Sales Log'!$A$5:$A$1004,"<"&DATE(YEAR(M$44),MONTH(M$44)+1,1),'Sales Log'!$B$5:$B$1004,$A58,'Sales Log'!$R$5:$R$1004,"<>EXAMPLE") -> 0 | N58: =SUM(B58:M58) -> 0
A59: Total | B59: =SUM(B45:B58) -> 0 | C59: =SUM(C45:C58) -> 0 | D59: =SUM(D45:D58) -> 0 | E59: =SUM(E45:E58) -> 0 | F59: =SUM(F45:F58) -> 0 | G59: =SUM(G45:G58) -> 0 | H59: =SUM(H45:H58) -> 0 | I59: =SUM(I45:I58) -> 0 | ... N59: =SUM(N45:N58) -> 0
A62: Payouts received (Payouts Reconciliation, by payout date) | D62: Compare with Net payout above; royalty timing lags 60-90 days (UNVERIFIED).
A63: Channel | B63: =DATE($B$3,1,1) -> 46023 | C63: =DATE($B$3,2,1) -> 46054 | D63: =DATE($B$3,3,1) -> 46082 | E63: =DATE($B$3,4,1) -> 46113 | F63: =DATE($B$3,5,1) -> 46143 | G63: =DATE($B$3,6,1) -> 46174 | H63: =DATE($B$3,7,1) -> 46204 | I63: =DATE($B$3,8,1) -> 46235 | J63: =DATE($B$3,9,1) -> 46266 | K63: =DATE($B$3,10,1) -> 46296 | L63: =DATE($B$3,11,1) -> 46327 | M63: =DATE($B$3,12,1) -> 46357 | N63: Total
A64: ='Chart of Accounts'!$A$66 -> Amazon KDP | B64: =SUMIFS('Payouts Reconciliation'!$C$5:$C$504,'Payouts Reconciliation'!$B$5:$B$504,">="&B$63,'Payouts Reconciliation'!$B$5:$B$504,"<"&DATE(YEAR(B$63),MONTH(B$63)+1,1),'Payouts Reconciliation'!$A$5:$A$504,$A64,'Payouts Reconciliation'!$O$5:$O$504,"<>EXAMPLE") -> 0 | C64: =SUMIFS('Payouts Reconciliation'!$C$5:$C$504,'Payouts Reconciliation'!$B$5:$B$504,">="&C$63,'Payouts Reconciliation'!$B$5:$B$504,"<"&DATE(YEAR(C$63),MONTH(C$63)+1,1),'Payouts Reconciliation'!$A$5:$A$504,$A64,'Payouts Reconciliation'!$O$5:$O$504,"<>EXAMPLE") -> 0 | D64: =SUMIFS('Payouts Reconciliation'!$C$5:$C$504,'Payouts Reconciliation'!$B$5:$B$504,">="&D$63,'Payouts Reconciliation'!$B$5:$B$504,"<"&DATE(YEAR(D$63),MONTH(D$63)+1,1),'Payouts Reconciliation'!$A$5:$A$504,$A64,'Payouts Reconciliation'!$O$5:$O$504,"<>EXAMPLE") -> 0 | E64: =SUMIFS('Payouts Reconciliation'!$C$5:$C$504,'Payouts Reconciliation'!$B$5:$B$504,">="&E$63,'Payouts Reconciliation'!$B$5:$B$504,"<"&DATE(YEAR(E$63),MONTH(E$63)+1,1),'Payouts Reconciliation'!$A$5:$A$504,$A64,'Payouts Reconciliation'!$O$5:$O$504,"<>EXAMPLE") -> 0 | F64: =SUMIFS('Payouts Reconciliation'!$C$5:$C$504,'Payouts Reconciliation'!$B$5:$B$504,">="&F$63,'Payouts Reconciliation'!$B$5:$B$504,"<"&DATE(YEAR(F$63),MONTH(F$63)+1,1),'Payouts Reconciliation'!$A$5:$A$504,$A64,'Payouts Reconciliation'!$O$5:$O$504,"<>EXAMPLE") -> 0 | G64: =SUMIFS('Payouts Reconciliation'!$C$5:$C$504,'Payouts Reconciliation'!$B$5:$B$504,">="&G$63,'Payouts Reconciliation'!$B$5:$B$504,"<"&DATE(YEAR(G$63),MONTH(G$63)+1,1),'Payouts Reconciliation'!$A$5:$A$504,$A64,'Payouts Reconciliation'!$O$5:$O$504,"<>EXAMPLE") -> 0 | H64: =SUMIFS('Payouts Reconciliation'!$C$5:$C$504,'Payouts Reconciliation'!$B$5:$B$504,">="&H$63,'Payouts Reconciliation'!$B$5:$B$504,"<"&DATE(YEAR(H$63),MONTH(H$63)+1,1),'Payouts Reconciliation'!$A$5:$A$504,$A64,'Payouts Reconciliation'!$O$5:$O$504,"<>EXAMPLE") -> 0 | I64: =SUMIFS('Payouts Reconciliation'!$C$5:$C$504,'Payouts Reconciliation'!$B$5:$B$504,">="&I$63,'Payouts Reconciliation'!$B$5:$B$504,"<"&DATE(YEAR(I$63),MONTH(I$63)+1,1),'Payouts Reconciliation'!$A$5:$A$504,$A64,'Payouts Reconciliation'!$O$5:$O$504,"<>EXAMPLE") -> 0 | ... M64: =SUMIFS('Payouts Reconciliation'!$C$5:$C$504,'Payouts Reconciliation'!$B$5:$B$504,">="&M$63,'Payouts Reconciliation'!$B$5:$B$504,"<"&DATE(YEAR(M$63),MONTH(M$63)+1,1),'Payouts Reconciliation'!$A$5:$A$504,$A64,'Payouts Reconciliation'!$O$5:$O$504,"<>EXAMPLE") -> 0 | N64: =SUM(B64:M64) -> 0
A65: ='Chart of Accounts'!$A$67 -> IngramSpark | B65: =SUMIFS('Payouts Reconciliation'!$C$5:$C$504,'Payouts Reconciliation'!$B$5:$B$504,">="&B$63,'Payouts Reconciliation'!$B$5:$B$504,"<"&DATE(YEAR(B$63),MONTH(B$63)+1,1),'Payouts Reconciliation'!$A$5:$A$504,$A65,'Payouts Reconciliation'!$O$5:$O$504,"<>EXAMPLE") -> 0 | C65: =SUMIFS('Payouts Reconciliation'!$C$5:$C$504,'Payouts Reconciliation'!$B$5:$B$504,">="&C$63,'Payouts Reconciliation'!$B$5:$B$504,"<"&DATE(YEAR(C$63),MONTH(C$63)+1,1),'Payouts Reconciliation'!$A$5:$A$504,$A65,'Payouts Reconciliation'!$O$5:$O$504,"<>EXAMPLE") -> 0 | D65: =SUMIFS('Payouts Reconciliation'!$C$5:$C$504,'Payouts Reconciliation'!$B$5:$B$504,">="&D$63,'Payouts Reconciliation'!$B$5:$B$504,"<"&DATE(YEAR(D$63),MONTH(D$63)+1,1),'Payouts Reconciliation'!$A$5:$A$504,$A65,'Payouts Reconciliation'!$O$5:$O$504,"<>EXAMPLE") -> 0 | E65: =SUMIFS('Payouts Reconciliation'!$C$5:$C$504,'Payouts Reconciliation'!$B$5:$B$504,">="&E$63,'Payouts Reconciliation'!$B$5:$B$504,"<"&DATE(YEAR(E$63),MONTH(E$63)+1,1),'Payouts Reconciliation'!$A$5:$A$504,$A65,'Payouts Reconciliation'!$O$5:$O$504,"<>EXAMPLE") -> 0 | F65: =SUMIFS('Payouts Reconciliation'!$C$5:$C$504,'Payouts Reconciliation'!$B$5:$B$504,">="&F$63,'Payouts Reconciliation'!$B$5:$B$504,"<"&DATE(YEAR(F$63),MONTH(F$63)+1,1),'Payouts Reconciliation'!$A$5:$A$504,$A65,'Payouts Reconciliation'!$O$5:$O$504,"<>EXAMPLE") -> 0 | G65: =SUMIFS('Payouts Reconciliation'!$C$5:$C$504,'Payouts Reconciliation'!$B$5:$B$504,">="&G$63,'Payouts Reconciliation'!$B$5:$B$504,"<"&DATE(YEAR(G$63),MONTH(G$63)+1,1),'Payouts Reconciliation'!$A$5:$A$504,$A65,'Payouts Reconciliation'!$O$5:$O$504,"<>EXAMPLE") -> 0 | H65: =SUMIFS('Payouts Reconciliation'!$C$5:$C$504,'Payouts Reconciliation'!$B$5:$B$504,">="&H$63,'Payouts Reconciliation'!$B$5:$B$504,"<"&DATE(YEAR(H$63),MONTH(H$63)+1,1),'Payouts Reconciliation'!$A$5:$A$504,$A65,'Payouts Reconciliation'!$O$5:$O$504,"<>EXAMPLE") -> 0 | I65: =SUMIFS('Payouts Reconciliation'!$C$5:$C$504,'Payouts Reconciliation'!$B$5:$B$504,">="&I$63,'Payouts Reconciliation'!$B$5:$B$504,"<"&DATE(YEAR(I$63),MONTH(I$63)+1,1),'Payouts Reconciliation'!$A$5:$A$504,$A65,'Payouts Reconciliation'!$O$5:$O$504,"<>EXAMPLE") -> 0 | ... M65: =SUMIFS('Payouts Reconciliation'!$C$5:$C$504,'Payouts Reconciliation'!$B$5:$B$504,">="&M$63,'Payouts Reconciliation'!$B$5:$B$504,"<"&DATE(YEAR(M$63),MONTH(M$63)+1,1),'Payouts Reconciliation'!$A$5:$A$504,$A65,'Payouts Reconciliation'!$O$5:$O$504,"<>EXAMPLE") -> 0 | N65: =SUM(B65:M65) -> 0
A66: ='Chart of Accounts'!$A$68 -> Etsy | B66: =SUMIFS('Payouts Reconciliation'!$C$5:$C$504,'Payouts Reconciliation'!$B$5:$B$504,">="&B$63,'Payouts Reconciliation'!$B$5:$B$504,"<"&DATE(YEAR(B$63),MONTH(B$63)+1,1),'Payouts Reconciliation'!$A$5:$A$504,$A66,'Payouts Reconciliation'!$O$5:$O$504,"<>EXAMPLE") -> 0 | C66: =SUMIFS('Payouts Reconciliation'!$C$5:$C$504,'Payouts Reconciliation'!$B$5:$B$504,">="&C$63,'Payouts Reconciliation'!$B$5:$B$504,"<"&DATE(YEAR(C$63),MONTH(C$63)+1,1),'Payouts Reconciliation'!$A$5:$A$504,$A66,'Payouts Reconciliation'!$O$5:$O$504,"<>EXAMPLE") -> 0 | D66: =SUMIFS('Payouts Reconciliation'!$C$5:$C$504,'Payouts Reconciliation'!$B$5:$B$504,">="&D$63,'Payouts Reconciliation'!$B$5:$B$504,"<"&DATE(YEAR(D$63),MONTH(D$63)+1,1),'Payouts Reconciliation'!$A$5:$A$504,$A66,'Payouts Reconciliation'!$O$5:$O$504,"<>EXAMPLE") -> 0 | E66: =SUMIFS('Payouts Reconciliation'!$C$5:$C$504,'Payouts Reconciliation'!$B$5:$B$504,">="&E$63,'Payouts Reconciliation'!$B$5:$B$504,"<"&DATE(YEAR(E$63),MONTH(E$63)+1,1),'Payouts Reconciliation'!$A$5:$A$504,$A66,'Payouts Reconciliation'!$O$5:$O$504,"<>EXAMPLE") -> 0 | F66: =SUMIFS('Payouts Reconciliation'!$C$5:$C$504,'Payouts Reconciliation'!$B$5:$B$504,">="&F$63,'Payouts Reconciliation'!$B$5:$B$504,"<"&DATE(YEAR(F$63),MONTH(F$63)+1,1),'Payouts Reconciliation'!$A$5:$A$504,$A66,'Payouts Reconciliation'!$O$5:$O$504,"<>EXAMPLE") -> 0 | G66: =SUMIFS('Payouts Reconciliation'!$C$5:$C$504,'Payouts Reconciliation'!$B$5:$B$504,">="&G$63,'Payouts Reconciliation'!$B$5:$B$504,"<"&DATE(YEAR(G$63),MONTH(G$63)+1,1),'Payouts Reconciliation'!$A$5:$A$504,$A66,'Payouts Reconciliation'!$O$5:$O$504,"<>EXAMPLE") -> 0 | H66: =SUMIFS('Payouts Reconciliation'!$C$5:$C$504,'Payouts Reconciliation'!$B$5:$B$504,">="&H$63,'Payouts Reconciliation'!$B$5:$B$504,"<"&DATE(YEAR(H$63),MONTH(H$63)+1,1),'Payouts Reconciliation'!$A$5:$A$504,$A66,'Payouts Reconciliation'!$O$5:$O$504,"<>EXAMPLE") -> 0 | I66: =SUMIFS('Payouts Reconciliation'!$C$5:$C$504,'Payouts Reconciliation'!$B$5:$B$504,">="&I$63,'Payouts Reconciliation'!$B$5:$B$504,"<"&DATE(YEAR(I$63),MONTH(I$63)+1,1),'Payouts Reconciliation'!$A$5:$A$504,$A66,'Payouts Reconciliation'!$O$5:$O$504,"<>EXAMPLE") -> 0 | ... M66: =SUMIFS('Payouts Reconciliation'!$C$5:$C$504,'Payouts Reconciliation'!$B$5:$B$504,">="&M$63,'Payouts Reconciliation'!$B$5:$B$504,"<"&DATE(YEAR(M$63),MONTH(M$63)+1,1),'Payouts Reconciliation'!$A$5:$A$504,$A66,'Payouts Reconciliation'!$O$5:$O$504,"<>EXAMPLE") -> 0 | N66: =SUM(B66:M66) -> 0
A67: ='Chart of Accounts'!$A$69 -> Teachers Pay Teachers | B67: =SUMIFS('Payouts Reconciliation'!$C$5:$C$504,'Payouts Reconciliation'!$B$5:$B$504,">="&B$63,'Payouts Reconciliation'!$B$5:$B$504,"<"&DATE(YEAR(B$63),MONTH(B$63)+1,1),'Payouts Reconciliation'!$A$5:$A$504,$A67,'Payouts Reconciliation'!$O$5:$O$504,"<>EXAMPLE") -> 0 | C67: =SUMIFS('Payouts Reconciliation'!$C$5:$C$504,'Payouts Reconciliation'!$B$5:$B$504,">="&C$63,'Payouts Reconciliation'!$B$5:$B$504,"<"&DATE(YEAR(C$63),MONTH(C$63)+1,1),'Payouts Reconciliation'!$A$5:$A$504,$A67,'Payouts Reconciliation'!$O$5:$O$504,"<>EXAMPLE") -> 0 | D67: =SUMIFS('Payouts Reconciliation'!$C$5:$C$504,'Payouts Reconciliation'!$B$5:$B$504,">="&D$63,'Payouts Reconciliation'!$B$5:$B$504,"<"&DATE(YEAR(D$63),MONTH(D$63)+1,1),'Payouts Reconciliation'!$A$5:$A$504,$A67,'Payouts Reconciliation'!$O$5:$O$504,"<>EXAMPLE") -> 0 | E67: =SUMIFS('Payouts Reconciliation'!$C$5:$C$504,'Payouts Reconciliation'!$B$5:$B$504,">="&E$63,'Payouts Reconciliation'!$B$5:$B$504,"<"&DATE(YEAR(E$63),MONTH(E$63)+1,1),'Payouts Reconciliation'!$A$5:$A$504,$A67,'Payouts Reconciliation'!$O$5:$O$504,"<>EXAMPLE") -> 0 | F67: =SUMIFS('Payouts Reconciliation'!$C$5:$C$504,'Payouts Reconciliation'!$B$5:$B$504,">="&F$63,'Payouts Reconciliation'!$B$5:$B$504,"<"&DATE(YEAR(F$63),MONTH(F$63)+1,1),'Payouts Reconciliation'!$A$5:$A$504,$A67,'Payouts Reconciliation'!$O$5:$O$504,"<>EXAMPLE") -> 0 | G67: =SUMIFS('Payouts Reconciliation'!$C$5:$C$504,'Payouts Reconciliation'!$B$5:$B$504,">="&G$63,'Payouts Reconciliation'!$B$5:$B$504,"<"&DATE(YEAR(G$63),MONTH(G$63)+1,1),'Payouts Reconciliation'!$A$5:$A$504,$A67,'Payouts Reconciliation'!$O$5:$O$504,"<>EXAMPLE") -> 0 | H67: =SUMIFS('Payouts Reconciliation'!$C$5:$C$504,'Payouts Reconciliation'!$B$5:$B$504,">="&H$63,'Payouts Reconciliation'!$B$5:$B$504,"<"&DATE(YEAR(H$63),MONTH(H$63)+1,1),'Payouts Reconciliation'!$A$5:$A$504,$A67,'Payouts Reconciliation'!$O$5:$O$504,"<>EXAMPLE") -> 0 | I67: =SUMIFS('Payouts Reconciliation'!$C$5:$C$504,'Payouts Reconciliation'!$B$5:$B$504,">="&I$63,'Payouts Reconciliation'!$B$5:$B$504,"<"&DATE(YEAR(I$63),MONTH(I$63)+1,1),'Payouts Reconciliation'!$A$5:$A$504,$A67,'Payouts Reconciliation'!$O$5:$O$504,"<>EXAMPLE") -> 0 | ... M67: =SUMIFS('Payouts Reconciliation'!$C$5:$C$504,'Payouts Reconciliation'!$B$5:$B$504,">="&M$63,'Payouts Reconciliation'!$B$5:$B$504,"<"&DATE(YEAR(M$63),MONTH(M$63)+1,1),'Payouts Reconciliation'!$A$5:$A$504,$A67,'Payouts Reconciliation'!$O$5:$O$504,"<>EXAMPLE") -> 0 | N67: =SUM(B67:M67) -> 0
A68: ='Chart of Accounts'!$A$70 -> TikTok Shop | B68: =SUMIFS('Payouts Reconciliation'!$C$5:$C$504,'Payouts Reconciliation'!$B$5:$B$504,">="&B$63,'Payouts Reconciliation'!$B$5:$B$504,"<"&DATE(YEAR(B$63),MONTH(B$63)+1,1),'Payouts Reconciliation'!$A$5:$A$504,$A68,'Payouts Reconciliation'!$O$5:$O$504,"<>EXAMPLE") -> 0 | C68: =SUMIFS('Payouts Reconciliation'!$C$5:$C$504,'Payouts Reconciliation'!$B$5:$B$504,">="&C$63,'Payouts Reconciliation'!$B$5:$B$504,"<"&DATE(YEAR(C$63),MONTH(C$63)+1,1),'Payouts Reconciliation'!$A$5:$A$504,$A68,'Payouts Reconciliation'!$O$5:$O$504,"<>EXAMPLE") -> 0 | D68: =SUMIFS('Payouts Reconciliation'!$C$5:$C$504,'Payouts Reconciliation'!$B$5:$B$504,">="&D$63,'Payouts Reconciliation'!$B$5:$B$504,"<"&DATE(YEAR(D$63),MONTH(D$63)+1,1),'Payouts Reconciliation'!$A$5:$A$504,$A68,'Payouts Reconciliation'!$O$5:$O$504,"<>EXAMPLE") -> 0 | E68: =SUMIFS('Payouts Reconciliation'!$C$5:$C$504,'Payouts Reconciliation'!$B$5:$B$504,">="&E$63,'Payouts Reconciliation'!$B$5:$B$504,"<"&DATE(YEAR(E$63),MONTH(E$63)+1,1),'Payouts Reconciliation'!$A$5:$A$504,$A68,'Payouts Reconciliation'!$O$5:$O$504,"<>EXAMPLE") -> 0 | F68: =SUMIFS('Payouts Reconciliation'!$C$5:$C$504,'Payouts Reconciliation'!$B$5:$B$504,">="&F$63,'Payouts Reconciliation'!$B$5:$B$504,"<"&DATE(YEAR(F$63),MONTH(F$63)+1,1),'Payouts Reconciliation'!$A$5:$A$504,$A68,'Payouts Reconciliation'!$O$5:$O$504,"<>EXAMPLE") -> 0 | G68: =SUMIFS('Payouts Reconciliation'!$C$5:$C$504,'Payouts Reconciliation'!$B$5:$B$504,">="&G$63,'Payouts Reconciliation'!$B$5:$B$504,"<"&DATE(YEAR(G$63),MONTH(G$63)+1,1),'Payouts Reconciliation'!$A$5:$A$504,$A68,'Payouts Reconciliation'!$O$5:$O$504,"<>EXAMPLE") -> 0 | H68: =SUMIFS('Payouts Reconciliation'!$C$5:$C$504,'Payouts Reconciliation'!$B$5:$B$504,">="&H$63,'Payouts Reconciliation'!$B$5:$B$504,"<"&DATE(YEAR(H$63),MONTH(H$63)+1,1),'Payouts Reconciliation'!$A$5:$A$504,$A68,'Payouts Reconciliation'!$O$5:$O$504,"<>EXAMPLE") -> 0 | I68: =SUMIFS('Payouts Reconciliation'!$C$5:$C$504,'Payouts Reconciliation'!$B$5:$B$504,">="&I$63,'Payouts Reconciliation'!$B$5:$B$504,"<"&DATE(YEAR(I$63),MONTH(I$63)+1,1),'Payouts Reconciliation'!$A$5:$A$504,$A68,'Payouts Reconciliation'!$O$5:$O$504,"<>EXAMPLE") -> 0 | ... M68: =SUMIFS('Payouts Reconciliation'!$C$5:$C$504,'Payouts Reconciliation'!$B$5:$B$504,">="&M$63,'Payouts Reconciliation'!$B$5:$B$504,"<"&DATE(YEAR(M$63),MONTH(M$63)+1,1),'Payouts Reconciliation'!$A$5:$A$504,$A68,'Payouts Reconciliation'!$O$5:$O$504,"<>EXAMPLE") -> 0 | N68: =SUM(B68:M68) -> 0
A69: ='Chart of Accounts'!$A$71 -> Shopify (website store) | B69: =SUMIFS('Payouts Reconciliation'!$C$5:$C$504,'Payouts Reconciliation'!$B$5:$B$504,">="&B$63,'Payouts Reconciliation'!$B$5:$B$504,"<"&DATE(YEAR(B$63),MONTH(B$63)+1,1),'Payouts Reconciliation'!$A$5:$A$504,$A69,'Payouts Reconciliation'!$O$5:$O$504,"<>EXAMPLE") -> 0 | C69: =SUMIFS('Payouts Reconciliation'!$C$5:$C$504,'Payouts Reconciliation'!$B$5:$B$504,">="&C$63,'Payouts Reconciliation'!$B$5:$B$504,"<"&DATE(YEAR(C$63),MONTH(C$63)+1,1),'Payouts Reconciliation'!$A$5:$A$504,$A69,'Payouts Reconciliation'!$O$5:$O$504,"<>EXAMPLE") -> 0 | D69: =SUMIFS('Payouts Reconciliation'!$C$5:$C$504,'Payouts Reconciliation'!$B$5:$B$504,">="&D$63,'Payouts Reconciliation'!$B$5:$B$504,"<"&DATE(YEAR(D$63),MONTH(D$63)+1,1),'Payouts Reconciliation'!$A$5:$A$504,$A69,'Payouts Reconciliation'!$O$5:$O$504,"<>EXAMPLE") -> 0 | E69: =SUMIFS('Payouts Reconciliation'!$C$5:$C$504,'Payouts Reconciliation'!$B$5:$B$504,">="&E$63,'Payouts Reconciliation'!$B$5:$B$504,"<"&DATE(YEAR(E$63),MONTH(E$63)+1,1),'Payouts Reconciliation'!$A$5:$A$504,$A69,'Payouts Reconciliation'!$O$5:$O$504,"<>EXAMPLE") -> 0 | F69: =SUMIFS('Payouts Reconciliation'!$C$5:$C$504,'Payouts Reconciliation'!$B$5:$B$504,">="&F$63,'Payouts Reconciliation'!$B$5:$B$504,"<"&DATE(YEAR(F$63),MONTH(F$63)+1,1),'Payouts Reconciliation'!$A$5:$A$504,$A69,'Payouts Reconciliation'!$O$5:$O$504,"<>EXAMPLE") -> 0 | G69: =SUMIFS('Payouts Reconciliation'!$C$5:$C$504,'Payouts Reconciliation'!$B$5:$B$504,">="&G$63,'Payouts Reconciliation'!$B$5:$B$504,"<"&DATE(YEAR(G$63),MONTH(G$63)+1,1),'Payouts Reconciliation'!$A$5:$A$504,$A69,'Payouts Reconciliation'!$O$5:$O$504,"<>EXAMPLE") -> 0 | H69: =SUMIFS('Payouts Reconciliation'!$C$5:$C$504,'Payouts Reconciliation'!$B$5:$B$504,">="&H$63,'Payouts Reconciliation'!$B$5:$B$504,"<"&DATE(YEAR(H$63),MONTH(H$63)+1,1),'Payouts Reconciliation'!$A$5:$A$504,$A69,'Payouts Reconciliation'!$O$5:$O$504,"<>EXAMPLE") -> 0 | I69: =SUMIFS('Payouts Reconciliation'!$C$5:$C$504,'Payouts Reconciliation'!$B$5:$B$504,">="&I$63,'Payouts Reconciliation'!$B$5:$B$504,"<"&DATE(YEAR(I$63),MONTH(I$63)+1,1),'Payouts Reconciliation'!$A$5:$A$504,$A69,'Payouts Reconciliation'!$O$5:$O$504,"<>EXAMPLE") -> 0 | ... M69: =SUMIFS('Payouts Reconciliation'!$C$5:$C$504,'Payouts Reconciliation'!$B$5:$B$504,">="&M$63,'Payouts Reconciliation'!$B$5:$B$504,"<"&DATE(YEAR(M$63),MONTH(M$63)+1,1),'Payouts Reconciliation'!$A$5:$A$504,$A69,'Payouts Reconciliation'!$O$5:$O$504,"<>EXAMPLE") -> 0 | N69: =SUM(B69:M69) -> 0
A70: ='Chart of Accounts'!$A$72 -> Stripe (website & invoices) | B70: =SUMIFS('Payouts Reconciliation'!$C$5:$C$504,'Payouts Reconciliation'!$B$5:$B$504,">="&B$63,'Payouts Reconciliation'!$B$5:$B$504,"<"&DATE(YEAR(B$63),MONTH(B$63)+1,1),'Payouts Reconciliation'!$A$5:$A$504,$A70,'Payouts Reconciliation'!$O$5:$O$504,"<>EXAMPLE") -> 0 | C70: =SUMIFS('Payouts Reconciliation'!$C$5:$C$504,'Payouts Reconciliation'!$B$5:$B$504,">="&C$63,'Payouts Reconciliation'!$B$5:$B$504,"<"&DATE(YEAR(C$63),MONTH(C$63)+1,1),'Payouts Reconciliation'!$A$5:$A$504,$A70,'Payouts Reconciliation'!$O$5:$O$504,"<>EXAMPLE") -> 0 | D70: =SUMIFS('Payouts Reconciliation'!$C$5:$C$504,'Payouts Reconciliation'!$B$5:$B$504,">="&D$63,'Payouts Reconciliation'!$B$5:$B$504,"<"&DATE(YEAR(D$63),MONTH(D$63)+1,1),'Payouts Reconciliation'!$A$5:$A$504,$A70,'Payouts Reconciliation'!$O$5:$O$504,"<>EXAMPLE") -> 0 | E70: =SUMIFS('Payouts Reconciliation'!$C$5:$C$504,'Payouts Reconciliation'!$B$5:$B$504,">="&E$63,'Payouts Reconciliation'!$B$5:$B$504,"<"&DATE(YEAR(E$63),MONTH(E$63)+1,1),'Payouts Reconciliation'!$A$5:$A$504,$A70,'Payouts Reconciliation'!$O$5:$O$504,"<>EXAMPLE") -> 0 | F70: =SUMIFS('Payouts Reconciliation'!$C$5:$C$504,'Payouts Reconciliation'!$B$5:$B$504,">="&F$63,'Payouts Reconciliation'!$B$5:$B$504,"<"&DATE(YEAR(F$63),MONTH(F$63)+1,1),'Payouts Reconciliation'!$A$5:$A$504,$A70,'Payouts Reconciliation'!$O$5:$O$504,"<>EXAMPLE") -> 0 | G70: =SUMIFS('Payouts Reconciliation'!$C$5:$C$504,'Payouts Reconciliation'!$B$5:$B$504,">="&G$63,'Payouts Reconciliation'!$B$5:$B$504,"<"&DATE(YEAR(G$63),MONTH(G$63)+1,1),'Payouts Reconciliation'!$A$5:$A$504,$A70,'Payouts Reconciliation'!$O$5:$O$504,"<>EXAMPLE") -> 0 | H70: =SUMIFS('Payouts Reconciliation'!$C$5:$C$504,'Payouts Reconciliation'!$B$5:$B$504,">="&H$63,'Payouts Reconciliation'!$B$5:$B$504,"<"&DATE(YEAR(H$63),MONTH(H$63)+1,1),'Payouts Reconciliation'!$A$5:$A$504,$A70,'Payouts Reconciliation'!$O$5:$O$504,"<>EXAMPLE") -> 0 | I70: =SUMIFS('Payouts Reconciliation'!$C$5:$C$504,'Payouts Reconciliation'!$B$5:$B$504,">="&I$63,'Payouts Reconciliation'!$B$5:$B$504,"<"&DATE(YEAR(I$63),MONTH(I$63)+1,1),'Payouts Reconciliation'!$A$5:$A$504,$A70,'Payouts Reconciliation'!$O$5:$O$504,"<>EXAMPLE") -> 0 | ... M70: =SUMIFS('Payouts Reconciliation'!$C$5:$C$504,'Payouts Reconciliation'!$B$5:$B$504,">="&M$63,'Payouts Reconciliation'!$B$5:$B$504,"<"&DATE(YEAR(M$63),MONTH(M$63)+1,1),'Payouts Reconciliation'!$A$5:$A$504,$A70,'Payouts Reconciliation'!$O$5:$O$504,"<>EXAMPLE") -> 0 | N70: =SUM(B70:M70) -> 0
A71: ='Chart of Accounts'!$A$73 -> PayPal Business | B71: =SUMIFS('Payouts Reconciliation'!$C$5:$C$504,'Payouts Reconciliation'!$B$5:$B$504,">="&B$63,'Payouts Reconciliation'!$B$5:$B$504,"<"&DATE(YEAR(B$63),MONTH(B$63)+1,1),'Payouts Reconciliation'!$A$5:$A$504,$A71,'Payouts Reconciliation'!$O$5:$O$504,"<>EXAMPLE") -> 0 | C71: =SUMIFS('Payouts Reconciliation'!$C$5:$C$504,'Payouts Reconciliation'!$B$5:$B$504,">="&C$63,'Payouts Reconciliation'!$B$5:$B$504,"<"&DATE(YEAR(C$63),MONTH(C$63)+1,1),'Payouts Reconciliation'!$A$5:$A$504,$A71,'Payouts Reconciliation'!$O$5:$O$504,"<>EXAMPLE") -> 0 | D71: =SUMIFS('Payouts Reconciliation'!$C$5:$C$504,'Payouts Reconciliation'!$B$5:$B$504,">="&D$63,'Payouts Reconciliation'!$B$5:$B$504,"<"&DATE(YEAR(D$63),MONTH(D$63)+1,1),'Payouts Reconciliation'!$A$5:$A$504,$A71,'Payouts Reconciliation'!$O$5:$O$504,"<>EXAMPLE") -> 0 | E71: =SUMIFS('Payouts Reconciliation'!$C$5:$C$504,'Payouts Reconciliation'!$B$5:$B$504,">="&E$63,'Payouts Reconciliation'!$B$5:$B$504,"<"&DATE(YEAR(E$63),MONTH(E$63)+1,1),'Payouts Reconciliation'!$A$5:$A$504,$A71,'Payouts Reconciliation'!$O$5:$O$504,"<>EXAMPLE") -> 0 | F71: =SUMIFS('Payouts Reconciliation'!$C$5:$C$504,'Payouts Reconciliation'!$B$5:$B$504,">="&F$63,'Payouts Reconciliation'!$B$5:$B$504,"<"&DATE(YEAR(F$63),MONTH(F$63)+1,1),'Payouts Reconciliation'!$A$5:$A$504,$A71,'Payouts Reconciliation'!$O$5:$O$504,"<>EXAMPLE") -> 0 | G71: =SUMIFS('Payouts Reconciliation'!$C$5:$C$504,'Payouts Reconciliation'!$B$5:$B$504,">="&G$63,'Payouts Reconciliation'!$B$5:$B$504,"<"&DATE(YEAR(G$63),MONTH(G$63)+1,1),'Payouts Reconciliation'!$A$5:$A$504,$A71,'Payouts Reconciliation'!$O$5:$O$504,"<>EXAMPLE") -> 0 | H71: =SUMIFS('Payouts Reconciliation'!$C$5:$C$504,'Payouts Reconciliation'!$B$5:$B$504,">="&H$63,'Payouts Reconciliation'!$B$5:$B$504,"<"&DATE(YEAR(H$63),MONTH(H$63)+1,1),'Payouts Reconciliation'!$A$5:$A$504,$A71,'Payouts Reconciliation'!$O$5:$O$504,"<>EXAMPLE") -> 0 | I71: =SUMIFS('Payouts Reconciliation'!$C$5:$C$504,'Payouts Reconciliation'!$B$5:$B$504,">="&I$63,'Payouts Reconciliation'!$B$5:$B$504,"<"&DATE(YEAR(I$63),MONTH(I$63)+1,1),'Payouts Reconciliation'!$A$5:$A$504,$A71,'Payouts Reconciliation'!$O$5:$O$504,"<>EXAMPLE") -> 0 | ... M71: =SUMIFS('Payouts Reconciliation'!$C$5:$C$504,'Payouts Reconciliation'!$B$5:$B$504,">="&M$63,'Payouts Reconciliation'!$B$5:$B$504,"<"&DATE(YEAR(M$63),MONTH(M$63)+1,1),'Payouts Reconciliation'!$A$5:$A$504,$A71,'Payouts Reconciliation'!$O$5:$O$504,"<>EXAMPLE") -> 0 | N71: =SUM(B71:M71) -> 0
A72: ='Chart of Accounts'!$A$74 -> Meta shop (FB/IG) | B72: =SUMIFS('Payouts Reconciliation'!$C$5:$C$504,'Payouts Reconciliation'!$B$5:$B$504,">="&B$63,'Payouts Reconciliation'!$B$5:$B$504,"<"&DATE(YEAR(B$63),MONTH(B$63)+1,1),'Payouts Reconciliation'!$A$5:$A$504,$A72,'Payouts Reconciliation'!$O$5:$O$504,"<>EXAMPLE") -> 0 | C72: =SUMIFS('Payouts Reconciliation'!$C$5:$C$504,'Payouts Reconciliation'!$B$5:$B$504,">="&C$63,'Payouts Reconciliation'!$B$5:$B$504,"<"&DATE(YEAR(C$63),MONTH(C$63)+1,1),'Payouts Reconciliation'!$A$5:$A$504,$A72,'Payouts Reconciliation'!$O$5:$O$504,"<>EXAMPLE") -> 0 | D72: =SUMIFS('Payouts Reconciliation'!$C$5:$C$504,'Payouts Reconciliation'!$B$5:$B$504,">="&D$63,'Payouts Reconciliation'!$B$5:$B$504,"<"&DATE(YEAR(D$63),MONTH(D$63)+1,1),'Payouts Reconciliation'!$A$5:$A$504,$A72,'Payouts Reconciliation'!$O$5:$O$504,"<>EXAMPLE") -> 0 | E72: =SUMIFS('Payouts Reconciliation'!$C$5:$C$504,'Payouts Reconciliation'!$B$5:$B$504,">="&E$63,'Payouts Reconciliation'!$B$5:$B$504,"<"&DATE(YEAR(E$63),MONTH(E$63)+1,1),'Payouts Reconciliation'!$A$5:$A$504,$A72,'Payouts Reconciliation'!$O$5:$O$504,"<>EXAMPLE") -> 0 | F72: =SUMIFS('Payouts Reconciliation'!$C$5:$C$504,'Payouts Reconciliation'!$B$5:$B$504,">="&F$63,'Payouts Reconciliation'!$B$5:$B$504,"<"&DATE(YEAR(F$63),MONTH(F$63)+1,1),'Payouts Reconciliation'!$A$5:$A$504,$A72,'Payouts Reconciliation'!$O$5:$O$504,"<>EXAMPLE") -> 0 | G72: =SUMIFS('Payouts Reconciliation'!$C$5:$C$504,'Payouts Reconciliation'!$B$5:$B$504,">="&G$63,'Payouts Reconciliation'!$B$5:$B$504,"<"&DATE(YEAR(G$63),MONTH(G$63)+1,1),'Payouts Reconciliation'!$A$5:$A$504,$A72,'Payouts Reconciliation'!$O$5:$O$504,"<>EXAMPLE") -> 0 | H72: =SUMIFS('Payouts Reconciliation'!$C$5:$C$504,'Payouts Reconciliation'!$B$5:$B$504,">="&H$63,'Payouts Reconciliation'!$B$5:$B$504,"<"&DATE(YEAR(H$63),MONTH(H$63)+1,1),'Payouts Reconciliation'!$A$5:$A$504,$A72,'Payouts Reconciliation'!$O$5:$O$504,"<>EXAMPLE") -> 0 | I72: =SUMIFS('Payouts Reconciliation'!$C$5:$C$504,'Payouts Reconciliation'!$B$5:$B$504,">="&I$63,'Payouts Reconciliation'!$B$5:$B$504,"<"&DATE(YEAR(I$63),MONTH(I$63)+1,1),'Payouts Reconciliation'!$A$5:$A$504,$A72,'Payouts Reconciliation'!$O$5:$O$504,"<>EXAMPLE") -> 0 | ... M72: =SUMIFS('Payouts Reconciliation'!$C$5:$C$504,'Payouts Reconciliation'!$B$5:$B$504,">="&M$63,'Payouts Reconciliation'!$B$5:$B$504,"<"&DATE(YEAR(M$63),MONTH(M$63)+1,1),'Payouts Reconciliation'!$A$5:$A$504,$A72,'Payouts Reconciliation'!$O$5:$O$504,"<>EXAMPLE") -> 0 | N72: =SUM(B72:M72) -> 0
A73: ='Chart of Accounts'!$A$75 -> Faire (wholesale) | B73: =SUMIFS('Payouts Reconciliation'!$C$5:$C$504,'Payouts Reconciliation'!$B$5:$B$504,">="&B$63,'Payouts Reconciliation'!$B$5:$B$504,"<"&DATE(YEAR(B$63),MONTH(B$63)+1,1),'Payouts Reconciliation'!$A$5:$A$504,$A73,'Payouts Reconciliation'!$O$5:$O$504,"<>EXAMPLE") -> 0 | C73: =SUMIFS('Payouts Reconciliation'!$C$5:$C$504,'Payouts Reconciliation'!$B$5:$B$504,">="&C$63,'Payouts Reconciliation'!$B$5:$B$504,"<"&DATE(YEAR(C$63),MONTH(C$63)+1,1),'Payouts Reconciliation'!$A$5:$A$504,$A73,'Payouts Reconciliation'!$O$5:$O$504,"<>EXAMPLE") -> 0 | D73: =SUMIFS('Payouts Reconciliation'!$C$5:$C$504,'Payouts Reconciliation'!$B$5:$B$504,">="&D$63,'Payouts Reconciliation'!$B$5:$B$504,"<"&DATE(YEAR(D$63),MONTH(D$63)+1,1),'Payouts Reconciliation'!$A$5:$A$504,$A73,'Payouts Reconciliation'!$O$5:$O$504,"<>EXAMPLE") -> 0 | E73: =SUMIFS('Payouts Reconciliation'!$C$5:$C$504,'Payouts Reconciliation'!$B$5:$B$504,">="&E$63,'Payouts Reconciliation'!$B$5:$B$504,"<"&DATE(YEAR(E$63),MONTH(E$63)+1,1),'Payouts Reconciliation'!$A$5:$A$504,$A73,'Payouts Reconciliation'!$O$5:$O$504,"<>EXAMPLE") -> 0 | F73: =SUMIFS('Payouts Reconciliation'!$C$5:$C$504,'Payouts Reconciliation'!$B$5:$B$504,">="&F$63,'Payouts Reconciliation'!$B$5:$B$504,"<"&DATE(YEAR(F$63),MONTH(F$63)+1,1),'Payouts Reconciliation'!$A$5:$A$504,$A73,'Payouts Reconciliation'!$O$5:$O$504,"<>EXAMPLE") -> 0 | G73: =SUMIFS('Payouts Reconciliation'!$C$5:$C$504,'Payouts Reconciliation'!$B$5:$B$504,">="&G$63,'Payouts Reconciliation'!$B$5:$B$504,"<"&DATE(YEAR(G$63),MONTH(G$63)+1,1),'Payouts Reconciliation'!$A$5:$A$504,$A73,'Payouts Reconciliation'!$O$5:$O$504,"<>EXAMPLE") -> 0 | H73: =SUMIFS('Payouts Reconciliation'!$C$5:$C$504,'Payouts Reconciliation'!$B$5:$B$504,">="&H$63,'Payouts Reconciliation'!$B$5:$B$504,"<"&DATE(YEAR(H$63),MONTH(H$63)+1,1),'Payouts Reconciliation'!$A$5:$A$504,$A73,'Payouts Reconciliation'!$O$5:$O$504,"<>EXAMPLE") -> 0 | I73: =SUMIFS('Payouts Reconciliation'!$C$5:$C$504,'Payouts Reconciliation'!$B$5:$B$504,">="&I$63,'Payouts Reconciliation'!$B$5:$B$504,"<"&DATE(YEAR(I$63),MONTH(I$63)+1,1),'Payouts Reconciliation'!$A$5:$A$504,$A73,'Payouts Reconciliation'!$O$5:$O$504,"<>EXAMPLE") -> 0 | ... M73: =SUMIFS('Payouts Reconciliation'!$C$5:$C$504,'Payouts Reconciliation'!$B$5:$B$504,">="&M$63,'Payouts Reconciliation'!$B$5:$B$504,"<"&DATE(YEAR(M$63),MONTH(M$63)+1,1),'Payouts Reconciliation'!$A$5:$A$504,$A73,'Payouts Reconciliation'!$O$5:$O$504,"<>EXAMPLE") -> 0 | N73: =SUM(B73:M73) -> 0
A74: ='Chart of Accounts'!$A$76 -> Merchant of record | B74: =SUMIFS('Payouts Reconciliation'!$C$5:$C$504,'Payouts Reconciliation'!$B$5:$B$504,">="&B$63,'Payouts Reconciliation'!$B$5:$B$504,"<"&DATE(YEAR(B$63),MONTH(B$63)+1,1),'Payouts Reconciliation'!$A$5:$A$504,$A74,'Payouts Reconciliation'!$O$5:$O$504,"<>EXAMPLE") -> 0 | C74: =SUMIFS('Payouts Reconciliation'!$C$5:$C$504,'Payouts Reconciliation'!$B$5:$B$504,">="&C$63,'Payouts Reconciliation'!$B$5:$B$504,"<"&DATE(YEAR(C$63),MONTH(C$63)+1,1),'Payouts Reconciliation'!$A$5:$A$504,$A74,'Payouts Reconciliation'!$O$5:$O$504,"<>EXAMPLE") -> 0 | D74: =SUMIFS('Payouts Reconciliation'!$C$5:$C$504,'Payouts Reconciliation'!$B$5:$B$504,">="&D$63,'Payouts Reconciliation'!$B$5:$B$504,"<"&DATE(YEAR(D$63),MONTH(D$63)+1,1),'Payouts Reconciliation'!$A$5:$A$504,$A74,'Payouts Reconciliation'!$O$5:$O$504,"<>EXAMPLE") -> 0 | E74: =SUMIFS('Payouts Reconciliation'!$C$5:$C$504,'Payouts Reconciliation'!$B$5:$B$504,">="&E$63,'Payouts Reconciliation'!$B$5:$B$504,"<"&DATE(YEAR(E$63),MONTH(E$63)+1,1),'Payouts Reconciliation'!$A$5:$A$504,$A74,'Payouts Reconciliation'!$O$5:$O$504,"<>EXAMPLE") -> 0 | F74: =SUMIFS('Payouts Reconciliation'!$C$5:$C$504,'Payouts Reconciliation'!$B$5:$B$504,">="&F$63,'Payouts Reconciliation'!$B$5:$B$504,"<"&DATE(YEAR(F$63),MONTH(F$63)+1,1),'Payouts Reconciliation'!$A$5:$A$504,$A74,'Payouts Reconciliation'!$O$5:$O$504,"<>EXAMPLE") -> 0 | G74: =SUMIFS('Payouts Reconciliation'!$C$5:$C$504,'Payouts Reconciliation'!$B$5:$B$504,">="&G$63,'Payouts Reconciliation'!$B$5:$B$504,"<"&DATE(YEAR(G$63),MONTH(G$63)+1,1),'Payouts Reconciliation'!$A$5:$A$504,$A74,'Payouts Reconciliation'!$O$5:$O$504,"<>EXAMPLE") -> 0 | H74: =SUMIFS('Payouts Reconciliation'!$C$5:$C$504,'Payouts Reconciliation'!$B$5:$B$504,">="&H$63,'Payouts Reconciliation'!$B$5:$B$504,"<"&DATE(YEAR(H$63),MONTH(H$63)+1,1),'Payouts Reconciliation'!$A$5:$A$504,$A74,'Payouts Reconciliation'!$O$5:$O$504,"<>EXAMPLE") -> 0 | I74: =SUMIFS('Payouts Reconciliation'!$C$5:$C$504,'Payouts Reconciliation'!$B$5:$B$504,">="&I$63,'Payouts Reconciliation'!$B$5:$B$504,"<"&DATE(YEAR(I$63),MONTH(I$63)+1,1),'Payouts Reconciliation'!$A$5:$A$504,$A74,'Payouts Reconciliation'!$O$5:$O$504,"<>EXAMPLE") -> 0 | ... M74: =SUMIFS('Payouts Reconciliation'!$C$5:$C$504,'Payouts Reconciliation'!$B$5:$B$504,">="&M$63,'Payouts Reconciliation'!$B$5:$B$504,"<"&DATE(YEAR(M$63),MONTH(M$63)+1,1),'Payouts Reconciliation'!$A$5:$A$504,$A74,'Payouts Reconciliation'!$O$5:$O$504,"<>EXAMPLE") -> 0 | N74: =SUM(B74:M74) -> 0
A75: ='Chart of Accounts'!$A$77 -> Amazon Associates | B75: =SUMIFS('Payouts Reconciliation'!$C$5:$C$504,'Payouts Reconciliation'!$B$5:$B$504,">="&B$63,'Payouts Reconciliation'!$B$5:$B$504,"<"&DATE(YEAR(B$63),MONTH(B$63)+1,1),'Payouts Reconciliation'!$A$5:$A$504,$A75,'Payouts Reconciliation'!$O$5:$O$504,"<>EXAMPLE") -> 0 | C75: =SUMIFS('Payouts Reconciliation'!$C$5:$C$504,'Payouts Reconciliation'!$B$5:$B$504,">="&C$63,'Payouts Reconciliation'!$B$5:$B$504,"<"&DATE(YEAR(C$63),MONTH(C$63)+1,1),'Payouts Reconciliation'!$A$5:$A$504,$A75,'Payouts Reconciliation'!$O$5:$O$504,"<>EXAMPLE") -> 0 | D75: =SUMIFS('Payouts Reconciliation'!$C$5:$C$504,'Payouts Reconciliation'!$B$5:$B$504,">="&D$63,'Payouts Reconciliation'!$B$5:$B$504,"<"&DATE(YEAR(D$63),MONTH(D$63)+1,1),'Payouts Reconciliation'!$A$5:$A$504,$A75,'Payouts Reconciliation'!$O$5:$O$504,"<>EXAMPLE") -> 0 | E75: =SUMIFS('Payouts Reconciliation'!$C$5:$C$504,'Payouts Reconciliation'!$B$5:$B$504,">="&E$63,'Payouts Reconciliation'!$B$5:$B$504,"<"&DATE(YEAR(E$63),MONTH(E$63)+1,1),'Payouts Reconciliation'!$A$5:$A$504,$A75,'Payouts Reconciliation'!$O$5:$O$504,"<>EXAMPLE") -> 0 | F75: =SUMIFS('Payouts Reconciliation'!$C$5:$C$504,'Payouts Reconciliation'!$B$5:$B$504,">="&F$63,'Payouts Reconciliation'!$B$5:$B$504,"<"&DATE(YEAR(F$63),MONTH(F$63)+1,1),'Payouts Reconciliation'!$A$5:$A$504,$A75,'Payouts Reconciliation'!$O$5:$O$504,"<>EXAMPLE") -> 0 | G75: =SUMIFS('Payouts Reconciliation'!$C$5:$C$504,'Payouts Reconciliation'!$B$5:$B$504,">="&G$63,'Payouts Reconciliation'!$B$5:$B$504,"<"&DATE(YEAR(G$63),MONTH(G$63)+1,1),'Payouts Reconciliation'!$A$5:$A$504,$A75,'Payouts Reconciliation'!$O$5:$O$504,"<>EXAMPLE") -> 0 | H75: =SUMIFS('Payouts Reconciliation'!$C$5:$C$504,'Payouts Reconciliation'!$B$5:$B$504,">="&H$63,'Payouts Reconciliation'!$B$5:$B$504,"<"&DATE(YEAR(H$63),MONTH(H$63)+1,1),'Payouts Reconciliation'!$A$5:$A$504,$A75,'Payouts Reconciliation'!$O$5:$O$504,"<>EXAMPLE") -> 0 | I75: =SUMIFS('Payouts Reconciliation'!$C$5:$C$504,'Payouts Reconciliation'!$B$5:$B$504,">="&I$63,'Payouts Reconciliation'!$B$5:$B$504,"<"&DATE(YEAR(I$63),MONTH(I$63)+1,1),'Payouts Reconciliation'!$A$5:$A$504,$A75,'Payouts Reconciliation'!$O$5:$O$504,"<>EXAMPLE") -> 0 | ... M75: =SUMIFS('Payouts Reconciliation'!$C$5:$C$504,'Payouts Reconciliation'!$B$5:$B$504,">="&M$63,'Payouts Reconciliation'!$B$5:$B$504,"<"&DATE(YEAR(M$63),MONTH(M$63)+1,1),'Payouts Reconciliation'!$A$5:$A$504,$A75,'Payouts Reconciliation'!$O$5:$O$504,"<>EXAMPLE") -> 0 | N75: =SUM(B75:M75) -> 0
A76: ='Chart of Accounts'!$A$78 -> Bookshop.org | B76: =SUMIFS('Payouts Reconciliation'!$C$5:$C$504,'Payouts Reconciliation'!$B$5:$B$504,">="&B$63,'Payouts Reconciliation'!$B$5:$B$504,"<"&DATE(YEAR(B$63),MONTH(B$63)+1,1),'Payouts Reconciliation'!$A$5:$A$504,$A76,'Payouts Reconciliation'!$O$5:$O$504,"<>EXAMPLE") -> 0 | C76: =SUMIFS('Payouts Reconciliation'!$C$5:$C$504,'Payouts Reconciliation'!$B$5:$B$504,">="&C$63,'Payouts Reconciliation'!$B$5:$B$504,"<"&DATE(YEAR(C$63),MONTH(C$63)+1,1),'Payouts Reconciliation'!$A$5:$A$504,$A76,'Payouts Reconciliation'!$O$5:$O$504,"<>EXAMPLE") -> 0 | D76: =SUMIFS('Payouts Reconciliation'!$C$5:$C$504,'Payouts Reconciliation'!$B$5:$B$504,">="&D$63,'Payouts Reconciliation'!$B$5:$B$504,"<"&DATE(YEAR(D$63),MONTH(D$63)+1,1),'Payouts Reconciliation'!$A$5:$A$504,$A76,'Payouts Reconciliation'!$O$5:$O$504,"<>EXAMPLE") -> 0 | E76: =SUMIFS('Payouts Reconciliation'!$C$5:$C$504,'Payouts Reconciliation'!$B$5:$B$504,">="&E$63,'Payouts Reconciliation'!$B$5:$B$504,"<"&DATE(YEAR(E$63),MONTH(E$63)+1,1),'Payouts Reconciliation'!$A$5:$A$504,$A76,'Payouts Reconciliation'!$O$5:$O$504,"<>EXAMPLE") -> 0 | F76: =SUMIFS('Payouts Reconciliation'!$C$5:$C$504,'Payouts Reconciliation'!$B$5:$B$504,">="&F$63,'Payouts Reconciliation'!$B$5:$B$504,"<"&DATE(YEAR(F$63),MONTH(F$63)+1,1),'Payouts Reconciliation'!$A$5:$A$504,$A76,'Payouts Reconciliation'!$O$5:$O$504,"<>EXAMPLE") -> 0 | G76: =SUMIFS('Payouts Reconciliation'!$C$5:$C$504,'Payouts Reconciliation'!$B$5:$B$504,">="&G$63,'Payouts Reconciliation'!$B$5:$B$504,"<"&DATE(YEAR(G$63),MONTH(G$63)+1,1),'Payouts Reconciliation'!$A$5:$A$504,$A76,'Payouts Reconciliation'!$O$5:$O$504,"<>EXAMPLE") -> 0 | H76: =SUMIFS('Payouts Reconciliation'!$C$5:$C$504,'Payouts Reconciliation'!$B$5:$B$504,">="&H$63,'Payouts Reconciliation'!$B$5:$B$504,"<"&DATE(YEAR(H$63),MONTH(H$63)+1,1),'Payouts Reconciliation'!$A$5:$A$504,$A76,'Payouts Reconciliation'!$O$5:$O$504,"<>EXAMPLE") -> 0 | I76: =SUMIFS('Payouts Reconciliation'!$C$5:$C$504,'Payouts Reconciliation'!$B$5:$B$504,">="&I$63,'Payouts Reconciliation'!$B$5:$B$504,"<"&DATE(YEAR(I$63),MONTH(I$63)+1,1),'Payouts Reconciliation'!$A$5:$A$504,$A76,'Payouts Reconciliation'!$O$5:$O$504,"<>EXAMPLE") -> 0 | ... M76: =SUMIFS('Payouts Reconciliation'!$C$5:$C$504,'Payouts Reconciliation'!$B$5:$B$504,">="&M$63,'Payouts Reconciliation'!$B$5:$B$504,"<"&DATE(YEAR(M$63),MONTH(M$63)+1,1),'Payouts Reconciliation'!$A$5:$A$504,$A76,'Payouts Reconciliation'!$O$5:$O$504,"<>EXAMPLE") -> 0 | N76: =SUM(B76:M76) -> 0
A77: ='Chart of Accounts'!$A$79 -> Direct (check / ACH / cash) | B77: =SUMIFS('Payouts Reconciliation'!$C$5:$C$504,'Payouts Reconciliation'!$B$5:$B$504,">="&B$63,'Payouts Reconciliation'!$B$5:$B$504,"<"&DATE(YEAR(B$63),MONTH(B$63)+1,1),'Payouts Reconciliation'!$A$5:$A$504,$A77,'Payouts Reconciliation'!$O$5:$O$504,"<>EXAMPLE") -> 0 | C77: =SUMIFS('Payouts Reconciliation'!$C$5:$C$504,'Payouts Reconciliation'!$B$5:$B$504,">="&C$63,'Payouts Reconciliation'!$B$5:$B$504,"<"&DATE(YEAR(C$63),MONTH(C$63)+1,1),'Payouts Reconciliation'!$A$5:$A$504,$A77,'Payouts Reconciliation'!$O$5:$O$504,"<>EXAMPLE") -> 0 | D77: =SUMIFS('Payouts Reconciliation'!$C$5:$C$504,'Payouts Reconciliation'!$B$5:$B$504,">="&D$63,'Payouts Reconciliation'!$B$5:$B$504,"<"&DATE(YEAR(D$63),MONTH(D$63)+1,1),'Payouts Reconciliation'!$A$5:$A$504,$A77,'Payouts Reconciliation'!$O$5:$O$504,"<>EXAMPLE") -> 0 | E77: =SUMIFS('Payouts Reconciliation'!$C$5:$C$504,'Payouts Reconciliation'!$B$5:$B$504,">="&E$63,'Payouts Reconciliation'!$B$5:$B$504,"<"&DATE(YEAR(E$63),MONTH(E$63)+1,1),'Payouts Reconciliation'!$A$5:$A$504,$A77,'Payouts Reconciliation'!$O$5:$O$504,"<>EXAMPLE") -> 0 | F77: =SUMIFS('Payouts Reconciliation'!$C$5:$C$504,'Payouts Reconciliation'!$B$5:$B$504,">="&F$63,'Payouts Reconciliation'!$B$5:$B$504,"<"&DATE(YEAR(F$63),MONTH(F$63)+1,1),'Payouts Reconciliation'!$A$5:$A$504,$A77,'Payouts Reconciliation'!$O$5:$O$504,"<>EXAMPLE") -> 0 | G77: =SUMIFS('Payouts Reconciliation'!$C$5:$C$504,'Payouts Reconciliation'!$B$5:$B$504,">="&G$63,'Payouts Reconciliation'!$B$5:$B$504,"<"&DATE(YEAR(G$63),MONTH(G$63)+1,1),'Payouts Reconciliation'!$A$5:$A$504,$A77,'Payouts Reconciliation'!$O$5:$O$504,"<>EXAMPLE") -> 0 | H77: =SUMIFS('Payouts Reconciliation'!$C$5:$C$504,'Payouts Reconciliation'!$B$5:$B$504,">="&H$63,'Payouts Reconciliation'!$B$5:$B$504,"<"&DATE(YEAR(H$63),MONTH(H$63)+1,1),'Payouts Reconciliation'!$A$5:$A$504,$A77,'Payouts Reconciliation'!$O$5:$O$504,"<>EXAMPLE") -> 0 | I77: =SUMIFS('Payouts Reconciliation'!$C$5:$C$504,'Payouts Reconciliation'!$B$5:$B$504,">="&I$63,'Payouts Reconciliation'!$B$5:$B$504,"<"&DATE(YEAR(I$63),MONTH(I$63)+1,1),'Payouts Reconciliation'!$A$5:$A$504,$A77,'Payouts Reconciliation'!$O$5:$O$504,"<>EXAMPLE") -> 0 | ... M77: =SUMIFS('Payouts Reconciliation'!$C$5:$C$504,'Payouts Reconciliation'!$B$5:$B$504,">="&M$63,'Payouts Reconciliation'!$B$5:$B$504,"<"&DATE(YEAR(M$63),MONTH(M$63)+1,1),'Payouts Reconciliation'!$A$5:$A$504,$A77,'Payouts Reconciliation'!$O$5:$O$504,"<>EXAMPLE") -> 0 | N77: =SUM(B77:M77) -> 0
A78: Total | B78: =SUM(B64:B77) -> 0 | C78: =SUM(C64:C77) -> 0 | D78: =SUM(D64:D77) -> 0 | E78: =SUM(E64:E77) -> 0 | F78: =SUM(F64:F77) -> 0 | G78: =SUM(G64:G77) -> 0 | H78: =SUM(H64:H77) -> 0 | I78: =SUM(I64:I77) -> 0 | ... N78: =SUM(N64:N77) -> 0
A81: Month at a glance (all channels)
A82: Line | B82: =DATE($B$3,1,1) -> 46023 | C82: =DATE($B$3,2,1) -> 46054 | D82: =DATE($B$3,3,1) -> 46082 | E82: =DATE($B$3,4,1) -> 46113 | F82: =DATE($B$3,5,1) -> 46143 | G82: =DATE($B$3,6,1) -> 46174 | H82: =DATE($B$3,7,1) -> 46204 | I82: =DATE($B$3,8,1) -> 46235 | J82: =DATE($B$3,9,1) -> 46266 | K82: =DATE($B$3,10,1) -> 46296 | L82: =DATE($B$3,11,1) -> 46327 | M82: =DATE($B$3,12,1) -> 46357 | N82: Total
A83: Gross sales + shipping charged | B83: =SUMIFS('Sales Log'!$G$5:$G$1004,'Sales Log'!$A$5:$A$1004,">="&B$82,'Sales Log'!$A$5:$A$1004,"<"&DATE(YEAR(B$82),MONTH(B$82)+1,1),'Sales Log'!$R$5:$R$1004,"<>EXAMPLE")+SUMIFS('Sales Log'!$I$5:$I$1004,'Sales Log'!$A$5:$A$1004,">="&B$82,'Sales Log'!$A$5:$A$1004,"<"&DATE(YEAR(B$82),MONTH(B$82)+1,1),'Sales Log'!$R$5:$R$1004,"<>EXAMPLE") -> 0 | C83: =SUMIFS('Sales Log'!$G$5:$G$1004,'Sales Log'!$A$5:$A$1004,">="&C$82,'Sales Log'!$A$5:$A$1004,"<"&DATE(YEAR(C$82),MONTH(C$82)+1,1),'Sales Log'!$R$5:$R$1004,"<>EXAMPLE")+SUMIFS('Sales Log'!$I$5:$I$1004,'Sales Log'!$A$5:$A$1004,">="&C$82,'Sales Log'!$A$5:$A$1004,"<"&DATE(YEAR(C$82),MONTH(C$82)+1,1),'Sales Log'!$R$5:$R$1004,"<>EXAMPLE") -> 0 | D83: =SUMIFS('Sales Log'!$G$5:$G$1004,'Sales Log'!$A$5:$A$1004,">="&D$82,'Sales Log'!$A$5:$A$1004,"<"&DATE(YEAR(D$82),MONTH(D$82)+1,1),'Sales Log'!$R$5:$R$1004,"<>EXAMPLE")+SUMIFS('Sales Log'!$I$5:$I$1004,'Sales Log'!$A$5:$A$1004,">="&D$82,'Sales Log'!$A$5:$A$1004,"<"&DATE(YEAR(D$82),MONTH(D$82)+1,1),'Sales Log'!$R$5:$R$1004,"<>EXAMPLE") -> 0 | E83: =SUMIFS('Sales Log'!$G$5:$G$1004,'Sales Log'!$A$5:$A$1004,">="&E$82,'Sales Log'!$A$5:$A$1004,"<"&DATE(YEAR(E$82),MONTH(E$82)+1,1),'Sales Log'!$R$5:$R$1004,"<>EXAMPLE")+SUMIFS('Sales Log'!$I$5:$I$1004,'Sales Log'!$A$5:$A$1004,">="&E$82,'Sales Log'!$A$5:$A$1004,"<"&DATE(YEAR(E$82),MONTH(E$82)+1,1),'Sales Log'!$R$5:$R$1004,"<>EXAMPLE") -> 0 | F83: =SUMIFS('Sales Log'!$G$5:$G$1004,'Sales Log'!$A$5:$A$1004,">="&F$82,'Sales Log'!$A$5:$A$1004,"<"&DATE(YEAR(F$82),MONTH(F$82)+1,1),'Sales Log'!$R$5:$R$1004,"<>EXAMPLE")+SUMIFS('Sales Log'!$I$5:$I$1004,'Sales Log'!$A$5:$A$1004,">="&F$82,'Sales Log'!$A$5:$A$1004,"<"&DATE(YEAR(F$82),MONTH(F$82)+1,1),'Sales Log'!$R$5:$R$1004,"<>EXAMPLE") -> 0 | G83: =SUMIFS('Sales Log'!$G$5:$G$1004,'Sales Log'!$A$5:$A$1004,">="&G$82,'Sales Log'!$A$5:$A$1004,"<"&DATE(YEAR(G$82),MONTH(G$82)+1,1),'Sales Log'!$R$5:$R$1004,"<>EXAMPLE")+SUMIFS('Sales Log'!$I$5:$I$1004,'Sales Log'!$A$5:$A$1004,">="&G$82,'Sales Log'!$A$5:$A$1004,"<"&DATE(YEAR(G$82),MONTH(G$82)+1,1),'Sales Log'!$R$5:$R$1004,"<>EXAMPLE") -> 0 | H83: =SUMIFS('Sales Log'!$G$5:$G$1004,'Sales Log'!$A$5:$A$1004,">="&H$82,'Sales Log'!$A$5:$A$1004,"<"&DATE(YEAR(H$82),MONTH(H$82)+1,1),'Sales Log'!$R$5:$R$1004,"<>EXAMPLE")+SUMIFS('Sales Log'!$I$5:$I$1004,'Sales Log'!$A$5:$A$1004,">="&H$82,'Sales Log'!$A$5:$A$1004,"<"&DATE(YEAR(H$82),MONTH(H$82)+1,1),'Sales Log'!$R$5:$R$1004,"<>EXAMPLE") -> 0 | I83: =SUMIFS('Sales Log'!$G$5:$G$1004,'Sales Log'!$A$5:$A$1004,">="&I$82,'Sales Log'!$A$5:$A$1004,"<"&DATE(YEAR(I$82),MONTH(I$82)+1,1),'Sales Log'!$R$5:$R$1004,"<>EXAMPLE")+SUMIFS('Sales Log'!$I$5:$I$1004,'Sales Log'!$A$5:$A$1004,">="&I$82,'Sales Log'!$A$5:$A$1004,"<"&DATE(YEAR(I$82),MONTH(I$82)+1,1),'Sales Log'!$R$5:$R$1004,"<>EXAMPLE") -> 0 | ... M83: =SUMIFS('Sales Log'!$G$5:$G$1004,'Sales Log'!$A$5:$A$1004,">="&M$82,'Sales Log'!$A$5:$A$1004,"<"&DATE(YEAR(M$82),MONTH(M$82)+1,1),'Sales Log'!$R$5:$R$1004,"<>EXAMPLE")+SUMIFS('Sales Log'!$I$5:$I$1004,'Sales Log'!$A$5:$A$1004,">="&M$82,'Sales Log'!$A$5:$A$1004,"<"&DATE(YEAR(M$82),MONTH(M$82)+1,1),'Sales Log'!$R$5:$R$1004,"<>EXAMPLE") -> 0 | N83: =SUM(B83:M83) -> 0
A84: Platform fees | B84: =SUMIFS('Sales Log'!$H$5:$H$1004,'Sales Log'!$A$5:$A$1004,">="&B$82,'Sales Log'!$A$5:$A$1004,"<"&DATE(YEAR(B$82),MONTH(B$82)+1,1),'Sales Log'!$R$5:$R$1004,"<>EXAMPLE") -> 0 | C84: =SUMIFS('Sales Log'!$H$5:$H$1004,'Sales Log'!$A$5:$A$1004,">="&C$82,'Sales Log'!$A$5:$A$1004,"<"&DATE(YEAR(C$82),MONTH(C$82)+1,1),'Sales Log'!$R$5:$R$1004,"<>EXAMPLE") -> 0 | D84: =SUMIFS('Sales Log'!$H$5:$H$1004,'Sales Log'!$A$5:$A$1004,">="&D$82,'Sales Log'!$A$5:$A$1004,"<"&DATE(YEAR(D$82),MONTH(D$82)+1,1),'Sales Log'!$R$5:$R$1004,"<>EXAMPLE") -> 0 | E84: =SUMIFS('Sales Log'!$H$5:$H$1004,'Sales Log'!$A$5:$A$1004,">="&E$82,'Sales Log'!$A$5:$A$1004,"<"&DATE(YEAR(E$82),MONTH(E$82)+1,1),'Sales Log'!$R$5:$R$1004,"<>EXAMPLE") -> 0 | F84: =SUMIFS('Sales Log'!$H$5:$H$1004,'Sales Log'!$A$5:$A$1004,">="&F$82,'Sales Log'!$A$5:$A$1004,"<"&DATE(YEAR(F$82),MONTH(F$82)+1,1),'Sales Log'!$R$5:$R$1004,"<>EXAMPLE") -> 0 | G84: =SUMIFS('Sales Log'!$H$5:$H$1004,'Sales Log'!$A$5:$A$1004,">="&G$82,'Sales Log'!$A$5:$A$1004,"<"&DATE(YEAR(G$82),MONTH(G$82)+1,1),'Sales Log'!$R$5:$R$1004,"<>EXAMPLE") -> 0 | H84: =SUMIFS('Sales Log'!$H$5:$H$1004,'Sales Log'!$A$5:$A$1004,">="&H$82,'Sales Log'!$A$5:$A$1004,"<"&DATE(YEAR(H$82),MONTH(H$82)+1,1),'Sales Log'!$R$5:$R$1004,"<>EXAMPLE") -> 0 | I84: =SUMIFS('Sales Log'!$H$5:$H$1004,'Sales Log'!$A$5:$A$1004,">="&I$82,'Sales Log'!$A$5:$A$1004,"<"&DATE(YEAR(I$82),MONTH(I$82)+1,1),'Sales Log'!$R$5:$R$1004,"<>EXAMPLE") -> 0 | ... M84: =SUMIFS('Sales Log'!$H$5:$H$1004,'Sales Log'!$A$5:$A$1004,">="&M$82,'Sales Log'!$A$5:$A$1004,"<"&DATE(YEAR(M$82),MONTH(M$82)+1,1),'Sales Log'!$R$5:$R$1004,"<>EXAMPLE") -> 0 | N84: =SUM(B84:M84) -> 0
A85: Expenses (excl. inventory purchases) | B85: =SUMIFS(Expenses!$D$5:$D$1004,Expenses!$A$5:$A$1004,">="&B$82,Expenses!$A$5:$A$1004,"<"&DATE(YEAR(B$82),MONTH(B$82)+1,1),Expenses!$C$5:$C$1004,"<>"&'Chart of Accounts'!$H$5,Expenses!$K$5:$K$1004,"<>EXAMPLE") -> 0 | C85: =SUMIFS(Expenses!$D$5:$D$1004,Expenses!$A$5:$A$1004,">="&C$82,Expenses!$A$5:$A$1004,"<"&DATE(YEAR(C$82),MONTH(C$82)+1,1),Expenses!$C$5:$C$1004,"<>"&'Chart of Accounts'!$H$5,Expenses!$K$5:$K$1004,"<>EXAMPLE") -> 0 | D85: =SUMIFS(Expenses!$D$5:$D$1004,Expenses!$A$5:$A$1004,">="&D$82,Expenses!$A$5:$A$1004,"<"&DATE(YEAR(D$82),MONTH(D$82)+1,1),Expenses!$C$5:$C$1004,"<>"&'Chart of Accounts'!$H$5,Expenses!$K$5:$K$1004,"<>EXAMPLE") -> 0 | E85: =SUMIFS(Expenses!$D$5:$D$1004,Expenses!$A$5:$A$1004,">="&E$82,Expenses!$A$5:$A$1004,"<"&DATE(YEAR(E$82),MONTH(E$82)+1,1),Expenses!$C$5:$C$1004,"<>"&'Chart of Accounts'!$H$5,Expenses!$K$5:$K$1004,"<>EXAMPLE") -> 0 | F85: =SUMIFS(Expenses!$D$5:$D$1004,Expenses!$A$5:$A$1004,">="&F$82,Expenses!$A$5:$A$1004,"<"&DATE(YEAR(F$82),MONTH(F$82)+1,1),Expenses!$C$5:$C$1004,"<>"&'Chart of Accounts'!$H$5,Expenses!$K$5:$K$1004,"<>EXAMPLE") -> 0 | G85: =SUMIFS(Expenses!$D$5:$D$1004,Expenses!$A$5:$A$1004,">="&G$82,Expenses!$A$5:$A$1004,"<"&DATE(YEAR(G$82),MONTH(G$82)+1,1),Expenses!$C$5:$C$1004,"<>"&'Chart of Accounts'!$H$5,Expenses!$K$5:$K$1004,"<>EXAMPLE") -> 0 | H85: =SUMIFS(Expenses!$D$5:$D$1004,Expenses!$A$5:$A$1004,">="&H$82,Expenses!$A$5:$A$1004,"<"&DATE(YEAR(H$82),MONTH(H$82)+1,1),Expenses!$C$5:$C$1004,"<>"&'Chart of Accounts'!$H$5,Expenses!$K$5:$K$1004,"<>EXAMPLE") -> 0 | I85: =SUMIFS(Expenses!$D$5:$D$1004,Expenses!$A$5:$A$1004,">="&I$82,Expenses!$A$5:$A$1004,"<"&DATE(YEAR(I$82),MONTH(I$82)+1,1),Expenses!$C$5:$C$1004,"<>"&'Chart of Accounts'!$H$5,Expenses!$K$5:$K$1004,"<>EXAMPLE") -> 0 | ... M85: =SUMIFS(Expenses!$D$5:$D$1004,Expenses!$A$5:$A$1004,">="&M$82,Expenses!$A$5:$A$1004,"<"&DATE(YEAR(M$82),MONTH(M$82)+1,1),Expenses!$C$5:$C$1004,"<>"&'Chart of Accounts'!$H$5,Expenses!$K$5:$K$1004,"<>EXAMPLE") -> 0 | N85: =SUM(B85:M85) -> 0
A86: Inventory purchased (1200) | B86: =SUMIFS(Expenses!$D$5:$D$1004,Expenses!$A$5:$A$1004,">="&B$82,Expenses!$A$5:$A$1004,"<"&DATE(YEAR(B$82),MONTH(B$82)+1,1),Expenses!$C$5:$C$1004,'Chart of Accounts'!$H$5,Expenses!$K$5:$K$1004,"<>EXAMPLE") -> 0 | C86: =SUMIFS(Expenses!$D$5:$D$1004,Expenses!$A$5:$A$1004,">="&C$82,Expenses!$A$5:$A$1004,"<"&DATE(YEAR(C$82),MONTH(C$82)+1,1),Expenses!$C$5:$C$1004,'Chart of Accounts'!$H$5,Expenses!$K$5:$K$1004,"<>EXAMPLE") -> 0 | D86: =SUMIFS(Expenses!$D$5:$D$1004,Expenses!$A$5:$A$1004,">="&D$82,Expenses!$A$5:$A$1004,"<"&DATE(YEAR(D$82),MONTH(D$82)+1,1),Expenses!$C$5:$C$1004,'Chart of Accounts'!$H$5,Expenses!$K$5:$K$1004,"<>EXAMPLE") -> 0 | E86: =SUMIFS(Expenses!$D$5:$D$1004,Expenses!$A$5:$A$1004,">="&E$82,Expenses!$A$5:$A$1004,"<"&DATE(YEAR(E$82),MONTH(E$82)+1,1),Expenses!$C$5:$C$1004,'Chart of Accounts'!$H$5,Expenses!$K$5:$K$1004,"<>EXAMPLE") -> 0 | F86: =SUMIFS(Expenses!$D$5:$D$1004,Expenses!$A$5:$A$1004,">="&F$82,Expenses!$A$5:$A$1004,"<"&DATE(YEAR(F$82),MONTH(F$82)+1,1),Expenses!$C$5:$C$1004,'Chart of Accounts'!$H$5,Expenses!$K$5:$K$1004,"<>EXAMPLE") -> 0 | G86: =SUMIFS(Expenses!$D$5:$D$1004,Expenses!$A$5:$A$1004,">="&G$82,Expenses!$A$5:$A$1004,"<"&DATE(YEAR(G$82),MONTH(G$82)+1,1),Expenses!$C$5:$C$1004,'Chart of Accounts'!$H$5,Expenses!$K$5:$K$1004,"<>EXAMPLE") -> 0 | H86: =SUMIFS(Expenses!$D$5:$D$1004,Expenses!$A$5:$A$1004,">="&H$82,Expenses!$A$5:$A$1004,"<"&DATE(YEAR(H$82),MONTH(H$82)+1,1),Expenses!$C$5:$C$1004,'Chart of Accounts'!$H$5,Expenses!$K$5:$K$1004,"<>EXAMPLE") -> 0 | I86: =SUMIFS(Expenses!$D$5:$D$1004,Expenses!$A$5:$A$1004,">="&I$82,Expenses!$A$5:$A$1004,"<"&DATE(YEAR(I$82),MONTH(I$82)+1,1),Expenses!$C$5:$C$1004,'Chart of Accounts'!$H$5,Expenses!$K$5:$K$1004,"<>EXAMPLE") -> 0 | ... M86: =SUMIFS(Expenses!$D$5:$D$1004,Expenses!$A$5:$A$1004,">="&M$82,Expenses!$A$5:$A$1004,"<"&DATE(YEAR(M$82),MONTH(M$82)+1,1),Expenses!$C$5:$C$1004,'Chart of Accounts'!$H$5,Expenses!$K$5:$K$1004,"<>EXAMPLE") -> 0 | N86: =SUM(B86:M86) -> 0
A87: MD sales tax you collected (liability, not income) | B87: =SUMIFS('Sales Log'!$J$5:$J$1004,'Sales Log'!$A$5:$A$1004,">="&B$82,'Sales Log'!$A$5:$A$1004,"<"&DATE(YEAR(B$82),MONTH(B$82)+1,1),'Sales Log'!$K$5:$K$1004,"N",'Sales Log'!$M$5:$M$1004,"MD",'Sales Log'!$R$5:$R$1004,"<>EXAMPLE") -> 0 | C87: =SUMIFS('Sales Log'!$J$5:$J$1004,'Sales Log'!$A$5:$A$1004,">="&C$82,'Sales Log'!$A$5:$A$1004,"<"&DATE(YEAR(C$82),MONTH(C$82)+1,1),'Sales Log'!$K$5:$K$1004,"N",'Sales Log'!$M$5:$M$1004,"MD",'Sales Log'!$R$5:$R$1004,"<>EXAMPLE") -> 0 | D87: =SUMIFS('Sales Log'!$J$5:$J$1004,'Sales Log'!$A$5:$A$1004,">="&D$82,'Sales Log'!$A$5:$A$1004,"<"&DATE(YEAR(D$82),MONTH(D$82)+1,1),'Sales Log'!$K$5:$K$1004,"N",'Sales Log'!$M$5:$M$1004,"MD",'Sales Log'!$R$5:$R$1004,"<>EXAMPLE") -> 0 | E87: =SUMIFS('Sales Log'!$J$5:$J$1004,'Sales Log'!$A$5:$A$1004,">="&E$82,'Sales Log'!$A$5:$A$1004,"<"&DATE(YEAR(E$82),MONTH(E$82)+1,1),'Sales Log'!$K$5:$K$1004,"N",'Sales Log'!$M$5:$M$1004,"MD",'Sales Log'!$R$5:$R$1004,"<>EXAMPLE") -> 0 | F87: =SUMIFS('Sales Log'!$J$5:$J$1004,'Sales Log'!$A$5:$A$1004,">="&F$82,'Sales Log'!$A$5:$A$1004,"<"&DATE(YEAR(F$82),MONTH(F$82)+1,1),'Sales Log'!$K$5:$K$1004,"N",'Sales Log'!$M$5:$M$1004,"MD",'Sales Log'!$R$5:$R$1004,"<>EXAMPLE") -> 0 | G87: =SUMIFS('Sales Log'!$J$5:$J$1004,'Sales Log'!$A$5:$A$1004,">="&G$82,'Sales Log'!$A$5:$A$1004,"<"&DATE(YEAR(G$82),MONTH(G$82)+1,1),'Sales Log'!$K$5:$K$1004,"N",'Sales Log'!$M$5:$M$1004,"MD",'Sales Log'!$R$5:$R$1004,"<>EXAMPLE") -> 0 | H87: =SUMIFS('Sales Log'!$J$5:$J$1004,'Sales Log'!$A$5:$A$1004,">="&H$82,'Sales Log'!$A$5:$A$1004,"<"&DATE(YEAR(H$82),MONTH(H$82)+1,1),'Sales Log'!$K$5:$K$1004,"N",'Sales Log'!$M$5:$M$1004,"MD",'Sales Log'!$R$5:$R$1004,"<>EXAMPLE") -> 0 | I87: =SUMIFS('Sales Log'!$J$5:$J$1004,'Sales Log'!$A$5:$A$1004,">="&I$82,'Sales Log'!$A$5:$A$1004,"<"&DATE(YEAR(I$82),MONTH(I$82)+1,1),'Sales Log'!$K$5:$K$1004,"N",'Sales Log'!$M$5:$M$1004,"MD",'Sales Log'!$R$5:$R$1004,"<>EXAMPLE") -> 0 | ... M87: =SUMIFS('Sales Log'!$J$5:$J$1004,'Sales Log'!$A$5:$A$1004,">="&M$82,'Sales Log'!$A$5:$A$1004,"<"&DATE(YEAR(M$82),MONTH(M$82)+1,1),'Sales Log'!$K$5:$K$1004,"N",'Sales Log'!$M$5:$M$1004,"MD",'Sales Log'!$R$5:$R$1004,"<>EXAMPLE") -> 0 | N87: =SUM(B87:M87) -> 0
A88: Rough profit before tax (gross + shipping - fees - expenses) | B88: =B83-B84-B85 -> 0 | C88: =C83-C84-C85 -> 0 | D88: =D83-D84-D85 -> 0 | E88: =E83-E84-E85 -> 0 | F88: =F83-F84-F85 -> 0 | G88: =G83-G84-G85 -> 0 | H88: =H83-H84-H85 -> 0 | I88: =I83-I84-I85 -> 0 | ... N88: =N83-N84-N85 -> 0
A89: Rough only: excludes COGS on inventory sold, mileage and home office. QBO/Xero is the official P&L.

Sheet Sales Tax
A1: Sales Tax - Maryland
A2: Maryland sales you made yourself (website store, Stripe, PayPal, invoices, events). Sales where a marketplace, Amazon (KDP) or a merchant of record collected the tax are shown for information only and EXCLUDED from your return (UNVERIFIED; accountant confirms). File every assigned period, including zero returns. Pay from the tax-reserve account.
A4: Tax year | B4: ='Channel Summary'!$B$3 -> 2026 | C4: From Channel Summary B3.
A5: Maryland general sales & use tax rate | B5: 0.06 | C5: 6% - reviewer's knowledge, UNVERIFIED (marylandtaxes.gov unreachable Sept 27, 2026). Digital products taxable at 6% since 2021 (UNVERIFIED). Source to check: https://www.marylandtaxes.gov/business/sales-use/index.php
A6: Filing frequency the Comptroller assigned | C6: Pick Monthly, Quarterly or Annual once the Comptroller tells you. Returns are due the 20th of the month after the period (UNVERIFIED). If the 20th is a weekend, file by the Friday before to be safe.
A8: Month | B8: Period end | C8: MD taxable sales you made | D8: MD sales tax you collected | E8: Expected tax at rate | F8: Difference (collected - expected) | G8: MD non-taxable direct sales | H8: MD sales via marketplaces / KDP / MoR (excluded) | I8: Tax those platforms collected (excluded) | J8: Return due (20th of next month) | K8: Filed on | L8: Confirmation # | M8: Amount paid | N8: Paid from tax reserve? (Y/N) | O8: Notes
A9: =DATE($B$4,1,1) -> 46023 | B9: =DATE($B$4,2,0) -> 46053 | C9: =SUMIFS('Sales Log'!$G$5:$G$1004,'Sales Log'!$A$5:$A$1004,">="&$A9,'Sales Log'!$A$5:$A$1004,"<="&$B9,'Sales Log'!$M$5:$M$1004,"MD",'Sales Log'!$K$5:$K$1004,"N",'Sales Log'!$N$5:$N$1004,"Y",'Sales Log'!$R$5:$R$1004,"<>EXAMPLE") -> 0 | D9: =SUMIFS('Sales Log'!$J$5:$J$1004,'Sales Log'!$A$5:$A$1004,">="&$A9,'Sales Log'!$A$5:$A$1004,"<="&$B9,'Sales Log'!$M$5:$M$1004,"MD",'Sales Log'!$K$5:$K$1004,"N",'Sales Log'!$R$5:$R$1004,"<>EXAMPLE") -> 0 | E9: =ROUND(C9*$B$5,2) -> 0 | F9: =D9-E9 -> 0 | G9: =SUMIFS('Sales Log'!$G$5:$G$1004,'Sales Log'!$A$5:$A$1004,">="&$A9,'Sales Log'!$A$5:$A$1004,"<="&$B9,'Sales Log'!$M$5:$M$1004,"MD",'Sales Log'!$K$5:$K$1004,"N",'Sales Log'!$N$5:$N$1004,"N",'Sales Log'!$R$5:$R$1004,"<>EXAMPLE") -> 0 | H9: =SUMIFS('Sales Log'!$G$5:$G$1004,'Sales Log'!$A$5:$A$1004,">="&$A9,'Sales Log'!$A$5:$A$1004,"<="&$B9,'Sales Log'!$M$5:$M$1004,"MD",'Sales Log'!$K$5:$K$1004,"Y",'Sales Log'!$R$5:$R$1004,"<>EXAMPLE") -> 0 | I9: =SUMIFS('Sales Log'!$J$5:$J$1004,'Sales Log'!$A$5:$A$1004,">="&$A9,'Sales Log'!$A$5:$A$1004,"<="&$B9,'Sales Log'!$M$5:$M$1004,"MD",'Sales Log'!$K$5:$K$1004,"Y",'Sales Log'!$R$5:$R$1004,"<>EXAMPLE") -> 0 | J9: =DATE($B$4,2,20) -> 46073
A10: =DATE($B$4,2,1) -> 46054 | B10: =DATE($B$4,3,0) -> 46081 | C10: =SUMIFS('Sales Log'!$G$5:$G$1004,'Sales Log'!$A$5:$A$1004,">="&$A10,'Sales Log'!$A$5:$A$1004,"<="&$B10,'Sales Log'!$M$5:$M$1004,"MD",'Sales Log'!$K$5:$K$1004,"N",'Sales Log'!$N$5:$N$1004,"Y",'Sales Log'!$R$5:$R$1004,"<>EXAMPLE") -> 0 | D10: =SUMIFS('Sales Log'!$J$5:$J$1004,'Sales Log'!$A$5:$A$1004,">="&$A10,'Sales Log'!$A$5:$A$1004,"<="&$B10,'Sales Log'!$M$5:$M$1004,"MD",'Sales Log'!$K$5:$K$1004,"N",'Sales Log'!$R$5:$R$1004,"<>EXAMPLE") -> 0 | E10: =ROUND(C10*$B$5,2) -> 0 | F10: =D10-E10 -> 0 | G10: =SUMIFS('Sales Log'!$G$5:$G$1004,'Sales Log'!$A$5:$A$1004,">="&$A10,'Sales Log'!$A$5:$A$1004,"<="&$B10,'Sales Log'!$M$5:$M$1004,"MD",'Sales Log'!$K$5:$K$1004,"N",'Sales Log'!$N$5:$N$1004,"N",'Sales Log'!$R$5:$R$1004,"<>EXAMPLE") -> 0 | H10: =SUMIFS('Sales Log'!$G$5:$G$1004,'Sales Log'!$A$5:$A$1004,">="&$A10,'Sales Log'!$A$5:$A$1004,"<="&$B10,'Sales Log'!$M$5:$M$1004,"MD",'Sales Log'!$K$5:$K$1004,"Y",'Sales Log'!$R$5:$R$1004,"<>EXAMPLE") -> 0 | I10: =SUMIFS('Sales Log'!$J$5:$J$1004,'Sales Log'!$A$5:$A$1004,">="&$A10,'Sales Log'!$A$5:$A$1004,"<="&$B10,'Sales Log'!$M$5:$M$1004,"MD",'Sales Log'!$K$5:$K$1004,"Y",'Sales Log'!$R$5:$R$1004,"<>EXAMPLE") -> 0 | J10: =DATE($B$4,3,20) -> 46101
A11: =DATE($B$4,3,1) -> 46082 | B11: =DATE($B$4,4,0) -> 46112 | C11: =SUMIFS('Sales Log'!$G$5:$G$1004,'Sales Log'!$A$5:$A$1004,">="&$A11,'Sales Log'!$A$5:$A$1004,"<="&$B11,'Sales Log'!$M$5:$M$1004,"MD",'Sales Log'!$K$5:$K$1004,"N",'Sales Log'!$N$5:$N$1004,"Y",'Sales Log'!$R$5:$R$1004,"<>EXAMPLE") -> 0 | D11: =SUMIFS('Sales Log'!$J$5:$J$1004,'Sales Log'!$A$5:$A$1004,">="&$A11,'Sales Log'!$A$5:$A$1004,"<="&$B11,'Sales Log'!$M$5:$M$1004,"MD",'Sales Log'!$K$5:$K$1004,"N",'Sales Log'!$R$5:$R$1004,"<>EXAMPLE") -> 0 | E11: =ROUND(C11*$B$5,2) -> 0 | F11: =D11-E11 -> 0 | G11: =SUMIFS('Sales Log'!$G$5:$G$1004,'Sales Log'!$A$5:$A$1004,">="&$A11,'Sales Log'!$A$5:$A$1004,"<="&$B11,'Sales Log'!$M$5:$M$1004,"MD",'Sales Log'!$K$5:$K$1004,"N",'Sales Log'!$N$5:$N$1004,"N",'Sales Log'!$R$5:$R$1004,"<>EXAMPLE") -> 0 | H11: =SUMIFS('Sales Log'!$G$5:$G$1004,'Sales Log'!$A$5:$A$1004,">="&$A11,'Sales Log'!$A$5:$A$1004,"<="&$B11,'Sales Log'!$M$5:$M$1004,"MD",'Sales Log'!$K$5:$K$1004,"Y",'Sales Log'!$R$5:$R$1004,"<>EXAMPLE") -> 0 | I11: =SUMIFS('Sales Log'!$J$5:$J$1004,'Sales Log'!$A$5:$A$1004,">="&$A11,'Sales Log'!$A$5:$A$1004,"<="&$B11,'Sales Log'!$M$5:$M$1004,"MD",'Sales Log'!$K$5:$K$1004,"Y",'Sales Log'!$R$5:$R$1004,"<>EXAMPLE") -> 0 | J11: =DATE($B$4,4,20) -> 46132
A12: =DATE($B$4,4,1) -> 46113 | B12: =DATE($B$4,5,0) -> 46142 | C12: =SUMIFS('Sales Log'!$G$5:$G$1004,'Sales Log'!$A$5:$A$1004,">="&$A12,'Sales Log'!$A$5:$A$1004,"<="&$B12,'Sales Log'!$M$5:$M$1004,"MD",'Sales Log'!$K$5:$K$1004,"N",'Sales Log'!$N$5:$N$1004,"Y",'Sales Log'!$R$5:$R$1004,"<>EXAMPLE") -> 0 | D12: =SUMIFS('Sales Log'!$J$5:$J$1004,'Sales Log'!$A$5:$A$1004,">="&$A12,'Sales Log'!$A$5:$A$1004,"<="&$B12,'Sales Log'!$M$5:$M$1004,"MD",'Sales Log'!$K$5:$K$1004,"N",'Sales Log'!$R$5:$R$1004,"<>EXAMPLE") -> 0 | E12: =ROUND(C12*$B$5,2) -> 0 | F12: =D12-E12 -> 0 | G12: =SUMIFS('Sales Log'!$G$5:$G$1004,'Sales Log'!$A$5:$A$1004,">="&$A12,'Sales Log'!$A$5:$A$1004,"<="&$B12,'Sales Log'!$M$5:$M$1004,"MD",'Sales Log'!$K$5:$K$1004,"N",'Sales Log'!$N$5:$N$1004,"N",'Sales Log'!$R$5:$R$1004,"<>EXAMPLE") -> 0 | H12: =SUMIFS('Sales Log'!$G$5:$G$1004,'Sales Log'!$A$5:$A$1004,">="&$A12,'Sales Log'!$A$5:$A$1004,"<="&$B12,'Sales Log'!$M$5:$M$1004,"MD",'Sales Log'!$K$5:$K$1004,"Y",'Sales Log'!$R$5:$R$1004,"<>EXAMPLE") -> 0 | I12: =SUMIFS('Sales Log'!$J$5:$J$1004,'Sales Log'!$A$5:$A$1004,">="&$A12,'Sales Log'!$A$5:$A$1004,"<="&$B12,'Sales Log'!$M$5:$M$1004,"MD",'Sales Log'!$K$5:$K$1004,"Y",'Sales Log'!$R$5:$R$1004,"<>EXAMPLE") -> 0 | J12: =DATE($B$4,5,20) -> 46162
A13: =DATE($B$4,5,1) -> 46143 | B13: =DATE($B$4,6,0) -> 46173 | C13: =SUMIFS('Sales Log'!$G$5:$G$1004,'Sales Log'!$A$5:$A$1004,">="&$A13,'Sales Log'!$A$5:$A$1004,"<="&$B13,'Sales Log'!$M$5:$M$1004,"MD",'Sales Log'!$K$5:$K$1004,"N",'Sales Log'!$N$5:$N$1004,"Y",'Sales Log'!$R$5:$R$1004,"<>EXAMPLE") -> 0 | D13: =SUMIFS('Sales Log'!$J$5:$J$1004,'Sales Log'!$A$5:$A$1004,">="&$A13,'Sales Log'!$A$5:$A$1004,"<="&$B13,'Sales Log'!$M$5:$M$1004,"MD",'Sales Log'!$K$5:$K$1004,"N",'Sales Log'!$R$5:$R$1004,"<>EXAMPLE") -> 0 | E13: =ROUND(C13*$B$5,2) -> 0 | F13: =D13-E13 -> 0 | G13: =SUMIFS('Sales Log'!$G$5:$G$1004,'Sales Log'!$A$5:$A$1004,">="&$A13,'Sales Log'!$A$5:$A$1004,"<="&$B13,'Sales Log'!$M$5:$M$1004,"MD",'Sales Log'!$K$5:$K$1004,"N",'Sales Log'!$N$5:$N$1004,"N",'Sales Log'!$R$5:$R$1004,"<>EXAMPLE") -> 0 | H13: =SUMIFS('Sales Log'!$G$5:$G$1004,'Sales Log'!$A$5:$A$1004,">="&$A13,'Sales Log'!$A$5:$A$1004,"<="&$B13,'Sales Log'!$M$5:$M$1004,"MD",'Sales Log'!$K$5:$K$1004,"Y",'Sales Log'!$R$5:$R$1004,"<>EXAMPLE") -> 0 | I13: =SUMIFS('Sales Log'!$J$5:$J$1004,'Sales Log'!$A$5:$A$1004,">="&$A13,'Sales Log'!$A$5:$A$1004,"<="&$B13,'Sales Log'!$M$5:$M$1004,"MD",'Sales Log'!$K$5:$K$1004,"Y",'Sales Log'!$R$5:$R$1004,"<>EXAMPLE") -> 0 | J13: =DATE($B$4,6,20) -> 46193
A14: =DATE($B$4,6,1) -> 46174 | B14: =DATE($B$4,7,0) -> 46203 | C14: =SUMIFS('Sales Log'!$G$5:$G$1004,'Sales Log'!$A$5:$A$1004,">="&$A14,'Sales Log'!$A$5:$A$1004,"<="&$B14,'Sales Log'!$M$5:$M$1004,"MD",'Sales Log'!$K$5:$K$1004,"N",'Sales Log'!$N$5:$N$1004,"Y",'Sales Log'!$R$5:$R$1004,"<>EXAMPLE") -> 0 | D14: =SUMIFS('Sales Log'!$J$5:$J$1004,'Sales Log'!$A$5:$A$1004,">="&$A14,'Sales Log'!$A$5:$A$1004,"<="&$B14,'Sales Log'!$M$5:$M$1004,"MD",'Sales Log'!$K$5:$K$1004,"N",'Sales Log'!$R$5:$R$1004,"<>EXAMPLE") -> 0 | E14: =ROUND(C14*$B$5,2) -> 0 | F14: =D14-E14 -> 0 | G14: =SUMIFS('Sales Log'!$G$5:$G$1004,'Sales Log'!$A$5:$A$1004,">="&$A14,'Sales Log'!$A$5:$A$1004,"<="&$B14,'Sales Log'!$M$5:$M$1004,"MD",'Sales Log'!$K$5:$K$1004,"N",'Sales Log'!$N$5:$N$1004,"N",'Sales Log'!$R$5:$R$1004,"<>EXAMPLE") -> 0 | H14: =SUMIFS('Sales Log'!$G$5:$G$1004,'Sales Log'!$A$5:$A$1004,">="&$A14,'Sales Log'!$A$5:$A$1004,"<="&$B14,'Sales Log'!$M$5:$M$1004,"MD",'Sales Log'!$K$5:$K$1004,"Y",'Sales Log'!$R$5:$R$1004,"<>EXAMPLE") -> 0 | I14: =SUMIFS('Sales Log'!$J$5:$J$1004,'Sales Log'!$A$5:$A$1004,">="&$A14,'Sales Log'!$A$5:$A$1004,"<="&$B14,'Sales Log'!$M$5:$M$1004,"MD",'Sales Log'!$K$5:$K$1004,"Y",'Sales Log'!$R$5:$R$1004,"<>EXAMPLE") -> 0 | J14: =DATE($B$4,7,20) -> 46223
A15: =DATE($B$4,7,1) -> 46204 | B15: =DATE($B$4,8,0) -> 46234 | C15: =SUMIFS('Sales Log'!$G$5:$G$1004,'Sales Log'!$A$5:$A$1004,">="&$A15,'Sales Log'!$A$5:$A$1004,"<="&$B15,'Sales Log'!$M$5:$M$1004,"MD",'Sales Log'!$K$5:$K$1004,"N",'Sales Log'!$N$5:$N$1004,"Y",'Sales Log'!$R$5:$R$1004,"<>EXAMPLE") -> 0 | D15: =SUMIFS('Sales Log'!$J$5:$J$1004,'Sales Log'!$A$5:$A$1004,">="&$A15,'Sales Log'!$A$5:$A$1004,"<="&$B15,'Sales Log'!$M$5:$M$1004,"MD",'Sales Log'!$K$5:$K$1004,"N",'Sales Log'!$R$5:$R$1004,"<>EXAMPLE") -> 0 | E15: =ROUND(C15*$B$5,2) -> 0 | F15: =D15-E15 -> 0 | G15: =SUMIFS('Sales Log'!$G$5:$G$1004,'Sales Log'!$A$5:$A$1004,">="&$A15,'Sales Log'!$A$5:$A$1004,"<="&$B15,'Sales Log'!$M$5:$M$1004,"MD",'Sales Log'!$K$5:$K$1004,"N",'Sales Log'!$N$5:$N$1004,"N",'Sales Log'!$R$5:$R$1004,"<>EXAMPLE") -> 0 | H15: =SUMIFS('Sales Log'!$G$5:$G$1004,'Sales Log'!$A$5:$A$1004,">="&$A15,'Sales Log'!$A$5:$A$1004,"<="&$B15,'Sales Log'!$M$5:$M$1004,"MD",'Sales Log'!$K$5:$K$1004,"Y",'Sales Log'!$R$5:$R$1004,"<>EXAMPLE") -> 0 | I15: =SUMIFS('Sales Log'!$J$5:$J$1004,'Sales Log'!$A$5:$A$1004,">="&$A15,'Sales Log'!$A$5:$A$1004,"<="&$B15,'Sales Log'!$M$5:$M$1004,"MD",'Sales Log'!$K$5:$K$1004,"Y",'Sales Log'!$R$5:$R$1004,"<>EXAMPLE") -> 0 | J15: =DATE($B$4,8,20) -> 46254
A16: =DATE($B$4,8,1) -> 46235 | B16: =DATE($B$4,9,0) -> 46265 | C16: =SUMIFS('Sales Log'!$G$5:$G$1004,'Sales Log'!$A$5:$A$1004,">="&$A16,'Sales Log'!$A$5:$A$1004,"<="&$B16,'Sales Log'!$M$5:$M$1004,"MD",'Sales Log'!$K$5:$K$1004,"N",'Sales Log'!$N$5:$N$1004,"Y",'Sales Log'!$R$5:$R$1004,"<>EXAMPLE") -> 0 | D16: =SUMIFS('Sales Log'!$J$5:$J$1004,'Sales Log'!$A$5:$A$1004,">="&$A16,'Sales Log'!$A$5:$A$1004,"<="&$B16,'Sales Log'!$M$5:$M$1004,"MD",'Sales Log'!$K$5:$K$1004,"N",'Sales Log'!$R$5:$R$1004,"<>EXAMPLE") -> 0 | E16: =ROUND(C16*$B$5,2) -> 0 | F16: =D16-E16 -> 0 | G16: =SUMIFS('Sales Log'!$G$5:$G$1004,'Sales Log'!$A$5:$A$1004,">="&$A16,'Sales Log'!$A$5:$A$1004,"<="&$B16,'Sales Log'!$M$5:$M$1004,"MD",'Sales Log'!$K$5:$K$1004,"N",'Sales Log'!$N$5:$N$1004,"N",'Sales Log'!$R$5:$R$1004,"<>EXAMPLE") -> 0 | H16: =SUMIFS('Sales Log'!$G$5:$G$1004,'Sales Log'!$A$5:$A$1004,">="&$A16,'Sales Log'!$A$5:$A$1004,"<="&$B16,'Sales Log'!$M$5:$M$1004,"MD",'Sales Log'!$K$5:$K$1004,"Y",'Sales Log'!$R$5:$R$1004,"<>EXAMPLE") -> 0 | I16: =SUMIFS('Sales Log'!$J$5:$J$1004,'Sales Log'!$A$5:$A$1004,">="&$A16,'Sales Log'!$A$5:$A$1004,"<="&$B16,'Sales Log'!$M$5:$M$1004,"MD",'Sales Log'!$K$5:$K$1004,"Y",'Sales Log'!$R$5:$R$1004,"<>EXAMPLE") -> 0 | J16: =DATE($B$4,9,20) -> 46285
A17: =DATE($B$4,9,1) -> 46266 | B17: =DATE($B$4,10,0) -> 46295 | C17: =SUMIFS('Sales Log'!$G$5:$G$1004,'Sales Log'!$A$5:$A$1004,">="&$A17,'Sales Log'!$A$5:$A$1004,"<="&$B17,'Sales Log'!$M$5:$M$1004,"MD",'Sales Log'!$K$5:$K$1004,"N",'Sales Log'!$N$5:$N$1004,"Y",'Sales Log'!$R$5:$R$1004,"<>EXAMPLE") -> 0 | D17: =SUMIFS('Sales Log'!$J$5:$J$1004,'Sales Log'!$A$5:$A$1004,">="&$A17,'Sales Log'!$A$5:$A$1004,"<="&$B17,'Sales Log'!$M$5:$M$1004,"MD",'Sales Log'!$K$5:$K$1004,"N",'Sales Log'!$R$5:$R$1004,"<>EXAMPLE") -> 0 | E17: =ROUND(C17*$B$5,2) -> 0 | F17: =D17-E17 -> 0 | G17: =SUMIFS('Sales Log'!$G$5:$G$1004,'Sales Log'!$A$5:$A$1004,">="&$A17,'Sales Log'!$A$5:$A$1004,"<="&$B17,'Sales Log'!$M$5:$M$1004,"MD",'Sales Log'!$K$5:$K$1004,"N",'Sales Log'!$N$5:$N$1004,"N",'Sales Log'!$R$5:$R$1004,"<>EXAMPLE") -> 0 | H17: =SUMIFS('Sales Log'!$G$5:$G$1004,'Sales Log'!$A$5:$A$1004,">="&$A17,'Sales Log'!$A$5:$A$1004,"<="&$B17,'Sales Log'!$M$5:$M$1004,"MD",'Sales Log'!$K$5:$K$1004,"Y",'Sales Log'!$R$5:$R$1004,"<>EXAMPLE") -> 0 | I17: =SUMIFS('Sales Log'!$J$5:$J$1004,'Sales Log'!$A$5:$A$1004,">="&$A17,'Sales Log'!$A$5:$A$1004,"<="&$B17,'Sales Log'!$M$5:$M$1004,"MD",'Sales Log'!$K$5:$K$1004,"Y",'Sales Log'!$R$5:$R$1004,"<>EXAMPLE") -> 0 | J17: =DATE($B$4,10,20) -> 46315
A18: =DATE($B$4,10,1) -> 46296 | B18: =DATE($B$4,11,0) -> 46326 | C18: =SUMIFS('Sales Log'!$G$5:$G$1004,'Sales Log'!$A$5:$A$1004,">="&$A18,'Sales Log'!$A$5:$A$1004,"<="&$B18,'Sales Log'!$M$5:$M$1004,"MD",'Sales Log'!$K$5:$K$1004,"N",'Sales Log'!$N$5:$N$1004,"Y",'Sales Log'!$R$5:$R$1004,"<>EXAMPLE") -> 0 | D18: =SUMIFS('Sales Log'!$J$5:$J$1004,'Sales Log'!$A$5:$A$1004,">="&$A18,'Sales Log'!$A$5:$A$1004,"<="&$B18,'Sales Log'!$M$5:$M$1004,"MD",'Sales Log'!$K$5:$K$1004,"N",'Sales Log'!$R$5:$R$1004,"<>EXAMPLE") -> 0 | E18: =ROUND(C18*$B$5,2) -> 0 | F18: =D18-E18 -> 0 | G18: =SUMIFS('Sales Log'!$G$5:$G$1004,'Sales Log'!$A$5:$A$1004,">="&$A18,'Sales Log'!$A$5:$A$1004,"<="&$B18,'Sales Log'!$M$5:$M$1004,"MD",'Sales Log'!$K$5:$K$1004,"N",'Sales Log'!$N$5:$N$1004,"N",'Sales Log'!$R$5:$R$1004,"<>EXAMPLE") -> 0 | H18: =SUMIFS('Sales Log'!$G$5:$G$1004,'Sales Log'!$A$5:$A$1004,">="&$A18,'Sales Log'!$A$5:$A$1004,"<="&$B18,'Sales Log'!$M$5:$M$1004,"MD",'Sales Log'!$K$5:$K$1004,"Y",'Sales Log'!$R$5:$R$1004,"<>EXAMPLE") -> 0 | I18: =SUMIFS('Sales Log'!$J$5:$J$1004,'Sales Log'!$A$5:$A$1004,">="&$A18,'Sales Log'!$A$5:$A$1004,"<="&$B18,'Sales Log'!$M$5:$M$1004,"MD",'Sales Log'!$K$5:$K$1004,"Y",'Sales Log'!$R$5:$R$1004,"<>EXAMPLE") -> 0 | J18: =DATE($B$4,11,20) -> 46346
A19: =DATE($B$4,11,1) -> 46327 | B19: =DATE($B$4,12,0) -> 46356 | C19: =SUMIFS('Sales Log'!$G$5:$G$1004,'Sales Log'!$A$5:$A$1004,">="&$A19,'Sales Log'!$A$5:$A$1004,"<="&$B19,'Sales Log'!$M$5:$M$1004,"MD",'Sales Log'!$K$5:$K$1004,"N",'Sales Log'!$N$5:$N$1004,"Y",'Sales Log'!$R$5:$R$1004,"<>EXAMPLE") -> 0 | D19: =SUMIFS('Sales Log'!$J$5:$J$1004,'Sales Log'!$A$5:$A$1004,">="&$A19,'Sales Log'!$A$5:$A$1004,"<="&$B19,'Sales Log'!$M$5:$M$1004,"MD",'Sales Log'!$K$5:$K$1004,"N",'Sales Log'!$R$5:$R$1004,"<>EXAMPLE") -> 0 | E19: =ROUND(C19*$B$5,2) -> 0 | F19: =D19-E19 -> 0 | G19: =SUMIFS('Sales Log'!$G$5:$G$1004,'Sales Log'!$A$5:$A$1004,">="&$A19,'Sales Log'!$A$5:$A$1004,"<="&$B19,'Sales Log'!$M$5:$M$1004,"MD",'Sales Log'!$K$5:$K$1004,"N",'Sales Log'!$N$5:$N$1004,"N",'Sales Log'!$R$5:$R$1004,"<>EXAMPLE") -> 0 | H19: =SUMIFS('Sales Log'!$G$5:$G$1004,'Sales Log'!$A$5:$A$1004,">="&$A19,'Sales Log'!$A$5:$A$1004,"<="&$B19,'Sales Log'!$M$5:$M$1004,"MD",'Sales Log'!$K$5:$K$1004,"Y",'Sales Log'!$R$5:$R$1004,"<>EXAMPLE") -> 0 | I19: =SUMIFS('Sales Log'!$J$5:$J$1004,'Sales Log'!$A$5:$A$1004,">="&$A19,'Sales Log'!$A$5:$A$1004,"<="&$B19,'Sales Log'!$M$5:$M$1004,"MD",'Sales Log'!$K$5:$K$1004,"Y",'Sales Log'!$R$5:$R$1004,"<>EXAMPLE") -> 0 | J19: =DATE($B$4,12,20) -> 46376
A20: =DATE($B$4,12,1) -> 46357 | B20: =DATE($B$4,13,0) -> 46387 | C20: =SUMIFS('Sales Log'!$G$5:$G$1004,'Sales Log'!$A$5:$A$1004,">="&$A20,'Sales Log'!$A$5:$A$1004,"<="&$B20,'Sales Log'!$M$5:$M$1004,"MD",'Sales Log'!$K$5:$K$1004,"N",'Sales Log'!$N$5:$N$1004,"Y",'Sales Log'!$R$5:$R$1004,"<>EXAMPLE") -> 0 | D20: =SUMIFS('Sales Log'!$J$5:$J$1004,'Sales Log'!$A$5:$A$1004,">="&$A20,'Sales Log'!$A$5:$A$1004,"<="&$B20,'Sales Log'!$M$5:$M$1004,"MD",'Sales Log'!$K$5:$K$1004,"N",'Sales Log'!$R$5:$R$1004,"<>EXAMPLE") -> 0 | E20: =ROUND(C20*$B$5,2) -> 0 | F20: =D20-E20 -> 0 | G20: =SUMIFS('Sales Log'!$G$5:$G$1004,'Sales Log'!$A$5:$A$1004,">="&$A20,'Sales Log'!$A$5:$A$1004,"<="&$B20,'Sales Log'!$M$5:$M$1004,"MD",'Sales Log'!$K$5:$K$1004,"N",'Sales Log'!$N$5:$N$1004,"N",'Sales Log'!$R$5:$R$1004,"<>EXAMPLE") -> 0 | H20: =SUMIFS('Sales Log'!$G$5:$G$1004,'Sales Log'!$A$5:$A$1004,">="&$A20,'Sales Log'!$A$5:$A$1004,"<="&$B20,'Sales Log'!$M$5:$M$1004,"MD",'Sales Log'!$K$5:$K$1004,"Y",'Sales Log'!$R$5:$R$1004,"<>EXAMPLE") -> 0 | I20: =SUMIFS('Sales Log'!$J$5:$J$1004,'Sales Log'!$A$5:$A$1004,">="&$A20,'Sales Log'!$A$5:$A$1004,"<="&$B20,'Sales Log'!$M$5:$M$1004,"MD",'Sales Log'!$K$5:$K$1004,"Y",'Sales Log'!$R$5:$R$1004,"<>EXAMPLE") -> 0 | J20: =DATE($B$4,13,20) -> 46407
A21: Year total | C21: =SUM(C9:C20) -> 0 | D21: =SUM(D9:D20) -> 0 | E21: =SUM(E9:E20) -> 0 | F21: =SUM(F9:F20) -> 0 | G21: =SUM(G9:G20) -> 0 | H21: =SUM(H9:H20) -> 0 | I21: =SUM(I9:I20) -> 0 | M21: =SUM(M9:M20) -> 0
A23: Quarterly and annual view (use the one that matches your filing frequency)
A24: Period | B24: Period end | C24: MD taxable sales you made | D24: MD sales tax you collected | E24: Expected tax at rate | F24: Difference | G24: MD non-taxable direct sales | H24: Marketplace / KDP / MoR sales (excluded) | I24: Tax platforms collected (excluded) | J24: Return due | K24: Filed on | L24: Confirmation # | M24: Amount paid | N24: Paid from tax reserve? (Y/N) | O24: Notes
A25: Q1 | B25: =B11 -> 46112 | C25: =SUM(C9:C11) -> 0 | D25: =SUM(D9:D11) -> 0 | E25: =SUM(E9:E11) -> 0 | F25: =SUM(F9:F11) -> 0 | G25: =SUM(G9:G11) -> 0 | H25: =SUM(H9:H11) -> 0 | I25: =SUM(I9:I11) -> 0 | J25: =DATE($B$4,4,20) -> 46132
A26: Q2 | B26: =B14 -> 46203 | C26: =SUM(C12:C14) -> 0 | D26: =SUM(D12:D14) -> 0 | E26: =SUM(E12:E14) -> 0 | F26: =SUM(F12:F14) -> 0 | G26: =SUM(G12:G14) -> 0 | H26: =SUM(H12:H14) -> 0 | I26: =SUM(I12:I14) -> 0 | J26: =DATE($B$4,7,20) -> 46223
A27: Q3 | B27: =B17 -> 46295 | C27: =SUM(C15:C17) -> 0 | D27: =SUM(D15:D17) -> 0 | E27: =SUM(E15:E17) -> 0 | F27: =SUM(F15:F17) -> 0 | G27: =SUM(G15:G17) -> 0 | H27: =SUM(H15:H17) -> 0 | I27: =SUM(I15:I17) -> 0 | J27: =DATE($B$4,10,20) -> 46315
A28: Q4 | B28: =B20 -> 46387 | C28: =SUM(C18:C20) -> 0 | D28: =SUM(D18:D20) -> 0 | E28: =SUM(E18:E20) -> 0 | F28: =SUM(F18:F20) -> 0 | G28: =SUM(G18:G20) -> 0 | H28: =SUM(H18:H20) -> 0 | I28: =SUM(I18:I20) -> 0 | J28: =DATE($B$4,13,20) -> 46407
A29: Annual | B29: =B20 -> 46387 | C29: =C21 -> 0 | D29: =D21 -> 0 | E29: =E21 -> 0 | F29: =F21 -> 0 | G29: =G21 -> 0 | H29: =H21 -> 0 | I29: =I21 -> 0 | J29: =DATE($B$4+1,1,20) -> 46407
A31: Notes (all UNVERIFIED - marylandtaxes.gov was unreachable on Sept 27, 2026; your accountant confirms):
A32: - Taxable when YOU sell to Maryland buyers: goods (books, card deck, merch) and digital products (printables, possibly the pre-recorded course and workshop kits). Live coaching and workshop fees are generally not taxable; goods sold at workshops are.
A33: - Excluded: Etsy, TikTok Shop, TpT (marketplace facilitators), KDP (Amazon is the seller), a merchant of record, and likely Faire.
A34: - Whether shipping charges are taxable in Maryland: ask the accountant (not included in taxable sales above).
A35: - Timely filers get a vendor collection credit (reported as 1.2% of the first $6,000 of tax and 0.9% after, capped per return).
A36: - Business filing may have moved to the Comptroller's 'Maryland Tax Connect' portal. Zero returns are still required.
A37: - Direct website sales into other states can create economic nexus there (often $100,000 of sales; some states also 200 transactions). Check once a quarter with the accountant.

Sheet Quarterly Estimates
A1: Quarterly Estimates (placeholders - your accountant sets the real payment)
A2: Federal Form 1040-ES and Maryland estimated payments on the LLC's profit (single-member LLC taxed by default = Schedule C + Schedule SE on your 1040; classification UNVERIFIED, accountant decides). The Sept 15, 2026 payment date has passed: if the business had 2026 profit, ask the accountant about a catch-up payment now. Not tax advice.
A4: Tax year | B4: ='Channel Summary'!$B$3 -> 2026 | C4: From Channel Summary B3.
A5: Net-earnings factor for SE tax | B5: 0.9235 | C5: 92.35% of net profit is subject to SE tax (reviewer's knowledge, UNVERIFIED). https://www.irs.gov/pub/irs-pdf/f1040es.pdf
A6: Self-employment tax rate | B6: 0.153 | C6: 15.3% = 12.4% Social Security (up to the annual wage base) + 2.9% Medicare (UNVERIFIED). Wage-base cap ignored here.
A7: SE tax applies when net SE earnings reach | B7: 400 | C7: $400 (UNVERIFIED).
A8: Set-aside % of profit to the tax reserve | B8: 0.25 | C8: Rule of thumb 25-30%, NOT an official figure. Your accountant sets it. Also move 100% of MD sales tax collected.
A9: Income-tax placeholder rate (accountant fills) | C9: Leave blank until your accountant gives you a rate; blank = 0.
A11: Quarter | B11: Period start | C11: Period end | D11: Federal due date | E11: Gross income (sales + shipping) | F11: Platform fees | G11: Expenses (excl. inventory) | H11: Mileage value | I11: Net profit (period) | J11: YTD net profit | K11: SE tax on YTD (placeholder) | L11: SE tax this period (placeholder) | M11: Income tax placeholder (period) | N11: Suggested set-aside (period) | O11: Federal payment (accountant sets) | P11: Federal paid on | Q11: Federal confirmation # | R11: Maryland payment (Form PV) | S11: Maryland paid on | T11: Notes
A12: Q1 | B12: =DATE($B$4,1,1) -> 46023 | C12: =DATE($B$4,3,31) -> 46112 | D12: 46127 | E12: =SUMIFS('Sales Log'!$G$5:$G$1004,'Sales Log'!$A$5:$A$1004,">="&$B12,'Sales Log'!$A$5:$A$1004,"<="&$C12,'Sales Log'!$R$5:$R$1004,"<>EXAMPLE")+SUMIFS('Sales Log'!$I$5:$I$1004,'Sales Log'!$A$5:$A$1004,">="&$B12,'Sales Log'!$A$5:$A$1004,"<="&$C12,'Sales Log'!$R$5:$R$1004,"<>EXAMPLE") -> 0 | F12: =SUMIFS('Sales Log'!$H$5:$H$1004,'Sales Log'!$A$5:$A$1004,">="&$B12,'Sales Log'!$A$5:$A$1004,"<="&$C12,'Sales Log'!$R$5:$R$1004,"<>EXAMPLE") -> 0 | G12: =SUMIFS(Expenses!$D$5:$D$1004,Expenses!$A$5:$A$1004,">="&$B12,Expenses!$A$5:$A$1004,"<="&$C12,Expenses!$C$5:$C$1004,"<>"&'Chart of Accounts'!$H$5,Expenses!$K$5:$K$1004,"<>EXAMPLE") -> 0 | H12: =SUMIFS('Mileage & Event Log'!$I$6:$I$505,'Mileage & Event Log'!$A$6:$A$505,">="&$B12,'Mileage & Event Log'!$A$6:$A$505,"<="&$C12,'Mileage & Event Log'!$L$6:$L$505,"<>EXAMPLE") -> 0 | I12: =E12-F12-G12-H12 -> 0 | J12: =SUM($I$12:I12) -> 0 | K12: =IF(J12*$B$5>=$B$7,ROUND(J12*$B$5*$B$6,2),0) -> 0 | L12: =K12 -> 0 | M12: =ROUND(MAX(0,I12)*$B$9,2) -> 0 | N12: =ROUND(MAX(0,I12)*$B$8,2) -> 0
A13: Q2 | B13: =DATE($B$4,4,1) -> 46113 | C13: =DATE($B$4,5,31) -> 46173 | D13: 46188 | E13: =SUMIFS('Sales Log'!$G$5:$G$1004,'Sales Log'!$A$5:$A$1004,">="&$B13,'Sales Log'!$A$5:$A$1004,"<="&$C13,'Sales Log'!$R$5:$R$1004,"<>EXAMPLE")+SUMIFS('Sales Log'!$I$5:$I$1004,'Sales Log'!$A$5:$A$1004,">="&$B13,'Sales Log'!$A$5:$A$1004,"<="&$C13,'Sales Log'!$R$5:$R$1004,"<>EXAMPLE") -> 0 | F13: =SUMIFS('Sales Log'!$H$5:$H$1004,'Sales Log'!$A$5:$A$1004,">="&$B13,'Sales Log'!$A$5:$A$1004,"<="&$C13,'Sales Log'!$R$5:$R$1004,"<>EXAMPLE") -> 0 | G13: =SUMIFS(Expenses!$D$5:$D$1004,Expenses!$A$5:$A$1004,">="&$B13,Expenses!$A$5:$A$1004,"<="&$C13,Expenses!$C$5:$C$1004,"<>"&'Chart of Accounts'!$H$5,Expenses!$K$5:$K$1004,"<>EXAMPLE") -> 0 | H13: =SUMIFS('Mileage & Event Log'!$I$6:$I$505,'Mileage & Event Log'!$A$6:$A$505,">="&$B13,'Mileage & Event Log'!$A$6:$A$505,"<="&$C13,'Mileage & Event Log'!$L$6:$L$505,"<>EXAMPLE") -> 0 | I13: =E13-F13-G13-H13 -> 0 | J13: =SUM($I$12:I13) -> 0 | K13: =IF(J13*$B$5>=$B$7,ROUND(J13*$B$5*$B$6,2),0) -> 0 | L13: =K13-K12 -> 0 | M13: =ROUND(MAX(0,I13)*$B$9,2) -> 0 | N13: =ROUND(MAX(0,I13)*$B$8,2) -> 0
A14: Q3 | B14: =DATE($B$4,6,1) -> 46174 | C14: =DATE($B$4,8,31) -> 46265 | D14: 46280 | E14: =SUMIFS('Sales Log'!$G$5:$G$1004,'Sales Log'!$A$5:$A$1004,">="&$B14,'Sales Log'!$A$5:$A$1004,"<="&$C14,'Sales Log'!$R$5:$R$1004,"<>EXAMPLE")+SUMIFS('Sales Log'!$I$5:$I$1004,'Sales Log'!$A$5:$A$1004,">="&$B14,'Sales Log'!$A$5:$A$1004,"<="&$C14,'Sales Log'!$R$5:$R$1004,"<>EXAMPLE") -> 0 | F14: =SUMIFS('Sales Log'!$H$5:$H$1004,'Sales Log'!$A$5:$A$1004,">="&$B14,'Sales Log'!$A$5:$A$1004,"<="&$C14,'Sales Log'!$R$5:$R$1004,"<>EXAMPLE") -> 0 | G14: =SUMIFS(Expenses!$D$5:$D$1004,Expenses!$A$5:$A$1004,">="&$B14,Expenses!$A$5:$A$1004,"<="&$C14,Expenses!$C$5:$C$1004,"<>"&'Chart of Accounts'!$H$5,Expenses!$K$5:$K$1004,"<>EXAMPLE") -> 0 | H14: =SUMIFS('Mileage & Event Log'!$I$6:$I$505,'Mileage & Event Log'!$A$6:$A$505,">="&$B14,'Mileage & Event Log'!$A$6:$A$505,"<="&$C14,'Mileage & Event Log'!$L$6:$L$505,"<>EXAMPLE") -> 0 | I14: =E14-F14-G14-H14 -> 0 | J14: =SUM($I$12:I14) -> 0 | K14: =IF(J14*$B$5>=$B$7,ROUND(J14*$B$5*$B$6,2),0) -> 0 | L14: =K14-K13 -> 0 | M14: =ROUND(MAX(0,I14)*$B$9,2) -> 0 | N14: =ROUND(MAX(0,I14)*$B$8,2) -> 0
A15: Q4 | B15: =DATE($B$4,9,1) -> 46266 | C15: =DATE($B$4,12,31) -> 46387 | D15: 46402 | E15: =SUMIFS('Sales Log'!$G$5:$G$1004,'Sales Log'!$A$5:$A$1004,">="&$B15,'Sales Log'!$A$5:$A$1004,"<="&$C15,'Sales Log'!$R$5:$R$1004,"<>EXAMPLE")+SUMIFS('Sales Log'!$I$5:$I$1004,'Sales Log'!$A$5:$A$1004,">="&$B15,'Sales Log'!$A$5:$A$1004,"<="&$C15,'Sales Log'!$R$5:$R$1004,"<>EXAMPLE") -> 0 | F15: =SUMIFS('Sales Log'!$H$5:$H$1004,'Sales Log'!$A$5:$A$1004,">="&$B15,'Sales Log'!$A$5:$A$1004,"<="&$C15,'Sales Log'!$R$5:$R$1004,"<>EXAMPLE") -> 0 | G15: =SUMIFS(Expenses!$D$5:$D$1004,Expenses!$A$5:$A$1004,">="&$B15,Expenses!$A$5:$A$1004,"<="&$C15,Expenses!$C$5:$C$1004,"<>"&'Chart of Accounts'!$H$5,Expenses!$K$5:$K$1004,"<>EXAMPLE") -> 0 | H15: =SUMIFS('Mileage & Event Log'!$I$6:$I$505,'Mileage & Event Log'!$A$6:$A$505,">="&$B15,'Mileage & Event Log'!$A$6:$A$505,"<="&$C15,'Mileage & Event Log'!$L$6:$L$505,"<>EXAMPLE") -> 0 | I15: =E15-F15-G15-H15 -> 0 | J15: =SUM($I$12:I15) -> 0 | K15: =IF(J15*$B$5>=$B$7,ROUND(J15*$B$5*$B$6,2),0) -> 0 | L15: =K15-K14 -> 0 | M15: =ROUND(MAX(0,I15)*$B$9,2) -> 0 | N15: =ROUND(MAX(0,I15)*$B$8,2) -> 0
A16: Year | E16: =SUM(E12:E15) -> 0 | F16: =SUM(F12:F15) -> 0 | G16: =SUM(G12:G15) -> 0 | H16: =SUM(H12:H15) -> 0 | I16: =SUM(I12:I15) -> 0 | L16: =SUM(L12:L15) -> 0 | M16: =SUM(M12:M15) -> 0 | N16: =SUM(N12:N15) -> 0 | O16: =SUM(O12:O15) -> 0 | R16: =SUM(R12:R15) -> 0
A18: How to read this tab:
A19: - Estimated tax payments are NOT business expenses. Pay from the tax-reserve account; book them to 3110 / 3120 Owner draw.
A20: - Penalty safe harbor: pay at least 90% of the 2026 tax or 100% of the 2025 tax (110% if 2025 AGI > $150,000) (UNVERIFIED).
A21: - Underpayment penalty = federal short-term rate + 3 points, figured on Form 2210 (UNVERIFIED current rate).
A22: - Pay through IRS Direct Pay, EFTPS or your IRS Online Account; save the confirmation number here and in the accountant folder.
A23: - Placeholders ignore the Social Security wage-base cap, the SE-tax deduction, the QBI deduction, credits and other income. Your accountant's number wins.

Sheet Mileage & Event Log
A1: Mileage & Event Log
A2: One row per business trip (supply runs, post office, workshops, school/PTA events, fairs). Write the purpose every time. Parking and tolls go in Expenses (6900). Enter the IRS standard mileage rate for the tax year in B3 when your accountant confirms it (not supplied here - UNVERIFIED).
A3: IRS standard mileage rate ($/mile) | D3: Total miles (excl. EXAMPLE) | E3: =SUMIFS($H$6:$H$505,$L$6:$L$505,"<>EXAMPLE") -> 0 | G3: Mileage value | H3: =SUMIFS($I$6:$I$505,$L$6:$L$505,"<>EXAMPLE") -> 0
A5: Date | B5: Business purpose | C5: Event name (if any) | D5: From | E5: To | F5: Round trip? (Y/N) | G5: One-way miles | H5: Total miles | I5: Mileage value | J5: Sales Log order IDs from this event | K5: Notes | L5: Example row
A6: 46313 | B6: EXAMPLE - deliver workshop kit and run book table | C6: EXAMPLE school family night | D6: Home office | E6: School event venue | F6: Y | G6: 12 | H6: =IF(G6="","",IF(F6="Y",G6*2,G6)) -> 24 | I6: =IF(H6="","",H6*$B$3) -> 0 | J6: EXAMPLE-EVT-001 to 004 | K6: EXAMPLE - made-up miles | L6: EXAMPLE
A7: 46317 | B7: EXAMPLE - post office: ship signed books | D7: Home office | E7: Post office | F7: Y | G7: 3.5 | H7: =IF(G7="","",IF(F7="Y",G7*2,G7)) -> 7 | I7: =IF(H7="","",H7*$B$3) -> 0 | K7: EXAMPLE | L7: EXAMPLE
H8: =IF(G8="","",IF(F8="Y",G8*2,G8)) | I8: =IF(H8="","",H8*$B$3)
H9: =IF(G9="","",IF(F9="Y",G9*2,G9)) | I9: =IF(H9="","",H9*$B$3)
H10: =IF(G10="","",IF(F10="Y",G10*2,G10)) | I10: =IF(H10="","",H10*$B$3)
H11: =IF(G11="","",IF(F11="Y",G11*2,G11)) | I11: =IF(H11="","",H11*$B$3)
H12: =IF(G12="","",IF(F12="Y",G12*2,G12)) | I12: =IF(H12="","",H12*$B$3)
H13: =IF(G13="","",IF(F13="Y",G13*2,G13)) | I13: =IF(H13="","",H13*$B$3)
H14: =IF(G14="","",IF(F14="Y",G14*2,G14)) | I14: =IF(H14="","",H14*$B$3)
H15: =IF(G15="","",IF(F15="Y",G15*2,G15)) | I15: =IF(H15="","",H15*$B$3)
H16: =IF(G16="","",IF(F16="Y",G16*2,G16)) | I16: =IF(H16="","",H16*$B$3)
H17: =IF(G17="","",IF(F17="Y",G17*2,G17)) | I17: =IF(H17="","",H17*$B$3)
H18: =IF(G18="","",IF(F18="Y",G18*2,G18)) | I18: =IF(H18="","",H18*$B$3)
H19: =IF(G19="","",IF(F19="Y",G19*2,G19)) | I19: =IF(H19="","",H19*$B$3)
... H505: =IF(G505="","",IF(F505="Y",G505*2,G505)) | I505: =IF(H505="","",H505*$B$3)

Sheet Accountant Packet
A1: Accountant Packet - checklist
A2: What your accountant receives, and when. Set Status from the drop-down. Put files in one shared folder with a sub-folder per month (e.g. 2026-10) plus 'Year-end 2026'. Never send passwords.
A3: Progress | B3: =COUNTIF(F5:F40,"Done")&" of "&(COUNTA(C5:C40)-COUNTIF(F5:F40,"N/A"))&" items done" -> 0 of 36 items done
A4: # | B4: Section | C4: Item | D4: Where it comes from | E4: Send by | F4: Status | G4: Date sent | H4: Location / link | I4: Notes
A5: 1 | B5: One-time setup | C5: Articles of organization, EIN letter (CP 575 or 147C), operating agreement | D5: Your records / ENTITY.md | E5: Once, at the first meeting | F5: Not started
A6: 2 | B6: One-time setup | C6: Trade-name (DBA) registration: 'Play Before Pixels' to AlphaPlay LLC (SDAT) | D6: Maryland SDAT | E6: When filed | F6: Not started
A7: 3 | B7: One-time setup | C7: Maryland sales & use tax registration updated for the new activities; filing frequency assigned | D7: Comptroller of Maryland | E7: When confirmed | F7: Not started
A8: 4 | B8: One-time setup | C8: Accountant's decisions: tax classification (Schedule C vs S-corp), which TIN to use on platform W-9s, set-aside % | D8: Accountant | E8: BEFORE any platform tax interview | F8: Not started
A9: 5 | B9: One-time setup | C9: Accountant invited to QBO/Xero with the 'Accountant' user type | D9: QBO / Xero | E9: When the ledger is created | F9: Not started
A10: 6 | B10: One-time setup | C10: List of every platform account (name, payout account last 4 digits, tax form it issues) - no passwords | D10: Chart of Accounts > Channel map | E10: Once; update when a channel is added | F10: Not started
A11: 7 | B11: Monthly | C11: Bank statement PDFs - business checking and tax reserve | D11: Bank | E11: 15th of the following month | F11: Not started
A12: 8 | B12: Monthly | C12: Business credit card statement PDF | D12: Card issuer | E12: 15th of the following month | F12: Not started
A13: 9 | B13: Monthly | C13: Platform reports: KDP royalty/payments, IngramSpark compensation, Etsy CSV, TikTok settlement, Shopify payouts, Stripe payout reconciliation, PayPal statement, TpT sales, Faire payouts, MoR payout, Associates/Bookshop earnings | D13: Each platform | E13: 15th of the following month | F13: Not started
A14: 10 | B14: Monthly | C14: Printful billing history | D14: Printful | E14: 15th of the following month | F14: Not started
A15: 11 | B15: Monthly | C15: Every receipt attached in QBO/Xero; nothing uncategorized; 'Ask My Accountant' items noted | D15: QBO / Xero | E15: 15th of the following month | F15: Not started
A16: 12 | B16: Monthly | C16: Payouts Reconciliation tab: every payout MATCHED (or explained) | D16: This workbook | E16: 15th of the following month | F16: Not started
... A40: 36 | B40: 2027 filings | C40: SDAT Annual Report for AlphaPlay LLC (fee reported $300, UNVERIFIED) + confirmation | D40: Maryland SDAT | E40: Apr 15, 2027 | F40: Not started
