Workbook

Sheet README
A1: Play Before Pixels — Education Groups Target Directory
A2: AlphaPlay LLC (trade name Play Before Pixels). Built September 28, 2026 from four verified research lists: early childhood, K–12 and libraries, parent groups, and international. Internal planning file; not for publication.
A4: Tabs and counts (live formulas; they update as you edit)
A5: Tab | B5: Rows | C5: Fit 5 | D5: Fit 4 | E5: Fit 3 | F5: Fit ≤2 | G5: Confirmed Y | H5: Status ≠ Not started
A6: All — ranked | B6: =COUNTA('All — ranked'!B2:B225) -> 224 | C6: =COUNTIF('All — ranked'!A2:A225,5) -> 10 | D6: =COUNTIF('All — ranked'!A2:A225,4) -> 46 | E6: =COUNTIF('All — ranked'!A2:A225,3) -> 95 | F6: =COUNTIF('All — ranked'!A2:A225,"<=2") -> 73 | G6: =COUNTIF('All — ranked'!L2:L225,"Y") -> 82 | H6: =COUNTA('All — ranked'!N2:N225)-COUNTIF('All — ranked'!N2:N225,"Not started") -> 0
A7: Early Childhood & Care | B7: =COUNTA('Early Childhood & Care'!B2:B49) -> 48 | C7: =COUNTIF('Early Childhood & Care'!A2:A49,5) -> 4 | D7: =COUNTIF('Early Childhood & Care'!A2:A49,4) -> 20 | E7: =COUNTIF('Early Childhood & Care'!A2:A49,3) -> 20 | F7: =COUNTIF('Early Childhood & Care'!A2:A49,"<=2") -> 4 | G7: =COUNTIF('Early Childhood & Care'!L2:L49,"Y") -> 38 | H7: =COUNTA('Early Childhood & Care'!N2:N49)-COUNTIF('Early Childhood & Care'!N2:N49,"Not started") -> 0
A8: K–12 & Libraries | B8: =COUNTA('K–12 & Libraries'!B2:B54) -> 53 | C8: =COUNTIF('K–12 & Libraries'!A2:A54,5) -> 5 | D8: =COUNTIF('K–12 & Libraries'!A2:A54,4) -> 11 | E8: =COUNTIF('K–12 & Libraries'!A2:A54,3) -> 26 | F8: =COUNTIF('K–12 & Libraries'!A2:A54,"<=2") -> 11 | G8: =COUNTIF('K–12 & Libraries'!L2:L54,"Y") -> 39 | H8: =COUNTA('K–12 & Libraries'!N2:N54)-COUNTIF('K–12 & Libraries'!N2:N54,"Not started") -> 0
A9: Parents & Advocacy | B9: =COUNTA('Parents & Advocacy'!B2:B65) -> 64 | C9: =COUNTIF('Parents & Advocacy'!A2:A65,5) -> 1 | D9: =COUNTIF('Parents & Advocacy'!A2:A65,4) -> 10 | E9: =COUNTIF('Parents & Advocacy'!A2:A65,3) -> 31 | F9: =COUNTIF('Parents & Advocacy'!A2:A65,"<=2") -> 22 | G9: =COUNTIF('Parents & Advocacy'!L2:L65,"Y") -> 10 | H9: =COUNTA('Parents & Advocacy'!N2:N65)-COUNTIF('Parents & Advocacy'!N2:N65,"Not started") -> 0
A10: International | B10: =COUNTA(International!B2:B66) -> 65 | C10: =COUNTIF(International!A2:A66,5) -> 1 | D10: =COUNTIF(International!A2:A66,4) -> 7 | E10: =COUNTIF(International!A2:A66,3) -> 21 | F10: =COUNTIF(International!A2:A66,"<=2") -> 36 | G10: =COUNTIF(International!L2:L66,"Y") -> 0 | H10: =COUNTA(International!N2:N66)-COUNTIF(International!N2:N66,"Not started") -> 0
A11: Category tabs total | B11: =SUM(B7:B10) -> 230 | C11: =SUM(C7:C10) -> 11 | D11: =SUM(D7:D10) -> 48 | E11: =SUM(E7:E10) -> 98 | F11: =SUM(F7:F10) -> 73 | G11: =SUM(G7:G10) -> 87 | H11: =SUM(H7:H10) -> 0
A12: Excluded (not targets) | B12: =COUNTA(Excluded!B2:B33) -> 32
A13: Six organizations appear in two category tabs (PTO Today, WECAN, AMS, AWSNA, ACSI, Defending the Early Years). "All — ranked" shows each once, so it has 6 fewer rows than the category tabs combined. Merged rows keep the higher fit, show Confirmed = Y only if both lists confirmed it, and carry both lists' notes.
A15: How to use
A16: 1. Work from "All — ranked". It is sorted by Fit (5 = best) and then Scope, national first; ties go to confirmed rows, then to groups with state affiliates or chapters, then to groups with a faceless channel. Use the filter arrows to narrow by Type, Scope, Confirmed or Status.
A17: 2. The shaded columns are yours to edit: Status (drop-down: Not started / Contacted / Applied / Booked / Partner / Declined), Next step, and Date (yyyy-mm-dd, the date of your last action). Next step is pre-filled with a suggested first action; overwrite it as you go. Example: Status = Contacted · Next step = "Follow up Oct 12 if no reply; ask for 2027 media kit" · Date = 2026-10-05.
A18: 3. Confirmed = N means at least one fact (site, date, price or reach method) could not be checked. Open the URL and confirm before spending money. Confirmed = Y still means "check the current prospectus": almost no exhibit prices are published, and prices marked as estimates or taken from older sell sheets are not quotes.
A19: 4. The category tabs hold the same rows with the category-specific notes. Update Status in "All — ranked" (the master); use the category tabs for reading.
A20: 5. Before any outreach, check the Excluded tab. If an event, chapter or mailing list includes people from an excluded organization, do not approach them.
A22: Outreach order
A23: Wave 1: Fit-5 national organizations with state affiliates. NAEYC Affiliate Network (then MDAEYC, DCAEYC and the VA, PA and DE affiliates) and NAFCC (then its state family child care associations, starting with MSFCCA). One national relationship opens many low-cost state tables, newsletters and member discounts.
A24: Wave 2: The other fit-5 national channels, all faceless or staffable by a hired rep: PTO Today (Vendor Directory + Leader Lowdown ad), IBPA (cooperative ALA display), WECAN (vendor table).
A25: Wave 3: Fit-5 home-state and regional groups: AIMS (directory), MDAEYC, MLA|DLA, MSFCCA. Time-sensitive: MSFCCA meets Oct 9–10, 2026 (offer a program ad or door prize now).
A26: Wave 4: Fit-4 national groups, faceless channels first: marketplaces and directories (Mackin, JLG, ClassWallet, Odyssey, National Microschooling Center), then ads and written articles (Exchange Press, AASL, AMS, AELL), then exhibits with a hired rep (NAEYC, NHSA, AMS, NAIS, Great Homeschool Conventions, HEAV).
... A45: Never contact or list the organizations on the Excluded tab. The mandatory exclusions are marked "Excluded — pending matters; ask employment counsel before any contact". The tab also lists near-exclusion skips, EdTech mission conflicts, clinical and licensure bodies, and monitor-only advocacy groups, each with the reason.

Sheet All — ranked
A1: Fit | B1: Name | C1: Type | D1: Scope | E1: Members/Reach | F1: Who they are | G1: Lead offer | H1: How to reach | I1: Cost | J1: Next dates | K1: URL | L1: Confirmed (Y/N) | M1: Notes | N1: Status | O1: Next step | P1: Date
A2: 5 | B2: NAEYC Affiliate Network (state and local AEYCs) | C2: network | D2: national (state and local affiliates in nearly every state) | E2: About 50 state affiliates plus local chapters; each runs conferences, PD and newsletters | F2: NAEYC's nonprofit state and local affiliates, which run conferences, PD communities and advocacy | G2: Classroom Pack site licenses; host-it-yourself workshop kits for chapter meetings; fundraiser program for chapters | H2: exhibit at state conferences, sponsor, newsletter ad, member discount | I2: Varies by affiliate. State-conference vendor tables are often a few hundred dollars (estimate; confirm with each affiliate). | J2: Rolling. Use the NAEYC Affiliate Event Calendar. | K2: https://www.naeyc.org/get-involved/membership/affiliates/network | L2: Y | M2: [Early Childhood] HOW TO FIND ALL: the Network of Affiliates page (pick a state), the Affiliate Event Calendar, the member-only Affiliate Directory, or NAEYC Customer Care at 800-424-2460. This is likely the cheapest, highest-return exhibit channel in the category. Skip any chapter event held in, or co-hosted with, MCPS. | N2: Not started | O2: Use NAEYC's Affiliate Event Calendar to list 2026–27 state conferences; request vendor-table and newsletter-ad rates from MD, DC, VA, PA and DE first.
A3: 5 | B3: National Association for Family Child Care (NAFCC) | C3: association / conference | D3: national (with state FCC association affiliates) | E3: Annual conference of 1,300+ family child care educators; conference promotion reaches 30,000+ contacts (first-pass snippet) | F3: National association for home-based (family) child care providers and small-business owners | G3: Printable family bundles 0-5; talk-along board books; card deck; 100-activity play guide (mixed-age home settings) | H3: exhibit, sponsor, partner/affiliate (customized partnership), member discount | I3: Not published. Email conference@nafcc.org (Development Team). | J3: 2026 held Jul 16-18, Chicago/Rosemont. 2027: Jul 15-17, 2027, Jacksonville FL. There is also a regional conference (nafcc.org/regional-conference); dates not sourced. | K3: https://nafcc.org/conference/sponsors-and-exhibitors/ | L3: Y | M3: [Early Childhood] Home-based providers buy their own materials, so this is a strong buyer fit. State FCC associations are listed through NAFCC. Montgomery County's family child care provider association is private and not excluded, but avoid any DHHS-run training tie-ins. | N3: Not started | O3: Email conference@nafcc.org for the Jul 15–17, 2027 Jacksonville sponsor/exhibitor package and propose a member-discount partnership.
A4: 5 | B4: Independent Book Publishers Association (IBPA): cooperative library displays and ad programs | C4: network | D4: national | E4: Independent publishers. IBPA's cooperative booth puts member titles in front of ALA Annual attendees. | F4: Trade association for independent publishers. Runs cooperative book displays at library and trade shows and member ad programs with School Library Journal and Library Journal. | G4: Library-binding picture books and talk-along board books | H4: exhibit (cooperative display), member discount, newsletter ad (SLJ/LJ member ad program) | I4: Membership starts at about $155 a year. ALA Annual 2027 full-shelf display: $725 per shelf for members (register by May 21, 2027; materials due May 26, 2027). In 2026 a single-title display cost $199 and a premium single-title display $249; both sold out. SLJ ad-program rates are at ibpa-online.org/page/SchoolLibraryJournal and were not in search results. | J4: ALA Annual 2027 cooperative booth, June 25–28, 2027, New Orleans | K4: https://www.ibpa-online.org | L4: Y | M4: [K–12] IBPA staffs the booth, making this the cheapest faceless way into the ALA exhibit hall. The 2026 single-title spots sold out, so register as soon as the 2027 spots open. | N4: Not started | O4: Join IBPA (about $155/yr) and reserve an ALA Annual 2027 full-shelf display ($725 member) as soon as 2027 spots open (the 2026 single-title spots sold out).
A5: 5 | B5: PTO Today (School Family Media): magazine, website, Leader Lowdown email, Vendor Directory, Expos | C5: publication / directory / conference | D5: national (US) | E5: By the company's own figures (from earlier search results): the magazine is mailed to 84,000+ K–8 school parent groups; ptotoday.com gets ~180,000 unique PTO/PTA-leader visitors a month (220,000+ at back-to-school); the Leader Lowdown email goes to 55,000+ opt-in subscribers; the Vendor Directory is promoted to 40,000+ weekly-newsletter subscribers | F5: For-profit media company (School Family Media) built to sell to PTO/PTA leaders. It sells print and digital ads, sponsored content, a vendor directory, sampling, and one-day regional PTO Today Expos. | G5: Group fundraiser program + host-it-yourself family play-night workshop kits; a research brief as a sponsored-content download | H5: vendor directory, newsletter ad (including 'sponsor takeover' issues of Leader Lowdown), sponsored content/guest article, magazine ad, exhibit (Expo) | I5: Expo prices from the 2023–24 sell sheets (dated): standard booth $995, premium corner $1,195, double $1,490, double premium $2,300, A&E/nonprofit tabletop $300. Sponsorship: $6,000 national (both events), $3,500 per local event, $2,750 remote. Magazine, banner, newsletter and directory rates are on rate cards at schoolfamilymedia.com (not captured). Re-check 2027 prices. | J5: Fall 2026 Expos: Secaucus, NJ (Sep 30, 2026) and Oaks, PA (Oct 7, 2026), probably too soon to book. The spring 2026 run was Feb 25–Apr 15 (Novi MI, Mesquite TX, Conroe TX, Edison NJ, Oakbrook Terrace IL, Marlborough MA). Expect a similar spring 2027 run (not yet announced). Ads and directory listings run year-round, with peak traffic at back-to-school (Jul–Sep 2027). | K5: https://www.ptotoday.com | L5: Y | M5: [Parents + K–12] Confirmed from earlier search results that cite ptotoday.com and schoolfamilymedia.com pages; DNS is live (AWS). This is the best faceless channel in the category: a paid, for-profit route to exactly the parent-group buyers of the fundraiser and workshop kits. Start with the Vendor Directory and a Leader Lowdown ad, and add a booth only once the ads prove out. Expo booths are sold at clientstore.ptotoday.com, and the Expo team is at expolive@ptotoday.com. || From the K–12 list: The newsletter and vendor directory are the most faceless options because nobody has to staff them. A booth needs a hired rep. Booth prices come from older sheets, so treat them as estimates. PTO Today also appears in the parents list; make sure one purchase is not counted in both lists. | N5: Not started | O5: Email jwilliams@ptotoday.com (800-644-3561 x201) for current rate cards; start with a Vendor Directory listing plus one Leader Lowdown ad.
A6: 5 | B6: WECAN – Waldorf Early Childhood Association of North America | C6: association | D6: national (North America) | E6: Waldorf early childhood and kindergarten teachers and programs | F6: Early-childhood arm of the Waldorf movement; strongly play-based and low-media | G6: Board books + 100-activity play guide + card deck + family bundles | H6: exhibit (vendor table) | I6: Vendor fees not published. Contact conference@waldorfearlychildhood.org. | J6: 2027 Early Childhood Educators Conference, Mar 19–21, 2027, Green Meadow Waldorf School / Threefold campus, Chestnut Ridge (Spring Valley) NY; online portion from Apr 3, 2027. Pacific Northwest regional conference Feb 13–14, 2027, Milwaukie OR. | K6: https://waldorfearlychildhood.org | L6: Y | M6: [K–12 + Early Childhood] The conference page confirms 'a variety of vendors.' The audience's values closely match the brand. Keep the pitch to talk and play and do not critique other approaches. Newsletter ads were not confirmed, so they have been removed from the reach methods. || From the Early Childhood list: Strongest philosophical match on screens. Waldorf kindergartens lean toward oral storytelling over picture books, so lead with the play guide and parent-facing family bundles. Check vendor policies; some Waldorf events limit commercial exhibits. | N6: Not started | O6: Email conference@waldorfearlychildhood.org about a vendor table and vendor policy for Mar 19–21, 2027 (Chestnut Ridge NY); lead with the play guide and family bundles.
A7: 5 | B7: PACEY (Professional Association for Childcare and Early Years) | C7: association | D7: international (UK - England & Wales) | E7: Childminders, nannies and nursery practitioners; historically cited at 20,000+ members (verify current figure) | F7: Membership charity for home-based childcare and early years practitioners in England and Wales. It was formerly the National Childminding Association and was renamed in 2013. It publishes a member magazine and runs member offers. | G7: Printable family bundle (0-5) re-edited for EYFS, the 100-activity play guide and the card deck. The host-it-yourself workshop kit suits childminding networks. | H7: member discount / partner benefit, magazine/newsletter ad, written guest article | I7: Not verified. Request the advertising media kit and partner-benefit terms. | J7: Not verified; ad placements are rolling | K7: https://www.pacey.org.uk | L7: N | M7: [International] Childminders buy their own resources, so this is the closest audience match abroad. Ads and member offers need no staff. Not verified whether PACEY takes overseas advertisers or partners; ask. UK VAT applies to digital sales to UK consumers. Needs a UK/EYFS edition and no health claims. Confirm the organisation's current status before paying, because UK early-years charities have been under funding pressure. | N7: Not started | O7: Open pacey.org.uk to confirm current status, then request the media kit and partner-benefit terms and ask whether overseas partners are accepted.
A8: 5 | B8: Association of Independent Maryland & DC Schools (AIMS) | C8: association | D8: state/regional (Maryland & DC) | E8: Independent schools in Maryland and DC | F8: Accrediting and membership association for independent schools in MD/DC | G8: Classroom pack site licenses + parent-education workshop kits + research briefs | H8: vendor directory (AIMS Business Directory), partner program (Business Partners) | I8: Pricing on request. Business Directory listings and Business Partner spots for 2026–27 are open. | J8: 2026–27 enrollment open now | K8: https://www.aimsmddc.org | L8: Y | M8: [K–12] Gives year-round, faceless reach with no event to staff. Member schools use the directory to find vendors. These are independent schools, not MCPS. | N8: Not started | O8: Request 2026–27 Business Directory and Business Partner pricing (enrollment is open now).
A9: 5 | B9: Maryland Association for the Education of Young Children (MDAEYC) | C9: association | D9: state (Maryland) | E9: Represents 1,700+ Maryland early childhood educators and families (first-pass snippet) | F9: Maryland's NAEYC state affiliate, with local chapters | G9: Classroom Pack + talk-along board books; workshop kits for chapter PD nights | H9: exhibit/sponsor at state events, newsletter ad, member discount, guest article | I9: Not published. Email info@mdaeyc.org. | J9: Not found. Ask about 2027 conference and events. | K9: https://mdaeyc.org/ | L9: Y | M9: [Early Childhood] Home-state partner. Keep outreach statewide and generic. Do not reference Montgomery County public-school programs, and skip any chapter event hosted at or with MCPS. | N9: Not started | O9: Email info@mdaeyc.org about 2027 conference vendor space, newsletter ads and a member discount; keep the pitch statewide.
A10: 5 | B10: Maryland Library Association (MLA | DLA joint conference) | C10: association | D10: state (Maryland, joint with Delaware) | E10: Public, school and academic library staff in MD/DE, including children's and youth services librarians | F10: State library association that runs the annual MLA|DLA conference and exhibit hall | G10: Library-binding picture books + host-it-yourself workshop kits for library family programs | H10: exhibit, sponsor | I10: Exhibitor registration page at mdlib.org/annual-conference/exhibitors. Rates not in search results. | J10: 2026 conference was May 6–8, 2026, Hyatt Regency Chesapeake Bay, Cambridge MD. 2027 dates not yet published; it is usually held in May. | K10: https://www.mdlib.org | L10: Y | M10: [K–12] The workshop kits fit public-library storytime and family programs. County library systems, including Montgomery County Public Libraries (a county library, not MCPS or DHHS), buy through this community. 'Resource listing' was not confirmed and has been removed from the reach methods. | N10: Not started | O10: Ask to be added to the 2027 exhibitor list at mdlib.org/annual-conference/exhibitors (the conference is usually in May).
A11: 5 | B11: Maryland State Family Child Care Association (MSFCCA) | C11: association / conference | D11: state (Maryland) | E11: Maryland family child care providers statewide, with county associations | F11: Maryland's family child care association; annual conference in Ocean City | G11: Family bundles 0-5; board books; play guide; card deck | H11: exhibit (vendor table), sponsor, member discount, newsletter ad | I11: Not published. Contact via msfcca.org. | J11: 33rd Annual Conference, Oct 9-10, 2026, Princess Royale Oceanfront Hotel, Ocean City MD (about 11 days out). 2027 TBA. | K11: https://www.msfcca.org/annualconference | L11: Y | M11: [Early Childhood] Home-state, small-provider audience, likely a low-cost table. Vendor space for Oct 2026 is probably closed. Ask about a program ad or door-prize donation now, and book a table for 2027. | N11: Not started | O11: Contact now, before the Oct 9–10, 2026 Ocean City conference: offer a program ad or door-prize donation, and reserve a 2027 vendor table.
A12: 4 | B12: Parents as Teachers National Center - International Conference | C12: network / conference | D12: national / international | E12: About 2,500 home-visiting professionals expected at the 2026 conference; large affiliate network | F12: Evidence-based home-visiting model network (parent educators, not a nurse model) | G12: Talk-along board books; family bundle 0-5; card deck (parent-educator handouts) | H12: exhibit, sponsor, partner/affiliate (affiliate outreach) | I12: Not published. See parentsasteachersconference.org. | J12: 2026 International Conference Oct 5-8, 2026, Portland OR. This is NEXT WEEK (the first pass wrongly said 'held'), so it is too late to exhibit. 2027 TBA. | K12: https://parentsasteachers.org/upcoming-events/ | L12: Y | M12: [Early Childhood] Parent educators hand materials to families at home, a direct fit for the talk/touch/play message. Target 2027 exhibit/sponsor and state PAT affiliate offices. | N12: Not started | O12: Ask for 2027 International Conference exhibitor/sponsor info (Oct 5–8, 2026 is too close) and how to reach state PAT affiliate offices.
A13: 4 | B13: State & Regional Head Start Associations (NHSA network) | C13: network | D13: national (state associations + regional associations aligned to Office of Head Start regions) | E13: Nearly every state plus regional associations | F13: State and regional Head Start associations that run training conferences, many with exhibit halls | G13: Classroom Pack; board books; parent family bundles | H13: exhibit at state/regional conferences, sponsor | I13: Varies. Regional exhibit fees are usually lower than national (estimate). | J13: Rolling. Check each state or regional site. | K13: https://nhsa.org/our-work/state-regional-associations/ | L13: Y | M13: [Early Childhood] HOW TO FIND ALL: NHSA's State & Regional Associations page. Region III (MD/DC/VA/PA/DE/WV) is the home region; the Virginia Head Start Association (headstartva.org) runs an annual training conference. Region IV's association is known for large conferences. Exclude Montgomery County (MD) Head Start from any member-list outreach. | N13: Not started | O13: From NHSA's State & Regional page, list the Region III associations (e.g., Virginia Head Start Association) and request 2027 exhibitor info; never solicit Montgomery County Head Start.
... A225: 1 | B225: Maryland PTA (Convention / Leadership Training) | C225: association / conference | D225: state (Maryland) | E225: Statewide PTA units, including Montgomery County's MCCPTA council | F225: State PTA for Maryland. | G225: Fundraiser program + workshop kits | H225: At most, a statewide resource listing not aimed at Montgomery County. No convention booth. | I225: Not verified | J225: Confirm at mdpta.org | K225: https://www.mdpta.org | L225: N | M225: [Parents] DNS only. Lowered to 1. MCCPTA is part of Maryland PTA, so statewide events draw Montgomery County PTA leaders and the MCPS staff who belong to PTAs, which is too close to the exclusion. Skip the convention. Never contact MCCPTA or any PTA inside an MCPS school. | N225: Not started | O225: CAUTION: no convention booth and no county-level contact. At most a statewide resource listing, and only after employment counsel says it is fine.

Sheet Early Childhood & Care
A1: Fit | B1: Name | C1: Type | D1: Scope | E1: Members/Reach | F1: Who they are | G1: Lead offer | H1: How to reach | I1: Cost | J1: Next dates | K1: URL | L1: Confirmed (Y/N) | M1: Notes | N1: Status | O1: Next step | P1: Date
A2: 5 | B2: NAEYC Affiliate Network (state and local AEYCs) | C2: network | D2: national (state and local affiliates in nearly every state) | E2: About 50 state affiliates plus local chapters; each runs conferences, PD and newsletters | F2: NAEYC's nonprofit state and local affiliates, which run conferences, PD communities and advocacy | G2: Classroom Pack site licenses; host-it-yourself workshop kits for chapter meetings; fundraiser program for chapters | H2: exhibit at state conferences, sponsor, newsletter ad, member discount | I2: Varies by affiliate. State-conference vendor tables are often a few hundred dollars (estimate; confirm with each affiliate). | J2: Rolling. Use the NAEYC Affiliate Event Calendar. | K2: https://www.naeyc.org/get-involved/membership/affiliates/network | L2: Y | M2: HOW TO FIND ALL: the Network of Affiliates page (pick a state), the Affiliate Event Calendar, the member-only Affiliate Directory, or NAEYC Customer Care at 800-424-2460. This is likely the cheapest, highest-return exhibit channel in the category. Skip any chapter event held in, or co-hosted with, MCPS. | N2: Not started | O2: Use NAEYC's Affiliate Event Calendar to list 2026–27 state conferences; request vendor-table and newsletter-ad rates from MD, DC, VA, PA and DE first.
A3: 5 | B3: National Association for Family Child Care (NAFCC) | C3: association / conference | D3: national (with state FCC association affiliates) | E3: Annual conference of 1,300+ family child care educators; conference promotion reaches 30,000+ contacts (first-pass snippet) | F3: National association for home-based (family) child care providers and small-business owners | G3: Printable family bundles 0-5; talk-along board books; card deck; 100-activity play guide (mixed-age home settings) | H3: exhibit, sponsor, partner/affiliate (customized partnership), member discount | I3: Not published. Email conference@nafcc.org (Development Team). | J3: 2026 held Jul 16-18, Chicago/Rosemont. 2027: Jul 15-17, 2027, Jacksonville FL. There is also a regional conference (nafcc.org/regional-conference); dates not sourced. | K3: https://nafcc.org/conference/sponsors-and-exhibitors/ | L3: Y | M3: Home-based providers buy their own materials, so this is a strong buyer fit. State FCC associations are listed through NAFCC. Montgomery County's family child care provider association is private and not excluded, but avoid any DHHS-run training tie-ins. | N3: Not started | O3: Email conference@nafcc.org for the Jul 15–17, 2027 Jacksonville sponsor/exhibitor package and propose a member-discount partnership.
A4: 5 | B4: Maryland Association for the Education of Young Children (MDAEYC) | C4: association | D4: state (Maryland) | E4: Represents 1,700+ Maryland early childhood educators and families (first-pass snippet) | F4: Maryland's NAEYC state affiliate, with local chapters | G4: Classroom Pack + talk-along board books; workshop kits for chapter PD nights | H4: exhibit/sponsor at state events, newsletter ad, member discount, guest article | I4: Not published. Email info@mdaeyc.org. | J4: Not found. Ask about 2027 conference and events. | K4: https://mdaeyc.org/ | L4: Y | M4: Home-state partner. Keep outreach statewide and generic. Do not reference Montgomery County public-school programs, and skip any chapter event hosted at or with MCPS. | N4: Not started | O4: Email info@mdaeyc.org about 2027 conference vendor space, newsletter ads and a member discount; keep the pitch statewide.
A5: 5 | B5: Maryland State Family Child Care Association (MSFCCA) | C5: association / conference | D5: state (Maryland) | E5: Maryland family child care providers statewide, with county associations | F5: Maryland's family child care association; annual conference in Ocean City | G5: Family bundles 0-5; board books; play guide; card deck | H5: exhibit (vendor table), sponsor, member discount, newsletter ad | I5: Not published. Contact via msfcca.org. | J5: 33rd Annual Conference, Oct 9-10, 2026, Princess Royale Oceanfront Hotel, Ocean City MD (about 11 days out). 2027 TBA. | K5: https://www.msfcca.org/annualconference | L5: Y | M5: Home-state, small-provider audience, likely a low-cost table. Vendor space for Oct 2026 is probably closed. Ask about a program ad or door-prize donation now, and book a table for 2027. | N5: Not started | O5: Contact now, before the Oct 9–10, 2026 Ocean City conference: offer a program ad or door-prize donation, and reserve a 2027 vendor table.
A6: 4 | B6: Parents as Teachers National Center - International Conference | C6: network / conference | D6: national / international | E6: About 2,500 home-visiting professionals expected at the 2026 conference; large affiliate network | F6: Evidence-based home-visiting model network (parent educators, not a nurse model) | G6: Talk-along board books; family bundle 0-5; card deck (parent-educator handouts) | H6: exhibit, sponsor, partner/affiliate (affiliate outreach) | I6: Not published. See parentsasteachersconference.org. | J6: 2026 International Conference Oct 5-8, 2026, Portland OR. This is NEXT WEEK (the first pass wrongly said 'held'), so it is too late to exhibit. 2027 TBA. | K6: https://parentsasteachers.org/upcoming-events/ | L6: Y | M6: Parent educators hand materials to families at home, a direct fit for the talk/touch/play message. Target 2027 exhibit/sponsor and state PAT affiliate offices. | N6: Not started | O6: Ask for 2027 International Conference exhibitor/sponsor info (Oct 5–8, 2026 is too close) and how to reach state PAT affiliate offices.
A7: 4 | B7: State & Regional Head Start Associations (NHSA network) | C7: network | D7: national (state associations + regional associations aligned to Office of Head Start regions) | E7: Nearly every state plus regional associations | F7: State and regional Head Start associations that run training conferences, many with exhibit halls | G7: Classroom Pack; board books; parent family bundles | H7: exhibit at state/regional conferences, sponsor | I7: Varies. Regional exhibit fees are usually lower than national (estimate). | J7: Rolling. Check each state or regional site. | K7: https://nhsa.org/our-work/state-regional-associations/ | L7: Y | M7: HOW TO FIND ALL: NHSA's State & Regional Associations page. Region III (MD/DC/VA/PA/DE/WV) is the home region; the Virginia Head Start Association (headstartva.org) runs an annual training conference. Region IV's association is known for large conferences. Exclude Montgomery County (MD) Head Start from any member-list outreach. | N7: Not started | O7: From NHSA's State & Regional page, list the Region III associations (e.g., Virginia Head Start Association) and request 2027 exhibitor info; never solicit Montgomery County Head Start.
A8: 4 | B8: American Montessori Society (AMS) - The Montessori Event + Montessori Life | C8: association / conference / publication | D8: national / international | E8: Largest US Montessori membership association; The Montessori Event has an exhibit hall; publishes Montessori Life | F8: US Montessori membership and accrediting association | G8: Card deck; play guide; library-bound picture books; Classroom Pack | H8: exhibit, sponsor, newsletter ad (Montessori Life ad) | I8: Not published. Request the 2027 exhibitor prospectus and Montessori Life media kit. | J8: The Montessori Event 2027, Mar 11-14, 2027, McCormick Place, Chicago IL | K8: https://amshq.org/event/the-montessori-event-2027/ | L8: Y | M8: Montessori favors realistic, hands-on materials, so keep product visuals realistic and non-fantasy for this audience. Also listed in the K–12 tab. | N8: Not started | O8: Request The Montessori Event 2027 (Chicago, Mar 11–14) exhibitor prospectus and the Montessori Life media kit.
A9: 4 | B9: Association for Early Learning Leaders (AELL, formerly NACCP) | C9: association / conference | D9: national | E9: Child care center directors and owners | F9: National association for early learning program administrators | G9: Classroom Pack site licenses; fundraiser program; workshop kits for staff PD | H9: exhibit, sponsor, newsletter ad (year-round advertising) | I9: Booth rate is in the prospectus (not shown). A booth includes 2 registrations; an extra exhibitor registration is $349. Contact Aryam Andom, 512-316-3817. | J9: 43rd Annual National Conference, Apr 7-10, 2027, Nashville TN | K9: https://www.earlylearningleaders.org/vendor/conference-exhibits-and-sponsorships/ | L9: Y | M9: Directors are the buyers for site licenses. Year-round ads: earlylearningleaders.org/vendor/advertising-opportunities/. | N9: Not started | O9: Call Aryam Andom (512-316-3817) for the Apr 7–10, 2027 Nashville prospectus and year-round ad rates.
A10: 4 | B10: Association for Nature-Based Education (ANBE, formerly ERAFANS) | C10: association | D10: national (based in Glen Arm, MD) | E10: Serves thousands of nature-based educators across the US (first-pass snippet) | F10: Nonprofit for forest/nature schools, nature preschools and farm schools; runs teacher trainings and retreats | G10: Play guide; card deck; workshop kits | H10: member discount, sponsor (trainings), resource listing | I10: Not published | J10: Rolling live trainings and retreats (spring 2026 events held) | K10: https://www.erafans.org/ | L10: Y | M10: Maryland-based, a natural local partner. After the rebrand the org may use a new primary domain; confirm erafans.org still resolves to the current site before printing it. | N10: Not started | O10: Confirm the post-rebrand domain (erafans.org), then email a member-discount and resource-listing inquiry.
A11: 4 | B11: Exchange Press (Exchange magazine, ExchangeEveryDay newsletter, Exchange Leadership hub) | C11: publication | D11: international | E11: Long-running leadership magazine for ECE directors (since 1978) plus a widely read daily e-newsletter | F11: Publisher of Exchange magazine, books and training for early childhood leaders | G11: Classroom Pack site licenses; research briefs | H11: newsletter ad (magazine and ExchangeEveryDay), guest article | I11: Not published. Request the media kit: 800-221-2864, info@ChildCareExchange.com. | J11: Rolling editorial calendar | K11: https://exchangepress.com/ | L11: Y | M11: Fit raised from 3: print and newsletter ads plus written practitioner articles are fully faceless and reach the directors who buy site licenses. | N11: Not started | O11: Request the media kit (info@ChildCareExchange.com, 800-221-2864) and pitch a written practitioner article.
A12: 4 | B12: Local Child Care Resource & Referral (CCR&R) agencies network | C12: network | D12: national (about 400 local agencies across all 50 states + DC) | E12: Each agency serves thousands of licensed providers and families locally | F12: Local agencies that train providers and refer families to child care (called Early Learning Coalitions in Florida, for example) | G12: Host-it-yourself workshop kits; family bundles as provider handouts; research briefs | H12: mailed/emailed outreach, resource listing, partner/affiliate (workshop-kit partnership) | I12: Free to contact. Kit sales and partnerships are negotiated. | J12: Rolling | K12: https://www.childcareaware.org/resources/ccrr-search/ | L12: Y | M12: HOW TO FIND ALL: CCAoA's CCR&R search by ZIP (if the path has moved, try /resources/ccrr-search-form/) and the State-by-State Resource Map (childcareaware.org/resources/state-by-state-resource-map/). Some CCR&Rs are county government units; skip the one run by Montgomery County (MD) DHHS. | N12: Not started | O12: Use CCAoA's CCR&R ZIP search to list 20 agencies (skip the Montgomery County DHHS unit) and mail a workshop-kit offer.
A13: 4 | B13: NAEYC (National Association for the Education of Young Children) - Annual Conference & Expo + publication advertising | C13: association / conference / publication | D13: national | E13: Largest US early-childhood association (about 60,000 members historically); the annual expo draws thousands of ECE educators and directors; also publishes Young Children and Teaching Young Children | F13: National professional association for birth-to-8 educators. 2026 is its centennial year. | G13: PreK-5 Screen-Free Classroom Pack + site license; talk-along board books; card deck | H13: exhibit, sponsor, newsletter ad (Young Children / Teaching Young Children print and digital ads, conference program/app ads) | I13: Not published. Request the Exhibitor Prospectus and media kit via naeyc.org/events/annual/exhibiting-and-advertising. Contacts from the first pass: Kathleen Lawrence (kathleen_lawrence@afassanoco.com, the outside exhibit-sales firm), Julia Minano (jminano@naeyc.org). Budget several thousand dollars for a 10x10 at a national expo (estimate, not a quote). | J13: Dec 5-7, 2026, Walter E. Washington Convention Center, Washington DC (per first-pass snippet; not re-opened). Dec 4-7, 2027, Chicago IL. No Professional Learning Institute in 2026. | K13: https://www.naeyc.org/events/annual/exhibiting-and-advertising | L13: Y | M13: Both dates run Saturday to Monday or Tuesday, a change from NAEYC's usual midweek format. Confirm them before committing. The DC show is about 10 weeks out, so a booth may be sold out; a program or app ad, or Chicago 2027, is more realistic. Magazine ads are fully faceless. A booth can be run by hired staff. Keep messaging positive ('talk, touch, play, paper first'). Do not target MCPS staff at the show. | N13: Not started | O13: Request the exhibitor prospectus and media kit; book a program/app or magazine ad for Dec 2026 and target Chicago (Dec 2027) for any booth.
... A49: 2 | B49: Maryland Child Care Training Calendar (MSDE-approved training listings) | C49: directory | D49: state (Maryland) | E49: Maryland licensed child care providers searching for approved training | F49: Statewide searchable calendar of MSDE-approved trainings and organizations, hosted by Maryland Family Network | G49: Workshop kits delivered by an approved trainer | H49: resource listing | I49: Free listing once MSDE training approval is granted | J49: Rolling | K49: https://www.marylandfamilynetwork.org/for-providers-training/maryland-child-care-training-calendar-0 | L49: Y | M49: Requires MSDE Child Care Trainer/Training Proposal approval, and the trainer's identity is disclosed. Only pursue through a contracted approved trainer. MSDE (a state agency) is not excluded. | N49: Not started | O49: Offer a free resource for their resource listing

Sheet K–12 & Libraries
A1: Fit | B1: Name | C1: Type | D1: Scope | E1: Members/Reach | F1: Who they are | G1: Lead offer | H1: How to reach | I1: Cost | J1: Next dates | K1: URL | L1: Confirmed (Y/N) | M1: Notes | N1: Status | O1: Next step | P1: Date
A2: 5 | B2: Independent Book Publishers Association (IBPA): cooperative library displays and ad programs | C2: network | D2: national | E2: Independent publishers. IBPA's cooperative booth puts member titles in front of ALA Annual attendees. | F2: Trade association for independent publishers. Runs cooperative book displays at library and trade shows and member ad programs with School Library Journal and Library Journal. | G2: Library-binding picture books and talk-along board books | H2: exhibit (cooperative display), member discount, newsletter ad (SLJ/LJ member ad program) | I2: Membership starts at about $155 a year. ALA Annual 2027 full-shelf display: $725 per shelf for members (register by May 21, 2027; materials due May 26, 2027). In 2026 a single-title display cost $199 and a premium single-title display $249; both sold out. SLJ ad-program rates are at ibpa-online.org/page/SchoolLibraryJournal and were not in search results. | J2: ALA Annual 2027 cooperative booth, June 25–28, 2027, New Orleans | K2: https://www.ibpa-online.org | L2: Y | M2: IBPA staffs the booth, making this the cheapest faceless way into the ALA exhibit hall. The 2026 single-title spots sold out, so register as soon as the 2027 spots open. | N2: Not started | O2: Join IBPA (about $155/yr) and reserve an ALA Annual 2027 full-shelf display ($725 member) as soon as 2027 spots open (the 2026 single-title spots sold out).
A3: 5 | B3: PTO Today / School Family Media (PTO Today magazine, Leader Lowdown, Expos) | C3: publication | D3: national (regional expos in NJ, PA, MI, TX, IL, MA) | E3: PTO Today magazine mailed to 84,000+ K–8 parent groups; 180,000+ monthly site visitors; Leader Lowdown e-newsletter reaches 55,000+ opt-in subscribers; vendor directory promoted to 40,000+ weekly-newsletter subscribers | F3: Main media company for school parent-group (PTO/PTA) leaders. It publishes the magazine, website and newsletters and runs one-day expos. | G3: Group fundraiser program + printable family bundles + host-it-yourself workshop kits (family screen-free night) | H3: newsletter ad (Leader Lowdown, including sponsor takeovers), vendor directory, sponsored content, exhibit (expo booth) | I3: Booth prices come from School Family Media's 2023–24 expo sell sheets: $995 standard, $1,195 premium corner, $1,490 double, $2,300 double premium, and a $300 tabletop for arts/enrichment and nonprofits. Sponsorships $2,750–$6,000. Rate cards for the magazine, banners, newsletter and directory are not in search results. Contact John Williams, jwilliams@ptotoday.com, 800-644-3561 x201. | J3: Secaucus NJ, Sep 30, 2026 (2 days away, too late). Oaks PA, Oct 7, 2026 (9 days away; ask about late space). Spring 2026 expos ran Feb 25–Apr 15; the spring 2027 schedule is not yet published. | K3: https://www.ptotoday.com | L3: Y | M3: The newsletter and vendor directory are the most faceless options because nobody has to staff them. A booth needs a hired rep. Booth prices come from older sheets, so treat them as estimates. PTO Today also appears in the parents list; make sure one purchase is not counted in both lists. Also listed in the Parents tab. | N3: Not started | O3: Email jwilliams@ptotoday.com (800-644-3561 x201) for current rate cards; start with a Vendor Directory listing plus one Leader Lowdown ad.
A4: 5 | B4: WECAN – Waldorf Early Childhood Association of North America | C4: association | D4: national (North America) | E4: Waldorf early childhood and kindergarten teachers and programs | F4: Early-childhood arm of the Waldorf movement; strongly play-based and low-media | G4: Board books + 100-activity play guide + card deck + family bundles | H4: exhibit (vendor table) | I4: Vendor fees not published. Contact conference@waldorfearlychildhood.org. | J4: 2027 Early Childhood Educators Conference, Mar 19–21, 2027, Green Meadow Waldorf School / Threefold campus, Chestnut Ridge (Spring Valley) NY; online portion from Apr 3, 2027. Pacific Northwest regional conference Feb 13–14, 2027, Milwaukie OR. | K4: https://waldorfearlychildhood.org | L4: Y | M4: The conference page confirms 'a variety of vendors.' The audience's values closely match the brand. Keep the pitch to talk and play and do not critique other approaches. Newsletter ads were not confirmed, so they have been removed from the reach methods. Also listed in the Early Childhood tab. | N4: Not started | O4: Email conference@waldorfearlychildhood.org about a vendor table and vendor policy for Mar 19–21, 2027 (Chestnut Ridge NY); lead with the play guide and family bundles.
A5: 5 | B5: Association of Independent Maryland & DC Schools (AIMS) | C5: association | D5: state/regional (Maryland & DC) | E5: Independent schools in Maryland and DC | F5: Accrediting and membership association for independent schools in MD/DC | G5: Classroom pack site licenses + parent-education workshop kits + research briefs | H5: vendor directory (AIMS Business Directory), partner program (Business Partners) | I5: Pricing on request. Business Directory listings and Business Partner spots for 2026–27 are open. | J5: 2026–27 enrollment open now | K5: https://www.aimsmddc.org | L5: Y | M5: Gives year-round, faceless reach with no event to staff. Member schools use the directory to find vendors. These are independent schools, not MCPS. | N5: Not started | O5: Request 2026–27 Business Directory and Business Partner pricing (enrollment is open now).
A6: 5 | B6: Maryland Library Association (MLA | DLA joint conference) | C6: association | D6: state (Maryland, joint with Delaware) | E6: Public, school and academic library staff in MD/DE, including children's and youth services librarians | F6: State library association that runs the annual MLA|DLA conference and exhibit hall | G6: Library-binding picture books + host-it-yourself workshop kits for library family programs | H6: exhibit, sponsor | I6: Exhibitor registration page at mdlib.org/annual-conference/exhibitors. Rates not in search results. | J6: 2026 conference was May 6–8, 2026, Hyatt Regency Chesapeake Bay, Cambridge MD. 2027 dates not yet published; it is usually held in May. | K6: https://www.mdlib.org | L6: Y | M6: The workshop kits fit public-library storytime and family programs. County library systems, including Montgomery County Public Libraries (a county library, not MCPS or DHHS), buy through this community. 'Resource listing' was not confirmed and has been removed from the reach methods. | N6: Not started | O6: Ask to be added to the 2027 exhibitor list at mdlib.org/annual-conference/exhibitors (the conference is usually in May).
A7: 4 | B7: American Association of School Librarians (AASL) | C7: association | D7: national | E7: National school librarian association (ALA division); publishes the Knowledge Quest journal | F7: National school librarian association. Holds a national conference every two years. | G7: Library-binding picture books + classroom pack | H7: exhibit, newsletter ad (AASL advertising page) | I7: 2027 exhibit prospectus not found. Ad options are at ala.org/aasl/pubs/advertising (rates not in search results). | J7: AASL 2027 National Conference, Oct 14–16, 2027, Portland OR | K7: https://www.ala.org/aasl | L7: Y | M7: The next national conference is a year away, which leaves time to budget. A journal or e-news ad is the faceless option. | N7: Not started | O7: Request ad rates at ala.org/aasl/pubs/advertising and budget for the Portland conference, Oct 14–16, 2027.
A8: 4 | B8: American Montessori Society (AMS) | C8: association | D8: national | E8: Montessori schools and teachers (early childhood through elementary) | F8: Largest Montessori membership organization in the US | G8: Board books + 100-activity play guide + card deck + classroom pack | H8: exhibit, sponsor | I8: Exhibitor pricing and Montessori Life ad rates not found | J8: The Montessori Event 2027, March 11–14, 2027, McCormick Place, Chicago | K8: https://amshq.org | L8: Y | M8: The exhibit hall features Montessori materials, furniture and books. Its hands-on, paper-and-materials culture fits the brand. Also listed in the Early Childhood tab. | N8: Not started | O8: Request The Montessori Event 2027 (Chicago, Mar 11–14) exhibitor prospectus and the Montessori Life media kit.
A9: 4 | B9: Association for Library Service to Children (ALSC) | C9: association | D9: national | E9: Children's librarians; the National Institute has about 300 attendees | F9: ALA division for library service to children | G9: Talk-along board books + library workshop kits | H9: sponsor, exhibit (National Institute) | I9: Corporate sponsorship tiers on request. Contact Sarah Polen, spolen@ala.org, 312-280-4026. | J9: National Institute exhibitor information is due 'later in 2026.' One listing places the next Institute in Buffalo NY; dates not confirmed. | K9: https://www.ala.org/alsc | L9: Y | M9: The earlier claim of 'affordable sponsorships' was not supported, since prices are on request. 'Resource listing' was not confirmed and has been removed. The focus on early literacy fits the brand. | N9: Not started | O9: Email Sarah Polen (spolen@ala.org) for sponsorship tiers and National Institute exhibitor information.
A10: 4 | B10: Junior Library Guild (JLG) | C10: network | D10: national | E10: Subscribing school and public libraries nationwide; 70+ 'Gold Standard' selection categories | F10: Library book-selection service that buys selected new titles for member libraries. Part of Media Source Inc. with School Library Journal, Library Journal and The Horn Book. | G10: Talk-along board books and picture books | H10: resource listing (publisher submission for JLG selection) | I10: Free to submit, with no guarantee of selection. Book club and book fair rights are required. | J10: Rolling. Submit 4–6 months before publication: at least 3 months before the pub date and 1 month before the first print run. Submissions go through the MSI portal, which also takes SLJ and Horn Book review copies. | K10: https://www.juniorlibraryguild.com/publishers | L10: Y | M10: ADDED during this check. A JLG selection is a strong signal to school librarians and can bring a bulk order. Set the next title's release date to allow for the lead time. | N10: Not started | O10: Submit the next title through the MSI portal 4–6 months before its publication date.
A11: 4 | B11: Mackin Educational Resources (Publisher Showcase) | C11: directory | D11: national | E11: Works with 60,000+ schools. Offers 4.2 million titles from 18,000+ publishers. Publisher Showcase pages reach 200,000+ Mackin customers. | F11: Major K–12 library book distributor. Launched MackinPublic for public libraries in Oct 2025 after Baker & Taylor closed. | G11: Library-binding picture books + talk-along board books | H11: vendor directory (catalog availability via IngramSpark distribution; paid Publisher Showcase landing page) | I11: Publisher Showcase is an annual fee; the amount is not published. Catalog availability comes through IngramSpark, which lists Mackin as a distribution partner. | J11: Ongoing | K11: https://home.mackin.com/publisher-showcase/ | L11: Y | M11: ADDED during this check. Year-round and faceless. School librarians place orders here, so a Showcase page puts the titles where purchase orders are written. Showcase members also get Mackin's TRENDS K–12 purchasing report. | N11: Not started | O11: Confirm IngramSpark distribution reaches Mackin, then request the Publisher Showcase annual fee.
A12: 4 | B12: NAIS – National Association of Independent Schools (Thrive Annual Conference) | C12: association | D12: national | E12: About 1,600 member independent schools; thousands attend Thrive | F12: National independent-school association; publishes Independent School magazine | G12: Classroom pack site licenses + parent-education workshop kits + research briefs | H12: exhibit ('The Quad'), sponsor | I12: Booth costs vary by city and the exhibitor kit is pending. Contact sponsorship@nais.org, 202-973-9700. | J12: NAIS Thrive 2027, March 3–5, 2027, Baltimore MD. Registration opens Oct 2026 (super early bird Oct 15). NAIS Gather, Dec 2–5, 2026, Boston, also has exhibits. | K12: https://www.nais.org | L12: Y | M12: Held in Baltimore, close to the founder. Magazine advertising was not confirmed in search results, so ask about it. | N12: Not started | O12: Email sponsorship@nais.org for the NAIS Thrive 2027 (Baltimore, Mar 3–5) exhibitor kit before super-early-bird Oct 15; ask about Gather (Dec 2–5, 2026).
A13: 4 | B13: National Association of Elementary School Principals (NAESP) | C13: association | D13: national | E13: National association of PreK–8 principals | F13: National voice for PreK–8 principals. Runs the National School Leaders Conference (formerly the Pre-K–8 Principals Conference) with an exhibit hall. | G13: PreK–5 classroom pack site licenses + research briefs + fundraiser program | H13: exhibit, sponsor | I13: 2027 booth rates not published; the only prospectus found dates from 2023. Contact Deborah Young, Conferences & Exhibits, 703-518-6296. | J13: 2027 National School Leaders Conference, July 22–24, 2027, Colorado Convention Center, Denver | K13: https://www.naesp.org | L13: Y | M13: Principal magazine advertising and guest articles were not confirmed, so ask about them before planning around them. A national booth is costly and in person. | N13: Not started | O13: Call Deborah Young (703-518-6296) for 2027 Denver booth rates; ask whether Principal magazine takes ads.
... A54: 2 | B54: Maryland Alliance of Public Charter Schools (MAPCS) | C54: association | D54: state (Maryland) | E54: Maryland public charter schools | F54: State charter school association | G54: Classroom pack site licenses + fundraiser program | H54: sponsor (ask), mailed/emailed outreach | I54: Sponsorship on request, (410) 919-9678 | J54: No 2026–27 conference found. The latest sponsor evidence is from a 2022 virtual conference. | K54: https://mdcharters.org | L54: N | M54: Fit lowered from 3 to 2. No current sponsorship program is confirmed, and past sponsors were mostly EdTech. Stay product-first and do not comment on them. | N54: Not started | O54: Verify the org, URL and dates on the official site; then request the sponsorship package (contact: (410) 919-9678)

Sheet Parents & Advocacy
A1: Fit | B1: Name | C1: Type | D1: Scope | E1: Members/Reach | F1: Who they are | G1: Lead offer | H1: How to reach | I1: Cost | J1: Next dates | K1: URL | L1: Confirmed (Y/N) | M1: Notes | N1: Status | O1: Next step | P1: Date
A2: 5 | B2: PTO Today (School Family Media): magazine, website, Leader Lowdown email, Vendor Directory, Expos | C2: publication / directory / conference | D2: national (US) | E2: By the company's own figures (from earlier search results): the magazine is mailed to 84,000+ K–8 school parent groups; ptotoday.com gets ~180,000 unique PTO/PTA-leader visitors a month (220,000+ at back-to-school); the Leader Lowdown email goes to 55,000+ opt-in subscribers; the Vendor Directory is promoted to 40,000+ weekly-newsletter subscribers | F2: For-profit media company (School Family Media) built to sell to PTO/PTA leaders. It sells print and digital ads, sponsored content, a vendor directory, sampling, and one-day regional PTO Today Expos. | G2: Group fundraiser program + host-it-yourself family play-night workshop kits; a research brief as a sponsored-content download | H2: vendor directory, newsletter ad (including 'sponsor takeover' issues of Leader Lowdown), sponsored content/guest article, magazine ad, exhibit (Expo) | I2: Expo prices from the 2023–24 sell sheets (dated): standard booth $995, premium corner $1,195, double $1,490, double premium $2,300, A&E/nonprofit tabletop $300. Sponsorship: $6,000 national (both events), $3,500 per local event, $2,750 remote. Magazine, banner, newsletter and directory rates are on rate cards at schoolfamilymedia.com (not captured). Re-check 2027 prices. | J2: Fall 2026 Expos: Secaucus, NJ (Sep 30, 2026) and Oaks, PA (Oct 7, 2026), probably too soon to book. The spring 2026 run was Feb 25–Apr 15 (Novi MI, Mesquite TX, Conroe TX, Edison NJ, Oakbrook Terrace IL, Marlborough MA). Expect a similar spring 2027 run (not yet announced). Ads and directory listings run year-round, with peak traffic at back-to-school (Jul–Sep 2027). | K2: https://www.ptotoday.com | L2: Y | M2: Confirmed from earlier search results that cite ptotoday.com and schoolfamilymedia.com pages; DNS is live (AWS). This is the best faceless channel in the category: a paid, for-profit route to exactly the parent-group buyers of the fundraiser and workshop kits. Start with the Vendor Directory and a Leader Lowdown ad, and add a booth only once the ads prove out. Expo booths are sold at clientstore.ptotoday.com, and the Expo team is at expolive@ptotoday.com. Also listed in the K–12 tab. | N2: Not started | O2: Email jwilliams@ptotoday.com (800-644-3561 x201) for current rate cards; start with a Vendor Directory listing plus one Leader Lowdown ad.
A3: 4 | B3: 1000 Books Before Kindergarten Foundation | C3: network / advocacy group | D3: national (US and Canada) | E3: Hundreds of libraries and other organizations run the 1000 Books Before Kindergarten challenge (per the foundation) | F3: Nevada 501(c)(3), founded in 2013, that promotes reading with newborns, infants and toddlers. It has corporate partners: Upstart (posters, bookmarks, reading records, incentives) and WAYB, a car-seat maker. | G3: Talk-along board books; a co-branded printable reading log or incentive using the brand's own art | H3: partner program (corporate partnership inquiry), resource listing | I3: Not verified (partnership terms unknown) | J3: Rolling | K3: https://1000booksbeforekindergarten.org | L3: Y | M3: New addition. Confirmed from earlier search results citing the foundation's own partnership announcements (Upstart, WAYB), which show it accepts for-profit partners. '1000 Books Before Kindergarten' is a registered trademark: use it only with written permission and never in ads. It overlaps the library list, so dedupe there. | N3: Not started | O3: Send a corporate partnership inquiry proposing a co-branded reading log; get written permission before using the trademarked name.
A4: 4 | B4: ClassWallet (Arizona ESA Marketplace; also NC ESA+) | C4: directory | D4: multi-state (US) | E4: Arizona Empowerment Scholarship Account families (and other ClassWallet ESA states), who shop pre-approved vendors in the ClassWallet Marketplace | F4: Payment and marketplace platform for state ESA programs. | G4: Books, play guide, bundles, card deck, course (under 'curriculum & instructional materials') | H4: vendor directory (ESA vendor registration with ClassWallet) | I4: Not verified (registration believed free) | J4: Rolling (vendors register year-round) | K4: https://classwallet.com | L4: Y | M4: New addition. Confirmed from earlier search results citing azed.gov's ClassWallet page and classwallet.com/arizona-esa: vendors register and verify credentials, and approved categories include curriculum and instructional materials. May duplicate a K-12 or procurement list, so dedupe there. | N4: Not started | O4: Register as an Arizona ESA vendor on ClassWallet under curriculum & instructional materials; follow eligible-expense rules exactly.
A5: 4 | B5: Great Homeschool Conventions | C5: conference | D5: national (US, five regional conventions) | E5: Five 2027 conventions, in the Southeast (SC), Missouri, Ohio, California and Texas, each with a large exhibit hall (attendance per city not captured) | F5: Homeschool convention series run by USA Home Education Association Inc. (USAHEA/GHC). | G5: Picture books, board books, 100-activity play guide, card deck, 5–12 bundle, written course | H5: exhibit (sponsorship and program ads not verified) | I5: Not published; ask through the exhibitor contact at greathomeschoolconventions.com/exhibitors. An inline booth is 10x10 in SC/OH/CA and 8x10 in MO/TX and includes a table, chair and sign; an endcap is two inline booths. Est. $1,000–$3,000 per booth per city (not verified). | J5: 2027 season in five cities; exact dates not captured (historically Feb–Jun). | K5: https://greathomeschoolconventions.com | L5: Y | M5: Confirmed from earlier search results citing the official Exhibitors, Rules and Regulations and state-update pages. Lowered from 5 because each city needs a staffed booth, travel and stock. Test a single city first (Ohio or SC are closest to Maryland). | N5: Not started | O5: Request 2027 booth pricing via greathomeschoolconventions.com/exhibitors and test one city (Ohio or SC) with a hired rep.
A6: 4 | B6: National Microschooling Center | C6: network / directory | D6: national (US) | E6: Hub for US microschool founders (member count not captured) | F6: Nonprofit hub for microschool founders. It runs the Partnership Provider Program (P3), a Preferred Provider Directory, the 'Access Point' learning-tools catalog and a Microschool Marketplace. | G6: PreK–5 screen-free classroom pack with site license, workshop kits, research briefs, library-binding books | H6: partner/vendor directory (join P3 with a member discount; get into the Access Point catalog) | I6: Not captured. P3 providers typically offer members a discount; ask whether there is a fee. | J6: Rolling | K6: https://microschoolingcenter.org | L6: Y | M6: Confirmed from earlier search results citing microschoolingcenter.org pages (Access Point, Preferred Provider Directory, P3). Apply by email through the P3 contact listed on the site. Fully faceless, and site licenses suit small schools. Raised from 3. The www. subdomain does not resolve; use the bare domain. | N6: Not started | O6: Email the P3 contact listed on microschoolingcenter.org to join the Preferred Provider Directory with a member discount.
A7: 4 | B7: Odyssey (ESA marketplace platform: Iowa, Louisiana GATOR, Utah Fits All, Wyoming, Georgia, Texas TEFA) | C7: directory | D7: multi-state (US) | E7: Families using state education savings accounts (ESAs) in the states Odyssey administers | F7: Company that runs state ESA programs and their vendor marketplaces; families spend ESA funds on approved vendors. | G7: Books (incl. library binding), play guide, 5–12 bundle, card deck, written course, PreK–5 classroom pack for microschools | H7: vendor directory (Odyssey vendor application for each state) | I7: Not verified (application believed free; check each state's vendor requirements and price caps, which Utah publishes) | J7: Rolling. Texas TEFA's first program year makes 2026–27 the time to apply. | K7: https://withodyssey.com | L7: Y | M7: New addition. Confirmed from earlier search results citing Odyssey's support pages ('How Can I Apply to Be A Vendor?', 'Vendor Application Lifecycle', the Utah Fits All and Louisiana GATOR vendor applications). A government-program channel: follow each state's eligible-expense rules exactly, make no health claims, and keep prices at or under any caps. May duplicate a K-12 or procurement list, so dedupe there. | N7: Not started | O7: Submit Odyssey vendor applications, Texas TEFA first, then Utah, Louisiana and Iowa; check each state's price caps.
A8: 4 | B8: Wild + Free | C8: network / conference | D8: national (US), with local groups | E8: Large nature-based homeschool community with local groups (size not verified) | F8: Community brand for families who favor nature, play, books and a slower childhood. It appears to be a company rather than a nonprofit (verify). | G8: Picture books, board books, 100-activity play guide, card deck | H8: brand partnership/sponsor, conference vendor space if offered, guest article (all unverified) | I8: Not verified | J8: Has held annual conferences. Confirm whether a 2027 event with vendor space exists at bewildandfree.org. | K8: https://www.bewildandfree.org | L8: N | M8: DNS only. A near-perfect match with 'talk, touch, play and paper', but no vendor or partner route could be verified. Lowered from 5. | N8: Not started | O8: Verify the org, URL and dates on the official site; then email a partnership inquiry offering a member discount
A9: 4 | B9: 1000 Hours Outside | C9: network / publication | D9: national / international | E9: Large parent following across podcast, email, social and trackers (size not verified) | F9: For-profit movement encouraging outdoor play to balance screen time. | G9: Play guide, card deck, picture books | H9: podcast/newsletter sponsorship, affiliate/shop partnership (unverified) | I9: Not verified (paid sponsorship) | J9: Rolling | K9: https://www.1000hoursoutside.com | L9: N | M9: DNS only (Squarespace). Because it is for-profit, a paid partnership is appropriate, and a host-read audio ad keeps the brand faceless. | N9: Not started | O9: Verify the org, URL and dates on the official site; then email a partnership inquiry offering a member discount
A10: 4 | B10: Homeschool Buyers Co-op | C10: directory / network | D10: national (US) | E10: Large free-membership group-buying club for homeschool families (member count not verified) | F10: Negotiates group discounts from curriculum and book vendors for member families. | G10: 100-activity play guide, 0–5 and 5–12 bundles, card deck, written course at a member price | H10: member discount/partner program (vendor listing) | I10: Not verified (usually a discount or revenue share, not a fee) | J10: Rolling | K10: https://www.homeschoolbuyersco-op.org | L10: N | M10: New addition (missed major faceless channel). DNS only: the site now resolves to Shopify hosting. Verify the vendor-application route before listing. | N10: Not started | O10: Verify the org, URL and dates on the official site; then email a partnership inquiry offering a member discount
A11: 4 | B11: HEAV (Home Educators Association of Virginia): Virginia Homeschool Convention | C11: association / conference | D11: state (Virginia) | E11: Large regional homeschool convention with a 'huge exhibit hall' (HEAV's own page title). Parents of only preschoolers attend free. | F11: Virginia homeschool association. Its annual convention is at the Greater Richmond Convention Center. | G11: Talk-along board books, picture books, play guide, 0–5 and 5–12 bundles, card deck | H11: exhibit (newsletter ads not verified) | I11: Not captured. Exhibit-hall applications opened in August 2026; check heav.org/convention/exhibitor-information. | J11: June 10–12, 2027, Greater Richmond Convention Center (from earlier search results) | K11: https://heav.org | L11: Y | M11: Confirmed from earlier search results citing heav.org pages (Convention, Exhibitor Information, Exhibit Hall, 'Parents of Preschoolers Attend Free'). Free entry for parents of preschoolers brings the exact 0–5 buyer. About a two-hour drive from Maryland, so a hired helper can staff the booth. Best first convention to test. Scored 4 rather than 5 only because the booth price is unknown and it needs staffing. | N11: Not started | O11: Apply for a booth for June 10–12, 2027 (applications open since Aug 2026) at heav.org/convention/exhibitor-information.
A12: 4 | B12: FPEA (Florida Parent Educators Association) Florida Homeschool Convention | C12: association / conference | D12: state (Florida) | E12: Historically one of the largest US homeschool conventions (15,000+ attendees reported; re-check) | F12: Florida homeschool association with an annual convention in Orlando. | G12: Books, play guide, bundles, card deck, course | H12: exhibit, sponsor (not verified) | I12: Not verified (est. $800–$2,500) | J12: Traditionally Memorial Day weekend; est. May 27–29, 2027 (Memorial Day is May 31, 2027). Confirm at fpea.com. | K12: https://fpea.com | L12: N | M12: DNS only (Cloudflare). Lowered from 5 because it is unverified and needs a staffed booth and air travel or freight. | N12: Not started | O12: Verify the org, URL and dates on the official site; then request the sponsorship package
A13: 3 | B13: National PTA (Convention) | C13: association / conference | D13: national (US) | E13: Millions of members in local PTA units nationwide (the current count was not captured; re-check at pta.org) | F13: Largest US parent-teacher volunteer association. It holds an annual national convention for state and local PTA leaders. | G13: Group fundraiser program + host-it-yourself family play-night kits + research briefs | H13: sponsor (through National PTA's Resource Development team / Meetings Department); exhibit only if a 2027 expo hall is offered (not confirmed) | I13: 2027 exhibit and sponsor prices are not published. As a benchmark, Washington State PTA's 2026 booth was $1,000 + tax. National sponsorship packages are usually much higher (not verified). | J13: Convention 2027: pta.org was taking session proposals. The date and city were not captured. It is historically held in early summer. | K13: https://www.pta.org | L13: Y | M13: Confirmed from earlier search results (pta.org Convention, Toolkit and Sponsors & Partners pages). The noncommercial policy is confirmed: all PTA bylaws require PTAs to be non-commercial; National PTA endorses no commercial product; sponsorship is allowed; and the PTA name may not be used to promote a vendor's goods. So never write 'PTA-approved' or similar. Fit lowered from 4 because the expo hall is unconfirmed, sponsorship is costly and a booth needs a hired staffer. PTO Today reaches the same leaders more cheaply. | N13: Not started | O13: Request the sponsorship package
... A65: 1 | B65: Maryland PTA (Convention / Leadership Training) | C65: association / conference | D65: state (Maryland) | E65: Statewide PTA units, including Montgomery County's MCCPTA council | F65: State PTA for Maryland. | G65: Fundraiser program + workshop kits | H65: At most, a statewide resource listing not aimed at Montgomery County. No convention booth. | I65: Not verified | J65: Confirm at mdpta.org | K65: https://www.mdpta.org | L65: N | M65: DNS only. Lowered to 1. MCCPTA is part of Maryland PTA, so statewide events draw Montgomery County PTA leaders and the MCPS staff who belong to PTAs, which is too close to the exclusion. Skip the convention. Never contact MCCPTA or any PTA inside an MCPS school. | N65: Not started | O65: CAUTION: no convention booth and no county-level contact. At most a statewide resource listing, and only after employment counsel says it is fine.

Sheet International
A1: Fit | B1: Name | C1: Type | D1: Scope | E1: Members/Reach | F1: Who they are | G1: Lead offer | H1: How to reach | I1: Cost | J1: Next dates | K1: URL | L1: Confirmed (Y/N) | M1: Notes | N1: Status | O1: Next step | P1: Date
A2: 5 | B2: PACEY (Professional Association for Childcare and Early Years) | C2: association | D2: international (UK - England & Wales) | E2: Childminders, nannies and nursery practitioners; historically cited at 20,000+ members (verify current figure) | F2: Membership charity for home-based childcare and early years practitioners in England and Wales. It was formerly the National Childminding Association and was renamed in 2013. It publishes a member magazine and runs member offers. | G2: Printable family bundle (0-5) re-edited for EYFS, the 100-activity play guide and the card deck. The host-it-yourself workshop kit suits childminding networks. | H2: member discount / partner benefit, magazine/newsletter ad, written guest article | I2: Not verified. Request the advertising media kit and partner-benefit terms. | J2: Not verified; ad placements are rolling | K2: https://www.pacey.org.uk | L2: N | M2: Childminders buy their own resources, so this is the closest audience match abroad. Ads and member offers need no staff. Not verified whether PACEY takes overseas advertisers or partners; ask. UK VAT applies to digital sales to UK consumers. Needs a UK/EYFS edition and no health claims. Confirm the organisation's current status before paying, because UK early-years charities have been under funding pressure. | N2: Not started | O2: Open pacey.org.uk to confirm current status, then request the media kit and partner-benefit terms and ask whether overseas partners are accepted.
A3: 4 | B3: Playgroup Australia (and state Playgroup associations) | C3: network | D3: international (Australia) | E3: National network of parent-led playgroups for 0-5 families, run through state/territory member organisations (verify) | F3: Peak body for community playgroups where parents, carers and young children meet to play. | G3: Talk-along board books (local POD), host-it-yourself workshop kit and card deck | H3: partner/affiliate, member discount, newsletter ad, resource listing | I3: Not verified | J3: Not verified; rolling | K3: https://www.playgroupaustralia.org.au | L3: N | M3: Parent-led play matches the brand closely. Approach state bodies separately (Playgroup Victoria, NSW, Queensland, WA, SA). Keep offers low-cost for the community sector. | N3: Not started | O3: When a local edition is ready: Verify the org, URL and dates on the official site; then request the media kit and ad rates
A4: 4 | B4: Early Childhood Australia (ECA) | C4: association | D4: international (Australia) | E4: National peak early childhood body with a large practitioner audience and a publishing arm (verify figures) | F4: Australia's national early childhood advocacy and professional body. It publishes 'Every Child' magazine, runs a shop and a blog, and holds a national conference. | G4: EYLF-aligned PreK classroom pack site licence, the 100-activity play guide and research briefs | H4: magazine ad (Every Child), guest article/blog, conference exhibit/sponsor, resource listing in ECA shop | I4: Not verified. Request the media kit and conference prospectus. | J4: Not verified; check the site for the next national conference (2026-27) | K4: https://www.earlychildhoodaustralia.org.au | L4: N | M4: Magazine and blog channels are faceless. The shop mostly sells ECA's own publications. Needs Australian spelling and terms. GST applies above A$75k, or use a merchant of record. Print books in Australia via POD. | N4: Not started | O4: When a local edition is ready: Verify the org, URL and dates on the official site; then request the media kit and ad rates
A5: 4 | B5: Early Childhood Ireland | C5: association | D5: international (Ireland) | E5: Several thousand member early years settings; historically cited at about 3,800 (verify) | F5: Ireland's largest early childhood membership organisation; runs conferences, publications and member services. | G5: Printable family bundles and PreK classroom pack re-edited for Aistear; workshop kits | H5: newsletter ad, member discount, exhibit/sponsor at annual conference | I5: Not verified. Request the exhibitor/sponsor pack. | J5: Not verified; check the site for the annual conference | K5: https://www.earlychildhoodireland.ie | L5: N | M5: English-language market. EU VAT via non-Union OSS applies from the first consumer digital sale. Start with newsletter ads and member offers; the conference needs staff. | N5: Not started | O5: When a local edition is ready: Verify the org, URL and dates on the official site; then request the media kit and ad rates
A6: 4 | B6: Early Years Alliance | C6: association | D6: international (UK - England) | E6: Pre-schools, nurseries and childminders; historically cited at about 14,000 member settings (verify) | F6: England's largest early years membership charity. It was formerly the Pre-school Learning Alliance and was renamed in 2019. It publishes 'Under 5' magazine and runs an online shop. | G6: PreK screen-free classroom pack (site licence, EYFS edition) and the talk-along board books. The workshop kit suits pre-school parent evenings. | H6: magazine ad (Under 5), sponsor/partner, resource listing in shop, guest article | I6: Not verified. Request the media kit. | J6: Not verified; check the events page for 2026-27 conferences | K6: https://www.eyalliance.org.uk | L6: N | M6: The shop mainly sells the Alliance's own publications; third-party stock is not assured, so ask. The Alliance campaigns on policy; the brand must stay neutral and must not comment on government or providers. UK edition needed. | N6: Not started | O6: When a local edition is ready: Verify the org, URL and dates on the official site; then request the media kit and ad rates
A7: 4 | B7: Family Day Care Australia | C7: association | D7: international (Australia) | E7: National peak body for family day care services and home-based educators (verify) | F7: Peak body representing family day care (home-based) educators and services; runs a national conference and member communications. | G7: Printable family bundles (0-5 and 5-12), card deck and play guide for home-based educators | H7: newsletter ad, member discount, conference exhibit/sponsor | I7: Not verified. Request the prospectus. | J7: Not verified; check the national conference schedule | K7: https://www.familydaycare.com.au | L7: N | M7: Home-based educators buy their own resources and care for mixed ages, so both bundles fit. Needs an Australian spelling edition. | N7: Not started | O7: When a local edition is ready: Verify the org, URL and dates on the official site; then request the media kit and ad rates
A8: 4 | B8: Nursery World (magazine), Nursery World Show and sister title Early Years Educator (EYE) | C8: publication | D8: international (UK) | E8: Leading UK early years trade magazine, website and newsletters, plus an annual London trade show (verify circulation and attendance) | F8: UK early years trade publisher (believed to be part of Mark Allen Group; verify). It runs the Nursery World Show, awards, and the sister title Early Years Educator. | G8: PreK classroom pack site licence and workshop kits. Library-binding picture books only once UK distribution exists. | H8: magazine/newsletter ad, sponsored content/advertorial, exhibit at Nursery World Show, written guest article | I8: Not verified. Request the combined media pack and exhibitor pack. A show stand plus hired staff and travel is likely to cost several thousand pounds. | J8: Not verified; the show is typically early February in London. Check the 2027 edition now, since stands sell in autumn. | K8: https://www.nurseryworld.co.uk | L8: N | M8: Ads and newsletter placements are fully faceless, so start there. The show needs hired booth staff. Ask about a combined Nursery World + EYE media package. | N8: Not started | O8: Request the combined Nursery World + EYE media pack; check 2027 show stand pricing now, since stands sell in autumn.
A9: 4 | B9: Teach Early Years / Teach Primary (Teachwire, Aceville Publications) | C9: publication | D9: international (UK) | E9: UK early years and primary teacher magazines, the Teachwire website and email newsletters (verify circulation) | F9: Commercial UK education magazines for early years and primary teachers. They carry product reviews, sponsored content and paid-entry resource awards (verify current awards). | G9: PreK-5 screen-free classroom pack site licence, the 100-activity play guide and the card deck | H9: magazine/newsletter ad, product review submission, awards entry, sponsored article | I9: Not verified. Request the media pack and awards entry fees. | J9: Not verified; ads are rolling, and the awards open once a year | K9: https://www.teachwire.net | L9: N | M9: ADDED. Fully faceless. It covers both 0-5 (Teach Early Years) and 5-12 (Teach Primary) buyers. Needs UK spelling and a UK edition. The same publisher's other titles are more tech-oriented; stick to the early-years and primary titles. | N9: Not started | O9: When a local edition is ready: Verify the org, URL and dates on the official site; then request the media kit and ad rates
A10: 3 | B10: COBIS (Council of British International Schools) | C10: association | D10: international (global; UK-based) | E10: British-curriculum international schools worldwide (verify count) | F10: Membership association of British international schools, with 'supporting member' supplier membership and an annual conference with exhibition. | G10: PreK-5 screen-free classroom pack site licence (EYFS/UK edition) and research briefs; workshop kit for parent evenings | H10: supporting (supplier) membership, newsletter ad, conference exhibit/sponsor | I10: Not verified. Request supporting-membership and sponsorship terms. | J10: Not verified; annual conference typically May (London area) | K10: https://www.cobis.org.uk | L10: N | M10: ADDED. English-language schools with budgets worldwide, and digital site licences avoid shipping. Supplier membership and ads are faceless. | N10: Not started | O10: When a local edition is ready: Verify the org, URL and dates on the official site; then request the media kit and ad rates
A11: 3 | B11: Australian Childcare Alliance (ACA) and state branches | C11: association | D11: international (Australia) | E11: National peak body for privately owned long day care services, with state branches (verify) | F11: Peak body for private early learning owners. Its state branches run conferences with trade exhibitions and member offers. | G11: PreK classroom pack site licence (multi-centre) and family printables for centres to give parents | H11: member offer / preferred supplier, newsletter ad, conference exhibit/sponsor | I11: Not verified | J11: Not verified; check national and state conference dates | K11: https://childcarealliance.org.au | L11: N | M11: ADDED. Centre owners buy multi-site licences. Conferences need staff, so start with member offers or ads. | N11: Not started | O11: When a local edition is ready: Verify the org, URL and dates on the official site; then request the media kit and ad rates
A12: 3 | B12: Childminding Ireland | C12: association | D12: international (Ireland) | E12: Irish childminders (verify) | F12: National membership body for childminders in Ireland. | G12: Printable family bundles, play guide and card deck | H12: member discount, newsletter ad | I12: Not verified | J12: Not verified | K12: https://www.childminding.ie | L12: N | M12: EU VAT OSS applies to consumer digital sales. English-language market. | N12: Not started | O12: When a local edition is ready: Verify the org, URL and dates on the official site; then request the media kit and ad rates
A13: 3 | B13: Community Early Learning Australia (CELA) | C13: association | D13: international (Australia - NSW-based, national) | E13: Not-for-profit community early learning services (verify) | F13: Peak body for community-based early learning services; publishes 'Rattler' magazine. | G13: PreK classroom pack and family printables | H13: magazine ad (Rattler), newsletter ad, member offer | I13: Not verified | J13: Not verified | K13: https://www.cela.org.au | L13: N | M13: ADDED. The magazine channel is faceless. | N13: Not started | O13: When a local edition is ready: Verify the org, URL and dates on the official site; then request the media kit and ad rates
... A66: 1 | B66: OMEP national committees - Mexico and Spain | C66: association | D66: international (Mexico; Spain) | E66: National early childhood professional committees (verify) | F66: Spanish-language national committees of OMEP that organise seminars and advocacy. | G66: Spanish-translated printable bundles and research briefs | H66: guest article, conference sponsor, resource listing | I66: Not verified | J66: Not verified | K66: https://omepworld.org | L66: N | M66: Lowered from 2. The URL is OMEP's global site; the national committees' own sites were not identified, so find them in OMEP's member directory. Approach only after full Spanish editions exist (Mexico and Spain variants). | N66: Not started | O66: When a local edition is ready: Verify the org, URL and dates on the official site; then offer a free resource for their resource listing

Sheet Excluded
A1: Group | B1: Name | C1: Why excluded or skipped | D1: Note
A2: Mandatory exclusion | B2: Montgomery County Public Schools (Maryland) and any of its schools or staff | C2: Includes MCPS administrator groups (e.g., MCAAP) and Montgomery County Head Start / pre-K classrooms run in MCPS. Never target MCPS staff met at any conference, chapter or network in this workbook. | D2: Excluded — pending matters; ask employment counsel before any contact
A3: Mandatory exclusion | B3: Montgomery County Education Association (MCEA) and its state and national affiliates | C3: Teachers' union for MCPS; affiliates include MSEA and NEA (below). | D3: Excluded — pending matters; ask employment counsel before any contact
A4: Mandatory exclusion | B4: Maryland State Education Association (MSEA) | C4: State affiliate of MCEA/NEA. | D4: Excluded — pending matters; ask employment counsel before any contact
A5: Mandatory exclusion | B5: National Education Association (NEA) | C5: Includes Student NEA chapters. | D5: Excluded — pending matters; ask employment counsel before any contact
A6: Mandatory exclusion | B6: Montgomery County (MD) Department of Health and Human Services | C6: Includes its Child Care Resource & Referral Center (Child Care Support Services, 1401 Rockville Pike, part of Maryland Family Network's network but DHHS-operated), its Head Start grantee role, and any DHHS-run Healthy Families or training site. | D6: Excluded — pending matters; ask employment counsel before any contact
A7: Mandatory exclusion | B7: Montgomery County (MD) DHHS Infants and Toddlers Program | C7: Also skip any Maryland DEC activity that involves this program. | D7: Excluded — pending matters; ask employment counsel before any contact
A8: Mandatory exclusion (precaution) | B8: Education International (EI) and its member unions abroad | C8: EI is the global teachers'-union federation NEA belongs to; its member unions are NEA's sister affiliates. Examples: NEU and NASUWT (UK), INTO (Ireland), CTF/FCE (Canada), AEU (Australia), NZEI Te Riu Roa and PPTA (NZ), SNTE (Mexico), FeSP-UGT and FECCOO (Spain). | D8: Excluded — pending matters; ask employment counsel before any contact
A9: Near-exclusion skip | B9: Montgomery County Council of PTAs (MCCPTA) and every PTA inside an MCPS school | C9: Organized around and operating inside MCPS schools. (Maryland PTA stays in the Parents tab at Fit 1 with a caution: no convention, no county-level contact.) | D9: Skipped — too close to the excluded parties; ask employment counsel before any contact
A10: Near-exclusion skip | B10: Maryland Association of Boards of Education (MABE) | C10: The Montgomery County Board of Education is a member. | D10: Skipped — too close to the excluded parties; ask employment counsel before any contact
A11: Near-exclusion skip | B11: Public School Superintendents' Association of Maryland (PSSAM) | C11: The MCPS superintendent is a member. | D11: Skipped — too close to the excluded parties; ask employment counsel before any contact
A12: Near-exclusion skip | B12: American Federation of Teachers (AFT) and other teachers' unions | C12: Not named in the exclusion but close to it; adding any union is the owner's call after counsel. | D12: Skipped — too close to the excluded parties; ask employment counsel before any contact
... A33: Not listed (not viable) | B33: Canadian Library Association | C33: Dissolved in 2016; succeeded by CFLA-FCAB (International tab). | D33: Not a target.
